{
    "earphone": "3.5mm Stereo Jack",
    "focus": "Full range Auto/Manual",
    "audioin": "2 XLR Line/ Mic. with selectable Phantom Power One 3.5mm stereo jack with Plug-on power",
    "lenstype": "Sony 10x zoom G-Lens",
    "compositevideoout": "One RCA via A/V Remote connector cable",
    "micin": "Two 3-Pin XLR  Line/Mic. with slectable phantom power and attenuation level. One sterero 3.5 mini jack with Plug-on power",
    "category": "camera",
    "usb": "Mini USB (host or Slave)",
    "specifications": "Included Lens Specifications Detail: 35mm Equivalent Video 26,3mm to 263mm Aperature 1.8mm Filter Diameter 37mm Focal Length 3.8 to 38mm Focus Full range Auto/Manual Image Stabilizer Optical SteadyShot Optical SteadyShot with Active Mode Iris Six blade iris Manual Auto Lens Type Sony 10x zoom G-Lens Maximum Relative Aperture F:1.8 Optical Zoom 10x 3.8~38mm Zoom Ratio Selectable Zoom ratio: 10x (14x Extended Zoom, 120x Digital Zoom) Inputs and Outputs Specifications Detail: Audio In 2 XLR Line/ Mic. with selectable Phantom Power One 3.5mm stereo jack with Plug-on power Audio Out Headphone: Stereo mini jack (x 1) \u00f83.5mm Two RCA via A/V Remote connector cable Audio/Video Remote Multi-Pin Connector A/V Remote connector Component Out Three RCA & L + R Audio via A/V Remote connector cable Composite Video Out One RCA via A/V Remote connector cable Earphone 3.5mm Stereo Jack MIC In Two 3-Pin XLR  Line/Mic. with slectable phantom power and attenuation level. One sterero 3.5 mini jack with Plug-on power Remote LANC type via A/V Remote connector USB Mini USB (host or Slave)",
    "filterdiameter": "37mm",
    "attr1star": "2 stars3 stars4 stars5 stars",
    "componentout": "Three RCA & L + R Audio via A/V Remote connector cable",
    "focallength": "3.8 to 38mm",
    "brand": "Sony",
    "imagestabilizer": "Optical SteadyShot Optical SteadyShot with Active Mode",
    "miscellaneous": "No",
    "includes": "Sony HXR-NX70U NXCAM Compact Camcorder AC-L200 AC Adapter / Charger NP-FV70 Rechargeable Camcorder Battery Pack (2060mAh, 8.4V) Power Cord ECM-XM1 Microphone Wind Screen XLR Adapter Lens Hood w/Lens Cover Large Eyecup Component A/V Cable A/V Connecting Cable Mini-USB Cable USB Adapter Cable RMT-845 Remote Commander Application Software (CD-ROM) 1 Year Limited Warranty",
    "iris": "Six blade iris Manual Auto",
    "audioout": "Headphone: Stereo mini jack (x 1) \u00f83.5mm Two RCA via A/V Remote connector cable",
    "remote": "LANC type via A/V Remote connector",
    "name": "Sony HXR-NX70U NXCAM Compact Camcorder",
    "attr35mmequivalent": "Video 26,3mm to 263mm",
    "opticalzoom": "10x 3.8~38mm"
}