{
    "weight": "Approx. 3.5 lb (1.6 kg)",
    "powerconsumption": "Maximum 16.7W (recording)",
    "sensitivity": "Not specified by manufacturer",
    "focus": "Auto / Manual",
    "audiosignalformat": "Dolby Digital 5.1-channel / 2-channel, Linear PCM 2-channel 48 kHz / 16-bit",
    "effectivepixels": "Motion Image 2D: 6.57 megapixels (2.19 megapixels x 3) [16:9] 3D: 6.21 megapixels (2.07 megapixels x 3) [16:9] Still Image 7.08 megapixels (2.36 megapixels x 3) [3:2] 6.57 megapixels (2.19 megapixels x 3) [16:9] 6.87 megapixels (2.29 megapixels x 3) [4:3]",
    "imagestabilization": "2D: HYBRID O.I.S. + 3D: POWER O.I.S.",
    "audiobitrates": "Dolby Digital: 384 kb/s (5.1-channel), 256 kb/s (2-channel) Linear PCM : 1.5 Mb/s (2-channel)",
    "manualcontrols": "Rings: Zoom, focus, iris Dial: Convergence",
    "category": "camera",
    "lens": "2x f/1.5 lenses with 12x zoom in 2D; 10x zoom in 3D",
    "memorycardslot": "2x SD card (SD up to 2 GB, SDHC up to 32 GB, and SDXC up to 64 GB)",
    "thumbnaildisplay": "20 thumbnails/page, 9 thumbnails/page, 1 thumbnail/page",
    "attr35mmequivalentfocallength": "Motion Image 2D: 29.8-368.8 mm [16:9] 3D: 32.0-320.0 mm [16:9] Still Image 2D: 29.8-369.0 mm [3:2], 29.8-368.8 mm [16:9], 31.0-372.0 mm [4:3] 3D: 32.0-320.0 mm [16:9]",
    "maximumrecordingtime": "With 64 GB storage MVC (3D) & 1080p60 (2D): 5 hours 15 minutes PH: 6 hours HA: 8 hours 30 minutes HE: 27 hours 30 minutes",
    "specifications": "Image Device 2x 3MOS (3x CMOS each) 1/4.1\" sensors Total Pixels 9.15 megapixels (3.05 megapixels x 3) Effective Pixels Motion Image 2D: 6.57 megapixels (2.19 megapixels x 3) [16:9] 3D: 6.21 megapixels (2.07 megapixels x 3) [16:9] Still Image 7.08 megapixels (2.36 megapixels x 3) [3:2] 6.57 megapixels (2.19 megapixels x 3) [16:9] 6.87 megapixels (2.29 megapixels x 3) [4:3] Lens 2x f/1.5 lenses with 12x zoom in 2D; 10x zoom in 3D Focal Length 2D: 2.84-34.1 mm 3D: 2.84-28.4 mm 35mm Equivalent Focal Length Motion Image 2D: 29.8-368.8 mm [16:9] 3D: 32.0-320.0 mm [16:9] Still Image 2D: 29.8-369.0 mm [3:2], 29.8-368.8 mm [16:9], 31.0-372.0 mm [4:3] 3D: 32.0-320.0 mm [16:9] Aperture 2D: f/1.5 (wide) to f/2.8 (tele) 3D: f/1.5 (wide) to f/2.7 (tele) Zoom Optical 2D: 12x 3D: 10x Intelligent 2D: 23x Digital 2D: 30x / 120x Horizontal Resolution Not specified by manufacturer Sensitivity Not specified by manufacturer Standard Subject Illumination 1400 lux Minimum Illumination 5 lux (iA mode ON: 1/30 second shutter) Minimum Object Distance (M.O.D.) 2D: Approx. 47\" (1.2 m) full zoom range Approx. 1.4\" (3.5 cm) wide range macro 3D: Approx. 2.5 m (all zoom range) Approx. 18\" (45 cm) wide range macro Focus Auto / Manual White Balance Auto / White Set / 3200K / 5600K / Ach / Bch Iris Auto / Manual Vertical Smear Not specified by manufacturer Signal System 3D: 1080i60, 1080p30, 1080p24 2D: 1080p60, 1080i60, 1080p30, 1080p24 Built-in Filters No LCD Monitor 3.48\" (8.83 cm) 16:9 3D (glasses-free) LCD monitor (1,152,000 dots) Viewfinder 0.45\" (11.5 mm) 16:9 EVF (approx. 1,226,880 dots) Shutter Speed Auto Slow Shutter On 60p, 60i, 30p mode: 1/30 to 1/8000 second 24p mode: 1/24 to 1/8000 second Auto Slow Shutter Off 60p, 60i, 30p mode: 1/60 to 1/8000 second 24p mode: 1/48 to 1/8000 second Gain Selection Not specified by manufacturer Signal-to-Noise Ratio Not specified by manufacturer Image Stabilization 2D: HYBRID O.I.S. + 3D: POWER O.I.S. Manual Controls Rings: Zoom, focus, iris Dial: Convergence Memory Card Slot 2x SD card (SD up to 2 GB, SDHC up to 32 GB, and SDXC up to 64 GB) Recording Format AVCHD 2.0 standard (AVCHD 3D / AVCHD Progressive) compliant Compression Technology 2D: MPEG-4 AVC / H.264 3D: MPEG-4 MVC / H.264 Bit Rates MVC (3D) & 1080p60 (2D): 28 Mb/s PH: 24 Mb/s HA: 17 Mb/s HE: 5 Mb/s Maximum Recording Time With 64 GB storage MVC (3D) & 1080p60 (2D): 5 hours 15 minutes PH: 6 hours HA: 8 hours 30 minutes HE: 27 hours 30 minutes Still Capture Recording Format: JPEG (DCF / Exif2.2), MPO (CIPA-007-2009) Aspect Ratio: 16:9 Image Size: 3 Mp [JPEG], (2304 x 1296), 2.1 Mp [JPEG], (1920 x 1080), 2.1 Mp [MPO + JPEG], (1920 x 1080) Thumbnail Display 20 thumbnails/page, 9 thumbnails/page, 1 thumbnail/page Audio Dynamic Range Not specified by manufacturer Audio Signal Format Dolby Digital 5.1-channel / 2-channel, Linear PCM 2-channel 48 kHz / 16-bit Audio Bitrates Dolby Digital: 384 kb/s (5.1-channel), 256 kb/s (2-channel) Linear PCM : 1.5 Mb/s (2-channel) Built-in Speaker Dynamic type (round) Input and Output Connectors XLR Inputs 2x 3-pin (INPUT 1, INPUT 2) LINE: 0 dBu, MIC: -50 dBu / -60 dBu (selectable in menu) HDMI Output 1x Type A Outputs 1080p, 1080i, 480p & 576p video and Dolby Digital & Linear PCM audio Headphone Output 1x stereo mini jack (3.5mm diameter) USB 2.0 1x USB Mini AV Multi Output Proprietary connector to component/composite/stereo audio (6x) RCAs Power Requirements 7.2V (battery) / 12V (AC adaptor) Power Consumption Maximum 16.7W (recording) Operating Temperature 32 to 104\u00b0F (0 to 40\u00b0C) Operating Humidity 10-80% (no condensation) Dimensions (WxHxD) Approx. 5.7 x 7.7 x 13.8\" (14.5 x 19.5 x 35.0 cm) Weight Approx. 3.5 lb (1.6 kg) System Requirements For HD Writer XE 1.0 software (Windows-only): OS Windows 7 (32-bit/64-bit): Starter/Home Basic/Home Premium/Professional/Ultimate Windows Vista (32-bit): Home Basic/Home Premium/Business/Ultimate SP1/SP2 Windows XP (32-bit): SP3 CPU Intel Pentium 4 2.8 GHz or higher When using playback function and MPEG-2 conversion function, Intel Core 2 Duo 2.16 GHz or higher Operation  on an upgraded OS is not guaranteed. When 2 or more USB devices are  connected to a PC, or when devices are connected though USB hubs or by  using extension cables, proper operation is not guaranteed. Operation on  an OS other than the one pre-installed is not guaranteed. Not  compatible with multi-boot environments or multi-monitor environments.  Not guaranteed on Windows XP Media Center Edition, Tablet PC Edition,  Windows Vista Enterprise, or Windows 7 Enterprise. Available with  administrator account in Windows XP; available with administrator  account or standard account in Windows Vista/Windows 7 (installation and  uninstallation require an administrator account).",
    "recordingformat": "AVCHD 2.0 standard (AVCHD 3D / AVCHD Progressive) compliant",
    "builtinfilters": "No",
    "totalpixels": "9.15 megapixels (3.05 megapixels x 3)",
    "aperture": "2D: f/1.5 (wide) to f/2.8 (tele) 3D: f/1.5 (wide) to f/2.7 (tele)",
    "dimensionswxhxd": "Approx. 5.7 x 7.7 x 13.8\" (14.5 x 19.5 x 35.0 cm)",
    "minimumillumination": "5 lux (iA mode ON: 1/30 second shutter)",
    "attr1star": "2 stars3 stars4 stars5 stars",
    "signaltonoiseratio": "Not specified by manufacturer",
    "focallength": "2D: 2.84-34.1 mm 3D: 2.84-28.4 mm",
    "brand": "Panasonic",
    "miscellaneous": "No",
    "includes": "Panasonic HDC-Z10000 Twin-Lens 2D/3D Camcorder AC Adapter AC Cable DC Cable CGA-D54 Lithium-Ion Battery Pack Battery Charger IR Remote with Lithium Metal Battery Component AV Cable (AV Multi) USB Cable Lens Cap HD Writer XE 1.0 Software 1 Year Limited Warranty",
    "gainselection": "Not specified by manufacturer",
    "signalsystem": "3D: 1080i60, 1080p30, 1080p24 2D: 1080p60, 1080i60, 1080p30, 1080p24",
    "minimumobjectdistancemod": "2D: Approx. 47\" (1.2 m) full zoom range Approx. 1.4\" (3.5 cm) wide range macro 3D: Approx. 2.5 m (all zoom range) Approx. 18\" (45 cm) wide range macro",
    "lcdmonitor": "3.48\" (8.83 cm) 16:9 3D (glasses-free) LCD monitor (1,152,000 dots)",
    "shutterspeed": "Auto Slow Shutter On 60p, 60i, 30p mode: 1/30 to 1/8000 second 24p mode: 1/24 to 1/8000 second Auto Slow Shutter Off 60p, 60i, 30p mode: 1/60 to 1/8000 second 24p mode: 1/48 to 1/8000 second",
    "powerrequirements": "7.2V (battery) / 12V (AC adaptor)",
    "operatingtemperature": "32 to 104\u00b0F (0 to 40\u00b0C)",
    "iris": "Auto / Manual",
    "imagedevice": "2x 3MOS (3x CMOS each) 1/4.1\" sensors",
    "name": "Panasonic HDC-Z10000 Twin-Lens 2D/3D Camcorder",
    "operatinghumidity": "10-80% (no condensation)",
    "zoom": "Optical 2D: 12x 3D: 10x Intelligent 2D: 23x Digital 2D: 30x / 120x",
    "systemrequirements": "For HD Writer XE 1.0 software (Windows-only): OS Windows 7 (32-bit/64-bit): Starter/Home Basic/Home Premium/Professional/Ultimate Windows Vista (32-bit): Home Basic/Home Premium/Business/Ultimate SP1/SP2 Windows XP (32-bit): SP3 CPU Intel Pentium 4 2.8 GHz or higher When using playback function and MPEG-2 conversion function, Intel Core 2 Duo 2.16 GHz or higher Operation  on an upgraded OS is not guaranteed. When 2 or more USB devices are  connected to a PC, or when devices are connected though USB hubs or by  using extension cables, proper operation is not guaranteed. Operation on  an OS other than the one pre-installed is not guaranteed. Not  compatible with multi-boot environments or multi-monitor environments.  Not guaranteed on Windows XP Media Center Edition, Tablet PC Edition,  Windows Vista Enterprise, or Windows 7 Enterprise. Available with  administrator account in Windows XP; available with administrator  account or standard account in Windows Vista/Windows 7 (installation and  uninstallation require an administrator account).",
    "viewfinder": "0.45\" (11.5 mm) 16:9 EVF (approx. 1,226,880 dots)",
    "horizontalresolution": "Not specified by manufacturer",
    "builtinspeaker": "Dynamic type (round)",
    "whitebalance": "Auto / White Set / 3200K / 5600K / Ach / Bch"
}