{
    "weight": "5.5 lb (2.5 kg)",
    "recordingmedia": "2x P2 card slots",
    "category": "camera",
    "maximumrecordingtime": "With 2x 64 GB P2 Cards ( not included ): Approx. 160 min for AVC-Intra 100 at 1080p24 Approx. 128 min for AVC-Intra 100 at 1080i60/50, 720p60/50 Approx. 320 min for AVC-Intra 100 at 720p24 Approx. 356 min for AVC-Intra 50 & DVCPRO50 Approx. 128 min for DVCPRO HD Approx. 512 min for DVCPRO/DV",
    "builtinfilters": "ND filter: OFF, 1/4, 1/16, 1/64",
    "attr1star": "2 stars3 stars4 stars5 stars",
    "videoformats": "1080i59.94/50, 1080p29.97/25/23.98, 720p59.94/50/29.97/25/23.98, 480i59.94, 480p29.97/23.98, 576i50, 576p25",
    "specifications": "Image Device 3x 1/3\"-type 2.2 Mp CMOS Lens Built-in; 22x optical zoom 3.9-86mm (28-616mm, 35mm equivalent) Signal System NTSC/PAL Built-in Filters ND filter: OFF, 1/4, 1/16, 1/64 LCD Monitor Not specified by manufacturer Viewfinder Not specified by manufacturer Recording Formats AVC-Intra 100, AVC-Intra 50, DVCPRO HD, DVCPRO50, DVCPRO, DV Video Formats 1080i59.94/50, 1080p29.97/25/23.98, 720p59.94/50/29.97/25/23.98, 480i59.94, 480p29.97/23.98, 576i50, 576p25 Video Compression AVC-Intra 100, AVC-Intra 50: MPEG-4 AVC / H.264 Intra profile DVCPRO HD: DV-based compression (SMPTE 370M) DVCPRO50, DVCPRO: DV-based compression (SMPTE 314M) DV: DV compression (IEC 61834-2) Audio Signal AVC-Intra 100/50, DVCPRO HD, DVCPRO50: 48 kHz, 16-bit, 4-channel DVCPRO/DV: 48 kHz, 16-bit, 2/4-channel switchable Recording Media 2x P2 card slots Maximum Recording Time With 2x 64 GB P2 Cards ( not included ): Approx. 160 min for AVC-Intra 100 at 1080p24 Approx. 128 min for AVC-Intra 100 at 1080i60/50, 720p60/50 Approx. 320 min for AVC-Intra 100 at 720p24 Approx. 356 min for AVC-Intra 50 & DVCPRO50 Approx. 128 min for DVCPRO HD Approx. 512 min for DVCPRO/DV Video Outputs 1x BNC for HD/SD-SDI HDMI: 1x HDMI Type A Audio Inputs 2x XLR 3-pin supporting 48V phantom power Other I/O Remote input for optional AG-EC4G Genlock input Timecode input/output IEEE 1394a USB 2.0 (host/device) Weight 5.5 lb (2.5 kg)",
    "brand": "Panasonic",
    "miscellaneous": "No",
    "includes": "Panasonic AG-HPX255 P2 HD Handheld Camcorder AC Adapter Battery Charger AC Cord DC Cord 5400mAh Battery Pack Wireless Remote Controller with Battery Microphone Holder Eye Cup Shoulder Strap P2 Card Driver Installer CD-ROM 1 Year Limited Warranty (Extends to Up to 5 Years with Online Registration)",
    "lens": "Built-in; 22x optical zoom 3.9-86mm (28-616mm, 35mm equivalent)",
    "videocompression": "AVC-Intra 100, AVC-Intra 50: MPEG-4 AVC / H.264 Intra profile DVCPRO HD: DV-based compression (SMPTE 370M) DVCPRO50, DVCPRO: DV-based compression (SMPTE 314M) DV: DV compression (IEC 61834-2)",
    "signalsystem": "NTSC/PAL",
    "recordingformats": "AVC-Intra 100, AVC-Intra 50, DVCPRO HD, DVCPRO50, DVCPRO, DV",
    "lcdmonitor": "Not specified by manufacturer",
    "videooutputs": "1x BNC for HD/SD-SDI HDMI: 1x HDMI Type A",
    "imagedevice": "3x 1/3\"-type 2.2 Mp CMOS",
    "name": "Panasonic AG-HPX255 P2 HD Handheld Camcorder",
    "viewfinder": "Not specified by manufacturer"
}