{
    "weight": "8.6 lbs (3.9kg) (body only)",
    "powerconsumption": "34W",
    "sensitivity": "2000 lux, 3200K, 89.9% Reflectance: F11 (1080/59.94i mode) F12 (1080/50i mode)",
    "audiosignalformat": "AVC-Intra 100/50: 48 kHz, 16 bit/24 bit switchable, 4ch DVCPRO HD/DVCPRO 50: 48 kHz, 16 bit, 4ch DVCPRO/DV: 48 kHz, 16 bit, 2ch/4ch switchable",
    "framerates": "1080/59.94i, 1080/29.97p over 59.94i 1080/23.98p over 59.94i, 1080/23.98pA over 59.94i 1080/29.97pN, 1080/23.98pN 1080/50i, 1080/25p over 50i, 1080/25pN 480/59.94i, 480/29.97p over 59.94i 480/23.98p over 59.94i, 480/23.98pA over 59.94i 576/50i, 576/25p over 50i",
    "attr1star": "2 stars3 stars4 stars5 stars",
    "memorycardslot": "P2 Card (x2)",
    "recordingplaybacktime": "(Using 2x 32GB P2 Cards) AVC-Intra 100: Approx. 64 min. AVC-Intra 50: Approx. 128 min. DVCPRO HD: Approx. 64 min. DVCPRO 50: Approx. 128 min. DVCPRO/DV: Approx. 256 min.",
    "recordingformat": "AVC-Intra 100, AVC-Intra 50, DVCPRO HD, DVCPRO50, DVCPRO, DV",
    "speaker": "28mm round shape x1",
    "builtinfilters": "Neutral Density: 1/4, 1/16, 1/64 Color Correction: 3200K, 4300K, 5600K, 6300K",
    "minimumillumination": "0.005 lx (F1.4, S.GAIN 42dB + DS.GAIN 34dB)",
    "category": "camera",
    "signaltonoiseratio": "DNR ON: 59 dB DNR OFF: 54 dB (standard)",
    "specifications": "Image Device 2/3\"-type 3CCD Picture Elements 2010 x 1120 total (1920 x 1280 effective) Lens Mount 2/3-bayonet type Horizontal Resolution 1,000 TV lines Signal-to-Noise Ratio DNR ON: 59 dB DNR OFF: 54 dB (standard) Sensitivity 2000 lux, 3200K, 89.9% Reflectance: F11 (1080/59.94i mode) F12 (1080/50i mode) Minimum Illumination 0.005 lx (F1.4, S.GAIN 42dB + DS.GAIN 34dB) Signal System NTSC / PAL Built-in Filters Neutral Density: 1/4, 1/16, 1/64 Color Correction: 3200K, 4300K, 5600K, 6300K LCD Monitor 3.5\" Color LCD Speaker 28mm round shape x1 Viewfinder Optional Shutter Speed 1/60 (50 Hz), 1/100 (59.94 Hz), 1/120, 1/250, 1/500, 1/1000, 1/2000, HALF 180.0\u00b0, 172.8\u00b0, 144.0\u00b0, 120.0\u00b0, 90.0\u00b0, 45.0\u00b0 Gain Selection -6, -3, 0, 3, 6, 9, 12, 18, 21, 24, 27, 30 dB Super Gain: 30, 36, 42 dB Memory Card Slot P2 Card (x2) Recording Format AVC-Intra 100, AVC-Intra 50, DVCPRO HD, DVCPRO50, DVCPRO, DV Frame Rates 1080/59.94i, 1080/29.97p over 59.94i 1080/23.98p over 59.94i, 1080/23.98pA over 59.94i 1080/29.97pN, 1080/23.98pN 1080/50i, 1080/25p over 50i, 1080/25pN 480/59.94i, 480/29.97p over 59.94i 480/23.98p over 59.94i, 480/23.98pA over 59.94i 576/50i, 576/25p over 50i Recording/Playback Time (Using 2x 32GB P2 Cards) AVC-Intra 100: Approx. 64 min. AVC-Intra 50: Approx. 128 min. DVCPRO HD: Approx. 64 min. DVCPRO 50: Approx. 128 min. DVCPRO/DV: Approx. 256 min. Audio Dynamic Range More than 85 dB (1 kHz, AWTD, 16 bit) More than 93 dB (1 kHz, AWTD, 24 bit) Audio Signal Format AVC-Intra 100/50: 48 kHz, 16 bit/24 bit switchable, 4ch DVCPRO HD/DVCPRO 50: 48 kHz, 16 bit, 4ch DVCPRO/DV: 48 kHz, 16 bit, 2ch/4ch switchable Audio  Frequency Response 20 Hz to 20 kHz \u00b11.0dB (reference level) Headroom 18/20 dB selectable Input and Output Connectors HD/SD-SDI: BNC (x1 Input, x1 Output) Monitor/SDI/Composite: BNC (x1 Output) Line/Mic: 3-pin XLR (x2 Input) Audio: 5-pin XLR (x1 Output) MIC: 5-pin XLR (x1 Input) Wireless: 25-pin D-Sub (x1 Input) Timecode: BNC (x1 Input, x1 Output) Genlock: BNC (x1 Input) USB 2.0: HOST Type A, DEVICE Type B (x1) Headphone: 3.5mm Stereo Mini (x2 Output) EVF: 20-pin Remote: 10-pin Lens: 12-pin GPS: 6-pin Power Requirements 12VDC (11-17V) Power Consumption 34W Operating Temperature 32\u00b0 to 104\u00b0F (-0&edg; to 40\u00b0C) Dimensions (WxHxD) 5.5 x 10.7 x 13.4\" (14 x 27.1 x 34 cm) (body only) Weight 8.6 lbs (3.9kg) (body only)",
    "brand": "Panasonic",
    "miscellaneous": "No",
    "includes": "Panasonic AJ-HPX3100GJ P2 HD Camcorder Shoulder Strap Audio Volume Knob w/Screw Connector Caps Mount Cap Software CD-ROM 1 Year Limited Warranty + 4 Years After Registration",
    "gainselection": "-6, -3, 0, 3, 6, 9, 12, 18, 21, 24, 27, 30 dB Super Gain: 30, 36, 42 dB",
    "signalsystem": "NTSC / PAL",
    "dimensionswxhxd": "5.5 x 10.7 x 13.4\" (14 x 27.1 x 34 cm) (body only)",
    "lensmount": "2/3-bayonet type",
    "lcdmonitor": "3.5\" Color LCD",
    "shutterspeed": "1/60 (50 Hz), 1/100 (59.94 Hz), 1/120, 1/250, 1/500, 1/1000, 1/2000, HALF 180.0\u00b0, 172.8\u00b0, 144.0\u00b0, 120.0\u00b0, 90.0\u00b0, 45.0\u00b0",
    "powerrequirements": "12VDC (11-17V)",
    "operatingtemperature": "32\u00b0 to 104\u00b0F (-0&edg; to 40\u00b0C)",
    "imagedevice": "2/3\"-type 3CCD",
    "headroom": "18/20 dB selectable",
    "name": "Panasonic AJ-HPX3100GJ P2 HD Camcorder - Camera Body Package",
    "pictureelements": "2010 x 1120 total (1920 x 1280 effective)",
    "horizontalresolution": "1,000 TV lines",
    "viewfinder": "Optional"
}