{
    "attr1star": "2 stars3 stars4 stars5 stars",
    "category": "camera",
    "imagedevice": "1/3\" 3MOS, 2.2 MP",
    "lcdmonitor": "3.5\", QHD, approximately 156k dots",
    "recordingframerate": "720 x 480: 59.94i, 29.97p 720 x 576: 50i, 25p 1280 x 720pN 23.98/29.97 1280 x 720p 23.98/25/29.97/50/59.94 1920 x 1080i 50/59.94 1920 x 1080pA 23.98 1920 x 1080pN 23.98/29.97 1920 x 1080p 23.98/25/29.97/50/59.94",
    "memorycardslot": "2 x Micro P2 1 x P2 1 x SD",
    "specifications": "Image Device 1/3\" 3MOS, 2.2 MP Resolution 1920 x 1080 Lens 22x Optical Zoom Lens Minimum Illumination 0.02 Lux (F1.6, Gain 18dB, 1 second exposure, High Sens mode) Built-in Filters ND Clear 1/4 1/16 1/64 Recording Frame Rate 720 x 480: 59.94i, 29.97p 720 x 576: 50i, 25p 1280 x 720pN 23.98/29.97 1280 x 720p 23.98/25/29.97/50/59.94 1920 x 1080i 50/59.94 1920 x 1080pA 23.98 1920 x 1080pN 23.98/29.97 1920 x 1080p 23.98/25/29.97/50/59.94 Recording Format AVC Intra 100/50 Inter LongG: G12/G25/G50 LongG6: Proxy DVCPROHD(except 720p/24p,30p,25p) DVCPRO50/DVCPRO/DV Note: The AJ-PX270 does not support all of the formats included  in the AVC-ULTRA family. AVC-200 is announced as an update available  June, 2014 Memory Card Slot 2 x Micro P2 1 x P2 1 x SD LCD Monitor 3.5\", QHD, approximately 156k dots Viewfinder 0.5\" OLED, approximately 1.76 MP resolution Input and Output Connectors Video Input Timecode: 1 x BNC Genlock: 1 x BNC (shared with video out) Video Output 3G-SDI: 1 x BNC Video: 1 x BNC (Combo Genlock in/Video out) Audio Input Balanced: 2 x XLR Audio Output Audio out: 1 x Headphone out: 1 x Power Requirements 7.2VDC Uses: VW-VBD58 battery Compatible: CGA-D54",
    "minimumillumination": "0.02 Lux (F1.6, Gain 18dB, 1 second exposure, High Sens mode)",
    "miscellaneous": "No",
    "lens": "22x Optical Zoom Lens",
    "recordingformat": "AVC Intra 100/50 Inter LongG: G12/G25/G50 LongG6: Proxy DVCPROHD(except 720p/24p,30p,25p) DVCPRO50/DVCPRO/DV Note: The AJ-PX270 does not support all of the formats included  in the AVC-ULTRA family. AVC-200 is announced as an update available  June, 2014",
    "builtinfilters": "ND Clear 1/4 1/16 1/64",
    "viewfinder": "0.5\" OLED, approximately 1.76 MP resolution",
    "includes": "Panasonic AJ-PX270 microP2 Handheld AVC-ULTRA HD Camcorder Battery (VW-VBD58) Battery Charger & AC Cable AC Adapter & AC Cable Shoulder Belt Mic Holder 2 x Screws for Mic Holder Eye Cup Lens Hood (Attached to Camera Body) Hand Strap (Attached to Camera Body) Limited 1-Year Warranty, Extendable to 5-Years with Product Registration",
    "resolution": "1920 x 1080",
    "brand": "Panasonic",
    "powerrequirements": "7.2VDC Uses: VW-VBD58 battery Compatible: CGA-D54",
    "name": "Panasonic AJ-PX270 microP2 Handheld AVC-ULTRA HD Camcorder"
}