{
    "shutterspeedrange": "59.94i: 1/60 to 1/2000 in 1/4 or 1/3 stops; SLS: 1/4, 1/8, 1/15, 1/30; CS: 59.94 to 250.27 Hz PF30: 1/30 to 1/2000 in 1/4 or 1/3 stops; SLS: \u00bc, 1/8; CS: 29.97 to 250.27 Hz 23.98p/PF24: 1/24 to 1/2000 in 1/4 or 1/3 stops; SLS: 1/3, 1/6, 1/12; CS: 23.97 to 250.27 Hz 50i: 1/50 to 1/2000 in 1/4 or 1/3 stops; SLS: 1/3, 1/6, 1/12 1/25; CS: 50.00 to 250.78 Hz PF25: 1/25 to 1/2000 in 1/4 or 1/3 stops; SLS: 1/3, 1/6, 1/12; CS: 25.00 to 250.78 Hz",
    "weight": "16.93 oz (480 g)",
    "videorecordmode": "24 Mbps LPCM: 1920 x 1080 at 60i, PF30, PF24, 24p, 50i, PF25 24 Mbps: 1920 x 1080 at 60i, PF30, PF24, 24p, 50i, PF25 17 Mbps: 1920 x 1080 at 60i, PF30, PF24, 24p, 50i, PF25 7 Mbps: 1440 x 1080 at 60i, PF30, PF24, 24p, 50i, PF25",
    "operatingtemperature": "Performance requirements 32 - 104\u00b0F (0 - 40\u00b0C), 85% relative humidity Operating requirements: 32 - 113\u00b0F (0 - 45\u00b0C), 60% relative humidity",
    "remoteterminal": "LANC compatible",
    "powersupply": "7.4 V DC (battery pack: BP-955) 8.4 V DC (DC IN)",
    "isorange": "320 to 80,000 in 1/3-step increments",
    "recordingmedia": "2 x SD/SDHC/SDXC card slots File system: FAT 32",
    "builtinspeaker": "Yes; 16 level settings",
    "effectivepixels": "Approx. 8.29 megapixels (3840 x 2160 pixels)",
    "imagestabilization": "Yes",
    "audiorecordmode": "24 Mbps mode: Linear PCM; 2-Channel; 16-Bit; 48 kHz All other modes: Dolby Digital AC3",
    "minimumsubjectillumination": "59.94 Hz: 0.3 lux 50 Hz: 0.25 lux",
    "category": "camera",
    "hdmioutput": "1 x Type A",
    "attr1star": "2 stars3 stars4 stars5 stars",
    "builtinmicrophone": "Stereo microphone built in to top handle",
    "usb": "1 x Mini-B USB 2.0",
    "minimumfocusdistance": "1.28'\u00a0(39 cm)",
    "formatcompatibility": "Canon (APS-C)",
    "specifications": "Image Sensor Sensor Super 35mm CMOS (24.6 x 13.8 mm) (28.2 mm diagonal) Total Pixels Approx. 9.84 megapixels (4206 x 2340) Effective Pixels Approx. 8.29 megapixels (3840 x 2160 pixels) Processor DIGIC DV III Color Filter RGB Primary Color Filter (Bayer Array) Lens System Lens Mount Canon EF mount with EF contacts ND Filters Clear, 2 stops (1/4), 4 stops (1/16), 6 stops (1/64) Iris Dial Manual setting in 1/2-step increments, 1/3-step increments, or fine Push auto iris control Peripheral Illumination Correction On supported Canon EF, EF-S, and Cinema lenses Exposure Control Exposure Modes Manual Push Auto Iris Control (metering system selection/AE shift possible) Metering Modes Standard Center Weighted, Spotlight, Backlight Gain Normal: -6 to 30 dB TBD Fine: 0 to 24 dB, in 0.5 dB increments ISO Range 320 to 80,000 in 1/3-step increments Shutter Modes OFF, ISO Speed, Shutter Angle, Slow Shutter, or Clear Scan Speed setting can be set in 1/2 or 1/3 stop increments Shutter Speed Range 59.94i: 1/60 to 1/2000 in 1/4 or 1/3 stops; SLS: 1/4, 1/8, 1/15, 1/30; CS: 59.94 to 250.27 Hz PF30: 1/30 to 1/2000 in 1/4 or 1/3 stops; SLS: \u00bc, 1/8; CS: 29.97 to 250.27 Hz 23.98p/PF24: 1/24 to 1/2000 in 1/4 or 1/3 stops; SLS: 1/3, 1/6, 1/12; CS: 23.97 to 250.27 Hz 50i: 1/50 to 1/2000 in 1/4 or 1/3 stops; SLS: 1/3, 1/6, 1/12 1/25; CS: 50.00 to 250.78 Hz PF25: 1/25 to 1/2000 in 1/4 or 1/3 stops; SLS: 1/3, 1/6, 1/12; CS: 25.00 to 250.78 Hz Shutter Angle Settings 59.94i: 360, 240, 216, 180, 120, 90, 60, 45, 30, 22.5, 15, 11.25 PF30: 360, 240, 216, 180, 120, 90, 60, 45, 30, 22.5, 15, 11.25 23.98p/PF24: 360, 345.6, 288, 240, 180, 172.8, 144, 120, 90, 86.4, 72, 60, 45, 30, 22.5, 15, 11.25 50i: 360, 300, 240, 180, 150, 120, 90, 60, 45, 30, 22.50, 15, 11.25 PF25: 360, 300, 240, 180, 150, 120, 90, 60, 45, 30, 22.50, 15, 11.25 Focus Control Settings Manual One-Shot AF Autofocus AF is dependent on interchangeable lenses Dual Pixel CMOS AF with Canon EF, EF-S, and Cinema lenses Video Signal System NTSC and PAL Recording Format Compression: MPEG-4, AVC/H.264 Maximum bit rate: 24 Mbps Color Space: 4:2:0 to SD card, 4:2:2 via uncompressed HDMI out HD to SD Conversion Format: MPEG-2; 9 Mbps Video Record Mode 24 Mbps LPCM: 1920 x 1080 at 60i, PF30, PF24, 24p, 50i, PF25 24 Mbps: 1920 x 1080 at 60i, PF30, PF24, 24p, 50i, PF25 17 Mbps: 1920 x 1080 at 60i, PF30, PF24, 24p, 50i, PF25 7 Mbps: 1440 x 1080 at 60i, PF30, PF24, 24p, 50i, PF25 Audio Audio Record Mode 24 Mbps mode: Linear PCM; 2-Channel; 16-Bit; 48 kHz All other modes: Dolby Digital AC3 Built-In Microphone Stereo microphone built in to top handle Audio Inputs 2 x XLR on top handle (Auto and Manual level settings) 1 x 3.5 mm terminal XLR Mic Trimming -12, -6, 0, +6, or +12 dB Limiter Available Audio Level Control Infinity to +18 dB, Automatic Separate controls for internal and externally connected microphones Phantom Power +48 V Headphone Output Level 16 Settings; volume is muted at lowest setting Built-in Speaker Yes; 16 level settings Tone 1 KHz tone available; -12, -18, or -20 dB Media Recording Media 2 x SD/SDHC/SDXC card slots File system: FAT 32 Maximum Recording Time 2GB SD Memory Card 24 Mbps 1920 x 1080: 10 minutes 17 Mbps 1920 x 1080: 15 minutes 7 Mbps 1440 x 1080: 35 minutes 4GB SD Memory Card 24 Mbps 1920 x 1080: 20 minutes 17 Mbps 1920 x 1080: 30 minutes 7 Mbps 1440 x 1080: 1 hours 10 minutes 6GB SD Memory Card 24 Mbps 1920 x 1080: 30 minutes 17 Mbps 1920 x 1080: 45 minutes 7 Mbps 1440 x 1080: 1 hour 45 minutes 8GB SD Memory Card 24 Mbps 1920 x 1080: 40 minutes 17 Mbps 1920 x 1080: 1 hour 7 Mbps 1440 x 1080: 2 hours 20 minutes 12GB SD Memory Card 24 Mbps 1920 x 1080: 1 hour 5 minutes 17 Mbps 1920 x 1080: 1 hour 30 minutes 7 Mbps 1440 x 1080: 3 hours 35 minutes 16GB SD Memory Card 24 Mbps 1920 x 1080: 1 hour 25 minutes 17 Mbps 1920 x 1080: 2 hours 5 minutes 7 Mbps 1440 x 1080: 4 hours 45 minutes 32GB SD Memory Card 24 Mbps 1920 x 1080: 2 hours 55 minutes 17 Mbps 1920 x 1080: 4 hours 10 minutes 7 Mbps 1440 x 1080: 9 hours 35 minutes 64GB SD Memory Card 24 Mbps 1920 x 1080: 5 hours 55 minutes 17 Mbps 1920 x 1080: 8 hours 20 minutes 7 Mbps 1440 x 1080: 19 hours 10 minutes Simultaneous REC./Relay REC. Yes LCD Display Type 3.5\" (8.9 cm) 640 x 480 922,000 pixels Adjustments Brightness, Contrast, Color, Sharpness, and Backlight (Normal or Bright) Viewfinder Type 0.24\" (0.61 cm) color 960x540 resolution 1,560,000 pixels Diopter Adjustment +2.0 to -5.5 Adjustments Brightness, Contrast, Color, and Backlight Inputs/Outputs HDMI Output 1 x Type A Timecode Embedded in HDMI output Audio Input 2 x Balanced 3-pin XLR on top handle unit 1 x 3.5 mm input jack on main body Headphone Jack 1 x 3.5mm stereo mini-jack Remote Terminal LANC compatible USB 1 x Mini-B USB 2.0 General White Balance Auto, Kelvin, Daylight, Tungsten, Set A, Set B White balance shift is available within Presets (-9 to +9) Waveform Monitor 2 Modes (Standard and RGB Component) Minimum Subject Illumination 59.94 Hz: 0.3 lux 50 Hz: 0.25 lux Language Support English, Japanese, Simplified Chinese, German, Spanish, French, Italian, Polish, Russian, Korean Power Supply 7.4 V DC (battery pack: BP-955) 8.4 V DC (DC IN) Operating Temperature Performance requirements 32 - 104\u00b0F (0 - 40\u00b0C), 85% relative humidity Operating requirements: 32 - 113\u00b0F (0 - 45\u00b0C), 60% relative humidity Dimensions (W x H x D) Body with Thumb Rest: 5.3 x 6.7 x 5.1 in (13.5 x 17 x 12.9 cm) Body with Grip: 7.2 x 6.7 x 5.1 in (18.2 x 17 x 12.9 cm) W/ Thumb Rest and handle: 5.6 x 11.1 x 9.3 in (14.2 x 28.1 x 23.6 cm) W/ Grip and handle: 7.2 x 11.1 x 9.3 in (18.2 x 28.1 x 23.6 cm) Weight Body only: approx. 2.2 lb (1.0 kg) Grip: approx. 8.1 oz (230 g) BP-955 Battery: 7.8 oz (220 g) Canon EF-S 18-135mm f/3.5-5.6 IS STM Lens Performance Focal Length 18 - 135mm Comparable  35mm Focal Length: 29 - 216 mm Aperture Maximum: f/3.5 - 5.6 Minimum: f/22.0 - 36.0 Camera Mount Type Canon EF-S Format Compatibility Canon (APS-C) Angle of View 74\u00b0\u00a020' - 11\u00b0\u00a030' Minimum Focus Distance 1.28'\u00a0(39 cm) Magnification 0.28x Elements/Groups 16/12 Features Image Stabilization Yes Autofocus Yes Tripod Collar No Physical Filter Thread Front:67 mm Dimensions (DxL) Approx. 3.02 x 3.78\" (76.6 x 96 mm) Weight 16.93 oz (480 g)",
    "magnification": "0.28x",
    "recordingformat": "Compression: MPEG-4, AVC/H.264 Maximum bit rate: 24 Mbps Color Space: 4:2:0 to SD card, 4:2:2 via uncompressed HDMI out HD to SD Conversion Format: MPEG-2; 9 Mbps",
    "meteringmodes": "Standard Center Weighted, Spotlight, Backlight",
    "aperture": "Maximum: f/3.5 - 5.6 Minimum: f/22.0 - 36.0",
    "dimensionswxhxd": "Body with Thumb Rest: 5.3 x 6.7 x 5.1 in (13.5 x 17 x 12.9 cm) Body with Grip: 7.2 x 6.7 x 5.1 in (18.2 x 17 x 12.9 cm) W/ Thumb Rest and handle: 5.6 x 11.1 x 9.3 in (14.2 x 28.1 x 23.6 cm) W/ Grip and handle: 7.2 x 11.1 x 9.3 in (18.2 x 28.1 x 23.6 cm)",
    "autofocus": "Yes",
    "tripodcollar": "No",
    "sensor": "Super 35mm CMOS (24.6 x 13.8 mm) (28.2 mm diagonal)",
    "audioinput": "2 x Balanced 3-pin XLR on top handle unit 1 x 3.5 mm input jack on main body",
    "maximumrecordingtime": "2GB SD Memory Card 24 Mbps 1920 x 1080: 10 minutes 17 Mbps 1920 x 1080: 15 minutes 7 Mbps 1440 x 1080: 35 minutes 4GB SD Memory Card 24 Mbps 1920 x 1080: 20 minutes 17 Mbps 1920 x 1080: 30 minutes 7 Mbps 1440 x 1080: 1 hours 10 minutes 6GB SD Memory Card 24 Mbps 1920 x 1080: 30 minutes 17 Mbps 1920 x 1080: 45 minutes 7 Mbps 1440 x 1080: 1 hour 45 minutes 8GB SD Memory Card 24 Mbps 1920 x 1080: 40 minutes 17 Mbps 1920 x 1080: 1 hour 7 Mbps 1440 x 1080: 2 hours 20 minutes 12GB SD Memory Card 24 Mbps 1920 x 1080: 1 hour 5 minutes 17 Mbps 1920 x 1080: 1 hour 30 minutes 7 Mbps 1440 x 1080: 3 hours 35 minutes 16GB SD Memory Card 24 Mbps 1920 x 1080: 1 hour 25 minutes 17 Mbps 1920 x 1080: 2 hours 5 minutes 7 Mbps 1440 x 1080: 4 hours 45 minutes 32GB SD Memory Card 24 Mbps 1920 x 1080: 2 hours 55 minutes 17 Mbps 1920 x 1080: 4 hours 10 minutes 7 Mbps 1440 x 1080: 9 hours 35 minutes 64GB SD Memory Card 24 Mbps 1920 x 1080: 5 hours 55 minutes 17 Mbps 1920 x 1080: 8 hours 20 minutes 7 Mbps 1440 x 1080: 19 hours 10 minutes",
    "waveformmonitor": "2 Modes (Standard and RGB Component)",
    "peripheralilluminationcorrection": "On supported Canon EF, EF-S, and Cinema lenses",
    "focallength": "18 - 135mm Comparable  35mm Focal Length: 29 - 216 mm",
    "brand": "Canon",
    "whitebalance": "Auto, Kelvin, Daylight, Tungsten, Set A, Set B White balance shift is available within Presets (-9 to +9)",
    "languagesupport": "English, Japanese, Simplified Chinese, German, Spanish, French, Italian, Polish, Russian, Korean",
    "miscellaneous": "No",
    "headphonejack": "1 x 3.5mm stereo mini-jack",
    "includes": "Canon EOS C100 Cinema EOS Camera Body with Dual Pixel CMOS AF Handle Unit BP-955 5200mAh Lithium-Ion Battery Pack CA-930 Compact Power Adapter Thumb Rest Tripod Base AC Cable DC Cable (for CA-930) Shoulder Strap SS-1200 CD-ROM with Data Import Utility Ver. 1.0 Limited 1-Year Warranty Canon EF-S 18-135mm f/3.5-5.6 IS STM Lens E-67 II 67mm Lens Cap Lens Dust Cap E (Rear) Limited 1-year Warranty",
    "colorfilter": "RGB Primary Color Filter (Bayer Array)",
    "signalsystem": "NTSC and PAL",
    "filterthread": "Front:67 mm",
    "angleofview": "74\u00b0\u00a020' - 11\u00b0\u00a030'",
    "diopteradjustment": "+2.0 to -5.5",
    "timecode": "Embedded in HDMI output",
    "lensmount": "Canon EF mount with EF contacts",
    "cameramounttype": "Canon EF-S",
    "name": "Canon EOS C100 Cinema EOS Camera with Dual Pixel CMOS AF and EF-S 18-135mm IS STM Lens",
    "settings": "Manual One-Shot AF",
    "type": "0.24\" (0.61 cm) color 960x540 resolution 1,560,000 pixels",
    "totalpixels": "Approx. 9.84 megapixels (4206 x 2340)",
    "exposuremodes": "Manual Push Auto Iris Control (metering system selection/AE shift possible)",
    "simultaneousrecrelayrec": "Yes",
    "dimensionsdxl": "Approx. 3.02 x 3.78\" (76.6 x 96 mm)",
    "gain": "Normal: -6 to 30 dB TBD Fine: 0 to 24 dB, in 0.5 dB increments",
    "processor": "DIGIC DV III",
    "elementsgroups": "16/12"
}