{
    "weight": "10 lbs (4.5kg)",
    "powerconsumption": "36W (w/LCD monitor OFF) 43W (SDI-IN, with AVC-Intra option, LCD Monitor ON)",
    "sensitivity": "F10 @2000 Lux",
    "audiosignalformat": "DVCPRO HD: 48kHz/16bits, 4CH DVCPRO 50: 48kHz/16bits, 4CH DVCPRO/DV: 48kHz/16bits, 2CH/4CH switchable",
    "category": "camera",
    "microphone": "Optional",
    "memorycardslot": "SD",
    "maximumrecordingtime": "On a single 32GB P2 card: DVCPRO HD: Approx. 32 min. DVCPRO 50: Approx. 64 min. DVCPRO/DV: Approx. 128 min.",
    "speaker": "None",
    "builtinfilters": "1: 3200K, 2: 5600K+1/8ND, 3: 5600K, 4: 5600K+1/64ND",
    "brand": "Panasonic",
    "attr1star": "2 stars3 stars4 stars5 stars",
    "signaltonoiseratio": "Not specified by manufacturer",
    "specifications": "Image Device 2/3\" 3CCD Resolution 1370 x 744 (1280 x 720 effective) Signal-to-Noise Ratio 54dB Horizontal Resolution 700 Sensitivity F10 @2000 Lux Minimum Illumination 0.007 Lux (F1.4, Super gain +48dB, Digital super gain +20 dB, Line mix gain +6dB) Vertical Smear Not specified by manufacturer Signal System 1080/59.94i, 30p, 24p 720/59.94p, 30p, 24p 480/59.94i, 30p, 24p 1080/50i, 25p 720/50p, 25p 576/50i, 25p Built-in Filters 1: 3200K, 2: 5600K+1/8ND, 3: 5600K, 4: 5600K+1/64ND LCD Monitor 3.5\" Speaker None Viewfinder Optional Microphone Optional Scan Matching Not specified by manufacturer Memory Card Slot SD Shutter Speed 1/60 (50Hz), 1/100 (59.94Hz), 1/120/, 1/250, 1/500, 1/1000, 1/2000 sec., and HALF Gain Selection -3/0/+3/+6/+9/+12/+15/+18/+21/+24/+27/+30 dB Digital Super Gain: +6/+10/+12/+15/+20 dB Maximum Recording Time On a single 32GB P2 card: DVCPRO HD: Approx. 32 min. DVCPRO 50: Approx. 64 min. DVCPRO/DV: Approx. 128 min. Audio Dynamic Range More than 85dB (1kHz, AWTD) Audio Signal Format DVCPRO HD: 48kHz/16bits, 4CH DVCPRO 50: 48kHz/16bits, 4CH DVCPRO/DV: 48kHz/16bits, 2CH/4CH switchable Audio Frequency Response 20Hz to 20kHz, \u00b11.0dB (reference level) Signal to Noise Ratio Not specified by manufacturer Input and Output Connectors HD/SD-SDI: BNC (x1 Output) Composite: BNC (x1 Output) Monitor: BNC (x1 Output) Genlock: BNC (x1 Input) Timecode: BNC (x1 Input, x1 Output) FireWire: IEEE 1394 (x1 Input, x1 Output) Audio IN (Ch1/2): 3-pin XLR (x2 Input) Mic IN: 5-pin XLR (x1 Input) Audio OUT (Ch1/2): 5-pin XLR (x1 Output) USB: USB 2.0 Power Requirements 12VDC Power Consumption 36W (w/LCD monitor OFF) 43W (SDI-IN, with AVC-Intra option, LCD Monitor ON) Operating Temperature 32 - 104\u00b0F, 0 - 40\u00b0C Dimensions (WxHxD) 5.4 x 8.5 x 12.5\" (13.7 x 21.6 x 31.7 cm) Weight 10 lbs (4.5kg)",
    "minimumillumination": "0.007 Lux (F1.4, Super gain +48dB, Digital super gain +20 dB, Line mix gain +6dB)",
    "miscellaneous": "No",
    "includes": "Panasonic AJ-HPX2000 2/3\" 3CCD P2 HD/SD Multi-Format Camcorder Shoulder Strap Front Audio Volume Knob 5-Year Warranty (1 Year + 4 years w/online registration)",
    "gainselection": "-3/0/+3/+6/+9/+12/+15/+18/+21/+24/+27/+30 dB Digital Super Gain: +6/+10/+12/+15/+20 dB",
    "signalsystem": "1080/59.94i, 30p, 24p 720/59.94p, 30p, 24p 480/59.94i, 30p, 24p 1080/50i, 25p 720/50p, 25p 576/50i, 25p",
    "dimensionswxhxd": "5.4 x 8.5 x 12.5\" (13.7 x 21.6 x 31.7 cm)",
    "lcdmonitor": "3.5\"",
    "shutterspeed": "1/60 (50Hz), 1/100 (59.94Hz), 1/120/, 1/250, 1/500, 1/1000, 1/2000 sec., and HALF",
    "powerrequirements": "12VDC",
    "operatingtemperature": "32 - 104\u00b0F, 0 - 40\u00b0C",
    "imagedevice": "2/3\" 3CCD",
    "name": "Panasonic AJ-HPX2000 2/3\" 3CCD P2 HD/SD Multi-Format Camcorder",
    "horizontalresolution": "700",
    "viewfinder": "Optional",
    "resolution": "1370 x 744 (1280 x 720 effective)"
}