{
    "audioformats": "UDF Mode (HD Recording) MPEG HD422 (MPEG-2 422P@HL): 4 channels, 48 kHz, 24-bit LPCM MPEG HD420 (1440x1080, MPEG-2 MP@HL): 4 channels, 48 kHz, 16-bit LPCM UDF Mode (SD Recording) DVCAM: 4 channels, 48 kHz, 16-bit FAT Mode (HD Recording) MPEG HD420 (1920 x 1080, MPEG-2 MP@HL): 2 channels, 48 kHz, 16-bit LPCM FAT Mode (SD Recording) DVCAM: 2 channels, 48 kHz, 16-bit LPCM",
    "powerconsumption": "12 W (while recording, EVF on, LCD off, IO Select off) 14 W (while recording, EVF on, LCD on, IO Select HD-SDI & HD HDMI)",
    "focus": "10 mm to infinity (wide), 800 mm to infinity (tele); auto/manual selectable",
    "recordingmedia": "2x slots for SBP-8/16/32 (GB) SxS ExpressCard/34 cards",
    "imagestabilization": "On/off selectable; shift lens",
    "storagetemperature": "-4 to 140\u00b0F (-20 to 60\u00b0C)",
    "attr1star": "2 stars3 stars4 stars5 stars",
    "microphone": "Omni-directional stereo electret condenser microphone",
    "imagingdevice": "1x 1/2.9\" Exmor CMOS sensor (1920 x 1080 effective picture elements)",
    "focallength": "5.4-54 mm (equivalent to 40-400 mm on a 35 mm lens)",
    "filterdiameter": "37 mm; pitch: 0.75 mm",
    "dimensionswxhxd": "Without Protrusions: 6.6 x 6.5 x 11.0\" (16.7 x 16.4 x 27.8 cm)",
    "gammacurve": "Selectable",
    "minimumillumination": "0.40 lux (typical) in 1920 x 1080i59.94 mode, f/1.8, +18 dB gain, with 64-frame accumulation, 100% video level 0.08 lux (typical) in 1920 x 1080i59.94 mode, f/1.8, +18 dB gain, with 64-frame accumulation, 50% video level",
    "category": "camera",
    "videoformats": "UDF Mode (HD Recording) MPEG HD422 (MPEG-2 422P@HL): CBR, 50 Mb/s MPEG HD420 (1440 x 1080, MPEG-2 MP@HL): HQ mode (VBR, maximum bit rate: 35 Mb/s) SP mode (CBR, 25 Mb/s) \u2013 playback only LP mode (VBR, maximum bit rate: 18 Mb/s) \u2013 playback only UDF Mode (SD Recording) DVCAM (CBR, 25 Mb/s) FAT Mode (HD Recording) MPEG HD420 (1920 x 1080, MPEG-2 MP@HL): HQ mode (VBR, maximum bit rate: 35 Mb/s) SP mode (CBR, 25 Mb/s) FAT Mode (SD Recording) DVCAM (CBR, 25 Mb/s)",
    "recordingframerate": "UDF HD422 Mode (MPEG-422P@HL, 50 Mb/s CBR): 1920 x 1080 at 59.94i, 50i, 29.97p, 25p, 23.98p 1280 x 720 at 59.94p, 50p, 23.98p DVCAM Mode: 720 x 480 at 59.94i, 29.97PsF 720 x 576 at 50i, 25PsF FAT HQ 1920 Mode (MPEG-2 MP@HL, 35 Mb/s VBR): 1920 x 1080 at 59.94i, 50i, 29.97p, 25p, 23.98p HQ 1440 Mode (MPEG-2 MP@HL, 35 Mb/s, VBR): 1440 x 1080 at 59.94i, 50i, 29.97p, 25p, 23.98p HQ 1280 Mode (MPEG-2 MP@HL, 35 Mb/s, VBR): 1280 x 720 at 59.94p, 50p, 29.97p, 25p, 23.98p SP 1440 Mode (MPEG-2 MP@H-14, 25 Mb/s CBR): 1440 x 1080 at 59.94i, 50i, 23.98p (2:3 pulldown) DVCAM Mode: 720 x 480 at 59.94i, 29.97PsF 720 x 576 at 50i, 25PsF",
    "specifications": "Imaging Device 1x 1/2.9\" Exmor CMOS sensor (1920 x 1080 effective picture elements) Lens 10x optical zoom fixed lens Focal Length 5.4-54 mm (equivalent to 40-400 mm on a 35 mm lens) Iris f/1.8-2.9; auto/manual selectable Focus 10 mm to infinity (wide), 800 mm to infinity (tele); auto/manual selectable Image Stabilization On/off selectable; shift lens Filter Diameter 37 mm; pitch: 0.75 mm Minimum Illumination 0.40 lux (typical) in 1920 x 1080i59.94 mode, f/1.8, +18 dB gain, with 64-frame accumulation, 100% video level 0.08 lux (typical) in 1920 x 1080i59.94 mode, f/1.8, +18 dB gain, with 64-frame accumulation, 50% video level Shutter Speed 1/32 to 1/2000 seconds Slow Shutter 2, 3, 4, 5, 6, 7, 8, 16, 32 and 64-frame accumulation Slow & Quick Motion Function 720p: 1-60 fps (1-50 fps in PAL area setting in UDF Mode) 1080p: 1-30 fps (1-25 fps in PAL area setting in UDF Mode) White Balance Preset (3200 K), Memory A, Memory B/ATW Gain -3, 0, 3, 6, 9, 12, 18 dB, auto gain control Gamma Curve Selectable Viewfinder 0.24\" color LCD: 392 (H) x 224 (V), 16:9 LCD Monitor 3.5\" color LCD monitor: 852 (H) x 3 (RGB) x 480 (V), 16:9 Microphone Omni-directional stereo electret condenser microphone Video Formats UDF Mode (HD Recording) MPEG HD422 (MPEG-2 422P@HL): CBR, 50 Mb/s MPEG HD420 (1440 x 1080, MPEG-2 MP@HL): HQ mode (VBR, maximum bit rate: 35 Mb/s) SP mode (CBR, 25 Mb/s) \u2013 playback only LP mode (VBR, maximum bit rate: 18 Mb/s) \u2013 playback only UDF Mode (SD Recording) DVCAM (CBR, 25 Mb/s) FAT Mode (HD Recording) MPEG HD420 (1920 x 1080, MPEG-2 MP@HL): HQ mode (VBR, maximum bit rate: 35 Mb/s) SP mode (CBR, 25 Mb/s) FAT Mode (SD Recording) DVCAM (CBR, 25 Mb/s) Audio Formats UDF Mode (HD Recording) MPEG HD422 (MPEG-2 422P@HL): 4 channels, 48 kHz, 24-bit LPCM MPEG HD420 (1440x1080, MPEG-2 MP@HL): 4 channels, 48 kHz, 16-bit LPCM UDF Mode (SD Recording) DVCAM: 4 channels, 48 kHz, 16-bit FAT Mode (HD Recording) MPEG HD420 (1920 x 1080, MPEG-2 MP@HL): 2 channels, 48 kHz, 16-bit LPCM FAT Mode (SD Recording) DVCAM: 2 channels, 48 kHz, 16-bit LPCM Recording Frame Rate UDF HD422 Mode (MPEG-422P@HL, 50 Mb/s CBR): 1920 x 1080 at 59.94i, 50i, 29.97p, 25p, 23.98p 1280 x 720 at 59.94p, 50p, 23.98p DVCAM Mode: 720 x 480 at 59.94i, 29.97PsF 720 x 576 at 50i, 25PsF FAT HQ 1920 Mode (MPEG-2 MP@HL, 35 Mb/s VBR): 1920 x 1080 at 59.94i, 50i, 29.97p, 25p, 23.98p HQ 1440 Mode (MPEG-2 MP@HL, 35 Mb/s, VBR): 1440 x 1080 at 59.94i, 50i, 29.97p, 25p, 23.98p HQ 1280 Mode (MPEG-2 MP@HL, 35 Mb/s, VBR): 1280 x 720 at 59.94p, 50p, 29.97p, 25p, 23.98p SP 1440 Mode (MPEG-2 MP@H-14, 25 Mb/s CBR): 1440 x 1080 at 59.94i, 50i, 23.98p (2:3 pulldown) DVCAM Mode: 720 x 480 at 59.94i, 29.97PsF 720 x 576 at 50i, 25PsF Recording Media 2x slots for SBP-8/16/32 (GB) SxS ExpressCard/34 cards Recording Time UDF Mode (HD Recording) 50 Mb/s MPEG HD422 (MPEG-2 422P@HL): Approx. 120 min with SBS-64G1A (64 GB) memory card 35 Mb/s VBR, HQ Mode MPEG HD420 (1440x1080, MPEG-2 MP@HL): Approx. 180 min with SBS-64G1A (64 GB) memory card UDF Mode (SD Recording) 25 Mb/s DVCAM: Approx. 220 min with SBS-64G1A (64 GB) memory card FAT Mode (HD Recording) 35 Mb/s VBR, HQ Mode - MPEG HD420 (MPEG-2 MP@HL): Approx. 200 min with SBS-64G1A (64 GB) memory card 25 Mb/s CBR, SP Mode \u2013 MPEG HD 420 (MPEG-2 MP@HL-14): Approx. 280 min with SBS-64G1A (64 GB) memory card FAT Mode (SD Recording) 25 Mb/s DVCAM: Approx. 220 min with SBS-64G1A (64 GB) memory card Battery Operation Times Approx. 240 min with BP-U60 battery ( sold separately ) I/O 1x BNC for genlock input (switchable to HD-Y / composite video output), 1.0 Vp-p, 75\u03a9 1x BNC for timecode input (switchable to timecode output), SMPTE-12M-2008, 0.5-1.8 Vp-p, 10k\u03a9 2x XLRs for audio input: 3-pin female; line, mic, mic +48 V selectable 1x BNC for HD/SD-SDI output: SMPTE 292M/259M 1x A/V multi-connector (10-pin) for audio output: -10 dBu (reference level), 47 k\u03a9 1x Stereo mini-jack for earphone output 1x Monitor speaker: monaural, 250 mW 1x 4-pin IEEE 1394 i.Link for HDV (HDV 1080i) / DV input/output, S400 1x USB 2.0 (device), mini-B type 1x HDMI output (type A) 1x DC jack for DC input Power Requirements 12 V DC Power Consumption 12 W (while recording, EVF on, LCD off, IO Select off) 14 W (while recording, EVF on, LCD on, IO Select HD-SDI & HD HDMI) Operating Temperature 32 to 104\u00b0F (0 to 40\u00b0C) Storage Temperature -4 to 140\u00b0F (-20 to 60\u00b0C) Operating Humidity 10-90% (relative humidity) Dimensions (W x H x D) Without Protrusions: 6.6 x 6.5 x 11.0\" (16.7 x 16.4 x 27.8 cm) Weight (Approx.) Body Only: 3.3 lb (1.5 kg) With Hood, Eyepiece, BP-U30 Battery & an SxS Card: 3.9 lb (1.8 kg)",
    "brand": "Sony",
    "miscellaneous": "No",
    "includes": "Sony PMW-100 XDCAM HD422 Handheld Camcorder BP-U30 Lithium-Ion Battery BC-U1 Battery Charger Shoulder Strap Lens Hood Lens Cap Infrared Remote Commander AV Connecting Cable USB Cable CR2032 Lithium Battery for Backup CR2025 Lithium Battery for IR Remote Utility Software CD-ROM 1 Year Limited Warranty (Labor)",
    "lens": "10x optical zoom fixed lens",
    "operatingtemperature": "32 to 104\u00b0F (0 to 40\u00b0C)",
    "gain": "-3, 0, 3, 6, 9, 12, 18 dB, auto gain control",
    "weightapprox": "Body Only: 3.3 lb (1.5 kg) With Hood, Eyepiece, BP-U30 Battery & an SxS Card: 3.9 lb (1.8 kg)",
    "lcdmonitor": "3.5\" color LCD monitor: 852 (H) x 3 (RGB) x 480 (V), 16:9",
    "shutterspeed": "1/32 to 1/2000 seconds",
    "powerrequirements": "12 V DC",
    "slowshutter": "2, 3, 4, 5, 6, 7, 8, 16, 32 and 64-frame accumulation",
    "iris": "f/1.8-2.9; auto/manual selectable",
    "name": "Sony PMW-100 XDCAM HD422 Handheld Camcorder",
    "operatinghumidity": "10-90% (relative humidity)",
    "viewfinder": "0.24\" color LCD: 392 (H) x 224 (V), 16:9",
    "recordingtime": "UDF Mode (HD Recording) 50 Mb/s MPEG HD422 (MPEG-2 422P@HL): Approx. 120 min with SBS-64G1A (64 GB) memory card 35 Mb/s VBR, HQ Mode MPEG HD420 (1440x1080, MPEG-2 MP@HL): Approx. 180 min with SBS-64G1A (64 GB) memory card UDF Mode (SD Recording) 25 Mb/s DVCAM: Approx. 220 min with SBS-64G1A (64 GB) memory card FAT Mode (HD Recording) 35 Mb/s VBR, HQ Mode - MPEG HD420 (MPEG-2 MP@HL): Approx. 200 min with SBS-64G1A (64 GB) memory card 25 Mb/s CBR, SP Mode \u2013 MPEG HD 420 (MPEG-2 MP@HL-14): Approx. 280 min with SBS-64G1A (64 GB) memory card FAT Mode (SD Recording) 25 Mb/s DVCAM: Approx. 220 min with SBS-64G1A (64 GB) memory card",
    "whitebalance": "Preset (3200 K), Memory A, Memory B/ATW"
}