{
    "weight": "5.3 lbs (2.4kg)",
    "powerconsumption": "17W (recording)",
    "colortemperature": "3200K/5600K preset, Ach, Bch",
    "audiosignalformat": "Dolby Digital/2 channels 48kHz, 16 bit, 384kbps HDMI Output: Linear PCM",
    "attr1star": "2 stars3 stars4 stars5 stars",
    "memorycardslot": "2 slots (for left/right)",
    "dimensionswxhxd": "6.25 x 7.4 x 18.7\" (15.8 x 18.7 x 47.4 cm)",
    "brand": "Panasonic",
    "category": "camera",
    "specifications": "Image Device (2) 1/4.1 type 3MOS Sensors Lens Motorized 5.6x zoom, F1.8 (WIDE) to F2.4 (TELE) Focal Length (f=4.2mm to 23.5mm) (35mm equivalent: 47.1mm to 264mm), 16:9 Picture Elements Effective 2,070,000 pixels x 3 (16:9) x 2 Signal System NTSC/PAL AVCHD MPEG-4 AVC/H.264 Compression 1080/60i, 1080/30p (over 60i) 1080/24p (native), 720/60p 1080/50i, 1080/25p (over 50i), 720/50p Audio Signal Format Dolby Digital/2 channels 48kHz, 16 bit, 384kbps HDMI Output: Linear PCM Minimum Illumination Not specified by manufacturer Minimum Object Distance (M.O.D.) Approx. 47.25\" (1.2m), all zoom range Color Temperature 3200K/5600K preset, Ach, Bch Data Rate Approx. 21 Mbps (VBR/PH mode) Recording Time Approx. 180 min. (32 GB SDHC Card) Recording Media SD Memory Card: 512 MB, 1 GB, 2 GB (FAT12 and FAT16) SDHC Memory Card: 4 GB, 6 GB, 8 GB, 12 GB, 16 GB, 32 GB (FAT32) Memory Card Slot 2 slots (for left/right) Shutter Speed 59.9Hz, Preset 60i, 60p mode: 1/60 sec., 1/100 sec., 1/120 sec., 1/250 sec. 30p mode: 1/30 sec., 1/50 sec., 1/60 sec., 1/120 sec., 1/250 sec. 24p mode: 1/24 sec., 1/50 sec., 1/60 sec., 1/120 sec., 1/250 sec. 59.9Hz, Synchro Scan 60i, 60p mode: 1/60.0 sec. to 1/250.0 sec. 30p mode: 1/30.0 sec. to 1/250.0 sec. 24p mode: 1/24.0 sec. to 1/250.0 sec. 50Hz, Preset 50i, 50p mode: 1/50 sec., 1/60 sec., 1/120 sec., 1/250 sec. 25p mode: 1/25 sec., 1/50 sec., 1/60 sec., 1/120 sec., 1/250 sec. 50Hz, Synchro Scan 50i, 50p mode: 1/50.0 sec. to 1/250.0 sec. 25p mode: 1/25.0 sec. to 1/250.0 sec. Gain Selection 0 to +24dB (variable in 1dB steps) LCD Monitor 3.2\" Color LCD (approx 921,000 pixels), 16:9 Viewfinder 0.45\" Color LCD (approx. 1.23MP), 16:9 Built-in Speaker 20mm (round) Input and Output Connectors HD-SDI: BNC (x2 Output) HDMI: HDMI 1.4a (x1 Output) Line/Mic: 3-pin XLR (x2 Input) Headphone: 3.5mm Mini (x1 Output) Remote: 2.5mm x2, 3.5mm x1 Power Requirements 7.2VDC (battery) 7.9VDC (AC adapter) Power Consumption 17W (recording) Operating Temperature 32 to 104\u00b0F (0 to 40\u00b0C) Dimensions (WxHxD) 6.25 x 7.4 x 18.7\" (15.8 x 18.7 x 47.4 cm) Weight 5.3 lbs (2.4kg)",
    "minimumillumination": "Not specified by manufacturer",
    "miscellaneous": "No",
    "includes": "Panasonic AG-3DA1 Integrated Twin-Lens 3D Camcorder AC Adapter w/Cable Battery Battery Charger w/Cable Microphone Holder Eyecup Lens Cap 2 x Terminal Cover Screw Spacer CD-ROM 1 Year Warranty (3 Years after Registration)",
    "gainselection": "0 to +24dB (variable in 1dB steps)",
    "signalsystem": "NTSC/PAL AVCHD MPEG-4 AVC/H.264 Compression 1080/60i, 1080/30p (over 60i) 1080/24p (native), 720/60p 1080/50i, 1080/25p (over 50i), 720/50p",
    "datarate": "Approx. 21 Mbps (VBR/PH mode)",
    "minimumobjectdistancemod": "Approx. 47.25\" (1.2m), all zoom range",
    "lcdmonitor": "3.2\" Color LCD (approx 921,000 pixels), 16:9",
    "shutterspeed": "59.9Hz, Preset 60i, 60p mode: 1/60 sec., 1/100 sec., 1/120 sec., 1/250 sec. 30p mode: 1/30 sec., 1/50 sec., 1/60 sec., 1/120 sec., 1/250 sec. 24p mode: 1/24 sec., 1/50 sec., 1/60 sec., 1/120 sec., 1/250 sec. 59.9Hz, Synchro Scan 60i, 60p mode: 1/60.0 sec. to 1/250.0 sec. 30p mode: 1/30.0 sec. to 1/250.0 sec. 24p mode: 1/24.0 sec. to 1/250.0 sec. 50Hz, Preset 50i, 50p mode: 1/50 sec., 1/60 sec., 1/120 sec., 1/250 sec. 25p mode: 1/25 sec., 1/50 sec., 1/60 sec., 1/120 sec., 1/250 sec. 50Hz, Synchro Scan 50i, 50p mode: 1/50.0 sec. to 1/250.0 sec. 25p mode: 1/25.0 sec. to 1/250.0 sec.",
    "powerrequirements": "7.2VDC (battery) 7.9VDC (AC adapter)",
    "operatingtemperature": "32 to 104\u00b0F (0 to 40\u00b0C)",
    "lens": "Motorized 5.6x zoom, F1.8 (WIDE) to F2.4 (TELE) Focal Length (f=4.2mm to 23.5mm) (35mm equivalent: 47.1mm to 264mm), 16:9",
    "imagedevice": "(2) 1/4.1 type 3MOS Sensors",
    "name": "Panasonic AG-3DA1 Integrated Twin-Lens 3D Camcorder",
    "pictureelements": "Effective 2,070,000 pixels x 3 (16:9) x 2",
    "recordingmedia": "SD Memory Card: 512 MB, 1 GB, 2 GB (FAT12 and FAT16) SDHC Memory Card: 4 GB, 6 GB, 8 GB, 12 GB, 16 GB, 32 GB (FAT32)",
    "builtinspeaker": "20mm (round)",
    "viewfinder": "0.45\" Color LCD (approx. 1.23MP), 16:9",
    "recordingtime": "Approx. 180 min. (32 GB SDHC Card)"
}