{
    "weight": "About 9.9 bs (4.5 kg) About 16.7 lbs (7.6 kg) in full-operation",
    "powerconsumption": "36 W",
    "sensitivity": "F10.0 at 2000 Lux, 89.9% reflect",
    "powersupply": "DC 12 V (11 V to 17 V)",
    "audioin": "XLR-3pin x 2 (CH1/CH2), LINE/MIC/MIC+48 V switchable LINE: -3/0/+4 dBu, MIC: -60/-50 dBu, MIC+48V: -60/-50 dBu,",
    "horizontalresolution": "700 TV lines at centre",
    "video": "Sampling Frequency: Y: 74.1758 MHz (59.94Hz), 74.25MHz (50Hz) PB/PR: 37.0879 MHz (59.94Hz), 37.125 MHz (50Hz) Quantization: 8 bits Compression Method: DCT and Variable-length Coding Compression Ratio: 1/6.3 (1080-50i/1080-25p), 1/6.7 (others) Error Correction: Reed Solomon Product Code Bit Rate: 100 Mbps Band Width: Y: 20MHz, PB/PR: 10MHz",
    "micin": "XLR-5pin x 1, Stereo, -40/-50 dBu, Phantom +48 V",
    "attr1star": "2 stars3 stars4 stars5 stars",
    "dimensions": "5-1/16\" x 10-11/16\" x 13\" (129 x 271 x 329 mm)",
    "dcin": "XLR-4pin, DC11V to 17 V",
    "name": "Panasonic AJ-HDX900 2/3\" 3-CCD DVCPRO HD Camcorder",
    "minimumillumination": "0.032 Lux at +36 dB +20 dB +6 dB Gain",
    "gps": "6-pin x 1, for AJ-GPS900G",
    "category": "camera",
    "specifications": "Power Supply: DC 12 V (11 V to 17 V) Power Consumption: 36 W Operating Humidity: 10 % to 85 % Operating Temperature: 32\u00b0F to 104\u00b0F (0\u00b0C to +40\u00b0C) Dimensions: 5-1/16\" x 10-11/16\" x 13\" (129 x 271 x 329 mm) Weight: About 9.9 bs (4.5 kg) About 16.7 lbs (7.6 kg) in full-operation Continuous Rec Time: About 120 min. with Anton/Bauer Dionic 80 CCD Elements: 2/3\"h HD Progressive CCD Picture Elements: Total: 1370 (H) x 744 (V), Effective: 1280 (H) x 720(V) Optical System: F 1.4 prism system Optical Filters: CC: Cross, 3200K, 4300K, 6300K ND: CLEAR, 1/4ND, 1/16ND, 1/64ND Quantization: 14 bits Sampling Frequency: 74.1758MHz (59.94Hz), 74.25MHz (50Hz) Programmable Gain: -3/0/+3/+6/+9/+12/+15/+18/+21/+24/+27/+30 dB Super Gain: +30/+36 dB Digital Super Gain: +6/+10/+12/+15/+20 dB Line Mix Gain: +6 dB (On/Off) Shutter Speed: 1/60 (50Hz), 1/100 (59.94Hz), 1/120, 1/250, 1/500, 1/1000, 1/2000 sec. and HALF Syncro Scan Shutter: 1/60.3 to 1/249.8 sec. (59.94i, 59.94p) 1/30.2 to 1/249.8 sec. (29.97p) 1/24.1 to 1/249.8 sec. (23.98p, 23.98pA) 1/50.2 to 1/209.5 sec. (50i, 50p) 1/25.2 to 1/209.5 sec. (25p) Sensitivity: F10.0 at 2000 Lux, 89.9% reflect Minimum Illumination: 0.032 Lux at +36 dB +20 dB +6 dB Gain Video S/N: 54 dB (typical) Horizontal Resolution: 700 TV lines at centre Registration Error: Less than 0.03 % (whole zone, without lens distortion) Lens Mount: 2/3\" Bayonet type VTR Section: Recording Format: DVCPRO HD-LP Tape: 6.35 mm wide metal tape (DVCPRO HD M cassette) Tape Speed: 67.640 mm/s (59.94Hz), 67.708 mm/s (50Hz) Max Rec Time: Approx. 33 min (using AJ-HP33EMG) FF/REW Time: About 1.5 min. (using AJ-HP33EMG) VIDEO: Sampling Frequency: Y: 74.1758 MHz (59.94Hz), 74.25MHz (50Hz) PB/PR: 37.0879 MHz (59.94Hz), 37.125 MHz (50Hz) Quantization: 8 bits Compression Method: DCT and Variable-length Coding Compression Ratio: 1/6.3 (1080-50i/1080-25p), 1/6.7 (others) Error Correction: Reed Solomon Product Code Bit Rate: 100 Mbps Band Width: Y: 20MHz, PB/PR: 10MHz AUDIO: Sampling Frequency: 48 kHz (sync. with video) Quantization: 16 bits Frequency Response: 20 Hz to 20 kHz, \u00b11.0 dB (reference level) Dynamic Range: More than 85 dB (1kHz, AWTD) Distortion: Within 0.1% (1 kHz, reference level) Wow & Flutter: Below measurable limit Head Room: 20 dB (AJ-HDX900P), 18 dB (AJ-HDX900E) MIC IN: XLR-5pin x 1, Stereo, -40/-50 dBu, Phantom +48 V Audio IN: XLR-3pin x 2 (CH1/CH2), LINE/MIC/MIC+48 V switchable LINE: -3/0/+4 dBu, MIC: -60/-50 dBu, MIC+48V: -60/-50 dBu, Wireless In: 25pin D-sub, -40 dBu GENLOCK IN: BNC x 1, 1.0 Vp-p, 75\u03a9 Timecode In: BNC x 1, 0.5 to 7.0 Vp-p, high impedance VIDEO OUT: BNC x 1, HD-SDI/SD-SDI/Compsite switchable HD-SDI/SD-SDI: 0.8 Vp-p, 75\u03a9 Composite: 1.0 Vp-p, 75\u03a9 Monitor Out: BNC x 1, HD-SDI/HD-Y switchable HD-SDI: 0.8Vp-p, 75\u03a9, HD-Y: 1.0Vp-p, 75\u03a9 Audio Out: XLR-5pin x 1, CH1/CH2, -3/0/+4 dBu Timecode Out: BNC x 1, 2.0 Vp-p, low impedance Phones: Stereo mini jack x 2 Lens: 12-pin x 1 Remote: 10-pin x 1, for AJ-RC10G DC In: XLR-4pin, DC11V to 17 V DC Out: DC Out: 4-pin x 1, DC11V to 17 V, max. 1.5 A EVF: 20-pin x 1 (59.94Hz/50Hz switchable) DVCPRO: 6-pin x 1, IEEE 1394 standard digital Interface GPS: 6-pin x 1, for AJ-GPS900G Receiver: UniSlotR Wireless Receiver *DVCPRO HD-LP tapes recorded with the AJ-HDX900 cannot be played on a conventional DVCPRO HD VTR (AJ-HD150/AJ-HD130DC).",
    "brand": "Panasonic",
    "miscellaneous": "No",
    "includes": "1-Year Warranty",
    "lens": "12-pin x 1",
    "lensmount": "2/3\" Bayonet type",
    "shutterspeed": "1/60 (50Hz), 1/100 (59.94Hz), 1/120, 1/250, 1/500, 1/1000, 1/2000 sec. and HALF",
    "videoout": "BNC x 1, HD-SDI/SD-SDI/Compsite switchable HD-SDI/SD-SDI: 0.8 Vp-p, 75\u03a9 Composite: 1.0 Vp-p, 75\u03a9",
    "audioout": "XLR-5pin x 1, CH1/CH2, -3/0/+4 dBu",
    "remote": "10-pin x 1, for AJ-RC10G",
    "operatingtemperature": "32\u00b0F to 104\u00b0F (0\u00b0C to +40\u00b0C)",
    "pictureelements": "Total: 1370 (H) x 744 (V), Effective: 1280 (H) x 720(V)",
    "operatinghumidity": "10 % to 85 %",
    "opticalsystem": "F 1.4 prism system",
    "evf": "20-pin x 1 (59.94Hz/50Hz switchable)",
    "receiver": "UniSlotR Wireless Receiver *DVCPRO HD-LP tapes recorded with the AJ-HDX900 cannot be played on a conventional DVCPRO HD VTR (AJ-HD150/AJ-HD130DC).",
    "audio": "Sampling Frequency: 48 kHz (sync. with video) Quantization: 16 bits Frequency Response: 20 Hz to 20 kHz, \u00b11.0 dB (reference level) Dynamic Range: More than 85 dB (1kHz, AWTD) Distortion: Within 0.1% (1 kHz, reference level) Wow & Flutter: Below measurable limit Head Room: 20 dB (AJ-HDX900P), 18 dB (AJ-HDX900E)"
}