{
    "weight": "Less than 3 lb / 1.4 kg (includes camera body, XLR handle unit, NP-FV70 battery, lens hood, and large eye-cup)",
    "powerconsumption": "Approx. 5.5 W (while recording with viewfinder and XAVC HD 1080/60i 50Mbps) Approx. 5.8 W (while recording with LCD and XAVC HD 1080/60i 50Mbps)",
    "mediacardslots": "2 x SD",
    "attr1star": "2 stars3 stars4 stars5 stars",
    "compression": "MPEG-4 AVC/H.264 Long-GOP 50 35 25",
    "recordingplaybacktime": "XAVC-L LPCM 2ch 50Mbps: approx. 120 min with 64 GB memory card LPCM 2ch 35Mbps: approx. 170 min with 64 GB memory card LPCM 2ch 25Mbps: approx. 220 min with 64 GB memory card AVCHD LPCM 2ch PS Mode: approx. 290 min with 64 GB memory card / 145 min with 32 GB memory card LPCM 2ch FX Mode: approx. 340 min with 64 GB memory card / 170 min with 32 GB memory card LPCM 2ch FH Mode: approx. 450 min with 64 GB memory card / 225 min with 32 GB memory card DV approx. 280 min with 64 GB memory card / 140 min with 32 GB memory card",
    "recordingformat": "XAVC Long XAVC-L 50: VBR, maximum 50Mbps, MPEG-4 H.264/AVC - LPCM 24-bit, 48kHz, 2 channels XAVC-L 35: VBR, maximum 35Mbps, MPEG-4 H.264/AVC - LPCM 24-bit, 48kHz, 2 channels XAVC-L 25: VBR, maximum 25Mbps, MPEG-4 H.264/AVC - LPCM 24-bit, 48kHz, 2 channels AVCHD VBR: maximum 28Mbps,m MPEG-4 H.264/AVC LPCM: 24-bit, 48kHz, 2 channels DVCAM CBR: 25Mb/s LPCM: 16-bit, 48kHz, 2 channels",
    "dimensionswxhxd": "4.8 x / 4.1 x 10.8\" / 120.7 x 103.5 x 274.3 mm ( with lens hood and eyecup)",
    "sensor": "1\" Exmor R CMOS 20MP sensor 14.2MP effective pixels",
    "category": "camera",
    "recordingframerate": "XAVC-L 50 1920 x 1080i 59.94, 50 1920 x 1080p 29.97, 23.98, 25p 1280 x 720p 59.94, 50 XAVC-L 35 > 1920 x 1080p 29.97, 23.98, 25p XAVC-L 25 1920 x 1080i 59.94, 50 AVCHD 1920 x 1080i 59.94, 50 1920 x 1080p 59.94, 50, 29.97, 23.98, 25p 1280 x 720p 59.94, 50 DV 720x480/59.94i 720x576/50i",
    "specifications": "Sensor 1\" Exmor R CMOS 20MP sensor 14.2MP effective pixels Lens 12x optical zoom 24x Clear Image Zoom 48x with digital extender Aperture: f/2.8 -f/4.5 Filter Built-In Optical 1: Clear 2: 1/4ND 3: 1/16ND 4: 1/64ND Video Sampling 4:2:2 10-bit Gain -3, 0, 3, 6, 9, 12,15, 18, 21, 24, 27, 30, 33 dB, AGC White Balance Preset (Indoor:3200K, Outdoor:5600K\u00b17 steps, Color temparature set range:2300-15000K), Onepush A, B, Auto selectable Compression MPEG-4 AVC/H.264 Long-GOP 50 35 25 Viewfinder Built-In LCD: 3.5\" type LCD (approx. 1.56M dots) Viewfinder: 0.39\" type OLED (approx. 1.44M dots) Recording Format XAVC Long XAVC-L 50: VBR, maximum 50Mbps, MPEG-4 H.264/AVC - LPCM 24-bit, 48kHz, 2 channels XAVC-L 35: VBR, maximum 35Mbps, MPEG-4 H.264/AVC - LPCM 24-bit, 48kHz, 2 channels XAVC-L 25: VBR, maximum 25Mbps, MPEG-4 H.264/AVC - LPCM 24-bit, 48kHz, 2 channels AVCHD VBR: maximum 28Mbps,m MPEG-4 H.264/AVC LPCM: 24-bit, 48kHz, 2 channels DVCAM CBR: 25Mb/s LPCM: 16-bit, 48kHz, 2 channels Recording Frame Rate XAVC-L 50 1920 x 1080i 59.94, 50 1920 x 1080p 29.97, 23.98, 25p 1280 x 720p 59.94, 50 XAVC-L 35 > 1920 x 1080p 29.97, 23.98, 25p XAVC-L 25 1920 x 1080i 59.94, 50 AVCHD 1920 x 1080i 59.94, 50 1920 x 1080p 59.94, 50, 29.97, 23.98, 25p 1280 x 720p 59.94, 50 DV 720x480/59.94i 720x576/50i Recording/Playback Time XAVC-L LPCM 2ch 50Mbps: approx. 120 min with 64 GB memory card LPCM 2ch 35Mbps: approx. 170 min with 64 GB memory card LPCM 2ch 25Mbps: approx. 220 min with 64 GB memory card AVCHD LPCM 2ch PS Mode: approx. 290 min with 64 GB memory card / 145 min with 32 GB memory card LPCM 2ch FX Mode: approx. 340 min with 64 GB memory card / 170 min with 32 GB memory card LPCM 2ch FH Mode: approx. 450 min with 64 GB memory card / 225 min with 32 GB memory card DV approx. 280 min with 64 GB memory card / 140 min with 32 GB memory card Outputs 1 x 3G-SDI 1 x HDMI 1 x Multi/Micro USB (Requires optional breakout cable) Audio 2 x 3-pin XLR female Media Card Slots 2 x SD Wireless NFC Wireless LAN Power Consumption Approx. 5.5 W (while recording with viewfinder and XAVC HD 1080/60i 50Mbps) Approx. 5.8 W (while recording with LCD and XAVC HD 1080/60i 50Mbps) Battery Operating Time approx. 200 min. with NP-FV70 battery (while playing with LCD, XAVC 1080/60i, 50Mbps) approx. 120min. with NP-FV70 battery (while recording with LCD, XAVC 1080/60i, 50Mbps) Temperature Operating 32 to 104\u00b0F / 0 to 40\u00b0C Storage -4 to 140\u00b0F / -20 to 60\u00b0C Dimensions (W x H x D) 4.8 x / 4.1 x 10.8\" / 120.7 x 103.5 x 274.3 mm ( with lens hood and eyecup) Weight Less than 3 lb / 1.4 kg (includes camera body, XLR handle unit, NP-FV70 battery, lens hood, and large eye-cup)",
    "outputs": "1 x 3G-SDI 1 x HDMI 1 x Multi/Micro USB (Requires optional breakout cable)",
    "brand": "Sony",
    "miscellaneous": "No",
    "includes": "Sony PXW-X70 Professional XDCAM Compact Camcorder XLR Handle Unit with Microphone Holder Lens Hood Lens Cap Eyecup Accessory Shoe Kit USB Cable Rechargeable Battery Pack (NP-FV70) AC Adapter AC-L200D AC Power Cord Wireless Remote Commander (RMT-845) CR2025 Battery Limited 1-Year Warranty",
    "lens": "12x optical zoom 24x Clear Image Zoom 48x with digital extender Aperture: f/2.8 -f/4.5",
    "gain": "-3, 0, 3, 6, 9, 12,15, 18, 21, 24, 27, 30, 33 dB, AGC",
    "temperature": "Operating 32 to 104\u00b0F / 0 to 40\u00b0C Storage -4 to 140\u00b0F / -20 to 60\u00b0C",
    "wireless": "NFC Wireless LAN",
    "name": "Sony PXW-X70 Professional XDCAM Compact Camcorder",
    "filter": "Built-In Optical 1: Clear 2: 1/4ND 3: 1/16ND 4: 1/64ND",
    "batteryoperatingtime": "approx. 200 min. with NP-FV70 battery (while playing with LCD, XAVC 1080/60i, 50Mbps) approx. 120min. with NP-FV70 battery (while recording with LCD, XAVC 1080/60i, 50Mbps)",
    "viewfinder": "Built-In LCD: 3.5\" type LCD (approx. 1.56M dots) Viewfinder: 0.39\" type OLED (approx. 1.44M dots)",
    "audio": "2 x 3-pin XLR female",
    "whitebalance": "Preset (Indoor:3200K, Outdoor:5600K\u00b17 steps, Color temparature set range:2300-15000K), Onepush A, B, Auto selectable"
}