{
    "pictbridge": "No",
    "lightexposurecontrol": "Program AE",
    "flashrangetele": "2 - 5.9m",
    "focallengthrangeff": "4.3 - 215 mm",
    "weight": "623g",
    "lightexposuremodes": "Aperture priority AE, Auto, Manual, Shutter priority AE",
    "macrofocusingrangewide": "0.01 - ?",
    "isosensitivity": "80, 1600, 3200, 12800",
    "stillimageresolutions": "5184 x 3888, 4896 x 3672, 4320 x 3240, 4224 x 3168, 4000 x 3000, 3648 x 2736, 3456 x 2592, 3264 x 2448, 3072 x 2304, 2592 x 1944, 2048 x 1536, 640 x 480, 1920 x 1080, 4896 x 2752, 4608 x 2592, 4320 x 2432, 4000 x 2248, 4000 x 2672, 3648 x 2432, 3456 x 2304",
    "weightincludingbattery": "650g",
    "opticalviewfinder": "No",
    "megapixel": "20.4 MP",
    "camerashutterspeedmax": "30s",
    "maximumimageresolution": "5184 x 3888 pixels",
    "lightexposurecorrection": "\u00b1 2EV (1/3EV step)",
    "compatiblememorycards": "MS Duo, MS PRO Duo, MS Pro-HG Duo, SD, SDHC, SDXC",
    "batterytype": "NP-BX1",
    "manualfocus": "Yes",
    "avoutput": "No",
    "sku": "DSCHX300B.CEH",
    "hdmiconnectortype": "Micro",
    "facedetection": "Yes",
    "display": "TFT",
    "lightmetering": "Centre-weighted, Spot",
    "specification": "Picture quality Image sensor size 25.4/58.4 mm (1/2.3\") Supported aspect ratios 3:2, 16:9 Still image resolution(s) 5184 x 3888, 4896 x 3672, 4320 x 3240, 4224 x 3168, 4000 x 3000, 3648 x 2736, 3456 x 2592, 3264 x 2448, 3072 x 2304, 2592 x 1944, 2048 x 1536, 640 x 480, 1920 x 1080, 4896 x 2752, 4608 x 2592, 4320 x 2432, 4000 x 2248, 4000 x 2672, 3648 x 2432, 3456 x 2304 Maximum image resolution 5184 x 3888 pixels Sensor type CMOS Camera type Compact Megapixel 20.4 MP Lens system Focal length range (f-f) 4.3 - 215 mm Minimum focal length (35mm film equiv) 2.4 cm Maximum focal length (35mm film equiv) 130 cm Minimum aperture 2.8 Maximum aperture 6.3 Digital zoom 100x Optical zoom 50x Focusing Focus adjustment Auto/Manual Auto focusing (AF) modes Centre weighted Auto Focus, Flexible Spot Auto Focus, Multi Point Auto Focus, Spot Auto Focus Macro focusing range (wide) 0.01 - ? Macro focusing range (tele) 2.4 - ? Light exposure ISO sensitivity 80, 1600, 3200, 12800 Light exposure modes Aperture priority AE, Auto, Manual, Shutter priority AE Light exposure control Program AE Light exposure correction \u00b1 2EV (1/3EV step) Light metering Centre-weighted, Spot ISO sensitivity (min) 80 ISO sensitivity (max) 12800 Shutter Camera shutter speed (min) 0.00025s Camera shutter speed (max) 30s Flash Flash modes Auto, Flash off, Flash on, Slow synchronization Built-in flash Yes Flash range (wide) 0.3 - 12.4m Flash range (tele) 2 - 5.9m Video Video resolutions 640 x 480, 1440 x 1080, 1920 x 1080 pixels Video formats supported MPEG Full HD Yes Maximum video resolution 1440 x 1080 pixels Memory Compatible memory cards MS Duo, MS PRO Duo, MS Pro-HG Duo, SD, SDHC, SDXC Display Display TFT Display diagonal 7.62 cm (3\") Display resolution (numeric) 921600 pixels Ports & interfaces USB version 2.0 HDMI connector type Micro PictBridge No HDMI Yes AV output No Camera Colour of product Black White balance Auto, Cloudy, Daylight, Fluorescent, Fluorescent H, Fluorescent L Scene modes Backlight, Beach, Fireworks, Landscape, Night portrait, Snow GPS No Battery Battery technology Lithium Battery life (CIPA standard) 400 shots Battery type NP-BX1 Power source type Battery Technical details Waterproof No Trimming Yes Optical viewfinder No Manual focus Yes HDMI Yes GPS No Face detection Yes Electrical viewfinder Yes Cool shot function Yes Conversion function No Design Colour of product Black Performance GPS No Weight & dimensions Width 12.96 cm Depth 10.32 cm Height 9.32 cm Weight 623g Weight (including battery) 650g Other features Waterproof No Trimming Yes Optical viewfinder No Manual focus Yes Focal length (35mm film equivalent) 24 - 1200 mm Face detection Yes Electrical viewfinder Yes Cool shot function Yes Conversion function No",
    "coolshotfunction": "Yes",
    "depth": "10.32 cm",
    "usbversion": "2.0",
    "width": "12.96 cm",
    "supportedaspectratios": "3:2, 16:9",
    "minimumfocallength35mmfilmequiv": "2.4 cm",
    "macrofocusingrangetele": "2.4 - ?",
    "imagesensorsize": "25.4/58.4 mm (1/2.3\")",
    "minimumaperture": "2.8",
    "videoformatssupported": "MPEG",
    "gps": "No",
    "category": "camera",
    "conversionfunction": "No",
    "displaydiagonal": "7.62 cm (3\")",
    "hdmi": "Yes",
    "waterproof": "No",
    "electricalviewfinder": "Yes",
    "maximumaperture": "6.3",
    "autofocusingafmodes": "Centre weighted Auto Focus, Flexible Spot Auto Focus, Multi Point Auto Focus, Spot Auto Focus",
    "sensortype": "CMOS",
    "ean": "4905524936735",
    "batterylifecipastandard": "400 shots",
    "fullhd": "Yes",
    "powersourcetype": "Battery",
    "displayresolutionnumeric": "921600 pixels",
    "manufacturer": "Sony",
    "isosensitivitymin": "80",
    "focallength35mmfilmequivalent": "24 - 1200 mm",
    "maximumvideoresolution": "1440 x 1080 pixels",
    "flashrangewide": "0.3 - 12.4m",
    "focusadjustment": "Auto/Manual",
    "cameratype": "Compact",
    "flashmodes": "Auto, Flash off, Flash on, Slow synchronization",
    "builtinflash": "Yes",
    "camerashutterspeedmin": "0.00025s",
    "colourofproduct": "Black",
    "batterytechnology": "Lithium",
    "scenemodes": "Backlight, Beach, Fireworks, Landscape, Night portrait, Snow",
    "opticalzoom": "50x",
    "isosensitivitymax": "12800",
    "height": "9.32 cm",
    "digitalzoom": "100x",
    "maximumfocallength35mmfilmequiv": "130 cm",
    "videoresolutions": "640 x 480, 1440 x 1080, 1920 x 1080 pixels",
    "trimming": "Yes",
    "shortdescription": "20.4MPx, Exmor R CMOS, 50x optical zoom, 7.5cm (3.0\") LCD, Full HD, Intelligent Auto, manual control",
    "whitebalance": "Auto, Cloudy, Daylight, Fluorescent, Fluorescent H, Fluorescent L"
}