{
    "hdmiversion": "1.4a",
    "wifi": "Yes",
    "focallengthrangeff": "18 - 55 mm",
    "weight": "375g",
    "audioformatssupported": "AAC",
    "isosensitivity": "100, 200, 400, 800, 1600, 3200, 6400, 12800, 25600, Auto",
    "fieldofview": "100%",
    "focus": "TTL",
    "height": "9.55 cm",
    "nearfieldcommunicationnfc": "Yes",
    "camerashutterspeedmax": "0.000125s",
    "maximumimageresolution": "5472 x 3648 pixels",
    "operatingtemperaturett": "0 - 40 \u00b0C",
    "lightexposurecorrection": "\u00b1 3EV (1/3EV step)",
    "isosensitivitymax": "25600",
    "batterytype": "BP1410",
    "sku": "EV-NX30ZZBGBGB",
    "batteryvoltage": "7.6V",
    "builtinmicrophone": "Yes",
    "motionjpegframerate": "60 fps",
    "numberofbatteriessupported": "1",
    "specification": "Picture quality Sensor format Advanced Photo System type-C (APS-C) Still image resolution(s) 5472 x 3648, 3888 x 2592, 2976 x1984, 1728x 1152, 2736 x 1824, 5472 x 3080, 3712 x 2088, 2944 x 1656, 1920 x 1080, 3648 x 3648, 2640 x 2640, 2000 x 2000, 1024 x 1024, 5472 x 3648, 2688 x 1512, 1920 x 1080 Total megapixels 21.6 MP Image sensor size (W x H) 23.5 x 15.7 mm Image stabilizer location Lens Maximum image resolution 5472 x 3648 pixels Sensor type CMOS Camera type Bridge Megapixel 20.3 MP Lens system Focal length range (f-f) 18 - 55 mm Minimum aperture 3.5 Maximum aperture 5.6 Lens mount interface Samsung NX Filter size 5.8 cm Focusing Focus TTL Auto focusing (AF) modes Continuous Auto Focus, Single Auto Focus Normal focusing range 11m Light exposure ISO sensitivity 100, 200, 400, 800, 1600, 3200, 6400, 12800, 25600, Auto Light exposure correction \u00b1 3EV (1/3EV step) ISO sensitivity (min) 100 ISO sensitivity (max) 25600 Shutter Camera shutter speed (min) 0.25s Camera shutter speed (max) 0.000125s Camera shutter type Electronic Video Video resolutions 320 x 240, 640 x 480, 1280 x 720, 1920 x 810, 1920 x 1080 pixels Video formats supported H.264, MP4 Motion JPEG frame rate 60 fps Full HD Yes Analog signal format system NTSC, PAL Maximum video resolution 1920 x 1080 pixels Audio Built-in microphone Yes Audio formats supported AAC Memory Compatible memory cards SD, SDHC, SDXC Memory slots 1 Display Display AMOLED Display diagonal 7.62 cm (3\") Display resolution 720 x 480 pixels Display resolution (numeric) 1037000 pixels Vari-angle LCD display Yes Touch sensitive screen Yes Field of view 100% Viewfinder Magnification 0.96x Ports & interfaces USB version 2.0 HDMI version 1.4a HDMI Yes Networking Near Field Communication (NFC) Yes Wi-Fi Yes Camera Image stabilizer location Lens Colour of product Black White balance Auto, Cloudy, Custom modes, Daylight, Flash, Fluorescent, Manual, Tungsten Scene modes Landscape, Portrait Shooting modes Aperture priority, Auto, Program, Shutter priority Camera playback Movie, Single image, Slide show, Thumbnails Battery Battery voltage 7.6V Battery life (CIPA standard) 360 shots Battery capacity 1410 mAh Battery life (max) 3h Battery type BP1410 Number of batteries supported 1 Power source type Battery Technical details HDMI Yes Design Colour of product Black Operational conditions Operating temperature (T-T) 0 - 40 \u00b0C Operating relative humidity (H-H) 5 - 85% Weight & dimensions Width 4.17 cm Depth 12.7 cm Height 9.55 cm Weight 375g",
    "ean": "8806085978430",
    "depth": "12.7 cm",
    "touchsensitivescreen": "Yes",
    "usbversion": "2.0",
    "width": "4.17 cm",
    "magnification": "0.96x",
    "sensorformat": "Advanced Photo System type-C (APS-C)",
    "displayresolution": "720 x 480 pixels",
    "minimumaperture": "3.5",
    "videoformatssupported": "H.264, MP4",
    "maximumaperture": "5.6",
    "category": "camera",
    "stillimageresolutions": "5472 x 3648, 3888 x 2592, 2976 x1984, 1728x 1152, 2736 x 1824, 5472 x 3080, 3712 x 2088, 2944 x 1656, 1920 x 1080, 3648 x 3648, 2640 x 2640, 2000 x 2000, 1024 x 1024, 5472 x 3648, 2688 x 1512, 1920 x 1080",
    "displaydiagonal": "7.62 cm (3\")",
    "hdmi": "Yes",
    "memoryslots": "1",
    "varianglelcddisplay": "Yes",
    "autofocusingafmodes": "Continuous Auto Focus, Single Auto Focus",
    "sensortype": "CMOS",
    "displayresolutionnumeric": "1037000 pixels",
    "scenemodes": "Landscape, Portrait",
    "normalfocusingrange": "11m",
    "batterycapacity": "1410 mAh",
    "fullhd": "Yes",
    "powersourcetype": "Battery",
    "operatingrelativehumidityhh": "5 - 85%",
    "manufacturer": "Samsung",
    "cameraplayback": "Movie, Single image, Slide show, Thumbnails",
    "isosensitivitymin": "100",
    "analogsignalformatsystem": "NTSC, PAL",
    "maximumvideoresolution": "1920 x 1080 pixels",
    "whitebalance": "Auto, Cloudy, Custom modes, Daylight, Flash, Fluorescent, Manual, Tungsten",
    "cameratype": "Bridge",
    "camerashuttertype": "Electronic",
    "camerashutterspeedmin": "0.25s",
    "batterylifemax": "3h",
    "compatiblememorycards": "SD, SDHC, SDXC",
    "lensmountinterface": "Samsung NX",
    "imagesensorsizewxh": "23.5 x 15.7 mm",
    "megapixel": "20.3 MP",
    "shootingmodes": "Aperture priority, Auto, Program, Shutter priority",
    "colourofproduct": "Black",
    "filtersize": "5.8 cm",
    "totalmegapixels": "21.6 MP",
    "batterylifecipastandard": "360 shots",
    "videoresolutions": "320 x 240, 640 x 480, 1280 x 720, 1920 x 810, 1920 x 1080 pixels",
    "shortdescription": "NX 30, 20.3MP, APS-C, 7.62 cm (3 \") AMOLED, HDMI, NFC, WLAN + 18 - 55mm F3.5 - 5.6 OIS III",
    "display": "AMOLED",
    "imagestabilizerlocation": "Lens"
}