{
    "lensstructureelementsgroups": "11/8",
    "isosensitivity": "100, 200, 400, 800, 1600, 3200, Auto",
    "stillimageresolutions": "4608 x 3456, 3264 x 2448, 2048 x 1536, 640 x 480, 4608 x 2592, 3264 x 1832, 1920 x 1080, 640 x 360, 4608 x 3072, 3264 x 2176, 2048 x 1368, 640 x 424, 3456 x 3456, 2448 x 2448, 1536 x 1536, 480 x 480",
    "focus": "TTL",
    "batterytype": "NB-6LH",
    "sku": "9342B012AA",
    "flashexposurecompensation": "Yes",
    "videoformatssupported": "H.264, MP4, MPEG4",
    "builtinprocessor": "DIGIC 4+ iSAPS",
    "sensortype": "CMOS",
    "batterylifecipastandard": "290 shots",
    "height": "6.1 cm",
    "boxcontents": "PowerShot SX600 HS Battery Pack NB-6LH Wrist Strap WS-800 User Manual Kit Battery Charger CB-2LYE AC Cable",
    "camerashutterspeedmin": "0.0005s",
    "pictbridge": "Yes",
    "flashrangetele": "1 - 2m",
    "weight": "188g",
    "audioformatssupported": "AAC",
    "autoexposureaelock": "Yes",
    "nearfieldcommunicationnfc": "Yes",
    "flashexposurelock": "Yes",
    "combinedzoom": "72x",
    "category": "camera",
    "hdmi": "Yes",
    "macoperatingsystemssupported": "Mac OS X 10.7 Lion, Mac OS X 10.8 Mountain Lion, Mac OS X 10.9 Mavericks",
    "imageformatssupported": "JPG",
    "lightmetering": "Centre-weighted, Evaluative (Multi-pattern), Spot",
    "specification": "Picture quality Image sensor size 25.4/58.4 mm (1/2.3\") Still image resolution(s) 4608 x 3456, 3264 x 2448, 2048 x 1536, 640 x 480, 4608 x 2592, 3264 x 1832, 1920 x 1080, 640 x 360, 4608 x 3072, 3264 x 2176, 2048 x 1368, 640 x 424, 3456 x 3456, 2448 x 2448, 1536 x 1536, 480 x 480 Image stabilizer Yes Image stabilizer location Lens Image formats supported JPG Maximum image resolution 4608 x 3456 pixels Sensor type CMOS Camera type Compact Megapixel 16 MP Lens system Focal length range (f-f) 4.5 - 81 mm Minimum focal length (35mm film equiv) 2.5 cm Maximum focal length (35mm film equiv) 40 cm Minimum aperture 6.9 Maximum aperture 3.8 Lens structure (elements/groups) 11/8 Combined zoom 72x Digital zoom 4x Optical zoom 18x Focusing Focus TTL Auto focusing (AF) modes Continuous Auto Focus, Face detection, Servo Auto Focus, Single Auto Focus, Tracking Auto Focus Closest focusing distance 0.05m Auto Focus (AF) lock Yes Auto Focus (AF) assist beam Yes Light exposure ISO sensitivity 100, 200, 400, 800, 1600, 3200, Auto Light exposure correction \u00b1 2EV (1/3EV step) Light metering Centre-weighted, Evaluative (Multi-pattern), Spot Auto Exposure (AE) lock Yes ISO sensitivity (min) 100 ISO sensitivity (max) 3200 Shutter Camera shutter speed (min) 0.0005s Camera shutter speed (max) 15s Flash Flash modes Auto, Flash off, Flash on, Manual, Red-eye reduction, Slow synchronization Built-in flash Yes Flash sync-speed 1/2000s Flash range (wide) 0.5 - 3.5m Flash range (tele) 1 - 2m Flash exposure lock Yes Flash exposure compensation Yes External flash connector Yes Video Video resolutions 640 x 480, 1280 x 720, 1920 x 1080 pixels Video formats supported H.264, MP4, MPEG4 Motion JPEG frame rate 30 fps Full HD Yes Analog signal format system NTSC, PAL Maximum video resolution 1920 x 1080 pixels Audio Built-in microphone Yes Audio formats supported AAC Memory Compatible memory cards SD, SDHC, SDXC Memory slots 1 Display Display TFT Display diagonal 7.62 cm (3\") Display resolution (numeric) 461000 pixels Field of view 100% Ports & interfaces USB version 2.0 HDMI connector type Micro PictBridge Yes USB connector type Mini-USB B HDMI Yes Networking Wi-Fi standards 802.11b, 802.11g, 802.11n Near Field Communication (NFC) Yes Wi-Fi Yes Camera Image stabilizer location Lens Colour of product Red White balance Auto, Cloudy, Custom modes, Daylight, Fluorescent, Fluorescent H, Tungsten Scene modes Fireworks, Portrait, Snow Photo effects Black&White, Neutral, Positive film, Vivid Self-timer 2, 10s Playback zoom (max) 10x Orientation sensor Yes On Screen Display (OSD) languages ARA, CHI (SIMPL), CHI (TR), CZE, DAN, DEU, DUT, ENG, ESP, FIN, FRE, GRE, HEB, HUN, ITA, JPN, KOR, NOR, POL, POR, RUM, RUS, SWE, THA, TUR, UKR Direct printing Yes Camera file system DPOF 1.1, Exif 2.3 Built-in processor DIGIC 4+ iSAPS Battery Battery technology Lithium-Ion (Li-Ion) Battery life (CIPA standard) 290 shots Battery type NB-6LH Number of batteries supported 1 Power source type Battery Operating system/software Windows operating systems supported Windows 7 Home Basic, Windows 7 Home Basic x64, Windows 7 Home Premium, Windows 7 Home Premium x64, Windows 7 Professional, Windows 7 Professional x64, Windows 7 Starter, Windows 7 Starter x64, Windows 7 Ultimate, Windows 7 Ultimate x64, Windows 8, Windows 8 Enterprise, Windows 8 Enterprise x64, Windows 8 Pro, Windows 8 Pro x64, Windows 8 x64, Windows Vista Business, Windows Vista Business x64, Windows Vista Enterprise, Windows Vista Enterprise x64, Windows Vista Home Basic, Windows Vista Home Basic x64, Windows Vista Home Premium, Windows Vista Home Premium x64, Windows Vista Ultimate, Windows Vista Ultimate x64, Windows XP Home, Windows XP Home x64, Windows XP Professional, Windows XP Professional x64 Mac operating systems supported Mac OS X 10.7 Lion, Mac OS X 10.8 Mountain Lion, Mac OS X 10.9 Mavericks Bundled software ImageBrowser EX Technical details HDMI Yes Direct printing Yes Processor Built-in processor DIGIC 4+ iSAPS Design Colour of product Red Performance Direct printing Yes Built-in processor DIGIC 4+ iSAPS Operational conditions Operating temperature (T-T) 0 - 40 \u00b0C Operating relative humidity (H-H) 10 - 90% System requirements Windows operating systems supported Windows 7 Home Basic, Windows 7 Home Basic x64, Windows 7 Home Premium, Windows 7 Home Premium x64, Windows 7 Professional, Windows 7 Professional x64, Windows 7 Starter, Windows 7 Starter x64, Windows 7 Ultimate, Windows 7 Ultimate x64, Windows 8, Windows 8 Enterprise, Windows 8 Enterprise x64, Windows 8 Pro, Windows 8 Pro x64, Windows 8 x64, Windows Vista Business, Windows Vista Business x64, Windows Vista Enterprise, Windows Vista Enterprise x64, Windows Vista Home Basic, Windows Vista Home Basic x64, Windows Vista Home Premium, Windows Vista Home Premium x64, Windows Vista Ultimate, Windows Vista Ultimate x64, Windows XP Home, Windows XP Home x64, Windows XP Professional, Windows XP Professional x64 Mac operating systems supported Mac OS X 10.7 Lion, Mac OS X 10.8 Mountain Lion, Mac OS X 10.9 Mavericks Weight & dimensions Width 10.38 cm Depth 2.6 cm Height 6.1 cm Weight 188g Packaging content Bundled software ImageBrowser EX Hand strap Yes Battery charger included Yes Batteries included Yes",
    "autofocusafassistbeam": "Yes",
    "selftimer": "2, 10s",
    "maximumaperture": "3.8",
    "minimumaperture": "6.9",
    "motionjpegframerate": "30 fps",
    "onscreendisplayosdlanguages": "ARA, CHI (SIMPL), CHI (TR), CZE, DAN, DEU, DUT, ENG, ESP, FIN, FRE, GRE, HEB, HUN, ITA, JPN, KOR, NOR, POL, POR, RUM, RUS, SWE, THA, TUR, UKR",
    "fullhd": "Yes",
    "interface": "Hi-Speed USB (MTP PTP) dedicated connector (Mini-B compatible) HDMI Micro Connector (HDMI-CEC compatible) A/V output (PAL/NTSC) Wi-Fi (IEEE802.11b/g/n) (2.4 GHz only) with NFC support",
    "displayresolutionnumeric": "461000 pixels",
    "manufacturer": "Canon",
    "isosensitivitymin": "100",
    "analogsignalformatsystem": "NTSC, PAL",
    "bundledsoftware": "ImageBrowser EX",
    "flashmodes": "Auto, Flash off, Flash on, Manual, Red-eye reduction, Slow synchronization",
    "builtinflash": "Yes",
    "compatiblememorycards": "SD, SDHC, SDXC",
    "isosensitivitymax": "3200",
    "hdmiconnectortype": "Micro",
    "warranty": "1 Year",
    "photoeffects": "Black&White, Neutral, Positive film, Vivid",
    "handstrap": "Yes",
    "megapixel": "16 MP",
    "wifistandards": "802.11b, 802.11g, 802.11n",
    "camerafilesystem": "DPOF 1.1, Exif 2.3",
    "builtinmicrophone": "Yes",
    "width": "10.38 cm",
    "windowsoperatingsystemssupported": "Windows 7 Home Basic, Windows 7 Home Basic x64, Windows 7 Home Premium, Windows 7 Home Premium x64, Windows 7 Professional, Windows 7 Professional x64, Windows 7 Starter, Windows 7 Starter x64, Windows 7 Ultimate, Windows 7 Ultimate x64, Windows 8, Windows 8 Enterprise, Windows 8 Enterprise x64, Windows 8 Pro, Windows 8 Pro x64, Windows 8 x64, Windows Vista Business, Windows Vista Business x64, Windows Vista Enterprise, Windows Vista Enterprise x64, Windows Vista Home Basic, Windows Vista Home Basic x64, Windows Vista Home Premium, Windows Vista Home Premium x64, Windows Vista Ultimate, Windows Vista Ultimate x64, Windows XP Home, Windows XP Home x64, Windows XP Professional, Windows XP Professional x64",
    "playbackzoommax": "10x",
    "imagesensorsize": "25.4/58.4 mm (1/2.3\")",
    "batteriesincluded": "Yes",
    "memoryslots": "1",
    "closestfocusingdistance": "0.05m",
    "batterychargerincluded": "Yes",
    "powersourcetype": "Battery",
    "operatingrelativehumidityhh": "10 - 90%",
    "flashrangewide": "0.5 - 3.5m",
    "cameratype": "Compact",
    "colourofproduct": "Red",
    "lcdscreensize": "3.0",
    "externalflashconnector": "Yes",
    "maximumfocallength35mmfilmequiv": "40 cm",
    "shortdescription": "PowerShot SX600 HS - CMOS 1/2.3\", 16MP, 4608 x 3456, DIGIC 4+ iSAPS, 4.5 - 81.0 mm, f/3.8 - f/6.9, 7.5 cm (3.0\") PureColor II G (TFT), (Full HD) 1920 x 1080, USB2.0, HDMI-micro, Wi-Fi (IEEE802.11b/g/n), SD, SDHC, SDXC, 188g",
    "display": "TFT",
    "imagestabilizerlocation": "Lens",
    "focallengthrangeff": "4.5 - 81 mm",
    "flashsyncspeed": "1/2000s",
    "fieldofview": "100%",
    "lightexposurecorrection": "\u00b1 2EV (1/3EV step)",
    "camerashutterspeedmax": "15s",
    "maximumimageresolution": "4608 x 3456 pixels",
    "operatingtemperaturett": "0 - 40 \u00b0C",
    "autofocusaflock": "Yes",
    "usbconnectortype": "Mini-USB B",
    "ean": "8714574616087",
    "digitalzoom": "4x",
    "usbversion": "2.0",
    "minimumfocallength35mmfilmequiv": "2.5 cm",
    "dimensionswxdxh": "103.8 x 26.0 x 61.0 mm mm",
    "maximumvideoresolution": "1920 x 1080 pixels",
    "imagestabilizer": "Yes",
    "displaydiagonal": "7.62 cm (3\")",
    "autofocusingafmodes": "Continuous Auto Focus, Face detection, Servo Auto Focus, Single Auto Focus, Tracking Auto Focus",
    "scenemodes": "Fireworks, Portrait, Snow",
    "videoresolutions": "640 x 480, 1280 x 720, 1920 x 1080 pixels",
    "directprinting": "Yes",
    "wifi": "Yes",
    "batterytechnology": "Lithium-Ion (Li-Ion)",
    "opticalzoom": "18x",
    "numberofbatteriessupported": "1",
    "depth": "2.6 cm",
    "orientationsensor": "Yes",
    "whitebalance": "Auto, Cloudy, Custom modes, Daylight, Fluorescent, Fluorescent H, Tungsten"
}