{
    "pictbridge": "No",
    "lightexposurecontrol": "\u00b1 2.0EV, 1/3EV step",
    "attr2dpanorama": "360\u00b0(11,520 x 1,080) / HR(10,480x4,096) / Wide(7,152 x 1,080/4,912 x 1,920) / Standard(4,912 x 1,080/3,424 x 1,920)",
    "opticalsensorsize": "1/0.0906 mm (1/2.3\")",
    "weight": "166 139 g",
    "isosensitivity": "ISO80-3200(iAuto), ISO80-12800(Superior Auto), ISO80-1600(Program Auto)",
    "stillimageresolutions": "Yes",
    "focus": "3.5-6.5",
    "opticalviewfinder": "No",
    "megapixel": "Approx. 18.2 MP",
    "recordingmedia": "SD Memory Card / SDHC Memory Card / SDXC Memory Card / microSD Memory Card* / microSDHC Memory Card* / microSDXC Memory Card* Memory Stick Duo / Memory Stick PRO Duo / Memory Stick PRO Duo (high speed) / Memory Stick PRO HG Duo / Memory Stick XC-HG Duo / Memory Stick Micro* / Memory Stick Micro (mark 2)*",
    "pictureeffects": "HDR Painting, Richtone Monochrome, Miniature, Toy camera, Pop Color, Partial Color, Soft High-key, Watercolor, Illustration",
    "smiledetection": "Yes",
    "focallengthrangeff": "4.3 - 86 mm",
    "category": "camera",
    "batterytype": "No",
    "manualfocus": "No",
    "avoutput": "No",
    "startuptime": "Approx. 2 sec.",
    "sku": "DSCWX300R.CEH",
    "imagerotation": "Yes",
    "batterypack": "Lithium N",
    "autodaylightsynchronizedflash": "No",
    "facedetection": "Yes",
    "shopfrontmode": "No",
    "lightmetering": "Yes",
    "specification": "Picture quality Optical sensor size 1/0.0906 mm (1/2.3\") Still image resolution(s) Yes Sensor type Exmor R CMOS Sensor Megapixel Approx. 18.2 MP Lens system Focal length range (f-f) 4.3 - 86 mm Filter size No Digital zoom 18M Appro.80 / 10M Appro.107 / 5M Appro.151 / VGA Appro.306 / 13M Appro.80 / 2M Appro.204x Optical zoom 20x Focusing Focus 3.5-6.5 Auto focusing (AF) modes Yes Smile detection Yes Auto Focus (AF) assist beam Auto / Off Light exposure ISO sensitivity ISO80-3200(iAuto), ISO80-12800(Superior Auto), ISO80-1600(Program Auto) Light exposure control \u00b1 2.0EV, 1/3EV step Light metering Yes Flash Flash modes Auto / Flash On / Slow Synchro / Flash Off / Advanced Flash Display Display TFT ClearPhoto Display diagonal 190.5 cm (7.5cm) Display resolution (numeric) 460.800 pixels Ports & interfaces PictBridge No AV output No Camera Colour of product Red White balance Y Auto,Daylight,Cloudy,Incandescent,Flash Scene modes Soft Snap / Soft Skin / Anti Motion Blur / Backlight Correction HDR / Night Portrait / Night Scene / High Sensitivity / Handheld Twilight / Beach / Snow / Fireworks / Gourmet / Pet Mode / Landscape Contrast adjustment No Saturation adjustment No Start-up time Approx. 2 sec. Playback zoom (max) YES On Screen Display (OSD) languages English, French, German, Spanish, Italian, Portuguese, Dutch, Swedish, Norwegian, Danish, Finnish, Polish, Czech, Hungarian, Turkish, Greek, Bulgarian, Croatian, Romanian Histogram Yes GPS No Camera file system Yes Sharpness levels No Battery Battery type No Operating system/software Bundled software PlayMemories Home Technical details Accessories included Rechargeable Battery Pack (NP-BX1), AC Adaptor (AC-UB10/UB10B), Micro USB cable, Wrist Strap, Instruction Manual, AC Power Cord Start-up time Approx. 2 sec. Waterproof No USB 2.0 connectors Yes Trimming Yes Recording media SD Memory Card / SDHC Memory Card / SDXC Memory Card / microSD Memory Card* / microSDHC Memory Card* / microSDXC Memory Card* Memory Stick Duo / Memory Stick PRO Duo / Memory Stick PRO Duo (high speed) / Memory Stick PRO HG Duo / Memory Stick XC-HG Duo / Memory Stick Micro* / Memory Stick Micro (mark 2)* Recording format Y JPEG Panorama Y N Optical viewfinder No Manual focus No Macro focusing range iAuto:AF(W:Approx.5cm(0.16') - ?, T:Approx.200cm(6.56') - ?) / Program Auto:AF(W:Approx.5cm(0.16') - ?, T:Approx.200cm(6.56') - ?) GPS No Face detection Yes Electrical viewfinder No Conversion function No Battery pack Lithium N Battery LED indicator No Aperture priority AE N iAuto(F3.5/F8.0(W), 2 steps with ND Filter) / Program Auto(F3.5/F8.0(W), 2 steps with ND Filter) Red-eye correction Auto / On / Off Supplied battery NP-BX1 Still image size(18M, 4896 x 3672) Yes Still image size(16M, 4608 x 3456) No Still image size (VGA, 640 x 480) Yes Still image size (9.0M, 3456 x 2592) No Still image size (8.0M, 3264 x 2448) No Still image size (7.2M, 3072 x 2304) No Still image size (5.0M, 2592 x 1944) Yes Still image size (3:2 mode, 4000 x 2672) No Still image size (3:2 mode, 3648 x 2432) No Still image size (3:2 mode, 3456 x 2304) No Still image size (3.1M, 2048 x 1536) No Still image size (16:9 mode, 4896 x 2752) Yes Still image size (16:9 mode, 4608 x 2592) No Still image size (16:9 mode, 4320 x 2432) No Still image size (16:9 mode, 4000 x 2248) No Still Image size (16:9 mode, 1920 x 1080) Yes Still image size (14M, 4320 x 3240) No Still image size (13M, 4224 x 3168) No Still image size (12M, 4000 x 3000) No Spot Auto Focus (AF) Yes Sony G lens compatible Yes Soft skin effect Yes Slideshow with music Yes Slideshow playback Yes Slideshow movie Yes Shop front mode No Print image matching Yes Picture transfer protocol (PTP) No Picture effects HDR Painting, Richtone Monochrome, Miniature, Toy camera, Pop Color, Partial Color, Soft High-key, Watercolor, Illustration NR slow shutter No Multi use Terminal with HD Multi Terminal, Hi-Speed USB(USB2.0), Micro HDMI Multi use terminal Yes Multi Point Auto Focus (AF) Yes Moving image size (640x480, 25fps, 3Mbps) Yes Moving image size (320x240, 30fps) No Moving image size (1920x1080, 60p, 28Mbps) No Moving image size (1920x1080, 50i, 24Mbps) Yes Moving image size (1920x1080, 50i, 17Mbps) Yes Moving image size (1440x1080, 25fps, 12Mbps) No Moving image size (1280x720, 30fps, 9Mbps) No Moving image size (1280x720, 25fps, 6Mbps) Yes Manual aperture No Index playback 16 / 25 images Image rotation Yes HD Playback Under 18M(4,896\u00d73,672) Hand Shake Alert No Flexible Spot Auto Focus (AF) No Exposure warning indicator No Disk/Memory Stick remaining indicator No Digital Print Order Format (DPOF) Yes Cue and Review Yes Clear RAW Noise Reduction No Clear image zoom 18M Approx.40x / 10M Approx.53x / 5M Approx.75x / VGA Approx.306x / 13M(16:9) Approx.40x / 2M(16:9) Approx.102x Carl Zeiss Vario-Tessar Lens No Burst Mode Approx.10 fps Burst interval Approx.0.1 sec.(10 shots) Bionz processor Yes Backlight correction Yes Background defocus Yes Auto image rotation Yes Auto grouping and & Best picture recognition Yes Auto daylight synchronized flash No Auto bright monitoring No 3D mode No 2D Panorama 360\u00b0(11,520 x 1,080) / HR(10,480x4,096) / Wide(7,152 x 1,080/4,912 x 1,920) / Standard(4,912 x 1,080/3,424 x 1,920) Moving Image Size (640x480, 30fps, 3Mbps) No Distance limitations using flash ISO Auto: Approx.0.2m - 4.3m(7 7/8 \" - 14 ft 1 3/8 \")(W) / Approx.2.0m - 2.4 m(6ft 6 3/4 \" - 7 ft 10 1/2 \")(T), ISO3200: > Approx.6.1 m(20 ft 1/4 \")(W) / Approx.3.4 m(11 ft 1 7/8 \")(T) Design Colour of product Red Performance GPS No Weight & dimensions Width 9.6 cm Depth 2.57 cm Height 5.49 cm Weight 166 139 g Packaging content Bundled software PlayMemories Home Technical details Optical sensor size 1/0.0906 mm (1/2.3\") SteadyShot SteadyShot capability,Optical SteadyShot capability Other features Accessories included Rechargeable Battery Pack (NP-BX1), AC Adaptor (AC-UB10/UB10B), Micro USB cable, Wrist Strap, Instruction Manual, AC Power Cord Waterproof No USB 2.0 connectors Yes Trimming Yes Recording media SD Memory Card / SDHC Memory Card / SDXC Memory Card / microSD Memory Card* / microSDHC Memory Card* / microSDXC Memory Card* Memory Stick Duo / Memory Stick PRO Duo / Memory Stick PRO Duo (high speed) / Memory Stick PRO HG Duo / Memory Stick XC-HG Duo / Memory Stick Micro* / Memory Stick Micro (mark 2)* Recording format Y JPEG Panorama Y N Optical viewfinder No Manual focus No Macro focusing range iAuto:AF(W:Approx.5cm(0.16') - ?, T:Approx.200cm(6.56') - ?) / Program Auto:AF(W:Approx.5cm(0.16') - ?, T:Approx.200cm(6.56') - ?) Focal length (35mm film equivalent) 25 - 500 mm Face detection Yes Electrical viewfinder No Conversion function No Camera shutter speed iAuto(4\" - 1/1600) / Program Auto(1\" - 1/1600) Battery pack Lithium N Battery LED indicator No Aperture priority AE N iAuto(F3.5/F8.0(W), 2 steps with ND Filter) / Program Auto(F3.5/F8.0(W), 2 steps with ND Filter) Red-eye correction Auto / On / Off Supplied battery NP-BX1 Still image size(18M, 4896 x 3672) Yes Still image size(16M, 4608 x 3456) No Still image size (VGA, 640 x 480) Yes Still image size (9.0M, 3456 x 2592) No Still image size (8.0M, 3264 x 2448) No Still image size (7.2M, 3072 x 2304) No Still image size (5.0M, 2592 x 1944) Yes Still image size (3:2 mode, 4000 x 2672) No Still image size (3:2 mode, 3648 x 2432) No Still image size (3:2 mode, 3456 x 2304) No Still image size (3.1M, 2048 x 1536) No Still image size (16:9 mode, 4896 x 2752) Yes Still image size (16:9 mode, 4608 x 2592) No Still image size (16:9 mode, 4320 x 2432) No Still image size (16:9 mode, 4000 x 2248) No Still Image size (16:9 mode, 1920 x 1080) Yes Still image size (14M, 4320 x 3240) No Still image size (13M, 4224 x 3168) No Still image size (12M, 4000 x 3000) No Spot Auto Focus (AF) Yes Sony G lens compatible Yes Soft skin effect Yes Slideshow with music Yes Slideshow playback Yes Slideshow movie Yes Shop front mode No Print image matching Yes Picture transfer protocol (PTP) No Picture effects HDR Painting, Richtone Monochrome, Miniature, Toy camera, Pop Color, Partial Color, Soft High-key, Watercolor, Illustration NR slow shutter No Multi use Terminal with HD Multi Terminal, Hi-Speed USB(USB2.0), Micro HDMI Multi use terminal Yes Multi Point Auto Focus (AF) Yes Moving image size (640x480, 25fps, 3Mbps) Yes Moving image size (320x240, 30fps) No Moving image size (1920x1080, 60p, 28Mbps) No Moving image size (1920x1080, 50i, 24Mbps) Yes Moving image size (1920x1080, 50i, 17Mbps) Yes Moving image size (1440x1080, 25fps, 12Mbps) No Moving image size (1280x720, 30fps, 9Mbps) No Moving image size (1280x720, 25fps, 6Mbps) Yes Manual aperture No Index playback 16 / 25 images Image rotation Yes HD Playback Under 18M(4,896\u00d73,672) Hand Shake Alert No Flexible Spot Auto Focus (AF) No Exposure warning indicator No Disk/Memory Stick remaining indicator No Digital Print Order Format (DPOF) Yes Cue and Review Yes Clear RAW Noise Reduction No Clear image zoom 18M Approx.40x / 10M Approx.53x / 5M Approx.75x / VGA Approx.306x / 13M(16:9) Approx.40x / 2M(16:9) Approx.102x Carl Zeiss Vario-Tessar Lens No Burst Mode Approx.10 fps Burst interval Approx.0.1 sec.(10 shots) Bionz processor Yes Backlight correction Yes Background defocus Yes Auto image rotation Yes Auto grouping and & Best picture recognition Yes Auto daylight synchronized flash No Auto bright monitoring No 3D mode No 2D Panorama 360\u00b0(11,520 x 1,080) / HR(10,480x4,096) / Wide(7,152 x 1,080/4,912 x 1,920) / Standard(4,912 x 1,080/3,424 x 1,920) Moving Image Size (640x480, 30fps, 3Mbps) No Distance limitations using flash ISO Auto: Approx.0.2m - 4.3m(7 7/8 \" - 14 ft 1 3/8 \")(W) / Approx.2.0m - 2.4 m(6ft 6 3/4 \" - 7 ft 10 1/2 \")(T), ISO3200: > Approx.6.1 m(20 ft 1/4 \")(W) / Approx.3.4 m(11 ft 1 7/8 \")(T)",
    "autofocusafassistbeam": "Auto / Off",
    "digitalzoom": "18M Appro.80 / 10M Appro.107 / 5M Appro.151 / VGA Appro.306 / 13M Appro.80 / 2M Appro.204x",
    "bionzprocessor": "Yes",
    "width": "9.6 cm",
    "recordingformat": "Y JPEG",
    "slideshowmovie": "Yes",
    "playbackzoommax": "YES",
    "steadyshot": "SteadyShot capability,Optical SteadyShot capability",
    "indexplayback": "16 / 25 images",
    "nrslowshutter": "No",
    "trimming": "Yes",
    "camerafilesystem": "Yes",
    "conversionfunction": "No",
    "sharpnesslevels": "No",
    "displaydiagonal": "190.5 cm (7.5cm)",
    "accessoriesincluded": "Rechargeable Battery Pack (NP-BX1), AC Adaptor (AC-UB10/UB10B), Micro USB cable, Wrist Strap, Instruction Manual, AC Power Cord",
    "whitebalance": "Y Auto,Daylight,Cloudy,Incandescent,Flash",
    "waterproof": "No",
    "electricalviewfinder": "No",
    "camerashutterspeed": "iAuto(4\" - 1/1600) / Program Auto(1\" - 1/1600)",
    "multiuseterminal": "Yes",
    "autofocusingafmodes": "Yes",
    "sensortype": "Exmor R CMOS Sensor",
    "contrastadjustment": "No",
    "ean": "4905524940060",
    "display": "TFT ClearPhoto",
    "suppliedbattery": "NP-BX1",
    "redeyecorrection": "Auto / On / Off",
    "histogram": "Yes",
    "onscreendisplayosdlanguages": "English, French, German, Spanish, Italian, Portuguese, Dutch, Swedish, Norwegian, Danish, Finnish, Polish, Czech, Hungarian, Turkish, Greek, Bulgarian, Croatian, Romanian",
    "aperturepriorityae": "N iAuto(F3.5/F8.0(W), 2 steps with ND Filter) / Program Auto(F3.5/F8.0(W), 2 steps with ND Filter)",
    "displayresolutionnumeric": "460.800 pixels",
    "manufacturer": "Sony",
    "focallength35mmfilmequivalent": "25 - 500 mm",
    "bundledsoftware": "PlayMemories Home",
    "burstmode": "Approx.10 fps",
    "autobrightmonitoring": "No",
    "flashmodes": "Auto / Flash On / Slow Synchro / Flash Off / Advanced Flash",
    "handshakealert": "No",
    "backgrounddefocus": "Yes",
    "colourofproduct": "Red",
    "scenemodes": "Soft Snap / Soft Skin / Anti Motion Blur / Backlight Correction HDR / Night Portrait / Night Scene / High Sensitivity / Handheld Twilight / Beach / Snow / Fireworks / Gourmet / Pet Mode / Landscape",
    "opticalzoom": "20x",
    "saturationadjustment": "No",
    "height": "5.49 cm",
    "reviews": "No",
    "depth": "2.57 cm",
    "filtersize": "No",
    "attr3dmode": "No",
    "panorama": "Y N",
    "gps": "No",
    "shortdescription": "More detail even in low-light wiht 20x optical zoom and Exmor R\u2122 CMOS sensor, 18.2MP, Full HD, Intelligent Auto, Wi-Fi",
    "clearimagezoom": "18M Approx.40x / 10M Approx.53x / 5M Approx.75x / VGA Approx.306x / 13M(16:9) Approx.40x / 2M(16:9) Approx.102x",
    "slideshowwithmusic": "Yes",
    "autoimagerotation": "Yes"
}