{
    "minimumram": "512 MB",
    "lightexposuremodes": "Aperture priority AE, Auto, Manual, Shutter priority AE",
    "isosensitivity": "80, 100, 200, 400, 800, 1600, 3200, Auto",
    "stillimageresolutions": "4608 x 3456, 4608 x 3072, 3648 x 2736, 4608 x 2592, 2592 x 1944, 1984 x 1488, 1920 x 1080, 1024 x 768, 2832 x 2832",
    "focus": "TTL",
    "automodefocusingrangetele": "3.5 - ?",
    "batterytype": "SLB-10A",
    "sku": "EC-WB350FBPWGB",
    "videoformatssupported": "H.264, MP4, MPEG4",
    "minimumprocessor": "Intel Core 2 Duo 1.66 GHz / AMD Athlon X2 Dual-Core 2.2 GHz",
    "imagestabilizer": "Yes",
    "sensortype": "CMOS",
    "batterylifecipastandard": "310 shots",
    "height": "6.51 cm",
    "cameraplayback": "Movie, Single image, Slide show, Thumbnails",
    "focusadjustment": "Auto/Manual",
    "audiosystem": "Mono",
    "batterylifemax": "2.6h",
    "macrofocusingrangewide": "0.1 - 0.8m",
    "camerashutterspeedmin": "16s",
    "lightexposurecontrol": "Program AE",
    "flashrangetele": "0.5 - 2.9m",
    "weight": "216g",
    "nearfieldcommunicationnfc": "Yes",
    "category": "camera",
    "motionjpegframerate": "30 fps",
    "macoperatingsystemssupported": "Yes",
    "imageformatssupported": "EXIF, JPG",
    "lightmetering": "Centre-weighted, Evaluative (Multi-pattern), Spot",
    "specification": "Picture quality Image sensor size 25.4/58.4 mm (1/2.3\") Still image resolution(s) 4608 x 3456, 4608 x 3072, 3648 x 2736, 4608 x 2592, 2592 x 1944, 1984 x 1488, 1920 x 1080, 1024 x 768, 2832 x 2832 Image stabilizer Yes Total megapixels 16.7 MP Image formats supported EXIF, JPG Maximum image resolution 4608 x 3456 pixels Sensor type CMOS Camera type Compact Megapixel 16.3 MP Lens system Focal length range (f-f) 4.1 - 86.1 mm Minimum focal length (35mm film equiv) 2.3 cm Maximum focal length (35mm film equiv) 48.3 cm Maximum aperture 2.8 Digital zoom 5x Optical zoom 21x Focusing Focus TTL Focus adjustment Auto/Manual Auto focusing (AF) modes Centre weighted Auto Focus, Face detection, Multi Point Auto Focus, Tracking Auto Focus Macro focusing range (wide) 0.1 - 0.8m Macro focusing range (tele) 1.5 - 3.5m Auto Mode focusing range (wide) 0.8 - ? Auto Mode focusing range (tele) 3.5 - ? Light exposure ISO sensitivity 80, 100, 200, 400, 800, 1600, 3200, Auto Light exposure modes Aperture priority AE, Auto, Manual, Shutter priority AE Light exposure control Program AE Light exposure correction \u00b1 2EV (1/3EV step) Light metering Centre-weighted, Evaluative (Multi-pattern), Spot ISO sensitivity (min) 80 ISO sensitivity (max) 3200 Shutter Camera shutter speed (min) 16s Camera shutter speed (max) 0.0005s Flash Flash modes Auto, Fill-in, Flash off, Red-eye reduction, Slow synchronization Flash recharging time 4s Flash range (wide) 0.3 - 4.1m Flash range (tele) 0.5 - 2.9m Video Video resolutions 640 x 480, 1280 x 720, 1920 x 1080 pixels Video formats supported H.264, MP4, MPEG4 Motion JPEG frame rate 30 fps Full HD Yes Analog signal format system NTSC, PAL Maximum video resolution 1920 x 1080 pixels Audio Built-in microphone Yes Voice recording Yes Audio system Mono Memory Internal memory 9.5 MB Compatible memory cards MicroSD (TransFlash), MicroSDHC, MicroSDXC Memory slots 1 Maximum memory card size 64 GB Display Display TFT Display diagonal 7.62 cm (3\") Display resolution (numeric) 460000 pixels Touch sensitive screen Yes Ports & interfaces USB version 2.0 DC-in jack Yes HDMI No Networking Near Field Communication (NFC) Yes Wi-Fi Yes Camera Colour of product White White balance Auto, Cloudy, Custom modes, Daylight, Fluorescent H, Fluorescent L, Tungsten Scene modes Backlight, Fireworks, Landscape, Night, Night portrait, Panorama, Portrait, Spotlight, Sunset Self-timer 2, 10s Camera playback Movie, Single image, Slide show, Thumbnails Camera file system DCF, Exif 2.21 Battery Battery life (CIPA standard) 310 shots Battery life (max) 2.6h Battery type SLB-10A Number of batteries supported 1 Power source type Battery Operating system/software Windows operating systems supported Yes Mac operating systems supported Yes Technical details HDMI No Audio system Mono Design Colour of product White Operational conditions Operating temperature (T-T) 0 - 40 \u00b0C Operating relative humidity (H-H) 5 - 85% System requirements Minimum hard disk space 250 MB Minimum RAM 512 MB Minimum processor Intel Core 2 Duo 1.66 GHz / AMD Athlon X2 Dual-Core 2.2 GHz Windows operating systems supported Yes Mac operating systems supported Yes Weight & dimensions Width 11.36 cm Depth 2.5 cm Height 6.51 cm Weight 216g Technical details Smartphone remote support Yes Built-in speaker(s) Yes Audio recording formats AAC",
    "touchsensitivescreen": "Yes",
    "selftimer": "2, 10s",
    "maximumaperture": "2.8",
    "hdmi": "No",
    "maximummemorycardsize": "64 GB",
    "fullhd": "Yes",
    "displayresolutionnumeric": "460000 pixels",
    "manufacturer": "Samsung",
    "isosensitivitymin": "80",
    "analogsignalformatsystem": "NTSC, PAL",
    "flashmodes": "Auto, Fill-in, Flash off, Red-eye reduction, Slow synchronization",
    "compatiblememorycards": "MicroSD (TransFlash), MicroSDHC, MicroSDXC",
    "isosensitivitymax": "3200",
    "videoresolutions": "640 x 480, 1280 x 720, 1920 x 1080 pixels",
    "megapixel": "16.3 MP",
    "camerafilesystem": "DCF, Exif 2.21",
    "builtinmicrophone": "Yes",
    "automodefocusingrangewide": "0.8 - ?",
    "width": "11.36 cm",
    "windowsoperatingsystemssupported": "Yes",
    "macrofocusingrangetele": "1.5 - 3.5m",
    "imagesensorsize": "25.4/58.4 mm (1/2.3\")",
    "voicerecording": "Yes",
    "memoryslots": "1",
    "internalmemory": "9.5 MB",
    "powersourcetype": "Battery",
    "operatingrelativehumidityhh": "5 - 85%",
    "flashrangewide": "0.3 - 4.1m",
    "cameratype": "Compact",
    "colourofproduct": "White",
    "maximumfocallength35mmfilmequiv": "48.3 cm",
    "shortdescription": "16.3MP, 1/2.3\" BSI CMOS, OIS, f=4.1-86.1mm, 21x zoom, 1080p, 30fps, 7.62 cm (3 \") LCD TFT, Wi-Fi, NFC, MicroSD, USB 2.0, AV, 216g",
    "display": "TFT",
    "focallengthrangeff": "4.1 - 86.1 mm",
    "camerashutterspeedmax": "0.0005s",
    "maximumimageresolution": "4608 x 3456 pixels",
    "operatingtemperaturett": "0 - 40 \u00b0C",
    "lightexposurecorrection": "\u00b1 2EV (1/3EV step)",
    "dcinjack": "Yes",
    "builtinspeakers": "Yes",
    "ean": "N/A",
    "depth": "2.5 cm",
    "usbversion": "2.0",
    "minimumfocallength35mmfilmequiv": "2.3 cm",
    "maximumvideoresolution": "1920 x 1080 pixels",
    "displaydiagonal": "7.62 cm (3\")",
    "minimumharddiskspace": "250 MB",
    "autofocusingafmodes": "Centre weighted Auto Focus, Face detection, Multi Point Auto Focus, Tracking Auto Focus",
    "scenemodes": "Backlight, Fireworks, Landscape, Night, Night portrait, Panorama, Portrait, Spotlight, Sunset",
    "flashrechargingtime": "4s",
    "wifi": "Yes",
    "opticalzoom": "21x",
    "totalmegapixels": "16.7 MP",
    "numberofbatteriessupported": "1",
    "digitalzoom": "5x",
    "whitebalance": "Auto, Cloudy, Custom modes, Daylight, Fluorescent H, Fluorescent L, Tungsten"
}