{
    "lensstructureelementsgroups": "12/10",
    "isosensitivity": "100, 200, 400, 1600, 3200, Auto",
    "stillimageresolutions": "4:3 - (L) 4000 x 3000, (M1) 2816 x 2112, (M2) 1600 x 1200, (S) 640 x 480 16:9 - (L) 4000 x 2248, (M1) 2816 x 1584, (M2) 1920 x 1080, (S) 640 x 360 3:2 - (L) 4000 x 2664, (M1) 2816 x 1880, (M2) 1600 x 1064, (S) 640 x 424 1:1 - (L) 2992 x 2992, (M1) 2112 x 2112, (M2) 1200 x 1200, (S) 480 x 480",
    "focus": "TTL",
    "batterytype": "Rechargeable Li-ion Battery NB-6LH",
    "sku": "9337B012AA",
    "flashexposurecompensation": "Yes",
    "videoformatssupported": "MOV",
    "waterproof": "Yes (25m)",
    "builtinprocessor": "DIGIC 4",
    "sensortype": "CMOS",
    "batterylifecipastandard": "300 shots",
    "height": "6.8 cm",
    "focusadjustment": "Auto/Manual",
    "camerashutterspeedmin": "15s",
    "shockproof": "Yes (2m)",
    "pictbridge": "Yes",
    "flashrangetele": "1 - 3m",
    "weight": "218g",
    "autoexposureaelock": "Yes",
    "flashexposurelock": "Yes",
    "displaydiagonal": "7.62 cm (3\")",
    "category": "camera",
    "macoperatingsystemssupported": "Mac OS X 10.7 Lion, Mac OS X 10.8 Mountain Lion, Mac OS X 10.9 Mavericks",
    "imageformatssupported": "JPG",
    "lightmetering": "Centre-weighted, Evaluative (Multi-pattern), Spot",
    "specification": "Picture quality Image sensor size 25.4/58.4 mm (1/2.3\") Still image resolution(s) 4:3 - (L) 4000 x 3000, (M1) 2816 x 2112, (M2) 1600 x 1200, (S) 640 x 480 16:9 - (L) 4000 x 2248, (M1) 2816 x 1584, (M2) 1920 x 1080, (S) 640 x 360 3:2 - (L) 4000 x 2664, (M1) 2816 x 1880, (M2) 1600 x 1064, (S) 640 x 424 1:1 - (L) 2992 x 2992, (M1) 2112 x 2112, (M2) 1200 x 1200, (S) 480 x 480 Image stabilizer Yes Image formats supported JPG Maximum image resolution 4000 x 3000 pixels Sensor type CMOS Camera type Compact Megapixel 12.1 MP Lens system Focal length range (f-f) 5 - 25 mm Minimum focal length (35mm film equiv) 2.8 cm Maximum focal length (35mm film equiv) 14 cm Minimum aperture 3.9 Maximum aperture 4.8 Lens structure (elements/groups) 12/10 Combined zoom 20x Digital zoom 4x Optical zoom 5x Focusing Focus TTL Focus adjustment Auto/Manual Auto focusing (AF) modes Continuous Auto Focus, Face detection, Servo Auto Focus, Single Auto Focus, Tracking Auto Focus Closest focusing distance 0.01m Auto Focus (AF) lock Yes Auto Focus (AF) assist beam Yes Light exposure ISO sensitivity 100, 200, 400, 1600, 3200, Auto Light exposure correction \u00b1 2EV (1/3EV step) Light metering Centre-weighted, Evaluative (Multi-pattern), Spot Auto Exposure (AE) lock Yes ISO sensitivity (min) 100 ISO sensitivity (max) 3200 Shutter Camera shutter speed (min) 15s Camera shutter speed (max) 0.000625s Flash Flash modes Auto, Flash off, Flash on, Manual, Red-eye reduction, Slow synchronization Built-in flash Yes Flash sync-speed 0.000625s Flash range (wide) 0.3 - 3.5m Flash range (tele) 1 - 3m Flash exposure lock Yes Flash exposure compensation Yes Video Video resolutions 320 x 240, 640 x 480, 1280 x 720, 1920 x 1080 pixels Resolution at capture speed 1280\u00d7720@30fps, 1920x1080@24fps, 640x480@120fps, 640x480@30fps Video formats supported MOV Full HD Yes Analog signal format system NTSC, PAL Maximum video resolution 1920 x 1080 pixels Audio Built-in microphone Yes Memory Compatible memory cards SD, SDHC, SDXC Memory slots 1 Display Display LCD Display diagonal 7.62 cm (3\") Ports & interfaces USB version 2.0 HDMI connector type Mini PictBridge Yes USB connector type Mini-USB B HDMI Yes Camera Colour of product Blue White balance Auto, Cloudy, Custom modes, Daylight, Fluorescent, Fluorescent H, Tungsten, Underwater Scene modes Fireworks, Night, Portrait, Snow, Underwater Photo effects Black&White, Neutral, Positive film, Sepia, Skin tones, Vivid Self-timer 2, 10s Playback zoom (max) 10x Languages support Multi Histogram Yes GPS Yes Camera file system DPOF 1.1, Exif 2.3 Built-in processor DIGIC 4 Battery Battery technology Lithium-Ion (Li-Ion) Battery life (CIPA standard) 300 shots Number of batteries supported 1 Power source type Battery Operating system/software Windows operating systems supported Yes Mac operating systems supported Mac OS X 10.7 Lion, Mac OS X 10.8 Mountain Lion, Mac OS X 10.9 Mavericks Technical details Resolution at capture speed 1280\u00d7720@30fps, 1920x1080@24fps, 640x480@120fps, 640x480@30fps Languages support Multi HDMI Yes GPS Yes Processor Built-in processor DIGIC 4 Design Colour of product Blue Performance GPS Yes Built-in processor DIGIC 4 Operational conditions Operating temperature (T-T) -10 - 40 \u00b0C Operating relative humidity (H-H) 10 - 90% System requirements Windows operating systems supported Yes Mac operating systems supported Mac OS X 10.7 Lion, Mac OS X 10.8 Mountain Lion, Mac OS X 10.9 Mavericks Weight & dimensions Width 10.94 cm Depth 2.75 cm Height 6.8 cm Weight 218g",
    "autofocusafassistbeam": "Yes",
    "selftimer": "2, 10s",
    "maximumaperture": "4.8",
    "minimumaperture": "3.9",
    "resolutionatcapturespeed": "1280\u00d7720@30fps, 1920x1080@24fps, 640x480@120fps, 640x480@30fps",
    "hdmi": "Yes",
    "camerashutterspeed": "1 \u2013 1/1600 sec. (factory default)  15 \u2013 1/1600 sec. (total range \u2013 varies by shooting mode)",
    "fullhd": "Yes",
    "manufacturer": "Canon",
    "isosensitivitymin": "100",
    "analogsignalformatsystem": "NTSC, PAL",
    "flashmodes": "Auto, Flash off, Flash on, Manual, Red-eye reduction, Slow synchronization",
    "builtinflash": "Yes",
    "compatiblememorycards": "SD, SDHC, SDXC",
    "isosensitivitymax": "3200",
    "languagessupport": "Multi",
    "hdmiconnectortype": "Mini",
    "videocapability": "Yes",
    "photoeffects": "Black&White, Neutral, Positive film, Sepia, Skin tones, Vivid",
    "megapixel": "12.1 MP",
    "camerafilesystem": "DPOF 1.1, Exif 2.3",
    "builtinmicrophone": "Yes",
    "width": "10.94 cm",
    "windowsoperatingsystemssupported": "Yes",
    "playbackzoommax": "10x",
    "imagesensorsize": "25.4/58.4 mm (1/2.3\")",
    "gps": "Yes",
    "memoryslots": "1",
    "closestfocusingdistance": "0.01m",
    "histogram": "Yes",
    "powersourcetype": "Battery",
    "operatingrelativehumidityhh": "10 - 90%",
    "flashrangewide": "0.3 - 3.5m",
    "cameratype": "Compact",
    "colourofproduct": "Blue",
    "lcdscreensize": "3",
    "maximumfocallength35mmfilmequiv": "14 cm",
    "shortdescription": "12.1 MP (4000 x 3000 max.), 1/2.3\" CMOS, 5x optical/4x digital zoom, ISO 100-3200, FHD video, 7.62 cm (3 \") TFT LCD, USB 2.0, Mini HDMI, 218 g",
    "display": "LCD",
    "focallengthrangeff": "5 - 25 mm",
    "flashsyncspeed": "0.000625s",
    "lightexposurecorrection": "\u00b1 2EV (1/3EV step)",
    "camerashutterspeedmax": "0.000625s",
    "maximumimageresolution": "4000 x 3000 pixels",
    "operatingtemperaturett": "-10 - 40 \u00b0C",
    "autofocusaflock": "Yes",
    "usbconnectortype": "Mini-USB B",
    "ean": "8714574616001",
    "digitalzoom": "4x",
    "usbversion": "2.0",
    "minimumfocallength35mmfilmequiv": "2.8 cm",
    "dimensionswxdxh": "109.4 x 27.5 x 68 mm",
    "maximumvideoresolution": "1920 x 1080 pixels",
    "imagestabilizer": "Yes",
    "combinedzoom": "20x",
    "freezeproof": "Yes (-10?C)",
    "autofocusingafmodes": "Continuous Auto Focus, Face detection, Servo Auto Focus, Single Auto Focus, Tracking Auto Focus",
    "scenemodes": "Fireworks, Night, Portrait, Snow, Underwater",
    "videoresolutions": "320 x 240, 640 x 480, 1280 x 720, 1920 x 1080 pixels",
    "batterytechnology": "Lithium-Ion (Li-Ion)",
    "opticalzoom": "5x",
    "numberofbatteriessupported": "1",
    "depth": "2.75 cm",
    "whitebalance": "Auto, Cloudy, Custom modes, Daylight, Fluorescent, Fluorescent H, Tungsten, Underwater"
}