{
    "videocapability": "Yes",
    "autofocusafassistbeam": "Yes",
    "isosensitivity": "100, 200, 400, 800, 1600, Auto",
    "stillimageresolutions": "4608 x 3456, 3264 x 2448, 2048 x 1536, 640 x 480, 4608 x 2592",
    "focus": "TTL",
    "batterytype": "NB-11L",
    "sku": "9145B007AA",
    "videoformatssupported": "H.264, MOV",
    "builtinprocessor": "DIGIC 4+",
    "sensortype": "CCD",
    "batterylifecipastandard": "210 shots",
    "height": "5.43 cm",
    "camerashutterspeedmin": "0.0005s",
    "pictbridge": "Yes",
    "flashrangetele": "1.3 - 1.5m",
    "weight": "130g",
    "bluetooth": "No",
    "flashexposurelock": "Yes",
    "displaydiagonal": "6.86 cm (2.7\")",
    "category": "camera",
    "macoperatingsystemssupported": "Mac OS X 10.7 Lion, Mac OS X 10.8 Mountain Lion, Mac OS X 10.9 Mavericks",
    "imageformatssupported": "JPG",
    "lightmetering": "Centre-weighted, Evaluative (Multi-pattern), Spot",
    "specification": "Picture quality Image sensor size 25.4/58.4 mm (1/2.3\") Still image resolution(s) 4608 x 3456, 3264 x 2448, 2048 x 1536, 640 x 480, 4608 x 2592 Image stabilizer Yes Image formats supported JPG Maximum image resolution 4608 x 3456 pixels Sensor type CCD Camera type Compact Megapixel 16 MP Lens system Focal length range (f-f) 5 - 40 mm Minimum focal length (35mm film equiv) 2.8 cm Maximum focal length (35mm film equiv) 22.4 cm Minimum aperture 6.9 Maximum aperture 3.2 Lens structure (elements/groups) 8/7 Combined zoom 32x Digital zoom 4x Optical zoom 8x Focusing Focus TTL Auto focusing (AF) modes Continuous Auto Focus, Face detection, Servo Auto Focus, Single Auto Focus, Tracking Auto Focus Closest focusing distance 0.01m Auto Focus (AF) points 9 Auto Focus (AF) lock Yes Auto Focus (AF) assist beam Yes Light exposure ISO sensitivity 100, 200, 400, 800, 1600, Auto Light exposure correction \u00b1 2EV (1/3EV step) Light metering Centre-weighted, Evaluative (Multi-pattern), Spot Auto Exposure (AE) lock Yes ISO sensitivity (min) 100 ISO sensitivity (max) 1600 Shutter Camera shutter speed (min) 0.0005s Camera shutter speed (max) 15s Flash Flash modes Auto, Flash off, Flash on, Manual, Red-eye reduction, Slow synchronization Built-in flash Yes Flash sync-speed 0.0005s Flash range (wide) 0.5 - 3m Flash range (tele) 1.3 - 1.5m Flash exposure lock Yes Video Video resolutions 640 x 480, 1280 x 720 pixels Video formats supported H.264, MOV Full HD No Analog signal format system NTSC, PAL Maximum video resolution 1280 x 720 pixels Audio Built-in microphone Yes Memory Compatible memory cards SD, SDHC, SDXC Memory slots 1 Display Display LCD Display diagonal 6.86 cm (2.7\") Display resolution (numeric) 230000 pixels Ports & interfaces USB version 2.0 PictBridge Yes USB connector type Mini-USB B HDMI No Networking Bluetooth No Camera Colour of product Grey White balance Auto, Cloudy, Custom modes, Daylight, Fluorescent, Fluorescent H, Tungsten Scene modes Fireworks, Portrait, Self-portrait, Snow Photo effects Black&White, Vivid Self-timer 2, 10s Playback zoom (max) 10x Languages support ARA, CHI (SIMPL), CHI (TR), CZE, DAN, DEU, DUT, ENG, ESP, FIN, FRE, GRE, HEB, HUN, ITA, JPN, KOR, NOR, POL, POR, RUM, RUS, SWE, THA, TUR, UKR Histogram Yes Camera file system DPOF 1.1, Exif 2.3 Built-in processor DIGIC 4+ Battery Battery technology Lithium-Ion (Li-Ion) Battery life (CIPA standard) 210 shots Battery type NB-11L Number of batteries supported 1 Power source type Battery Operating system/software Windows operating systems supported Windows 7 Home Basic, Windows 7 Home Basic x64, Windows 7 Home Premium, Windows 7 Home Premium x64, Windows 7 Professional, Windows 7 Professional x64, Windows 7 Starter, Windows 7 Starter x64, Windows 7 Ultimate, Windows 7 Ultimate x64, Windows 8, Windows 8 Enterprise, Windows 8 Enterprise x64, Windows 8 Pro, Windows 8 Pro x64, Windows 8 x64, Windows 8.1, Windows 8.1 Enterprise, Windows 8.1 Enterprise x64, Windows 8.1 Pro, Windows 8.1 Pro x64, Windows 8.1 x64, Windows Vista Business, Windows Vista Business x64, Windows Vista Enterprise, Windows Vista Enterprise x64, Windows Vista Home Basic, Windows Vista Home Basic x64, Windows Vista Home Premium, Windows Vista Home Premium x64, Windows Vista Ultimate, Windows Vista Ultimate x64, Windows XP Home, Windows XP Home x64, Windows XP Professional, Windows XP Professional x64 Mac operating systems supported Mac OS X 10.7 Lion, Mac OS X 10.8 Mountain Lion, Mac OS X 10.9 Mavericks Bundled software ImageBrowser EX Technical details Languages support ARA, CHI (SIMPL), CHI (TR), CZE, DAN, DEU, DUT, ENG, ESP, FIN, FRE, GRE, HEB, HUN, ITA, JPN, KOR, NOR, POL, POR, RUM, RUS, SWE, THA, TUR, UKR HDMI No Processor Built-in processor DIGIC 4+ Design Colour of product Grey Performance Built-in processor DIGIC 4+ Operational conditions Operating temperature (T-T) 0 - 40 \u00b0C Operating relative humidity (H-H) 10 - 90% System requirements Windows operating systems supported Windows 7 Home Basic, Windows 7 Home Basic x64, Windows 7 Home Premium, Windows 7 Home Premium x64, Windows 7 Professional, Windows 7 Professional x64, Windows 7 Starter, Windows 7 Starter x64, Windows 7 Ultimate, Windows 7 Ultimate x64, Windows 8, Windows 8 Enterprise, Windows 8 Enterprise x64, Windows 8 Pro, Windows 8 Pro x64, Windows 8 x64, Windows 8.1, Windows 8.1 Enterprise, Windows 8.1 Enterprise x64, Windows 8.1 Pro, Windows 8.1 Pro x64, Windows 8.1 x64, Windows Vista Business, Windows Vista Business x64, Windows Vista Enterprise, Windows Vista Enterprise x64, Windows Vista Home Basic, Windows Vista Home Basic x64, Windows Vista Home Premium, Windows Vista Home Premium x64, Windows Vista Ultimate, Windows Vista Ultimate x64, Windows XP Home, Windows XP Home x64, Windows XP Professional, Windows XP Professional x64 Mac operating systems supported Mac OS X 10.7 Lion, Mac OS X 10.8 Mountain Lion, Mac OS X 10.9 Mavericks Weight & dimensions Width 9.52 cm Depth 2.21 cm Height 5.43 cm Weight 130g Packaging content Bundled software ImageBrowser EX",
    "lensstructureelementsgroups": "8/7",
    "selftimer": "2, 10s",
    "maximumaperture": "3.2",
    "minimumaperture": "6.9",
    "hdmi": "No",
    "camerashutterspeed": "1 \u2013 1/2000 sec. (factory default)  15 \u2013 1/2000 sec. (total range \u2013 varies by shooting mode)",
    "fullhd": "No",
    "displayresolutionnumeric": "230000 pixels",
    "manufacturer": "Canon",
    "isosensitivitymin": "100",
    "analogsignalformatsystem": "NTSC, PAL",
    "bundledsoftware": "ImageBrowser EX",
    "flashmodes": "Auto, Flash off, Flash on, Manual, Red-eye reduction, Slow synchronization",
    "builtinflash": "Yes",
    "compatiblememorycards": "SD, SDHC, SDXC",
    "isosensitivitymax": "1600",
    "languagessupport": "ARA, CHI (SIMPL), CHI (TR), CZE, DAN, DEU, DUT, ENG, ESP, FIN, FRE, GRE, HEB, HUN, ITA, JPN, KOR, NOR, POL, POR, RUM, RUS, SWE, THA, TUR, UKR",
    "videoresolutions": "640 x 480, 1280 x 720 pixels",
    "warranty": "1 Year",
    "photoeffects": "Black&White, Vivid",
    "megapixel": "16 MP",
    "camerafilesystem": "DPOF 1.1, Exif 2.3",
    "builtinmicrophone": "Yes",
    "width": "9.52 cm",
    "windowsoperatingsystemssupported": "Windows 7 Home Basic, Windows 7 Home Basic x64, Windows 7 Home Premium, Windows 7 Home Premium x64, Windows 7 Professional, Windows 7 Professional x64, Windows 7 Starter, Windows 7 Starter x64, Windows 7 Ultimate, Windows 7 Ultimate x64, Windows 8, Windows 8 Enterprise, Windows 8 Enterprise x64, Windows 8 Pro, Windows 8 Pro x64, Windows 8 x64, Windows 8.1, Windows 8.1 Enterprise, Windows 8.1 Enterprise x64, Windows 8.1 Pro, Windows 8.1 Pro x64, Windows 8.1 x64, Windows Vista Business, Windows Vista Business x64, Windows Vista Enterprise, Windows Vista Enterprise x64, Windows Vista Home Basic, Windows Vista Home Basic x64, Windows Vista Home Premium, Windows Vista Home Premium x64, Windows Vista Ultimate, Windows Vista Ultimate x64, Windows XP Home, Windows XP Home x64, Windows XP Professional, Windows XP Professional x64",
    "playbackzoommax": "10x",
    "imagesensorsize": "25.4/58.4 mm (1/2.3\")",
    "memoryslots": "1",
    "closestfocusingdistance": "0.01m",
    "histogram": "Yes",
    "powersourcetype": "Battery",
    "operatingrelativehumidityhh": "10 - 90%",
    "flashrangewide": "0.5 - 3m",
    "cameratype": "Compact",
    "colourofproduct": "Grey",
    "lcdscreensize": "2.7",
    "reviews": "No",
    "maximumfocallength35mmfilmequiv": "22.4 cm",
    "shortdescription": "Digital IXUS 150 - 16 MP (4608 x 3456), 1/2.3\" CCD, ISO 100-1600, 6.858 cm (2.7 \") LCD, USB 2.0, 130 g",
    "display": "LCD",
    "focallengthrangeff": "5 - 40 mm",
    "flashsyncspeed": "0.0005s",
    "lightexposurecorrection": "\u00b1 2EV (1/3EV step)",
    "camerashutterspeedmax": "15s",
    "maximumimageresolution": "4608 x 3456 pixels",
    "operatingtemperaturett": "0 - 40 \u00b0C",
    "autofocusaflock": "Yes",
    "usbconnectortype": "Mini-USB B",
    "ean": "8714574615349",
    "digitalzoom": "4x",
    "usbversion": "2.0",
    "minimumfocallength35mmfilmequiv": "2.8 cm",
    "dimensionswxdxh": "95.2 x 22.1 x 54.3 mm",
    "maximumvideoresolution": "1280 x 720 pixels",
    "imagestabilizer": "Yes",
    "combinedzoom": "32x",
    "autofocusafpoints": "9",
    "autofocusingafmodes": "Continuous Auto Focus, Face detection, Servo Auto Focus, Single Auto Focus, Tracking Auto Focus",
    "scenemodes": "Fireworks, Portrait, Self-portrait, Snow",
    "wifi": "No",
    "batterytechnology": "Lithium-Ion (Li-Ion)",
    "opticalzoom": "8x",
    "numberofbatteriessupported": "1",
    "depth": "2.21 cm",
    "autoexposureaelock": "Yes",
    "whitebalance": "Auto, Cloudy, Custom modes, Daylight, Fluorescent, Fluorescent H, Tungsten"
}