{
    "videocapability": "Yes",
    "flashrangetele": "2 - 3m",
    "cablesincluded": "USB",
    "weight": "246g",
    "numberofbatteriessupported": "1",
    "audioformatssupported": "AC3",
    "isosensitivity": "80, 100, 200, 400, 800, 1600, 3200, 6400, 12800, Auto",
    "stillimageresolutions": "5184 x 3456, 3648 x 2432, 2592 x 1728, 5184 x 3888, 3648 x 2736, 2592 x 1944, 5184 x 2920, 3648 x 2056, 1920 x 1080, 3888 x 3888, 2736 x 2736, 1920 x 1920, 7152 x 1080, 4912 x 1920, 4912 1080, 3424 x 1920, 11520 x 1080",
    "height": "6.36 cm",
    "nearfieldcommunicationnfc": "Yes",
    "lightexposurecorrection": "\u00b1 2EV (1/3EV step)",
    "maximumimageresolution": "5184 x 3456 pixels",
    "hdmiconnectortype": "Micro",
    "tripodmountable": "Yes",
    "focallengthrangeff": "4.3 - 129 mm",
    "lcdscreensize": "3",
    "batterytype": "NP-BX1",
    "sku": "DSCHX60B.CEH",
    "usbversion": "2.0",
    "builtinmicrophone": "Yes",
    "batteriesincluded": "Yes",
    "contrastadjustment": "Yes",
    "imageformatssupported": "JPG",
    "specification": "Picture quality Image sensor size 25.4/58.4 mm (1/2.3\") Supported aspect ratios 1:1, 3:2, 4:3, 16:9 Still image resolution(s) 5184 x 3456, 3648 x 2432, 2592 x 1728, 5184 x 3888, 3648 x 2736, 2592 x 1944, 5184 x 2920, 3648 x 2056, 1920 x 1080, 3888 x 3888, 2736 x 2736, 1920 x 1920, 7152 x 1080, 4912 x 1920, 4912 1080, 3424 x 1920, 11520 x 1080 Image stabilizer Yes Image formats supported JPG Maximum image resolution 5184 x 3456 pixels Sensor type CMOS Camera type Compact Megapixel 20.4 MP Lens system Focal length range (f-f) 4.3 - 129 mm Minimum aperture 6.3 Maximum aperture 3.5 Lens structure (elements/groups) 11/10 Optical zoom 30x Focusing Auto focusing (AF) modes Continuous Auto Focus, Single Auto Focus Macro focusing range (wide) 0.05 - ? Macro focusing range (tele) 2.0 - ? Auto Mode focusing range (wide) 0.05 - ? Auto Mode focusing range (tele) 2.0 - ? Light exposure ISO sensitivity 80, 100, 200, 400, 800, 1600, 3200, 6400, 12800, Auto Light exposure correction \u00b1 2EV (1/3EV step) ISO sensitivity (min) 80 ISO sensitivity (max) 12800 Flash Flash modes Auto, Flash off, Flash on, Slow synchronization Built-in flash Yes Flash range (wide) 0.25 - 5.6m Flash range (tele) 2 - 3m Video Video resolutions 640 x 480, 1440 x 1080, 1920 x 1080 pixels Video formats supported MP4 Motion JPEG frame rate 30 fps Full HD Yes Analog signal format system NTSC, PAL Maximum video resolution 1920 x 1080 pixels Audio Built-in microphone Yes Voice recording Yes Audio system Stereo Audio formats supported AC3 Memory Compatible memory cards MS Duo, MS PRO Duo, MS PRO Duo Mark 2, MS Pro-HG Duo, SD, SDHC, SDXC Display Display LCD Display diagonal 7.62 cm (3\") Display resolution (numeric) 921600 pixels Viewfinder Viewfinder type No Ports & interfaces USB version 2.0 HDMI connector type Micro HDMI Yes Networking Wi-Fi standards 802.11b, 802.11g, 802.11n Near Field Communication (NFC) Yes Wi-Fi Yes Camera Colour of product Black White balance Auto, Custom modes, Daylight, Flash, Fluorescent, Incandescent Scene modes Beach, Fireworks, Landscape, Night portrait, Portrait, Snow Self-timer 2, 10s Contrast adjustment Yes Tripod mountable Yes GPS No Brightness adjustment Yes Battery Battery life (CIPA standard) 380 shots Battery type NP-BX1 Number of batteries supported 1 Power source type Battery Operating system/software Windows operating systems supported Yes Technical details Quick start guide Yes HDMI Yes GPS No Audio system Stereo Design Colour of product Black Performance GPS No System requirements Windows operating systems supported Yes Weight & dimensions Width 10.81 cm Depth 3.83 cm Height 6.36 cm Weight 246g Weight (including battery) 272g Packaging content Quick start guide Yes Cables included USB Batteries included Yes AC adapter included Yes",
    "lensstructureelementsgroups": "11/10",
    "selftimer": "2, 10s",
    "width": "10.81 cm",
    "supportedaspectratios": "1:1, 3:2, 4:3, 16:9",
    "windowsoperatingsystemssupported": "Yes",
    "maximumaperture": "3.5",
    "imagesensorsize": "25.4/58.4 mm (1/2.3\")",
    "minimumaperture": "6.3",
    "voicerecording": "Yes",
    "videoformatssupported": "MP4",
    "macrofocusingrangetele": "2.0 - ?",
    "motionjpegframerate": "30 fps",
    "category": "camera",
    "weightincludingbattery": "272g",
    "imagestabilizer": "Yes",
    "displaydiagonal": "7.62 cm (3\")",
    "automodefocusingrangetele": "2.0 - ?",
    "ean": "4905524980110",
    "isosensitivitymin": "80",
    "camerashutterspeed": "iAuto (4 - 1/1600) / Program Auto (1 - 1/1600) / Aperture Priority (8 - 1/1600) / Shutter Priority (30 - 1/1600) / Manual (30 - 1/1600)",
    "hdmi": "Yes",
    "autofocusingafmodes": "Continuous Auto Focus, Single Auto Focus",
    "sensortype": "CMOS",
    "scenemodes": "Beach, Fireworks, Landscape, Night portrait, Portrait, Snow",
    "display": "LCD",
    "batterylifecipastandard": "380 shots",
    "fullhd": "Yes",
    "dimensionswxdxh": "108.1 x 38.3 x 63.6 mm",
    "wifi": "Yes",
    "powersourcetype": "Battery",
    "displayresolutionnumeric": "921600 pixels",
    "manufacturer": "Sony",
    "brightnessadjustment": "Yes",
    "acadapterincluded": "Yes",
    "analogsignalformatsystem": "NTSC, PAL",
    "maximumvideoresolution": "1920 x 1080 pixels",
    "macrofocusingrangewide": "0.05 - ?",
    "flashrangewide": "0.25 - 5.6m",
    "cameratype": "Compact",
    "builtinflash": "Yes",
    "audiosystem": "Stereo",
    "colourofproduct": "Black",
    "compatiblememorycards": "MS Duo, MS PRO Duo, MS PRO Duo Mark 2, MS Pro-HG Duo, SD, SDHC, SDXC",
    "wifistandards": "802.11b, 802.11g, 802.11n",
    "isosensitivitymax": "12800",
    "megapixel": "20.4 MP",
    "flashmodes": "Auto, Flash off, Flash on, Slow synchronization",
    "depth": "3.83 cm",
    "viewfindertype": "No",
    "opticalzoom": "30x",
    "whitebalance": "Auto, Custom modes, Daylight, Flash, Fluorescent, Incandescent",
    "videoresolutions": "640 x 480, 1440 x 1080, 1920 x 1080 pixels",
    "gps": "No",
    "shortdescription": "20.4MP, 1/2.3 type (7.82mm) Exmor R CMOS, Sony G, 30x Opt. Zoom) 3.0\" TFT, MS XC-HG Duo/SDXC, BIONZ X, MicroUSB, MicroHDMI, Wi-Fi, NFC, 272g",
    "automodefocusingrangewide": "0.05 - ?",
    "quickstartguide": "Yes"
}