{
    "lightexposuremodes": "Aperture priority AE, Auto, Manual, Shutter priority AE",
    "isosensitivity": "100, 200, 400, 800, 1600, 3200, Auto",
    "stillimageresolutions": "4608 x 3456, 3264 x 2448, 2048 x 1536, 640 x 480, 4608 x 2592, 3264 x 1832, 1920 x 1080, 640 x 360, 4608 x 3072, 3264 x 2176, 2048 x 1368, 640 x 424, 3456 x 3456, 2448 x 2448, 1536 x 1536, 480 x 480",
    "focus": "TTL",
    "acadapterincluded": "Yes",
    "batterytype": "NB-6LH",
    "sku": "9338B014AA",
    "videoformatssupported": "AVC, H.264, MP4, MPEG4",
    "weightincludingbattery": "269g",
    "imagestabilizer": "Yes",
    "sensortype": "CMOS",
    "batterylifecipastandard": "250 shots",
    "imageprocessor": "DIGIC 6",
    "camerashutterspeedmin": "1s",
    "pictbridge": "Yes",
    "flashrangetele": "1 - 2m",
    "weight": "269 g",
    "audioformatssupported": "LC-AAC",
    "autoexposureaelock": "Yes",
    "flashexposurelock": "Yes",
    "category": "camera",
    "macoperatingsystemssupported": "Mac OS X 10.7 Lion, Mac OS X 10.8 Mountain Lion, Mac OS X 10.9 Mavericks",
    "imageformatssupported": "JPG",
    "lightmetering": "Centre-weighted, Evaluative (Multi-pattern), Spot",
    "specification": "Picture quality Image sensor size 25.4/58.4 mm (1/2.3\") Still image resolution(s) 4608 x 3456, 3264 x 2448, 2048 x 1536, 640 x 480, 4608 x 2592, 3264 x 1832, 1920 x 1080, 640 x 360, 4608 x 3072, 3264 x 2176, 2048 x 1368, 640 x 424, 3456 x 3456, 2448 x 2448, 1536 x 1536, 480 x 480 Image stabilizer Yes Image formats supported JPG Maximum image resolution 4608 x 3456 pixels Sensor type CMOS Camera type Compact Megapixel 16.1 MP Lens system Focal length range (f-f) 4.5 - 135 mm Minimum focal length (35mm film equiv) 2.5 cm Maximum focal length (35mm film equiv) 75 cm Minimum aperture 3.2 Maximum aperture 6.9 Lens structure (elements/groups) 13/10 Digital zoom 120x Optical zoom 30x Focusing Focus TTL Auto focusing (AF) modes Continuous Auto Focus, Servo Auto Focus, Single Auto Focus, Tracking Auto Focus Smile detection Yes Auto Focus (AF) points selection Auto, Manual Light exposure ISO sensitivity 100, 200, 400, 800, 1600, 3200, Auto Light exposure modes Aperture priority AE, Auto, Manual, Shutter priority AE Light exposure correction \u00b1 2EV (1/3EV step) Light metering Centre-weighted, Evaluative (Multi-pattern), Spot Auto Exposure (AE) lock Yes Shutter Camera shutter speed (min) 1s Camera shutter speed (max) 0.0003125s Flash Flash modes Auto, Flash off, Flash on, Manual, Red-eye reduction, Slow synchronization Built-in flash Yes Flash range (wide) 0.5 - 3.5m Flash range (tele) 1 - 2m Flash exposure lock Yes Flash exposure correction \u00b12EV (1/3 EV step) Video Video formats supported AVC, H.264, MP4, MPEG4 Full HD Yes Maximum video resolution 1920 x 1080 pixels Audio Built-in microphone Yes Audio formats supported LC-AAC Memory Compatible memory cards SD, SDHC, SDXC Display Display LCD Display diagonal 7.62 cm (3\") Display resolution (numeric) 922000 pixels Field of view 100% Ports & interfaces USB version 2.0 HDMI connector type Micro PictBridge Yes USB connector type Mini-USB B HDMI Yes Networking Wi-Fi standards 802.11b, 802.11g, 802.11n Wi-Fi Yes Camera Colour of product Black White balance Auto, Cloudy, Custom modes, Daylight, Fluorescent, Fluorescent H, Manual, Tungsten Scene modes Fireworks, Portrait, Snow, Sports Shooting modes Aperture priority, Program, Shutter priority Photo effects Black&White, Neutral, Positive film, Sepia, Vivid Self-timer 2, 10s Playback zoom (max) 10x Orientation sensor Yes On Screen Display (OSD) languages ARA, CHI (SIMPL), CHI (TR), CZE, DAN, DEU, DUT, ENG, ESP, FIN, FRE, GRE, HEB, HUN, IND, ITA, JPN, KOR, NOR, PER, POL, POR, RUM, RUS, SWE, THA, TUR, UKR, VIE Histogram Yes Camera file system DCF, DPOF 1.1, Exif 2.3 Battery Battery technology Lithium-Ion (Li-Ion) Battery life (CIPA standard) 250 shots Battery type NB-6LH Power source type Battery Operating system/software Windows operating systems supported Yes Mac operating systems supported Mac OS X 10.7 Lion, Mac OS X 10.8 Mountain Lion, Mac OS X 10.9 Mavericks Bundled software ImageBrowser EX PhotoStitch Map Utility Technical details Carrying case Yes HDMI Yes Design Colour of product Black Operational conditions Operating temperature (T-T) 0 - 40 \u00b0C Operating relative humidity (H-H) 10 - 90% System requirements Windows operating systems supported Yes Mac operating systems supported Mac OS X 10.7 Lion, Mac OS X 10.8 Mountain Lion, Mac OS X 10.9 Mavericks Weight & dimensions Width 12.27 cm Depth 3.48 cm Height 6.58 cm Weight (including battery) 269g Packaging content Carrying case Yes Bundled software ImageBrowser EX PhotoStitch Map Utility Cables included USB Battery charger included Yes Batteries included Yes AC adapter included Yes Technical details Image processor DIGIC 6",
    "lensstructureelementsgroups": "13/10",
    "selftimer": "2, 10s",
    "maximumaperture": "6.9",
    "minimumaperture": "3.2",
    "hdmi": "Yes",
    "camerashutterspeed": "1 \u2013 1/3200 sec. (factory default)  15 \u2013 1/3200 sec. (total range \u2013 varies by shooting mode)",
    "onscreendisplayosdlanguages": "ARA, CHI (SIMPL), CHI (TR), CZE, DAN, DEU, DUT, ENG, ESP, FIN, FRE, GRE, HEB, HUN, IND, ITA, JPN, KOR, NOR, PER, POL, POR, RUM, RUS, SWE, THA, TUR, UKR, VIE",
    "fullhd": "Yes",
    "smiledetection": "Yes",
    "displayresolutionnumeric": "922000 pixels",
    "manufacturer": "Canon",
    "bundledsoftware": "ImageBrowser EX PhotoStitch Map Utility",
    "flashmodes": "Auto, Flash off, Flash on, Manual, Red-eye reduction, Slow synchronization",
    "builtinflash": "Yes",
    "compatiblememorycards": "SD, SDHC, SDXC",
    "hdmiconnectortype": "Micro",
    "videocapability": "Yes",
    "photoeffects": "Black&White, Neutral, Positive film, Sepia, Vivid",
    "cablesincluded": "USB",
    "megapixel": "16.1 MP",
    "wifistandards": "802.11b, 802.11g, 802.11n",
    "camerafilesystem": "DCF, DPOF 1.1, Exif 2.3",
    "builtinmicrophone": "Yes",
    "width": "12.27 cm",
    "windowsoperatingsystemssupported": "Yes",
    "playbackzoommax": "10x",
    "imagesensorsize": "25.4/58.4 mm (1/2.3\")",
    "batteriesincluded": "Yes",
    "ean": "8714574617527",
    "histogram": "Yes",
    "batterychargerincluded": "Yes",
    "powersourcetype": "Battery",
    "operatingrelativehumidityhh": "10 - 90%",
    "flashrangewide": "0.5 - 3.5m",
    "cameratype": "Compact",
    "colourofproduct": "Black",
    "lcdscreensize": "3",
    "shootingmodes": "Aperture priority, Program, Shutter priority",
    "maximumfocallength35mmfilmequiv": "75 cm",
    "shortdescription": "16.1 MP CMOS, 30x, ISO 100-3200, Full-HD, DIGIC 6, 7.62 cm (3.0 \") LCD, USB, micro-HDMI, Wi-Fi",
    "display": "LCD",
    "maximumimageresolution": "4608 x 3456 pixels",
    "focallengthrangeff": "4.5 - 135 mm",
    "autofocusafpointsselection": "Auto, Manual",
    "fieldofview": "100%",
    "camerashutterspeedmax": "0.0003125s",
    "flashexposurecorrection": "\u00b12EV (1/3 EV step)",
    "operatingtemperaturett": "0 - 40 \u00b0C",
    "lightexposurecorrection": "\u00b1 2EV (1/3EV step)",
    "usbconnectortype": "Mini-USB B",
    "depth": "3.48 cm",
    "usbversion": "2.0",
    "minimumfocallength35mmfilmequiv": "2.5 cm",
    "dimensionswxdxh": "112.7 x 34.8 x 65.8 mm",
    "maximumvideoresolution": "1920 x 1080 pixels",
    "displaydiagonal": "7.62 cm (3\")",
    "autofocusingafmodes": "Continuous Auto Focus, Servo Auto Focus, Single Auto Focus, Tracking Auto Focus",
    "scenemodes": "Fireworks, Portrait, Snow, Sports",
    "wifi": "Yes",
    "batterytechnology": "Lithium-Ion (Li-Ion)",
    "opticalzoom": "30x",
    "height": "6.58 cm",
    "digitalzoom": "120x",
    "orientationsensor": "Yes",
    "whitebalance": "Auto, Cloudy, Custom modes, Daylight, Fluorescent, Fluorescent H, Manual, Tungsten"
}