{
    "lensstructureelementsgroups": "12/10",
    "lightexposuremodes": "Aperture priority AE, Auto, Manual, Shutter priority AE",
    "isosensitivity": "80, 100, 200, 400, 800, 1600, 3200, 6400, Auto",
    "stillimageresolutions": "480 x 480, 640 x 360, 640 x 424, 640 x 480, 1200 x 1200, 1600 x 1064, 1600 x 1200, 1920 x 1080, 2112 x 2112, 2816 x 1584, 2816 x 1880, 2816 x 2112, 2992 x 2992, 4000 x 2248, 4000 x 2664, 4000 x 3000",
    "focus": "TTL",
    "acadapterincluded": "Yes",
    "batterytype": "NB-6L",
    "avoutput": "Yes",
    "sku": "8224B010AA",
    "usb20portsquantity": "1",
    "supportedaspectratios": "3:2, 4:3, 16:9",
    "flashexposurecompensation": "Yes",
    "videoformatssupported": "H.263, H.264, MPEG2, MPEG4",
    "maximumaperture": "6.8",
    "weightincludingbattery": "233g",
    "builtinprocessor": "DIGIC 6",
    "sensortype": "CMOS",
    "batterylifecipastandard": "260 shots",
    "height": "6.28 cm",
    "cameraplayback": "Movie, Single image",
    "focusadjustment": "Auto/Manual",
    "camerashutterspeedmin": "0.0003125s",
    "batterylifemax": "3.5h",
    "pictbridge": "Yes",
    "lightexposurecontrol": "Program AE",
    "flashrangetele": "1 - 2m",
    "autoexposureaelock": "Yes",
    "flashexposurelock": "Yes",
    "displaydiagonal": "7.62 cm (3\")",
    "category": "camera",
    "macoperatingsystemssupported": "Mac OS X 10.6 Snow Leopard, Mac OS X 10.7 Lion, Mac OS X 10.8 Mountain Lion",
    "imageformatssupported": "EXIF, JPG",
    "lightmetering": "Centre-weighted, Evaluative (Multi-pattern), Spot",
    "specification": "Picture quality Image sensor size 25.4/58.4 mm (1/2.3\") Supported aspect ratios 3:2, 4:3, 16:9 Still image resolution(s) 480 x 480, 640 x 360, 640 x 424, 640 x 480, 1200 x 1200, 1600 x 1064, 1600 x 1200, 1920 x 1080, 2112 x 2112, 2816 x 1584, 2816 x 1880, 2816 x 2112, 2992 x 2992, 4000 x 2248, 4000 x 2664, 4000 x 3000 Image stabilizer Yes Image formats supported EXIF, JPG Maximum image resolution 4000 x 3000 pixels Sensor type CMOS Camera type Compact Megapixel 12.1 MP Lens system Focal length range (f-f) 4.5 - 90 mm Minimum focal length (35mm film equiv) 2.5 cm Maximum focal length (35mm film equiv) 50 cm Minimum aperture 3.5 Maximum aperture 6.8 Lens structure (elements/groups) 12/10 Lens type Wide-angle zoom Digital zoom 4x Optical zoom 20x Focusing Focus TTL Focus adjustment Auto/Manual Auto focusing (AF) modes Continuous Auto Focus, Face detection, Servo Auto Focus, Single Auto Focus, Tracking Auto Focus Smile detection Yes Closest focusing distance 0.05m Auto Focus (AF) points 1 Auto Focus (AF) lock Yes Auto Focus (AF) assist beam Yes Light exposure ISO sensitivity 80, 100, 200, 400, 800, 1600, 3200, 6400, Auto Light exposure modes Aperture priority AE, Auto, Manual, Shutter priority AE Light exposure control Program AE Light exposure correction \u00b1 2EV (1/3EV step) Light metering Centre-weighted, Evaluative (Multi-pattern), Spot Auto Exposure (AE) lock Yes ISO sensitivity (min) 80 ISO sensitivity (max) 6400 Shutter Camera shutter speed (min) 0.0003125s Camera shutter speed (max) 15s Flash Flash modes Auto, Flash off, Flash on, Manual, Red-eye reduction, Slow synchronization Built-in flash Yes Flash sync-speed 0.0005s Flash range (wide) 0.5 - 3.5m Flash range (tele) 1 - 2m Flash exposure lock Yes Flash exposure correction \u00b12EV (1/3 EV step) Flash exposure compensation Yes External flash connector Yes Video Video resolutions 320 x 240, 640 x 480, 1280 x 720, 1920 x 1080 pixels Resolution at capture speed 1280\u00d7720@30fps, 640x480@30fps Video formats supported H.263, H.264, MPEG2, MPEG4 Motion JPEG frame rate 60 fps Full HD Yes Analog signal format system NTSC, PAL Maximum video resolution 1920 x 1080 pixels Memory Compatible memory cards SD, SDHC, SDXC Memory slots 1 Display Display TFT Display diagonal 7.62 cm (3\") Display resolution (numeric) 461000 pixels Field of view 100% Ports & interfaces PictBridge Yes USB 2.0 ports quantity 1 USB connector type Mini-USB B HDMI ports quantity 1 AV output Yes Networking Wi-Fi standards 802.11b, 802.11g, 802.11n Wi-Fi Yes Camera Colour of product Black White balance Auto, Cloudy, Custom modes, Daylight, Fluorescent, Fluorescent H, Tungsten, Underwater Scene modes Fireworks, Night, Portrait, Snow, Sports, Underwater Shooting modes Aperture priority, Auto, Manual, Movie, Program, Scene, Shutter priority Photo effects Black&White, Neutral, Positive film, Sepia, Vivid Self-timer 2, 10s Contrast adjustment Yes Camera playback Movie, Single image Orientation sensor Yes Languages support ARA, CHI (SIMPL), CHI (TR), CZE, DAN, DEU, DUT, ENG, ESP, FIN, FRE, GRE, HUN, ITA, JPN, KOR, NOR, POL, POR, RUM, RUS, SWE, THA, TUR, UKR Histogram Yes GPS Yes Direct printing Yes Custom colour Yes Camera file system DCF, DPOF 1.1, Exif 2.3 Built-in processor DIGIC 6 Brightness adjustment Yes Battery Battery technology Lithium-Ion (Li-Ion) Battery life (CIPA standard) 260 shots Battery life (max) 3.5h Battery type NB-6L Number of batteries supported 1 Power source type Battery Operating system/software Windows operating systems supported Windows 7 Home Basic, Windows 7 Home Basic x64, Windows 7 Home Premium, Windows 7 Home Premium x64, Windows 7 Professional, Windows 7 Professional x64, Windows 7 Starter, Windows 7 Starter x64, Windows 7 Ultimate, Windows 7 Ultimate x64, Windows 8, Windows 8 Enterprise, Windows 8 Enterprise x64, Windows 8 Pro, Windows 8 Pro x64, Windows 8 x64, Windows Vista Business, Windows Vista Business x64, Windows Vista Enterprise, Windows Vista Enterprise x64, Windows Vista Home Basic, Windows Vista Home Basic x64, Windows Vista Home Premium, Windows Vista Home Premium x64, Windows Vista Ultimate, Windows Vista Ultimate x64, Windows XP Home, Windows XP Home x64, Windows XP Professional, Windows XP Professional x64 Mac operating systems supported Mac OS X 10.6 Snow Leopard, Mac OS X 10.7 Lion, Mac OS X 10.8 Mountain Lion Technical details Quick start guide Yes USB 2.0 ports quantity 1 HDMI ports quantity 1 Resolution at capture speed 1280\u00d7720@30fps, 640x480@30fps Languages support ARA, CHI (SIMPL), CHI (TR), CZE, DAN, DEU, DUT, ENG, ESP, FIN, FRE, GRE, HUN, ITA, JPN, KOR, NOR, POL, POR, RUM, RUS, SWE, THA, TUR, UKR GPS Yes Direct printing Yes Processor Built-in processor DIGIC 6 Design Colour of product Black Performance GPS Yes Direct printing Yes Built-in processor DIGIC 6 Operational conditions Operating temperature (T-T) 0 - 40 \u00b0C Operating relative humidity (H-H) 10 - 90% System requirements Windows operating systems supported Windows 7 Home Basic, Windows 7 Home Basic x64, Windows 7 Home Premium, Windows 7 Home Premium x64, Windows 7 Professional, Windows 7 Professional x64, Windows 7 Starter, Windows 7 Starter x64, Windows 7 Ultimate, Windows 7 Ultimate x64, Windows 8, Windows 8 Enterprise, Windows 8 Enterprise x64, Windows 8 Pro, Windows 8 Pro x64, Windows 8 x64, Windows Vista Business, Windows Vista Business x64, Windows Vista Enterprise, Windows Vista Enterprise x64, Windows Vista Home Basic, Windows Vista Home Basic x64, Windows Vista Home Premium, Windows Vista Home Premium x64, Windows Vista Ultimate, Windows Vista Ultimate x64, Windows XP Home, Windows XP Home x64, Windows XP Professional, Windows XP Professional x64 Mac operating systems supported Mac OS X 10.6 Snow Leopard, Mac OS X 10.7 Lion, Mac OS X 10.8 Mountain Lion Weight & dimensions Width 10.64 cm Depth 3.26 cm Height 6.28 cm Weight (including battery) 233g Packaging content Quick start guide Yes Hand strap Yes Cables included AC, USB Battery charger included Yes Batteries included Yes AC adapter included Yes Other features USB 2.0 ports quantity 1 HDMI ports quantity 1",
    "autofocusafassistbeam": "Yes",
    "selftimer": "2, 10s",
    "customcolour": "Yes",
    "minimumaperture": "3.5",
    "resolutionatcapturespeed": "1280\u00d7720@30fps, 640x480@30fps",
    "motionjpegframerate": "60 fps",
    "fullhd": "Yes",
    "smiledetection": "Yes",
    "displayresolutionnumeric": "461000 pixels",
    "manufacturer": "Canon",
    "isosensitivitymin": "80",
    "analogsignalformatsystem": "NTSC, PAL",
    "flashmodes": "Auto, Flash off, Flash on, Manual, Red-eye reduction, Slow synchronization",
    "builtinflash": "Yes",
    "compatiblememorycards": "SD, SDHC, SDXC",
    "isosensitivitymax": "6400",
    "languagessupport": "ARA, CHI (SIMPL), CHI (TR), CZE, DAN, DEU, DUT, ENG, ESP, FIN, FRE, GRE, HUN, ITA, JPN, KOR, NOR, POL, POR, RUM, RUS, SWE, THA, TUR, UKR",
    "videoresolutions": "320 x 240, 640 x 480, 1280 x 720, 1920 x 1080 pixels",
    "quickstartguide": "Yes",
    "photoeffects": "Black&White, Neutral, Positive film, Sepia, Vivid",
    "cablesincluded": "AC, USB",
    "handstrap": "Yes",
    "megapixel": "12.1 MP",
    "wifistandards": "802.11b, 802.11g, 802.11n",
    "camerafilesystem": "DCF, DPOF 1.1, Exif 2.3",
    "width": "10.64 cm",
    "contrastadjustment": "Yes",
    "windowsoperatingsystemssupported": "Windows 7 Home Basic, Windows 7 Home Basic x64, Windows 7 Home Premium, Windows 7 Home Premium x64, Windows 7 Professional, Windows 7 Professional x64, Windows 7 Starter, Windows 7 Starter x64, Windows 7 Ultimate, Windows 7 Ultimate x64, Windows 8, Windows 8 Enterprise, Windows 8 Enterprise x64, Windows 8 Pro, Windows 8 Pro x64, Windows 8 x64, Windows Vista Business, Windows Vista Business x64, Windows Vista Enterprise, Windows Vista Enterprise x64, Windows Vista Home Basic, Windows Vista Home Basic x64, Windows Vista Home Premium, Windows Vista Home Premium x64, Windows Vista Ultimate, Windows Vista Ultimate x64, Windows XP Home, Windows XP Home x64, Windows XP Professional, Windows XP Professional x64",
    "imagesensorsize": "25.4/58.4 mm (1/2.3\")",
    "gps": "Yes",
    "batteriesincluded": "Yes",
    "memoryslots": "1",
    "closestfocusingdistance": "0.05m",
    "histogram": "Yes",
    "batterychargerincluded": "Yes",
    "powersourcetype": "Battery",
    "operatingrelativehumidityhh": "10 - 90%",
    "brightnessadjustment": "Yes",
    "flashrangewide": "0.5 - 3.5m",
    "cameratype": "Compact",
    "colourofproduct": "Black",
    "shootingmodes": "Aperture priority, Auto, Manual, Movie, Program, Scene, Shutter priority",
    "maximumfocallength35mmfilmequiv": "50 cm",
    "lenstype": "Wide-angle zoom",
    "shortdescription": "PowerShot SX280 HS - 12.1MP, 4000 x 3000, CMOS 1/2.3\", DIGIC 6, f/3.5 - f/6.8, TTL, ISO: 80-6400, 7.62 cm (3 \") PureColor II G (TFT), 1920x1080/60fps, WLAN 802.11b/g/n, GPS, USB, mini HDMI, PAL/NTSC, SD/SDHC/SDXC, 233g, Black",
    "display": "TFT",
    "maximumimageresolution": "4000 x 3000 pixels",
    "focallengthrangeff": "4.5 - 90 mm",
    "flashsyncspeed": "0.0005s",
    "fieldofview": "100%",
    "externalflashconnector": "Yes",
    "autofocusaflock": "Yes",
    "camerashutterspeedmax": "15s",
    "flashexposurecorrection": "\u00b12EV (1/3 EV step)",
    "operatingtemperaturett": "0 - 40 \u00b0C",
    "lightexposurecorrection": "\u00b1 2EV (1/3EV step)",
    "usbconnectortype": "Mini-USB B",
    "ean": "8714574598604",
    "digitalzoom": "4x",
    "minimumfocallength35mmfilmequiv": "2.5 cm",
    "maximumvideoresolution": "1920 x 1080 pixels",
    "imagestabilizer": "Yes",
    "hdmiportsquantity": "1",
    "autofocusafpoints": "1",
    "autofocusingafmodes": "Continuous Auto Focus, Face detection, Servo Auto Focus, Single Auto Focus, Tracking Auto Focus",
    "scenemodes": "Fireworks, Night, Portrait, Snow, Sports, Underwater",
    "directprinting": "Yes",
    "wifi": "Yes",
    "batterytechnology": "Lithium-Ion (Li-Ion)",
    "opticalzoom": "20x",
    "numberofbatteriessupported": "1",
    "depth": "3.26 cm",
    "orientationsensor": "Yes",
    "whitebalance": "Auto, Cloudy, Custom modes, Daylight, Fluorescent, Fluorescent H, Tungsten, Underwater"
}