{
    "pictbridge": "No",
    "photoeffects": "Black&White, Negative film, Sepia",
    "wifi": "Yes",
    "weight": "410g",
    "lightexposuremodes": "Aperture priority AE, Auto, Manual, Shutter priority AE",
    "audioformatssupported": "AAC",
    "bluetoothversion": "4.0",
    "stillimageresolutions": "JPEG (3:2):20.0M (5472 x 3648), 10.1M (3888 x 2592), 5.9M (2976 x 1984), 2.0M (1728 x 1152), 5.0M (2736 x 1824): Burst mode only JPEG (16:9):16.9M (5472 x 3080), 7.8M (3712 x 2088), 4.9M (2944 x 1656), 2.1M (1920 x 1080) JPEG (1:1):13.3M (3648 x 3648), 7.0M (2640 x 2640), 4.0M (2000 x 2000), 1.1M (1024 x 1024) RAW : 20.0M (5472 x 3648) * 3D Lens Image Size: JPEG (16:9) 4.1M (2688 x 1512), (16:9) 2.1M (1920 x 1080)",
    "height": "2.57 cm",
    "acadapterincluded": "Yes",
    "datanetwork": "4G, HSPA+, LTE",
    "camerashutterspeedmax": "30s",
    "maximumimageresolution": "5472 x 3648 pixels",
    "operatingtemperaturett": "0 - 40 \u00b0C",
    "lightexposurecorrection": "\u00b1 3EV (1/3EV step)",
    "displaydiagonal": "12.12 cm (4.77\")",
    "seconddisplay": "No",
    "sku": "EK-GN120ZKABTU",
    "totalmegapixels": "21.6 MP",
    "powersourcetype": "Battery",
    "builtinmicrophone": "Yes",
    "wifistandards": "802.11a, 802.11b, 802.11g, 802.11n",
    "imageformatssupported": "JPEG XR",
    "specification": "Picture quality Supported aspect ratios 1:1, 3:2, 16:9 Still image resolution(s) JPEG (3:2):20.0M (5472 x 3648), 10.1M (3888 x 2592), 5.9M (2976 x 1984), 2.0M (1728 x 1152), 5.0M (2736 x 1824): Burst mode only JPEG (16:9):16.9M (5472 x 3080), 7.8M (3712 x 2088), 4.9M (2944 x 1656), 2.1M (1920 x 1080) JPEG (1:1):13.3M (3648 x 3648), 7.0M (2640 x 2640), 4.0M (2000 x 2000), 1.1M (1024 x 1024) RAW : 20.0M (5472 x 3648) * 3D Lens Image Size: JPEG (16:9) 4.1M (2688 x 1512), (16:9) 2.1M (1920 x 1080) Image stabilizer Yes Total megapixels 21.6 MP Image formats supported JPEG XR Maximum image resolution 5472 x 3648 pixels Sensor type CMOS Megapixel 20.3 MP Focusing Focus adjustment Auto/Manual Auto focusing (AF) modes Contrast Detection Auto Focus, Face detection Light exposure ISO sensitivity 100, 200, 400, 800, 1600, 3200, 6400, 12800, 25600, Auto Light exposure modes Aperture priority AE, Auto, Manual, Shutter priority AE Light exposure correction \u00b1 3EV (1/3EV step) ISO sensitivity (min) 100 ISO sensitivity (max) 25600 Shutter Camera shutter speed (max) 30s Camera shutter type Electronic Flash Shoe mounting point type Hot Flash modes Auto, Fill-in, Flash off, Red-eye reduction Built-in flash Yes Video Video resolutions 320 x 240, 640 x 480, 1280 x 720, 1920 x 810, 1920 x 1080 pixels Video formats supported H.264, MP4 Motion JPEG frame rate 30 fps Full HD Yes Maximum video resolution 1920 x 1080 pixels Audio Built-in microphone Yes Voice recording Yes Audio formats supported AAC Memory Internal memory 16 MB Compatible memory cards microSD (TransFlash), SDHC, SDXC Memory slots 1 Maximum memory card size 64 GB Display Display aspect ratio 16:9 Display LCD Display diagonal 12.12 cm (4.77\") Display resolution 1280 x 720 pixels Touch sensitive screen Yes Second display No Viewfinder Magnification 0.68x Ports & interfaces PictBridge No USB 2.0 ports quantity 1 HDMI ports quantity 1 Networking Data network 4G, HSPA+, LTE Wi-Fi standards 802.11a, 802.11b, 802.11g, 802.11n Bluetooth Yes Bluetooth version 4.0 Wi-Fi Yes Camera Colour of product Black White balance Auto, Cloudy, Custom modes, Daylight, Flash, Fluorescent H, Fluorescent L, Tungsten Scene modes Close-up (macro), Fireworks, Landscape, Night, Panorama, Party (indoor), Pet, Portrait, Snow, Sunrise, Sunset Photo effects Black&White, Negative film, Sepia Self-timer 2, 5, 10, 30s Processor clock speed 1.6 MHz Built-in processor Quad Core Battery Battery life (CIPA standard) 440 shots Battery capacity 4360 mAh Power source type Battery Technical details USB 2.0 ports quantity 1 HDMI ports quantity 1 Processor Processor clock speed 1.6 MHz Built-in processor Quad Core Design Colour of product Black Performance Processor clock speed 1.6 MHz Built-in processor Quad Core Operational conditions Operating temperature (T-T) 0 - 40 \u00b0C Operating relative humidity (H-H) 5 - 85% Weight & dimensions Width 13.65 cm Depth 10.12 cm Height 2.57 cm Weight 410g Weight (including battery) 495g Packaging content AC adapter included Yes Other features USB 2.0 ports quantity 1 HDMI ports quantity 1",
    "memoryslots": "1",
    "depth": "10.12 cm",
    "touchsensitivescreen": "Yes",
    "selftimer": "2, 5, 10, 30s",
    "width": "13.65 cm",
    "magnification": "0.68x",
    "supportedaspectratios": "1:1, 3:2, 16:9",
    "displayresolution": "1280 x 720 pixels",
    "maximumvideoresolution": "1920 x 1080 pixels",
    "processorclockspeed": "1.6 MHz",
    "displayaspectratio": "16:9",
    "videoformatssupported": "H.264, MP4",
    "isosensitivitymax": "25600",
    "category": "camera",
    "weightincludingbattery": "495g",
    "maximummemorycardsize": "64 GB",
    "hdmiportsquantity": "1",
    "motionjpegframerate": "30 fps",
    "ean": "8806085645233",
    "builtinprocessor": "Quad Core",
    "autofocusingafmodes": "Contrast Detection Auto Focus, Face detection",
    "internalmemory": "16 MB",
    "scenemodes": "Close-up (macro), Fireworks, Landscape, Night, Panorama, Party (indoor), Pet, Portrait, Snow, Sunrise, Sunset",
    "batterycapacity": "4360 mAh",
    "fullhd": "Yes",
    "bluetooth": "Yes",
    "usb20portsquantity": "1",
    "megapixel": "20.3 MP",
    "manufacturer": "Samsung",
    "sensortype": "CMOS",
    "imagestabilizer": "Yes",
    "isosensitivity": "100, 200, 400, 800, 1600, 3200, 6400, 12800, 25600, Auto",
    "focusadjustment": "Auto/Manual",
    "flashmodes": "Auto, Fill-in, Flash off, Red-eye reduction",
    "camerashuttertype": "Electronic",
    "operatingrelativehumidityhh": "5 - 85%",
    "compatiblememorycards": "microSD (TransFlash), SDHC, SDXC",
    "isosensitivitymin": "100",
    "voicerecording": "Yes",
    "reviews": "No",
    "colourofproduct": "Black",
    "builtinflash": "Yes",
    "whitebalance": "Auto, Cloudy, Custom modes, Daylight, Flash, Fluorescent H, Fluorescent L, Tungsten",
    "batterylifecipastandard": "440 shots",
    "videoresolutions": "320 x 240, 640 x 480, 1280 x 720, 1920 x 810, 1920 x 1080 pixels",
    "shortdescription": "20.3 Mpix, ScLCD 4.77\" 1280 x 720 HD, 16 GB, 1.6GHz CPU, USB 2.0, HDMI 1.4b",
    "display": "LCD"
}