{
    "lightexposuremodes": "Aperture priority AE, Auto, Manual, Shutter priority AE",
    "isosensitivity": "100, 200, 400, 800, 1600, 3200, 6400, 12800, 25600, 51200",
    "stillimageresolutions": "6000 x 4000, 4240 x 2832, 3008 x 2000, 6000 x 3376, 4240 x 2400, 3008 x 1688, 12416 x 1856, 5536 x 2160, 8192 x 1856, 3872 x 2160",
    "acadapterincluded": "Yes",
    "batterytype": "NP-FW50",
    "sku": "ILCE6000LBZDI.EU",
    "sensorformat": "Advanced Photo System type-C (APS-C)",
    "videoformatssupported": "AVCHD, H.264, MP4, MPEG4",
    "preflash": "Yes",
    "weightincludingbattery": "344g",
    "builtinprocessor": "BIONZ X",
    "sensortype": "CMOS",
    "batterylifecipastandard": "360 shots",
    "imageprocessor": "BIONZ X",
    "normalfocusingrange": "0.3 - 3.0m",
    "camerashutterspeedmin": "30s",
    "batterylifemax": "1.5h",
    "audiosystem": "Stereo",
    "lightexposurecontrol": "Program AE",
    "weight": "285g",
    "nearfieldcommunicationnfc": "Yes",
    "tripodmountable": "Yes",
    "category": "camera",
    "macoperatingsystemssupported": "Mac OS X 10.6 Snow Leopard, Mac OS X 10.7 Lion, Mac OS X 10.8 Mountain Lion, Mac OS X 10.9 Mavericks",
    "imageformatssupported": "JPG",
    "lightmetering": "Centre-weighted, Evaluative (Multi-pattern), Spot",
    "specification": "Picture quality Sensor format Advanced Photo System type-C (APS-C) Supported aspect ratios 3:2, 16:9 Still image resolution(s) 6000 x 4000, 4240 x 2832, 3008 x 2000, 6000 x 3376, 4240 x 2400, 3008 x 1688, 12416 x 1856, 5536 x 2160, 8192 x 1856, 3872 x 2160 Image stabilizer Yes Total megapixels 24.7 MP Image sensor size (W x H) 23.5 x 15.6 mm Image stabilizer location Lens Image formats supported JPG Maximum image resolution 6000 x 4000 pixels Sensor type CMOS Camera type MILC Megapixel 24.3 MP Lens system Focal length range (f-f) 17 - 70 mm Extra/Smart zoom 4x Lens mount interface Sony E Focusing Auto focusing (AF) modes Continuous Auto Focus Smile detection Yes Normal focusing range 0.3 - 3.0m Auto Focus (AF) points selection Auto Auto Focus (AF) points 179 Auto Focus (AF) lock Yes Auto Focus (AF) assist beam Yes Light exposure ISO sensitivity 100, 200, 400, 800, 1600, 3200, 6400, 12800, 25600, 51200 Light exposure modes Aperture priority AE, Auto, Manual, Shutter priority AE Light exposure control Program AE Light exposure correction \u00b15EV (1/2; 1/3 EV step) Light metering Centre-weighted, Evaluative (Multi-pattern), Spot ISO sensitivity (min) 100 ISO sensitivity (max) 51200 Shutter Camera shutter speed (min) 30s Camera shutter speed (max) 0.00025s Camera shutter type Electronic Flash Flash modes Auto, Fill-in, Flash off, Flash on, Red-eye reduction, Slow synchronization Built-in flash Yes Pre-flash Yes Flash sync-speed 1/160s Flash exposure correction \u00b13EV (1/2; 1/3 EV step) External flash connector Yes Video Video resolutions 1920 x 1080 pixels Video formats supported AVCHD, H.264, MP4, MPEG4 Full HD Yes Audio Built-in microphone Yes Audio system Stereo Memory Compatible memory cards MS PRO Duo, MS Pro-HG Duo, MS XC-HG Duo, SD, SDHC, SDXC Display Display TFT Display diagonal 7.62 cm (3\") Display resolution (numeric) 921600 pixels Field of view 100% Viewfinder Viewfinder type Electrical Magnification 1.07x Ports & interfaces HDMI connector type Micro USB connector type USB B HDMI Yes Networking Near Field Communication (NFC) Yes Wi-Fi Yes Camera Image stabilizer location Lens Colour of product Black White balance Auto, Cloudy, Daylight, Flash, Fluorescent, Incandescent, Shade, Underwater Scene modes Portrait, Landscape, Sunset, Night Portrait Photo effects Neutral, Vivid Self-timer 2, 10s Contrast adjustment Yes Saturation adjustment Yes Tripod mountable Yes Histogram Yes Camera file system DCF 2.0, Exif 2.3, RAW Built-in processor BIONZ X Brightness adjustment Yes Battery Battery life (CIPA standard) 360 shots Battery life (max) 1.5h Battery type NP-FW50 Number of batteries supported 1 Power source type Battery Operating system/software Windows operating systems supported Windows 7 Home Basic, Windows 7 Home Basic x64, Windows 7 Home Premium, Windows 7 Home Premium x64, Windows 7 Professional, Windows 7 Professional x64, Windows 7 Starter, Windows 7 Starter x64, Windows 7 Ultimate, Windows 7 Ultimate x64, Windows 8, Windows 8 Enterprise, Windows 8 Enterprise x64, Windows 8 Pro, Windows 8 Pro x64, Windows 8 x64, Windows 8.1, Windows 8.1 Enterprise, Windows 8.1 Enterprise x64, Windows 8.1 Pro, Windows 8.1 Pro x64, Windows 8.1 x64, Windows Vista Business, Windows Vista Business x64, Windows Vista Enterprise, Windows Vista Enterprise x64, Windows Vista Home Basic, Windows Vista Home Basic x64, Windows Vista Home Premium, Windows Vista Home Premium x64, Windows Vista Ultimate Mac operating systems supported Mac OS X 10.6 Snow Leopard, Mac OS X 10.7 Lion, Mac OS X 10.8 Mountain Lion, Mac OS X 10.9 Mavericks Technical details Pre-flash Yes HDMI Yes Audio system Stereo Processor Built-in processor BIONZ X Design Colour of product Black Performance Built-in processor BIONZ X System requirements Windows operating systems supported Windows 7 Home Basic, Windows 7 Home Basic x64, Windows 7 Home Premium, Windows 7 Home Premium x64, Windows 7 Professional, Windows 7 Professional x64, Windows 7 Starter, Windows 7 Starter x64, Windows 7 Ultimate, Windows 7 Ultimate x64, Windows 8, Windows 8 Enterprise, Windows 8 Enterprise x64, Windows 8 Pro, Windows 8 Pro x64, Windows 8 x64, Windows 8.1, Windows 8.1 Enterprise, Windows 8.1 Enterprise x64, Windows 8.1 Pro, Windows 8.1 Pro x64, Windows 8.1 x64, Windows Vista Business, Windows Vista Business x64, Windows Vista Enterprise, Windows Vista Enterprise x64, Windows Vista Home Basic, Windows Vista Home Basic x64, Windows Vista Home Premium, Windows Vista Home Premium x64, Windows Vista Ultimate Mac operating systems supported Mac OS X 10.6 Snow Leopard, Mac OS X 10.7 Lion, Mac OS X 10.8 Mountain Lion, Mac OS X 10.9 Mavericks Weight & dimensions Width 12 cm Depth 4.51 cm Height 6.69 cm Weight 285g Weight (including battery) 344g Packaging content Hand strap Yes Cables included USB Battery charger included Yes Batteries included Yes AC adapter included Yes Technical details Image processor BIONZ X Smartphone remote support Yes Built-in speaker(s) Yes",
    "autofocusafassistbeam": "Yes",
    "selftimer": "2, 10s",
    "saturationadjustment": "Yes",
    "hdmi": "Yes",
    "fullhd": "Yes",
    "extrasmartzoom": "4x",
    "smiledetection": "Yes",
    "displayresolutionnumeric": "921600 pixels",
    "manufacturer": "Sony",
    "isosensitivitymin": "100",
    "flashmodes": "Auto, Fill-in, Flash off, Flash on, Red-eye reduction, Slow synchronization",
    "builtinflash": "Yes",
    "compatiblememorycards": "MS PRO Duo, MS Pro-HG Duo, MS XC-HG Duo, SD, SDHC, SDXC",
    "isosensitivitymax": "51200",
    "videoresolutions": "1920 x 1080 pixels",
    "photoeffects": "Neutral, Vivid",
    "cablesincluded": "USB",
    "handstrap": "Yes",
    "height": "6.69 cm",
    "camerafilesystem": "DCF 2.0, Exif 2.3, RAW",
    "builtinmicrophone": "Yes",
    "contrastadjustment": "Yes",
    "width": "12 cm",
    "magnification": "1.07x",
    "supportedaspectratios": "3:2, 16:9",
    "windowsoperatingsystemssupported": "Windows 7 Home Basic, Windows 7 Home Basic x64, Windows 7 Home Premium, Windows 7 Home Premium x64, Windows 7 Professional, Windows 7 Professional x64, Windows 7 Starter, Windows 7 Starter x64, Windows 7 Ultimate, Windows 7 Ultimate x64, Windows 8, Windows 8 Enterprise, Windows 8 Enterprise x64, Windows 8 Pro, Windows 8 Pro x64, Windows 8 x64, Windows 8.1, Windows 8.1 Enterprise, Windows 8.1 Enterprise x64, Windows 8.1 Pro, Windows 8.1 Pro x64, Windows 8.1 x64, Windows Vista Business, Windows Vista Business x64, Windows Vista Enterprise, Windows Vista Enterprise x64, Windows Vista Home Basic, Windows Vista Home Basic x64, Windows Vista Home Premium, Windows Vista Home Premium x64, Windows Vista Ultimate",
    "batteriesincluded": "Yes",
    "ean": "5013493248403",
    "histogram": "Yes",
    "batterychargerincluded": "Yes",
    "powersourcetype": "Battery",
    "megapixel": "24.3 MP",
    "brightnessadjustment": "Yes",
    "cameratype": "MILC",
    "camerashuttertype": "Electronic",
    "colourofproduct": "Black",
    "lensmountinterface": "Sony E",
    "reviews": "No",
    "externalflashconnector": "Yes",
    "shortdescription": "Body + 16-70mm, 24.3 MP, APS-C type (23.5 x 15.6mm) Exmor APS HD CMOS, 6000 x 4000, Memory Stick XC-HG Duo, SDXC, ISO 100 - 51200, 7.62 cm (3.0 \") TFT",
    "display": "TFT",
    "imagestabilizerlocation": "Lens",
    "focallengthrangeff": "17 - 70 mm",
    "autofocusafpointsselection": "Auto",
    "flashsyncspeed": "1/160s",
    "fieldofview": "100%",
    "autofocusaflock": "Yes",
    "camerashutterspeedmax": "0.00025s",
    "maximumimageresolution": "6000 x 4000 pixels",
    "lightexposurecorrection": "\u00b15EV (1/2; 1/3 EV step)",
    "usbconnectortype": "USB B",
    "builtinspeakers": "Yes",
    "imagestabilizer": "Yes",
    "displaydiagonal": "7.62 cm (3\")",
    "autofocusafpoints": "179",
    "autofocusingafmodes": "Continuous Auto Focus",
    "scenemodes": "Portrait, Landscape, Sunset, Night Portrait",
    "hdmiconnectortype": "Micro",
    "wifi": "Yes",
    "flashexposurecorrection": "\u00b13EV (1/2; 1/3 EV step)",
    "imagesensorsizewxh": "23.5 x 15.6 mm",
    "totalmegapixels": "24.7 MP",
    "numberofbatteriessupported": "1",
    "depth": "4.51 cm",
    "viewfindertype": "Electrical",
    "whitebalance": "Auto, Cloudy, Daylight, Flash, Fluorescent, Incandescent, Shade, Underwater"
}