{
    "hdmiversion": "1.4a",
    "colourofproduct": "Black",
    "minimumram": "250 MB",
    "numberofbatteriessupported": "1",
    "audioformatssupported": "AAC",
    "isosensitivity": "100, 200, 400, 800, 1600, 12800, 25600",
    "fieldofview": "100%",
    "height": "6.37 cm",
    "lightexposurecorrection": "\u00b1 3EV (1/3EV step)",
    "builtinprocessor": "DRIMe IV",
    "camerashutterspeedmax": "0.000166667s",
    "maximumimageresolution": "5472 x 3648 pixels",
    "tripodmountable": "Yes",
    "displaydiagonal": "8.41 cm (3.31\")",
    "isosensitivitymax": "25600",
    "batterytype": "BP1130",
    "camerafilesystem": "DPOF 1.1, Exif 2.21",
    "category": "camera",
    "imageediting": "Crop, Resizing, Rotating",
    "builtinmicrophone": "Yes",
    "weight": "280g",
    "autofocusingafmodes": "Continuous Auto Focus, Single Auto Focus",
    "usbconnectortype": "Micro-USB B",
    "imageformatssupported": "JPG, RAW",
    "lightmetering": "Centre-weighted, Evaluative (Multi-pattern), Spot",
    "specification": "Picture quality Supported aspect ratios 3:2, 16:9 Still image resolution(s) 1024 x 1024, 1728 x 1152, 1920 x 1080, 2000 x 2000, 2112 x 2112, 2640 x 2640, 2736 x 1824, 2944 x 1656, 2976 x 1984, 3648 x 3648, 3712 x 2088, 3888 x 2592, 5472 x 3080 Total megapixels 21.6 MP Image formats supported JPG, RAW Maximum image resolution 5472 x 3648 pixels Sensor type CMOS Camera type MILC Megapixel 20.3 MP Lens system Lens mount interface Samsung NX Focusing Auto focusing (AF) modes Continuous Auto Focus, Single Auto Focus Light exposure ISO sensitivity 100, 200, 400, 800, 1600, 12800, 25600 Light exposure correction \u00b1 3EV (1/3EV step) Light metering Centre-weighted, Evaluative (Multi-pattern), Spot ISO sensitivity (min) 100 ISO sensitivity (max) 25600 Shutter Camera shutter speed (min) 30s Camera shutter speed (max) 0.000166667s Flash Flash modes Auto, Fill-in, Forced off, Red-eye reduction Built-in flash Yes Flash sync-speed 1/180s Video Video resolutions 320 x 240, 640 x 480, 1280 x 720, 1920 x 810, 1920 x 1080 pixels Video formats supported H.264, MP4, MPEG4 Full HD Yes Analog signal format system NTSC, PAL Maximum video resolution 1920 x 1080 pixels Audio Built-in microphone Yes Voice recording Yes Audio formats supported AAC Memory Compatible memory cards SD, SDHC, SDXC Display Display AMOLED Display diagonal 8.41 cm (3.31\") Display resolution 800 x 400 pixels Display resolution (numeric) 768000 pixels Vari-angle LCD display Yes Touch sensitive screen Yes Field of view 100% Ports & interfaces USB version 2.0 HDMI version 1.4a USB 2.0 ports quantity 1 USB connector type Micro-USB B HDMI ports quantity 1 HDMI Yes Networking Wi-Fi standards 802.11b, 802.11g, 802.11n Wi-Fi Yes Camera Colour of product Black White balance Auto, Cloudy, Custom modes, Daylight, Flash, Fluorescent, Manual, Tungsten Scene modes Fireworks, Night, Panorama, Sunset Shooting modes Aperture priority, Auto, Lens priority, Manual, Program, Shutter priority Saturation adjustment Yes Camera playback Movie, Single image Tripod mountable Yes On Screen Display (OSD) languages ARA, CHI (SIMPL), CHI (TR), CZE, DAN, DEU, DUT, ESP, EST, FIN, FRE, GRE, HUN, ITA, KOR, LAV, NOR, POL, POR, SWE, THA, TUR Image quality adjustment Brightness, Contrast Image editing Crop, Resizing, Rotating Histogram Yes GPS Yes Camera file system DPOF 1.1, Exif 2.21 Built-in processor DRIMe IV Anti-dust function Yes Battery Battery life (CIPA standard) 320 shots Battery capacity 1130 mAh Battery life (max) 2.66h Battery type BP1130 Number of batteries supported 1 Power source type Battery Technical details Frame rate 60 fps USB 2.0 ports quantity 1 HDMI ports quantity 1 HDMI Yes GPS Yes Processor Built-in processor DRIMe IV Design Colour of product Black Performance GPS Yes Built-in processor DRIMe IV Operational conditions Operating relative humidity (H-H) 5 - 85% System requirements Minimum hard disk space 250 MB Minimum RAM 250 MB Minimum processor Intel Core 2 Duo 1.66 GHz / AMD Athlon X2 Dual-Core 2.2 GHz Weight & dimensions Width 12.2 cm Depth 4.07 cm Height 6.37 cm Weight 280g Other features Frame rate 60 fps USB 2.0 ports quantity 1 HDMI ports quantity 1",
    "touchsensitivescreen": "Yes",
    "usbversion": "2.0",
    "width": "12.2 cm",
    "displayresolutionnumeric": "768000 pixels",
    "supportedaspectratios": "3:2, 16:9",
    "displayresolution": "800 x 400 pixels",
    "imagequalityadjustment": "Brightness, Contrast",
    "maximumvideoresolution": "1920 x 1080 pixels",
    "flashsyncspeed": "1/180s",
    "videoformatssupported": "H.264, MP4, MPEG4",
    "gps": "Yes",
    "sku": "EV-NX300ZBATGB",
    "histogram": "Yes",
    "stillimageresolutions": "1024 x 1024, 1728 x 1152, 1920 x 1080, 2000 x 2000, 2112 x 2112, 2640 x 2640, 2736 x 1824, 2944 x 1656, 2976 x 1984, 3648 x 3648, 3712 x 2088, 3888 x 2592, 5472 x 3080",
    "antidustfunction": "Yes",
    "voicerecording": "Yes",
    "hdmi": "Yes",
    "ean": "8806085570610",
    "minimumprocessor": "Intel Core 2 Duo 1.66 GHz / AMD Athlon X2 Dual-Core 2.2 GHz",
    "varianglelcddisplay": "Yes",
    "hdmiportsquantity": "1",
    "minimumharddiskspace": "250 MB",
    "onscreendisplayosdlanguages": "ARA, CHI (SIMPL), CHI (TR), CZE, DAN, DEU, DUT, ESP, EST, FIN, FRE, GRE, HUN, ITA, KOR, LAV, NOR, POL, POR, SWE, THA, TUR",
    "sensortype": "CMOS",
    "scenemodes": "Fireworks, Night, Panorama, Sunset",
    "batterycapacity": "1130 mAh",
    "fullhd": "Yes",
    "usb20portsquantity": "1",
    "wifi": "Yes",
    "powersourcetype": "Battery",
    "operatingrelativehumidityhh": "5 - 85%",
    "manufacturer": "Samsung",
    "cameraplayback": "Movie, Single image",
    "isosensitivitymin": "100",
    "analogsignalformatsystem": "NTSC, PAL",
    "whitebalance": "Auto, Cloudy, Custom modes, Daylight, Flash, Fluorescent, Manual, Tungsten",
    "lensmountinterface": "Samsung NX",
    "cameratype": "MILC",
    "flashmodes": "Auto, Fill-in, Forced off, Red-eye reduction",
    "builtinflash": "Yes",
    "camerashutterspeedmin": "30s",
    "batterylifemax": "2.66h",
    "framerate": "60 fps",
    "compatiblememorycards": "SD, SDHC, SDXC",
    "wifistandards": "802.11b, 802.11g, 802.11n",
    "saturationadjustment": "Yes",
    "megapixel": "20.3 MP",
    "shootingmodes": "Aperture priority, Auto, Lens priority, Manual, Program, Shutter priority",
    "depth": "4.07 cm",
    "totalmegapixels": "21.6 MP",
    "batterylifecipastandard": "320 shots",
    "videoresolutions": "320 x 240, 640 x 480, 1280 x 720, 1920 x 810, 1920 x 1080 pixels",
    "shortdescription": "NX300 - 20.3 MP, CMOS 23.5 x 15.7 mm, 8.4074 cm (3.31 \") AMOLED (800 x 480), SDXC, GPS, Wi-Fi 802.11b/g/n, HDMI 1.4a",
    "display": "AMOLED"
}