{
    "lenssystem": "E-Mount",
    "pictbridge": "No",
    "photoeffects": "Black&White, Neutral, Sepia, Vivid",
    "wifi": "Yes",
    "focallengthrangeff": "28 - 70 mm",
    "weight": "416g",
    "lightexposuremodes": "Aperture priority AE, Auto, Manual, Shutter priority AE",
    "audioformatssupported": "AAC",
    "isosensitivity": "Still images: ISO 100-25600 equivalent (1/3 EV step) (ISO numbers up from ISO 50 can be set as expanded ISO range.) AUTO (ISO 100-6400 selectable lower limit and upper limit) Movies: ISO 200-25600 equivalent (1/3 EV step) / AUTO (ISO 200-6400 equivalent)",
    "stillimageresolutions": "6000 x 4000 3936 x 2624 3008 x 2000",
    "height": "9.44 cm",
    "nearfieldcommunicationnfc": "Yes",
    "lightexposurecorrection": "\u00b1 5EV (1/3EV step)",
    "lenstype": "28-70mm Zoom Lens",
    "maximumimageresolution": "6000 x 4000 pixels",
    "operatingtemperaturett": "0 - 40 \u00b0C",
    "autofocusaflock": "Yes",
    "isosensitivitymax": "25600",
    "batterytype": "NP-FW50",
    "camerafilesystem": "DPOF 1.1, Exif 2.3, RAW",
    "category": "camera",
    "selftimer": "2, 10s",
    "powersourcetype": "Battery",
    "builtinmicrophone": "Yes",
    "mountingtype": "Bayonet",
    "liveview": "Yes",
    "imageformatssupported": "JPG, RAW",
    "lightmetering": "Centre-weighted, Evaluative (Multi-pattern), Spot",
    "specification": "Picture quality Still image resolution(s) 6000 x 4000 3936 x 2624 3008 x 2000 Image stabilizer Yes Total megapixels 24.7 MP Image formats supported JPG, RAW Maximum image resolution 6000 x 4000 pixels Sensor type CMOS Camera type SLR Kit Megapixel 24.3 MP Lens system Mounting type Bayonet Focal length range (f-f) 28 - 70 mm Lens mount interface Sony E Focusing Focus adjustment Auto/Manual Auto focusing (AF) modes Continuous Auto Focus, Multi Point Auto Focus, Single Auto Focus Auto Focus (AF) lock Yes Auto Focus (AF) assist beam Yes Light exposure Light exposure modes Aperture priority AE, Auto, Manual, Shutter priority AE Light exposure correction \u00b1 5EV (1/3EV step) Light metering Centre-weighted, Evaluative (Multi-pattern), Spot ISO sensitivity (min) 100 ISO sensitivity (max) 25600 Shutter Camera shutter speed (min) 0.000125s Camera shutter speed (max) 0.004s Flash Flash modes Auto, Fill-in, Flash off, Flash on, Pre-flash, Red-eye reduction, Slow synchronization Built-in flash Yes Pre-flash Yes Flash sync-speed 4s Video Video resolutions 640 x 480, 1440 x 1080, 1920 x 1080 pixels Video formats supported AVCHD, MPEG4 Full HD Yes Maximum video resolution 1920 x 1080 pixels Audio Built-in microphone Yes Voice recording Yes Audio formats supported AAC Memory Compatible memory cards MS PRO Duo, MS Pro-HG Duo, SD, SDHC, SDXC Display Display LCD Display diagonal 7.62 cm (3\") Display resolution (numeric) 921600 pixels Viewfinder Viewfinder type Electrical Viewfinder screen size 1.27 cm (0.5\") Ports & interfaces USB version 2.0 PictBridge No HDMI Yes Networking Near Field Communication (NFC) Yes Wi-Fi Yes Camera Colour of product Black White balance Auto, Cloudy, Custom modes, Daylight, Fluorescent, Incandescent, Shade, Underwater Scene modes Landscape, Night landscape, Portrait, Sunset Photo effects Black&White, Neutral, Sepia, Vivid Self-timer 2, 10s Live view Yes Camera file system DPOF 1.1, Exif 2.3, RAW Battery Battery life (CIPA standard) 270 shots Battery type NP-FW50 Number of batteries supported 1 Power source type Battery Operating system/software Windows operating systems supported Yes Technical details Quick start guide Yes Pre-flash Yes HDMI Yes Design Colour of product Black Operational conditions Operating temperature (T-T) 0 - 40 \u00b0C System requirements Windows operating systems supported Yes Weight & dimensions Width 12.69 cm Depth 4.82 cm Height 9.44 cm Weight 416g Packaging content Quick start guide Yes Batteries included Yes",
    "autofocusafassistbeam": "Yes",
    "usbversion": "2.0",
    "width": "12.69 cm",
    "windowsoperatingsystemssupported": "Yes",
    "dimensionswxdxh": "126.9 x 48.2 x 94.4 mm",
    "maximumvideoresolution": "1920 x 1080 pixels",
    "type": "Interchangeable-Lens Camera",
    "flashsyncspeed": "4s",
    "videoformatssupported": "AVCHD, MPEG4",
    "preflash": "Yes",
    "sku": "ILCE7KB.CE",
    "displaydiagonal": "7.62 cm (3\")",
    "voicerecording": "Yes",
    "hdmi": "Yes",
    "ean": "4905524958645",
    "viewfinderscreensize": "1.27 cm (0.5\")",
    "imagestabilizer": "Yes",
    "autofocusingafmodes": "Continuous Auto Focus, Multi Point Auto Focus, Single Auto Focus",
    "sensortype": "CMOS",
    "scenemodes": "Landscape, Night landscape, Portrait, Sunset",
    "display": "LCD",
    "batterylifecipastandard": "270 shots",
    "fullhd": "Yes",
    "numberofbatteriessupported": "1",
    "megapixel": "24.3 MP",
    "displayresolutionnumeric": "921600 pixels",
    "manufacturer": "Sony",
    "isosensitivitymin": "100",
    "batteriesincluded": "Yes",
    "focusadjustment": "Auto/Manual",
    "cameratype": "SLR Kit",
    "builtinflash": "Yes",
    "camerashutterspeedmin": "0.000125s",
    "colourofproduct": "Black",
    "compatiblememorycards": "MS PRO Duo, MS Pro-HG Duo, SD, SDHC, SDXC",
    "lensmountinterface": "Sony E",
    "lcdscreensize": "3",
    "totalmegapixels": "24.7 MP",
    "flashmodes": "Auto, Fill-in, Flash off, Flash on, Pre-flash, Red-eye reduction, Slow synchronization",
    "depth": "4.82 cm",
    "viewfindertype": "Electrical",
    "camerashutterspeedmax": "0.004s",
    "videoresolutions": "640 x 480, 1440 x 1080, 1920 x 1080 pixels",
    "shortdescription": "4K Ultra-HD 24.3MP Exmor CMOS, JPEG/RAW 6000x4000, Full-HD AVCHD/MP4, Wi-Fi, NFC, 7.62 cm (3 \") 921k LCD, MS/SD, HDMI, USB, 416g + SEL-2870 (28-70mm F3.5-5.6 ED)",
    "whitebalance": "Auto, Cloudy, Custom modes, Daylight, Fluorescent, Incandescent, Shade, Underwater",
    "quickstartguide": "Yes"
}