{
    "lightexposuremodes": "Aperture priority AE, Auto, Manual, Shutter priority AE",
    "stillimageresolutions": "4000 x 3000 4000 x 2664 4000 x 2248 2992 x 2992 2816 x 2112 2816 x 1864 2816 x 1584 2112 x 2112 2048 x 1536 2048 x 1360 1920 x 1080 1536 x 1536",
    "focus": "TTL",
    "acadapterincluded": "Yes",
    "batterytype": "NP-48",
    "sku": "P10NC11760A",
    "supportedaspectratios": "1:1, 3:2, 4:3, 16:9",
    "videoformatssupported": "MOV",
    "weightincludingbattery": "206g",
    "imagestabilizer": "Yes",
    "sensortype": "CMOS",
    "batterylifecipastandard": "240 shots",
    "height": "5.85 cm",
    "camerashutterspeedmin": "0.003s",
    "macrofocusingrangewide": "0.03 - 3.0m",
    "pictbridge": "Yes",
    "lightexposurecontrol": "Program AE",
    "flashrangetele": "0.8 - 2.7m",
    "weight": "187g",
    "audioformatssupported": "LPCM",
    "category": "camera",
    "hdmi": "Yes",
    "imageformatssupported": "JPG, RAW",
    "lightmetering": "Centre-weighted, Evaluative (Multi-pattern), Spot",
    "specification": "Picture quality Image sensor size 25.4/58.4 mm (1/2.3\") Supported aspect ratios 1:1, 3:2, 4:3, 16:9 Still image resolution(s) 4000 x 3000 4000 x 2664 4000 x 2248 2992 x 2992 2816 x 2112 2816 x 1864 2816 x 1584 2112 x 2112 2048 x 1536 2048 x 1360 1920 x 1080 1536 x 1536 Image stabilizer Yes Total megapixels 14.5 MP Image formats supported JPG, RAW Maximum image resolution 4000 x 3000 pixels Sensor type CMOS Camera type Compact Megapixel 12 MP Lens system Focal length range (f-f) 6.4 - 25.6 mm Minimum focal length (35mm film equiv) 2.5 cm Maximum focal length (35mm film equiv) 10 cm Minimum aperture 1.8 Maximum aperture 11 Lens structure (elements/groups) 7/6 Digital zoom 4x Optical zoom 4x Focusing Focus TTL Auto focusing (AF) modes Continuous Auto Focus, Face detection, Multi Point Auto Focus, Single Auto Focus, Tracking Auto Focus Macro focusing range (wide) 0.03 - 3.0m Macro focusing range (tele) 0.50 - 3.0m Auto Mode focusing range (wide) 0.5 - ? Auto Mode focusing range (tele) 0.8 - ? Light exposure Light exposure modes Aperture priority AE, Auto, Manual, Shutter priority AE Light exposure control Program AE Light exposure correction \u00b1 3EV (1/3EV step) Light metering Centre-weighted, Evaluative (Multi-pattern), Spot ISO sensitivity (min) 100 ISO sensitivity (max) 12800 Shutter Camera shutter speed (min) 0.003s Camera shutter speed (max) 0.25s Flash Flash modes Auto, Forced off, Red-eye reduction, Slow synchronization, Suppressed Built-in flash Yes Flash range (wide) 0.5 - 7.4m Flash range (tele) 0.8 - 2.7m Video Video resolutions 640 x 480, 1280 x 720, 1920 x 1080 pixels Video formats supported MOV Full HD Yes Maximum video resolution 1920 x 1080 pixels Audio Built-in microphone Yes Voice recording Yes Audio formats supported LPCM Memory Internal memory 66 MB Compatible memory cards SD, SDHC, SDXC Memory slots 1 Display Display LCD Display diagonal 7.62 cm (3\") Display resolution (numeric) 920000 pixels Field of view 100% Viewfinder Viewfinder type No Ports & interfaces USB version 2.0 HDMI connector type Micro PictBridge Yes HDMI Yes Networking Wi-Fi standards 802.11b, 802.11g, 802.11n Wi-Fi Yes Camera Colour of product Black White balance Auto, Custom modes, Fluorescent H, Fluorescent L, Incandescent, Shade, Underwater Scene modes Beach, Close-up (macro), Documents, Fireworks, Landscape, Night, Party (indoor), Portrait, Snow, Sunset, Underwater Self-timer 2, 10s Camera file system DPOF 1.1, Exif 2.3, RAW Battery Battery technology Lithium-Ion (Li-Ion) Battery life (CIPA standard) 240 shots Battery type NP-48 Number of batteries supported 1 Power source type Battery Operating system/software Windows operating systems supported Yes Technical details Quick start guide Yes HDMI Yes Design Colour of product Black Operational conditions Operating temperature (T-T) 0 - 40 \u00b0C Operating relative humidity (H-H) 10 - 80% System requirements Windows operating systems supported Yes Weight & dimensions Width 10 cm Depth 3.33 cm Height 5.85 cm Weight 187g Weight (including battery) 206g Packaging content Quick start guide Yes Hand strap Yes Cables included USB Batteries included Yes AC adapter included Yes",
    "lensstructureelementsgroups": "7/6",
    "selftimer": "2, 10s",
    "maximumaperture": "11",
    "minimumaperture": "1.8",
    "automodefocusingrangetele": "0.8 - ?",
    "fullhd": "Yes",
    "displayresolutionnumeric": "920000 pixels",
    "manufacturer": "Fujifilm",
    "isosensitivitymin": "100",
    "flashmodes": "Auto, Forced off, Red-eye reduction, Slow synchronization, Suppressed",
    "builtinflash": "Yes",
    "compatiblememorycards": "SD, SDHC, SDXC",
    "isosensitivitymax": "12800",
    "videoresolutions": "640 x 480, 1280 x 720, 1920 x 1080 pixels",
    "quickstartguide": "Yes",
    "cablesincluded": "USB",
    "handstrap": "Yes",
    "megapixel": "12 MP",
    "camerafilesystem": "DPOF 1.1, Exif 2.3, RAW",
    "builtinmicrophone": "Yes",
    "automodefocusingrangewide": "0.5 - ?",
    "width": "10 cm",
    "windowsoperatingsystemssupported": "Yes",
    "macrofocusingrangetele": "0.50 - 3.0m",
    "imagesensorsize": "25.4/58.4 mm (1/2.3\")",
    "voicerecording": "Yes",
    "batteriesincluded": "Yes",
    "memoryslots": "1",
    "internalmemory": "66 MB",
    "powersourcetype": "Battery",
    "operatingrelativehumidityhh": "10 - 80%",
    "flashrangewide": "0.5 - 7.4m",
    "cameratype": "Compact",
    "opticalzoom": "4x",
    "colourofproduct": "Black",
    "maximumfocallength35mmfilmequiv": "10 cm",
    "shortdescription": "12MP, 2/3\" CMOS, Full-HD 1920x108060p/30p, Wi-Fi 802.11b/g/n, PictBridge, SD/SDHC/SDXC, USB 2.0, microHDMI, 7.62 cm (3.0 \") LCD 920K, 206g",
    "display": "LCD",
    "focallengthrangeff": "6.4 - 25.6 mm",
    "fieldofview": "100%",
    "camerashutterspeedmax": "0.25s",
    "maximumimageresolution": "4000 x 3000 pixels",
    "operatingtemperaturett": "0 - 40 \u00b0C",
    "lightexposurecorrection": "\u00b1 3EV (1/3EV step)",
    "ean": "4547410263312",
    "digitalzoom": "4x",
    "usbversion": "2.0",
    "minimumfocallength35mmfilmequiv": "2.5 cm",
    "maximumvideoresolution": "1920 x 1080 pixels",
    "displaydiagonal": "7.62 cm (3\")",
    "autofocusingafmodes": "Continuous Auto Focus, Face detection, Multi Point Auto Focus, Single Auto Focus, Tracking Auto Focus",
    "scenemodes": "Beach, Close-up (macro), Documents, Fireworks, Landscape, Night, Party (indoor), Portrait, Snow, Sunset, Underwater",
    "hdmiconnectortype": "Micro",
    "wifi": "Yes",
    "batterytechnology": "Lithium-Ion (Li-Ion)",
    "wifistandards": "802.11b, 802.11g, 802.11n",
    "totalmegapixels": "14.5 MP",
    "numberofbatteriessupported": "1",
    "depth": "3.33 cm",
    "viewfindertype": "No",
    "whitebalance": "Auto, Custom modes, Fluorescent H, Fluorescent L, Incandescent, Shade, Underwater"
}