{
    "focallengthrangeff": "4.6 - 23 mm",
    "weight": "109g",
    "isosensitivity": "Auto",
    "stillimageresolutions": "5152 x 3864 3648 x 2736 2592 x 1944 5152 x 2896 1920 x 1080",
    "height": "5.55 cm",
    "acadapterincluded": "Yes",
    "camerashutterspeedmax": "2s",
    "maximumimageresolution": "5152 x 3864 pixels",
    "lightexposurecorrection": "\u00b1 2EV (1/3EV step)",
    "batterytype": "NP-BN",
    "sku": "DSCW800S.CEH",
    "reviews": "No",
    "batteriesincluded": "Yes",
    "display": "LCD",
    "specification": "Picture quality Image sensor size 25.4/58.4 mm (1/2.3\") Still image resolution(s) 5152 x 3864 3648 x 2736 2592 x 1944 5152 x 2896 1920 x 1080 Image stabilizer Yes Maximum image resolution 5152 x 3864 pixels Sensor type CCD Camera type Compact Megapixel 20.1 MP Lens system Focal length range (f-f) 4.6 - 23 mm Digital zoom 40x Optical zoom 5x Focusing Auto focusing (AF) modes Centre weighted Auto Focus, Face tracking, Multi Point Auto Focus, Tracking Auto Focus Light exposure ISO sensitivity Auto Light exposure correction \u00b1 2EV (1/3EV step) ISO sensitivity (min) 100 ISO sensitivity (max) 3200 Shutter Camera shutter speed (min) 0.000666s Camera shutter speed (max) 2s Flash Flash modes Auto, Flash off, Flash on, Slow synchronization Built-in flash Yes Video Video resolutions 320 x 240, 640 x 480 pixels Motion JPEG frame rate 30 fps Full HD No Maximum video resolution 640 x 480 pixels Memory Internal memory 29 MB Compatible memory cards MicroSD (TransFlash), MicroSDHC, MicroSDXC, MS Duo, MS Micro (M2), MS PRO Duo, MS Pro-HG Duo, MS XC-HG Duo, SD, SDHC, SDXC Display Display LCD Display diagonal 6.86 cm (2.7\") Display resolution (numeric) 230400 pixels Ports & interfaces HDMI No Camera Colour of product Silver White balance Auto, Daylight, Cloudy, Incandescent, Flash Scene modes Night Portrait, Landscape, Portrait, Beach, Snow Battery Battery life (CIPA standard) 200 shots Battery type NP-BN Power source type Battery Technical details HDMI No Design Colour of product Silver Weight & dimensions Width 9.68 cm Depth 2.08 cm Height 5.55 cm Weight 109g Weight (including battery) 125g Packaging content Battery charger included Yes Batteries included Yes AC adapter included Yes",
    "isosensitivitymin": "100",
    "depth": "2.08 cm",
    "width": "9.68 cm",
    "imagesensorsize": "25.4/58.4 mm (1/2.3\")",
    "maximumvideoresolution": "640 x 480 pixels",
    "motionjpegframerate": "30 fps",
    "category": "camera",
    "weightincludingbattery": "125g",
    "displaydiagonal": "6.86 cm (2.7\")",
    "hdmi": "No",
    "ean": "4905524978698",
    "imagestabilizer": "Yes",
    "autofocusingafmodes": "Centre weighted Auto Focus, Face tracking, Multi Point Auto Focus, Tracking Auto Focus",
    "internalmemory": "29 MB",
    "batterychargerincluded": "Yes",
    "scenemodes": "Night Portrait, Landscape, Portrait, Beach, Snow",
    "batterylifecipastandard": "200 shots",
    "fullhd": "No",
    "powersourcetype": "Battery",
    "displayresolutionnumeric": "230400 pixels",
    "manufacturer": "Sony",
    "sensortype": "CCD",
    "cameratype": "Compact",
    "flashmodes": "Auto, Flash off, Flash on, Slow synchronization",
    "builtinflash": "Yes",
    "camerashutterspeedmin": "0.000666s",
    "colourofproduct": "Silver",
    "compatiblememorycards": "MicroSD (TransFlash), MicroSDHC, MicroSDXC, MS Duo, MS Micro (M2), MS PRO Duo, MS Pro-HG Duo, MS XC-HG Duo, SD, SDHC, SDXC",
    "opticalzoom": "5x",
    "isosensitivitymax": "3200",
    "megapixel": "20.1 MP",
    "digitalzoom": "40x",
    "videoresolutions": "320 x 240, 640 x 480 pixels",
    "shortdescription": "20.1MP, 1/2.3\" CCD, 4.6 - 23mm, ISO 100 - 3200, 6.858 cm (2.7 \") LCD, 29MB",
    "whitebalance": "Auto, Daylight, Cloudy, Incandescent, Flash"
}