{
    "lightexposurecontrol": "Program AE",
    "flashrangetele": "2.5 - 3.6m",
    "cablesincluded": "USB",
    "camerashutterspeedmin": "0.000588s",
    "weight": "577g",
    "lightexposuremodes": "Aperture priority AE, Auto, Manual, Shutter priority AE",
    "isosensitivity": "100, 200, 400, 800, 1600, 3200, 6400, 12800, Auto",
    "stillimageresolutions": "L : (4:3) 4608 x 3456 / (3:2) 4608 x 3072 / (16:9) 4608 x 2592 / (1:1) 3456 x 3456 M : (4:3) 3264 x 2448 / (3:2) 3264 x 2176 / (16:9) 3264 x 1840 / (1:1) 2432 x 2432 S : (4:3) 2304 x 1728 / (3:2) 2304 x 1536 / (16:9) 1920 x 1080 / (1:1) 1728 x 1728",
    "focus": "TTL",
    "megapixel": "16.2 MP",
    "camerashutterspeedmax": "8s",
    "opticalzoom": "50x",
    "operatingtemperaturett": "0 - 40 \u00b0C",
    "lightexposurecorrection": "\u00b1 2EV (1/3EV step)",
    "focallengthrangeff": "4.3 - 215 mm",
    "lightmetering": "Evaluative (Multi-pattern), Spot",
    "camerafilesystem": "DCF, DPOF",
    "category": "camera",
    "selftimer": "2, 10s",
    "powersourcetype": "Battery",
    "batteriesincluded": "Yes",
    "display": "LCD",
    "specification": "Picture quality Image sensor size 25.4/58.4 mm (1/2.3\") Supported aspect ratios 1:1, 3:2, 4:3, 16:9 Still image resolution(s) L : (4:3) 4608 x 3456 / (3:2) 4608 x 3072 / (16:9) 4608 x 2592 / (1:1) 3456 x 3456 M : (4:3) 3264 x 2448 / (3:2) 3264 x 2176 / (16:9) 3264 x 1840 / (1:1) 2432 x 2432 S : (4:3) 2304 x 1728 / (3:2) 2304 x 1536 / (16:9) 1920 x 1080 / (1:1) 1728 x 1728 Image stabilizer Yes Image stabilizer location Lens Maximum image resolution 4608 x 3456 pixels Sensor type CMOS Camera type Bridge Megapixel 16.2 MP Lens system Focal length range (f-f) 4.3 - 215 mm Minimum focal length (35mm film equiv) 2.4 cm Maximum focal length (35mm film equiv) 120 cm Minimum aperture 2.9 Maximum aperture 6.5 Lens structure (elements/groups) 17/12 Combined zoom 100x Digital zoom 2x Optical zoom 50x Focusing Focus TTL Focus adjustment Auto Smile detection Yes Light exposure ISO sensitivity 100, 200, 400, 800, 1600, 3200, 6400, 12800, Auto Light exposure modes Aperture priority AE, Auto, Manual, Shutter priority AE Light exposure control Program AE Light exposure correction \u00b1 2EV (1/3EV step) Light metering Evaluative (Multi-pattern), Spot ISO sensitivity (min) 100 ISO sensitivity (max) 12800 Shutter Camera shutter speed (min) 0.000588s Camera shutter speed (max) 8s Camera shutter type Electronic, Mechanical Flash Flash modes Auto, Forced on, Slow synchronization, Suppressed Built-in flash Yes Flash range (wide) 0.4 - 7m Flash range (tele) 2.5 - 3.6m Video Video resolutions 640 x 480, 1280 x 720, 1920 x 1080 pixels Full HD Yes Maximum video resolution 1920 x 1080 pixels Audio Audio system Stereo Memory Internal memory 38 MB Compatible memory cards SD, SDHC, SDXC Display Display LCD Display diagonal 7.62 cm (3\") Display resolution (numeric) 201000 pixels Viewfinder Viewfinder type Electrical Viewfinder screen size 5.08 mm (0.2\") Ports & interfaces USB version 2.0 HDMI connector type Mini HDMI Yes Networking Wi-Fi standards 802.11b, 802.11g, 802.11n Wi-Fi Yes Camera Image stabilizer location Lens Colour of product Black White balance Custom modes, Fine, Fluorescent, Fluorescent H, Fluorescent L, Incandescent, Shade Self-timer 2, 10s Histogram Yes Camera file system DCF, DPOF Battery Battery technology Alkaline Battery life (CIPA standard) 300 shots Power source type Battery Technical details Wrist strap included Yes HDMI Yes Audio system Stereo Design Colour of product Black Operational conditions Operating temperature (T-T) 0 - 40 \u00b0C Weight & dimensions Width 12.26 cm Depth 11.62 cm Height 8.69 cm Weight 577g Weight (including battery) 670g Packaging content Wrist strap included Yes Cables included USB Batteries included Yes",
    "lensstructureelementsgroups": "17/12",
    "depth": "11.62 cm",
    "usbversion": "2.0",
    "width": "12.26 cm",
    "supportedaspectratios": "1:1, 3:2, 4:3, 16:9",
    "minimumfocallength35mmfilmequiv": "2.4 cm",
    "maximumaperture": "6.5",
    "imagesensorsize": "25.4/58.4 mm (1/2.3\")",
    "maximumvideoresolution": "1920 x 1080 pixels",
    "displaydiagonal": "7.62 cm (3\")",
    "sku": "P10NC12610A",
    "weightincludingbattery": "670g",
    "combinedzoom": "100x",
    "hdmi": "Yes",
    "ean": "4547410262803",
    "viewfinderscreensize": "5.08 mm (0.2\")",
    "isosensitivitymin": "100",
    "imagestabilizer": "Yes",
    "histogram": "Yes",
    "internalmemory": "38 MB",
    "batterylifecipastandard": "300 shots",
    "fullhd": "Yes",
    "wifi": "Yes",
    "smiledetection": "Yes",
    "displayresolutionnumeric": "201000 pixels",
    "manufacturer": "Fujifilm",
    "sensortype": "CMOS",
    "hdmiconnectortype": "Mini",
    "minimumaperture": "2.9",
    "flashrangewide": "0.4 - 7m",
    "focusadjustment": "Auto",
    "cameratype": "Bridge",
    "flashmodes": "Auto, Forced on, Slow synchronization, Suppressed",
    "camerashuttertype": "Electronic, Mechanical",
    "audiosystem": "Stereo",
    "colourofproduct": "Black",
    "batterytechnology": "Alkaline",
    "compatiblememorycards": "SD, SDHC, SDXC",
    "wifistandards": "802.11b, 802.11g, 802.11n",
    "isosensitivitymax": "12800",
    "height": "8.69 cm",
    "digitalzoom": "2x",
    "viewfindertype": "Electrical",
    "maximumfocallength35mmfilmequiv": "120 cm",
    "builtinflash": "Yes",
    "videoresolutions": "640 x 480, 1280 x 720, 1920 x 1080 pixels",
    "shortdescription": "16.2MP, 1/2.3\" CMOS, 50x(2x digital), 7.62 cm (3 \") LCD",
    "whitebalance": "Custom modes, Fine, Fluorescent, Fluorescent H, Fluorescent L, Incandescent, Shade",
    "imagestabilizerlocation": "Lens",
    "maximumimageresolution": "4608 x 3456 pixels"
}