{
    "isosensitivity": "80, 1600, 3200, 12800",
    "stillimageresolutions": "5184 x 3888 3648 x 2736 2592 x 1944 1920 x 1080 640 x 480",
    "acadapterincluded": "Yes",
    "batterytype": "NP-BX1",
    "avoutput": "No",
    "sku": "DSCHX50B.CEH",
    "facedetection": "Yes",
    "supportedaspectratios": "16:9",
    "trimming": "Yes",
    "weightincludingbattery": "272g",
    "waterproof": "No",
    "imagestabilizer": "Yes",
    "sensortype": "CMOS",
    "batterylifecipastandard": "400 shots",
    "height": "6.43 cm",
    "cameraplayback": "Movie, Single image, Slide show",
    "multiburstmode": "Yes",
    "boxcontents": "Rechargeable Battery AC Adapter USB Cable Accessory Shoe Cap Instruction Manual",
    "focusadjustment": "Auto/Manual",
    "camerashutterspeedmin": "0.000625s",
    "shockproof": "No",
    "macrofocusingrangewide": "0.05 - ?",
    "pictbridge": "No",
    "flashrangetele": "2 - 3m",
    "weight": "245g",
    "category": "camera",
    "hdmi": "Yes",
    "imageformatssupported": "JPG",
    "lightmetering": "Centre-weighted, Evaluative (Multi-pattern), Spot",
    "specification": "Picture quality Image sensor size 25.4/58.4 mm (1/2.3\") Supported aspect ratios 16:9 Still image resolution(s) 5184 x 3888 3648 x 2736 2592 x 1944 1920 x 1080 640 x 480 Image stabilizer Yes Image formats supported JPG Maximum image resolution 5184 x 3888 pixels Sensor type CMOS Camera type Compact Megapixel 20.4 MP Lens system Focal length range (f-f) 4.3 - 129 mm Minimum focal length (35mm film equiv) 2.4 cm Maximum focal length (35mm film equiv) 72 cm Minimum aperture 3.5 Maximum aperture 6.3 Digital zoom 486x Optical zoom 30x Focusing Focus adjustment Auto/Manual Auto focusing (AF) modes Centre weighted Auto Focus, Face detection, Flexible Spot Auto Focus, Multi Point Auto Focus, Spot Auto Focus Smile detection Yes Macro focusing range (wide) 0.05 - ? Macro focusing range (tele) 2 - ? Light exposure ISO sensitivity 80, 1600, 3200, 12800 Light exposure correction \u00b1 2EV (1/3EV step) Light metering Centre-weighted, Evaluative (Multi-pattern), Spot ISO sensitivity (min) 80 ISO sensitivity (max) 12800 Shutter Camera shutter speed (min) 0.000625s Camera shutter speed (max) 4s Flash Flash modes Auto, Flash off, Flash on, Red-eye reduction, Slow synchronization Built-in flash Yes Flash range (wide) 0.25 - 5.6m Flash range (tele) 2 - 3m Video Video resolutions 640 x 480, 1280 x 720, 1440 x 1080, 1920 x 1080 pixels Motion JPEG frame rate 25 fps Full HD Yes Maximum video resolution 1920 x 1080 pixels Audio Built-in microphone Yes Memory Compatible memory cards MicroSD (TransFlash), MicroSDHC, SD, SDHC, SDXC Display Display TFT Display diagonal 7.62 cm (3\") Display resolution (numeric) 921600 pixels Second display No Ports & interfaces USB version 2.0 HDMI connector type Micro PictBridge No HDMI Yes AV output No Networking Wi-Fi Yes Camera Colour of product Black White balance Auto, Cloudy, Daylight, Flash, Fluorescent, Incandescent, Push Scene modes Beach, Close-up (macro), Fireworks, Landscape, Night portrait, Pet, Snow, Twilight, Night Portrait Photo effects Black&White Contrast adjustment Yes Saturation adjustment Yes Camera playback Movie, Single image, Slide show Multi burst mode Yes Start-up time 1900 ms Playback zoom (max) 8x Languages support BUL, CZE, DAN, DEU, DUT, ENG, ESP, FIN, FRE, GRE, HUN, ITA, NOR, POL, POR, RUM, RUS, SWE, TUR Image editing Rotating, Trimming Histogram Yes GPS No Camera file system DCF, DPOF Battery Battery technology Lithium-Ion (Li-Ion) Battery life (CIPA standard) 400 shots Battery type NP-BX1 Number of batteries supported 1 Power source type Battery Technical details Quick start guide Yes Start-up time 1900 ms Waterproof No Trimming Yes Panorama Yes Optical viewfinder No Manual focus Yes Languages support BUL, CZE, DAN, DEU, DUT, ENG, ESP, FIN, FRE, GRE, HUN, ITA, NOR, POL, POR, RUM, RUS, SWE, TUR HDMI Yes GPS No Face detection Yes Electrical viewfinder No Design Colour of product Black Performance GPS No Weight & dimensions Width 10.81 cm Depth 3.83 cm Height 6.43 cm Weight 245g Weight (including battery) 272g Packaging content Quick start guide Yes Cables included USB Batteries included Yes AC adapter included Yes Other features Waterproof No Trimming Yes Panorama Yes Optical viewfinder No Manual focus Yes Face detection Yes Electrical viewfinder No",
    "maximumaperture": "6.3",
    "minimumaperture": "3.5",
    "saturationadjustment": "Yes",
    "motionjpegframerate": "25 fps",
    "camerashutterspeed": "iAuto (4 - 1/1600) / Program Auto (1 - 1/1600)",
    "fullhd": "Yes",
    "smiledetection": "Yes",
    "displayresolutionnumeric": "921600 pixels",
    "manufacturer": "Sony",
    "isosensitivitymin": "80",
    "flashmodes": "Auto, Flash off, Flash on, Red-eye reduction, Slow synchronization",
    "builtinflash": "Yes",
    "compatiblememorycards": "MicroSD (TransFlash), MicroSDHC, SD, SDHC, SDXC",
    "isosensitivitymax": "12800",
    "languagessupport": "BUL, CZE, DAN, DEU, DUT, ENG, ESP, FIN, FRE, GRE, HUN, ITA, NOR, POL, POR, RUM, RUS, SWE, TUR",
    "hdmiconnectortype": "Micro",
    "quickstartguide": "Yes",
    "warranty": "1 Year",
    "photoeffects": "Black&White",
    "cablesincluded": "USB",
    "opticalviewfinder": "No",
    "megapixel": "20.4 MP",
    "camerafilesystem": "DCF, DPOF",
    "imageediting": "Rotating, Trimming",
    "builtinmicrophone": "Yes",
    "width": "10.81 cm",
    "panorama": "Yes",
    "contrastadjustment": "Yes",
    "macrofocusingrangetele": "2 - ?",
    "playbackzoommax": "8x",
    "imagesensorsize": "25.4/58.4 mm (1/2.3\")",
    "gps": "No",
    "batteriesincluded": "Yes",
    "ean": "4905524944570",
    "electricalviewfinder": "No",
    "histogram": "Yes",
    "powersourcetype": "Battery",
    "flashrangewide": "0.25 - 5.6m",
    "cameratype": "Compact",
    "colourofproduct": "Black",
    "lcdscreensize": "3",
    "maximumfocallength35mmfilmequiv": "72 cm",
    "shortdescription": "7.62 cm (3.0 \") TFT, 20.4 MP, 30/486x, 1/2.3 CMOS, 24-720mm, SD/SDHC/SDXC/microSD/microSDHC, USB 2.0, Black",
    "display": "TFT",
    "focallengthrangeff": "4.3 - 129 mm",
    "camerashutterspeedmax": "4s",
    "maximumimageresolution": "5184 x 3888 pixels",
    "lightexposurecorrection": "\u00b1 2EV (1/3EV step)",
    "seconddisplay": "No",
    "manualfocus": "Yes",
    "startuptime": "1900 ms",
    "digitalzoom": "486x",
    "usbversion": "2.0",
    "minimumfocallength35mmfilmequiv": "2.4 cm",
    "dimensionswxdxh": "108.1 x 38.3 x 64.3 mm",
    "maximumvideoresolution": "1920 x 1080 pixels",
    "displaydiagonal": "7.62 cm (3\")",
    "freezeproof": "No",
    "autofocusingafmodes": "Centre weighted Auto Focus, Face detection, Flexible Spot Auto Focus, Multi Point Auto Focus, Spot Auto Focus",
    "scenemodes": "Beach, Close-up (macro), Fireworks, Landscape, Night portrait, Pet, Snow, Twilight, Night Portrait",
    "videoresolutions": "640 x 480, 1280 x 720, 1440 x 1080, 1920 x 1080 pixels",
    "wifi": "Yes",
    "batterytechnology": "Lithium-Ion (Li-Ion)",
    "opticalzoom": "30x",
    "numberofbatteriessupported": "1",
    "depth": "3.83 cm",
    "whitebalance": "Auto, Cloudy, Daylight, Flash, Fluorescent, Incandescent, Push"
}