{
    "flashrangetele": "2 - 2.4m",
    "cablesincluded": "USB",
    "weight": "137g",
    "macrofocusingrangewide": "0.05 - ?",
    "isosensitivity": "80, 100, 200, 400, 800, 1600, 3200, 6400, 12800",
    "stillimageresolutions": "4896 x 3264, 3648 x 2432, 2592 x 1728, 4896 x 3672, 3648 x 2736, 2592 x 1944, 4896 x 2752, 3648 x 2056, 1920 x 1080, 3664 x 3664, 2736 x 2736, 1920 x 1920, 7152 x 1080, 4912 x 1920, 4912 x 1080, 3424 x 1920, 11520 x 1080",
    "height": "5.49 cm",
    "acadapterincluded": "Yes",
    "tripodmountable": "Yes",
    "camerashutterspeedmax": "4s",
    "maximumimageresolution": "4896 x 3264 pixels",
    "lightexposurecorrection": "\u00b1 2EV (1/3EV step)",
    "focallengthrangeff": "4.3 - 86 mm",
    "lcdscreensize": "2.7",
    "batterytype": "NP-BX1",
    "flashmodes": "Auto, Flash off, Flash on, Slow synchronization",
    "sku": "DSCWX350W.CEH",
    "selftimer": "2, 10s",
    "builtinmicrophone": "Yes",
    "automodefocusingrangetele": "2 - ?",
    "autofocusingafmodes": "Contrast Detection Auto Focus, Single Auto Focus",
    "usbconnectortype": "Micro-USB B",
    "whitebalance": "Auto, Cloudy, Custom modes, Daylight, Flash, Fluorescent, Incandescent",
    "specification": "Picture quality Image sensor size 25.4/58.4 mm (1/2.3\") Supported aspect ratios 1:1, 3:2, 4:3, 16:9 Still image resolution(s) 4896 x 3264, 3648 x 2432, 2592 x 1728, 4896 x 3672, 3648 x 2736, 2592 x 1944, 4896 x 2752, 3648 x 2056, 1920 x 1080, 3664 x 3664, 2736 x 2736, 1920 x 1920, 7152 x 1080, 4912 x 1920, 4912 x 1080, 3424 x 1920, 11520 x 1080 Image stabilizer Yes Maximum image resolution 4896 x 3264 pixels Sensor type CMOS Camera type Compact Megapixel 18.2 MP Lens system Focal length range (f-f) 4.3 - 86 mm Minimum aperture 6.5 Maximum aperture 3.5 Lens structure (elements/groups) 11/10 Digital zoom 80x Optical zoom 20x Focusing Focus adjustment Auto Auto focusing (AF) modes Contrast Detection Auto Focus, Single Auto Focus Macro focusing range (wide) 0.05 - ? Macro focusing range (tele) 2 - ? Auto Mode focusing range (wide) 0.05 - ? Auto Mode focusing range (tele) 2 - ? Light exposure ISO sensitivity 80, 100, 200, 400, 800, 1600, 3200, 6400, 12800 Light exposure correction \u00b1 2EV (1/3EV step) ISO sensitivity (min) 80 ISO sensitivity (max) 12800 Shutter Camera shutter speed (min) 0.00017s Camera shutter speed (max) 4s Flash Flash modes Auto, Flash off, Flash on, Slow synchronization Built-in flash Yes Flash range (wide) 0.2 - 4.3m Flash range (tele) 2 - 2.4m Video Video resolutions 640 x 480, 1440 x 1080, 1920 x 1080 pixels Full HD Yes Maximum video resolution 1920 x 1080 pixels Audio Built-in microphone Yes Voice recording Yes Memory Compatible memory cards MicroSD (TransFlash), MicroSDHC, MicroSDXC, MS Duo, MS PRO Duo, MS Pro-HG, MS Pro-HG Duo, MS XC-HG Duo, SD, SDHC, SDXC Display Display TFT Display diagonal 7.62 cm (3\") Display resolution (numeric) 460800 pixels Ports & interfaces USB version 2.0 HDMI connector type Micro USB connector type Micro-USB B HDMI Yes Networking Wi-Fi standards 802.11b, 802.11g, 802.11n Near Field Communication (NFC) Yes Wi-Fi Yes Camera Colour of product White White balance Auto, Cloudy, Custom modes, Daylight, Flash, Fluorescent, Incandescent Scene modes Backlight, Beach, Fireworks, Landscape, Night portrait, Pet, Portrait, Snow Shooting modes Auto, Manual, Movie Self-timer 2, 10s Contrast adjustment Yes Tripod mountable Yes Brightness adjustment Yes Battery Battery life (CIPA standard) 470 shots Battery life (max) 3.92h Battery type NP-BX1 Number of batteries supported 1 Power source type Battery Technical details Wrist strap included Yes Quick start guide Yes HDMI Yes Design Colour of product White Weight & dimensions Width 9.6 cm Depth 2.57 cm Height 5.49 cm Weight 137g Weight (including battery) 164g Packaging content Wrist strap included Yes Quick start guide Yes Cables included USB Batteries included Yes AC adapter included Yes",
    "lensstructureelementsgroups": "11/10",
    "depth": "2.57 cm",
    "usbversion": "2.0",
    "contrastadjustment": "Yes",
    "colourofproduct": "White",
    "supportedaspectratios": "1:1, 3:2, 4:3, 16:9",
    "maximumaperture": "3.5",
    "imagesensorsize": "25.4/58.4 mm (1/2.3\")",
    "minimumaperture": "6.5",
    "voicerecording": "Yes",
    "macrofocusingrangetele": "2 - ?",
    "category": "camera",
    "weightincludingbattery": "164g",
    "imagestabilizer": "Yes",
    "displaydiagonal": "7.62 cm (3\")",
    "hdmi": "Yes",
    "ean": "4905524981087",
    "isosensitivitymin": "80",
    "camerashutterspeed": "iAuto(2 - 1/1.600) / Program Auto(1 - 1/1.600)",
    "automodefocusingrangewide": "0.05 - ?",
    "sensortype": "CMOS",
    "scenemodes": "Backlight, Beach, Fireworks, Landscape, Night portrait, Pet, Portrait, Snow",
    "display": "TFT",
    "batterylifecipastandard": "470 shots",
    "fullhd": "Yes",
    "dimensionswxdxh": "90.7 x 16.7 x 51.5 mm",
    "wifi": "Yes",
    "powersourcetype": "Battery",
    "displayresolutionnumeric": "460800 pixels",
    "manufacturer": "Sony",
    "brightnessadjustment": "Yes",
    "nearfieldcommunicationnfc": "Yes",
    "hdmiconnectortype": "Micro",
    "maximumvideoresolution": "1920 x 1080 pixels",
    "batteriesincluded": "Yes",
    "flashrangewide": "0.2 - 4.3m",
    "focusadjustment": "Auto",
    "cameratype": "Compact",
    "shootingmodes": "Auto, Manual, Movie",
    "builtinflash": "Yes",
    "camerashutterspeedmin": "0.00017s",
    "batterylifemax": "3.92h",
    "compatiblememorycards": "MicroSD (TransFlash), MicroSDHC, MicroSDXC, MS Duo, MS PRO Duo, MS Pro-HG, MS Pro-HG Duo, MS XC-HG Duo, SD, SDHC, SDXC",
    "wifistandards": "802.11b, 802.11g, 802.11n",
    "isosensitivitymax": "12800",
    "megapixel": "18.2 MP",
    "numberofbatteriessupported": "1",
    "digitalzoom": "80x",
    "boxcontents": "Rechargeable Battery Pack(NP-BN1) Battery Charger Multi Connector Cable Power Cord Wrist Strap CD-ROM",
    "opticalzoom": "20x",
    "videoresolutions": "640 x 480, 1440 x 1080, 1920 x 1080 pixels",
    "shortdescription": "DSC-WX350 - 18.2 MP, 1/2.3 type (7.82mm) Exmor R CMOS, 20x(Optical Zoom), 7.62 cm (3.0 \") TFT, Memory Stick XC-HG Duo/SDXC, BIONZ X, Micro USB, Micro HDMI, WI-FI, NFC",
    "width": "9.6 cm",
    "quickstartguide": "Yes"
}