{
    "autofocusafassistbeam": "Yes",
    "isosensitivity": "80, 6400, Auto",
    "stillimageresolutions": "14M (4228x3216) 10M (1:1) (3216x3216) 10M (16:9) (4224x2376) 7M (3072x2304) 5M (16:9) (3072x1728) 5M (2592x1944) 4M (16:9) (2592x1464) 3M (2048x1536) 2M (16:9) (1920x1080) 1024 (1024x768) 640 (640x480)",
    "focus": "TTL",
    "batterytype": "D-LI92",
    "sku": "08076",
    "videoformatssupported": "AVI",
    "weightincludingbattery": "164g",
    "waterproof": "Yes (10m)",
    "imagestabilizer": "Yes",
    "sensortype": "CCD",
    "batterylifecipastandard": "260 shots",
    "height": "5.85 cm",
    "cameraplayback": "Movie, Single image, Slide show, Thumbnails",
    "normalfocusingrange": "0.5 - ?",
    "focusadjustment": "Auto/Manual",
    "camerashutterspeedmin": "0.25s",
    "flashrangetele": "0.2 - 2.5m",
    "weight": "143g",
    "audioformatssupported": "WAV",
    "category": "camera",
    "hdmi": "Yes",
    "macoperatingsystemssupported": "Mac OS X 10.6 Snow Leopard, Mac OS X 10.7 Lion, Mac OS X 10.8 Mountain Lion, Mac OS X 10.9 Mavericks",
    "imageformatssupported": "JPG",
    "lightmetering": "Centre-weighted, Evaluative (Multi-pattern), Spot",
    "specification": "Picture quality Image sensor size 25.4/58.4 mm (1/2.3\") Still image resolution(s) 14M (4228x3216) 10M (1:1) (3216x3216) 10M (16:9) (4224x2376) 7M (3072x2304) 5M (16:9) (3072x1728) 5M (2592x1944) 4M (16:9) (2592x1464) 3M (2048x1536) 2M (16:9) (1920x1080) 1024 (1024x768) 640 (640x480) Image stabilizer Yes Total megapixels 14.48 MP Image formats supported JPG Maximum image resolution 4228 x 3216 pixels Sensor type CCD Camera type Compact Megapixel 14 MP Lens system Focal length range (f-f) 5 - 25 mm Minimum focal length (35mm film equiv) 2.8 cm Maximum focal length (35mm film equiv) 14 cm Minimum aperture 4.2 Maximum aperture 3.5 Lens structure (elements/groups) 11/9 Digital zoom 6.7x Optical zoom 5x Focusing Focus TTL Focus adjustment Auto/Manual Auto focusing (AF) modes Multi Point Auto Focus, Spot Auto Focus, Tracking Auto Focus Normal focusing range 0.5 - ? Closest focusing distance 0.01m Auto Focus (AF) points 9 Auto Focus (AF) assist beam Yes Light exposure ISO sensitivity 80, 6400, Auto Light exposure correction \u00b1 2EV (1/3EV step) Light metering Centre-weighted, Evaluative (Multi-pattern), Spot ISO sensitivity (min) 80 ISO sensitivity (max) 6400 Shutter Camera shutter speed (min) 0.25s Camera shutter speed (max) 0.000667s Flash Flash modes Auto, Flash off, Flash on, Red-eye reduction Built-in flash Yes Flash range (wide) 0.2 - 3.9m Flash range (tele) 0.2 - 2.5m Video Video resolutions 320 x 240, 640 x 480, 1280 x 720 pixels Video formats supported AVI Motion JPEG frame rate 30 fps Full HD No Maximum video resolution 1280 x 720 pixels Audio Built-in microphone Yes Audio formats supported WAV Memory Internal memory 97 MB Compatible memory cards SD, SDHC, SDXC Display Display TFT Display diagonal 6.86 cm (2.7\") Display resolution (numeric) 230000 pixels Viewfinder Viewfinder type Electrical Ports & interfaces USB version 2.0 HDMI connector type Micro HDMI Yes Camera Colour of product Red White balance Auto, Custom modes, Daylight, Fluorescent, Shade, Tungsten Scene modes Candlelight, Children, Fireworks, Food, Landscape, Night, Night portrait, Pet, Portrait, Snow, Sports, Surf, Underwater Photo effects Antique, Black&White, Sepia Self-timer 2, 10s Camera playback Movie, Single image, Slide show, Thumbnails On Screen Display (OSD) languages CHI (SIMPL), CHI (TR), CZE, DAN, DEU, DUT, ENG, ESP, FIN, FRE, GRE, HUN, ITA, JPN, KOR, POL, POR, RUS, SWE, THA, TUR Image editing Crop, Resizing, Rotating Camera file system DCF 2.0, DPOF, Exif 2.3, PRINT Image Matching III Battery Battery technology Lithium-Ion (Li-Ion) Battery life (CIPA standard) 260 shots Battery type D-LI92 Power source type Battery Operating system/software Windows operating systems supported Yes Mac operating systems supported Mac OS X 10.6 Snow Leopard, Mac OS X 10.7 Lion, Mac OS X 10.8 Mountain Lion, Mac OS X 10.9 Mavericks Technical details Protection features Crash proof, Dust resistant, Water resistant HDMI Yes Design Protection features Crash proof, Dust resistant, Water resistant Colour of product Red System requirements Windows operating systems supported Yes Mac operating systems supported Mac OS X 10.6 Snow Leopard, Mac OS X 10.7 Lion, Mac OS X 10.8 Mountain Lion, Mac OS X 10.9 Mavericks Weight & dimensions Width 11.55 cm Depth 2.85 cm Height 5.85 cm Weight 143g Weight (including battery) 164g Packaging content Cables included USB Battery charger included Yes Batteries included Yes",
    "lensstructureelementsgroups": "11/9",
    "selftimer": "2, 10s",
    "maximumaperture": "3.5",
    "minimumaperture": "4.2",
    "motionjpegframerate": "30 fps",
    "camerashutterspeed": "1/1500  - 1/4sec.",
    "onscreendisplayosdlanguages": "CHI (SIMPL), CHI (TR), CZE, DAN, DEU, DUT, ENG, ESP, FIN, FRE, GRE, HUN, ITA, JPN, KOR, POL, POR, RUS, SWE, THA, TUR",
    "fullhd": "No",
    "displayresolutionnumeric": "230000 pixels",
    "manufacturer": "Ricoh",
    "isosensitivitymin": "80",
    "flashmodes": "Auto, Flash off, Flash on, Red-eye reduction",
    "builtinflash": "Yes",
    "compatiblememorycards": "SD, SDHC, SDXC",
    "isosensitivitymax": "6400",
    "videoresolutions": "320 x 240, 640 x 480, 1280 x 720 pixels",
    "videocapability": "Yes",
    "photoeffects": "Antique, Black&White, Sepia",
    "cablesincluded": "USB",
    "megapixel": "14 MP",
    "camerafilesystem": "DCF 2.0, DPOF, Exif 2.3, PRINT Image Matching III",
    "imageediting": "Crop, Resizing, Rotating",
    "builtinmicrophone": "Yes",
    "width": "11.55 cm",
    "windowsoperatingsystemssupported": "Yes",
    "imagesensorsize": "25.4/58.4 mm (1/2.3\")",
    "batteriesincluded": "Yes",
    "ean": "0027075275102",
    "closestfocusingdistance": "0.01m",
    "internalmemory": "97 MB",
    "batterychargerincluded": "Yes",
    "powersourcetype": "Battery",
    "flashrangewide": "0.2 - 3.9m",
    "cameratype": "Compact",
    "colourofproduct": "Red",
    "lcdscreensize": "2.7",
    "reviews": "No",
    "maximumfocallength35mmfilmequiv": "14 cm",
    "shortdescription": "14MP, 1/2.3\" CCD, PENTAX 5-25mm lens, 6.858 cm (2.7 \") LCD, USB, HDMI",
    "display": "TFT",
    "focallengthrangeff": "5 - 25 mm",
    "camerashutterspeedmax": "0.000667s",
    "maximumimageresolution": "4228 x 3216 pixels",
    "lightexposurecorrection": "\u00b1 2EV (1/3EV step)",
    "depth": "2.85 cm",
    "usbversion": "2.0",
    "minimumfocallength35mmfilmequiv": "2.8 cm",
    "dimensionswxdxh": "58.5 x 28.5 x 115.5 mm",
    "maximumvideoresolution": "1280 x 720 pixels",
    "displaydiagonal": "6.86 cm (2.7\")",
    "freezeproof": "Yes (-10?C)",
    "autofocusafpoints": "9",
    "autofocusingafmodes": "Multi Point Auto Focus, Spot Auto Focus, Tracking Auto Focus",
    "scenemodes": "Candlelight, Children, Fireworks, Food, Landscape, Night, Night portrait, Pet, Portrait, Snow, Sports, Surf, Underwater",
    "hdmiconnectortype": "Micro",
    "batterytechnology": "Lithium-Ion (Li-Ion)",
    "opticalzoom": "5x",
    "totalmegapixels": "14.48 MP",
    "digitalzoom": "6.7x",
    "viewfindertype": "Electrical",
    "whitebalance": "Auto, Custom modes, Daylight, Fluorescent, Shade, Tungsten"
}