{
    "videocapability": "Yes",
    "pictbridge": "Yes",
    "photoeffects": "black&white, Neutral",
    "focallengthrangeff": "15 - 85 mm",
    "cameraplayback": "movie, single image, slide show",
    "weight": "820g",
    "lightexposuremodes": "aperture priority AE, auto, manual, shutter priority AE",
    "stillimageresolutions": "5184 x 3456",
    "megapixel": "18 MP",
    "builtinprocessor": "Dual DIGIC 4",
    "lenstype": "15-85mm Lens",
    "flashexposurelock": "Yes",
    "operatingtemperaturett": "0 - 40 \u00b0C",
    "autofocusaflock": "Yes",
    "displaydiagonal": "7.62 cm (3\")",
    "lightmetering": "Centre-weighted, Spot",
    "sku": "3814B028AA",
    "powersourcetype": "Battery",
    "batterytype": "LP-E6",
    "specification": "Picture quality Supported aspect ratios 3:2 Still image resolution(s) 5184 x 3456 Image stabilizer Yes Maximum image resolution 5184 x 3456 pixels Sensor type CMOS Camera type SLR Kit Megapixel 18 MP Lens system Focal length range (f-f) 15 - 85 mm Minimum aperture 3.5 Maximum aperture 5.6 Focusing Auto focusing (AF) modes selective auto focus Auto Focus (AF) lock Yes Auto Focus (AF) assist beam Yes Light exposure Light exposure modes aperture priority AE, auto, manual, shutter priority AE Light metering Centre-weighted, Spot Shutter Camera shutter speed (min) 0.000125s Camera shutter speed (max) 30s Camera shutter type electronic Flash Flash modes auto, manual, Pre-flash, Red-eye reduction, second curtain synchro Built-in flash Yes Flash recharging time 3s Flash exposure lock Yes Video Video formats supported MOV Motion JPEG frame rate 29.97 fps Full HD No Maximum video resolution 1920 x 1080 pixels Memory Compatible memory cards cf Display Display LCD Display diagonal 7.62 cm (3\") Display resolution (numeric) 920000 pixels Viewfinder Viewfinder type electrical Magnification 1x Ports & interfaces USB 2.0 ports quantity 1 HDMI ports quantity 1 Camera Colour of product Black White balance auto, Cloudy, custom modes, daylight, flash, Fluorescent, Shade, Tungsten Scene modes Landscape, Portrait, Sports Photo effects black&white, Neutral Camera playback movie, single image, slide show Playback zoom (max) 10x Histogram Yes Built-in processor Dual DIGIC 4 Battery Battery technology Lithium-Ion (Li-Ion) Battery type LP-E6 Power source type Battery Operating system/software Bundled software ZoomBrowser EX / ImageBrowser Technical details USB 2.0 ports quantity 1 HDMI ports quantity 1 Lens system EF/EF-S Interface USB Compatible operating systems Windows XP (SP2/SP3) / Vista inc. SP1 Mac OS X v10.4-10.5 Digital SLR Yes Processor Built-in processor Dual DIGIC 4 Design Colour of product Black Performance Built-in processor Dual DIGIC 4 Operational conditions Operating temperature (T-T) 0 - 40 \u00b0C Operating relative humidity (H-H) 0 - 85% System requirements Mac compatibility Yes Weight & dimensions Width 14.82 cm Depth 7.35 cm Height 11.07 cm Weight 820g Packaging content Bundled software ZoomBrowser EX / ImageBrowser Other features USB 2.0 ports quantity 1 Video capability Yes HDMI ports quantity 1 Lens system EF/EF-S Interface USB Compatible operating systems Windows XP (SP2/SP3) / Vista inc. SP1 Mac OS X v10.4-10.5 Digital SLR Yes",
    "autofocusafassistbeam": "Yes",
    "usb20portsquantity": "1",
    "width": "14.82 cm",
    "magnification": "1x",
    "supportedaspectratios": "3:2",
    "maximumaperture": "5.6",
    "digitalslr": "Yes",
    "dimensionswxdxh": "148.2 x 110.7 x 73.5 mm",
    "minimumaperture": "3.5",
    "type": "Single Lens Kit",
    "videoformatssupported": "MOV",
    "lenssystem": "EF/EF-S",
    "category": "camera",
    "maccompatibility": "Yes",
    "hdmiportsquantity": "1",
    "motionjpegframerate": "29.97 fps",
    "ean": "8714574542621",
    "compatibleoperatingsystems": "Windows XP (SP2/SP3) / Vista inc. SP1 Mac OS X v10.4-10.5",
    "playbackzoommax": "10x",
    "autofocusingafmodes": "selective auto focus",
    "sensortype": "CMOS",
    "displayresolutionnumeric": "920000 pixels",
    "scenemodes": "Landscape, Portrait, Sports",
    "fullhd": "No",
    "interface": "USB",
    "histogram": "Yes",
    "operatingrelativehumidityhh": "0 - 85%",
    "manufacturer": "Canon",
    "flashrechargingtime": "3s",
    "imagestabilizer": "Yes",
    "maximumvideoresolution": "1920 x 1080 pixels",
    "bundledsoftware": "ZoomBrowser EX / ImageBrowser",
    "boxcontents": "Battery Charger",
    "cameratype": "SLR Kit",
    "flashmodes": "auto, manual, Pre-flash, Red-eye reduction, second curtain synchro",
    "camerashuttertype": "electronic",
    "camerashutterspeedmin": "0.000125s",
    "colourofproduct": "Black",
    "batterytechnology": "Lithium-Ion (Li-Ion)",
    "compatiblememorycards": "cf",
    "lcdscreensize": "3.0",
    "height": "11.07 cm",
    "depth": "7.35 cm",
    "viewfindertype": "electrical",
    "builtinflash": "Yes",
    "whitebalance": "auto, Cloudy, custom modes, daylight, flash, Fluorescent, Shade, Tungsten",
    "camerashutterspeedmax": "30s",
    "shortdescription": "EOS 7D + EF-S 15-85mm f/3.5-5.6 IS USM - 22.3mm x 14.9mm CMOS, 18.00 megapixels, Dual \"DIGIC 4\", 7.62 cm (3.0 \") Clear View II TFT, CompactFlash",
    "display": "LCD",
    "warranty": "1 Years Warranty",
    "maximumimageresolution": "5184 x 3456 pixels"
}