{
    "pictbridge": "Yes",
    "autofocusafassistbeam": "Yes",
    "cablesincluded": "AC, USB",
    "autofocusafpointsselection": "Auto",
    "weight": "133g",
    "isosensitivity": "100, 200, 400, 800, 1600, Auto",
    "stillimageresolutions": "4:3 - (L) 4608 x 3456, (M1) 3264 x 2448, (M2) 1600 x 1200, (S) 640 x 480 16:9 - (L) 4608 x 2592, (M1) 3264 x 1832, (M2) 1920 x 1080, (S) 640 x 360 3:2 - (L) 4608 x 3072, (M1) 3264 x 2176, (M2) 1600 x 1064, (S) 640 x 424 1:1 - (L) 3456 x 3456, (M1) 2448 x 2448, (M2) 1200 x 1200, (S) 480 x 480",
    "focus": "TTL",
    "height": "5.6 cm",
    "acadapterincluded": "Yes",
    "camerashutterspeedmax": "0.0005s",
    "maximumimageresolution": "4608 x 3456 pixels",
    "operatingtemperaturett": "0 - 40 \u00b0C",
    "autofocusaflock": "Yes",
    "focallengthrangeff": "5 - 40 mm",
    "camerafilesystem": "DCF",
    "category": "camera",
    "depth": "2.06 cm",
    "whitebalance": "Auto, Cloudy, Custom modes, Daylight, Fluorescent, Fluorescent H, Tungsten",
    "usbconnectortype": "Mini-USB B",
    "specification": "Picture quality Image sensor size 25.4/58.4 mm (1/2.3\") Supported aspect ratios 1:1, 3:2, 4:3, 16:9 Still image resolution(s) 4:3 - (L) 4608 x 3456, (M1) 3264 x 2448, (M2) 1600 x 1200, (S) 640 x 480 16:9 - (L) 4608 x 2592, (M1) 3264 x 1832, (M2) 1920 x 1080, (S) 640 x 360 3:2 - (L) 4608 x 3072, (M1) 3264 x 2176, (M2) 1600 x 1064, (S) 640 x 424 1:1 - (L) 3456 x 3456, (M1) 2448 x 2448, (M2) 1200 x 1200, (S) 480 x 480 Image stabilizer Yes Image stabilizer location Lens Maximum image resolution 4608 x 3456 pixels Sensor type CCD Camera type Compact Megapixel 16 MP Lens system Focal length range (f-f) 5 - 40 mm Minimum focal length (35mm film equiv) 2.8 cm Maximum focal length (35mm film equiv) 22.4 cm Lens structure (elements/groups) 8/7 Extra/Smart zoom 16x Combined zoom 32x Digital zoom 4x Optical zoom 8x Focusing Focus TTL Auto focusing (AF) modes Centre weighted Auto Focus, Face detection Closest focusing distance 0.01m Auto Focus (AF) points selection Auto Auto Focus (AF) points 9 Auto Focus (AF) lock Yes Auto Focus (AF) assist beam Yes Light exposure ISO sensitivity 100, 200, 400, 800, 1600, Auto Auto Exposure (AE) lock Yes ISO sensitivity (min) 100 ISO sensitivity (max) 1600 Shutter Camera shutter speed (min) 0.0005s Camera shutter speed (max) 0.0005s Flash Flash modes Auto, Flash off, Flash on, Slow synchronization Built-in flash Yes Flash exposure lock Yes Flash exposure compensation Yes Video Video resolutions 640 x 480, 1280 x 720 pixels Resolution at capture speed 1280x720@25fps, 640x480@30fps Full HD No Maximum video resolution 1280 x 720 pixels Memory Compatible memory cards SD, SDHC, SDXC Display Display TFT Display diagonal 7.62 cm (3\") Display resolution (numeric) 460000 pixels Ports & interfaces PictBridge Yes USB connector type Mini-USB B Networking Wi-Fi standards 802.11b, 802.11g, 802.11n Wi-Fi Yes Camera Image stabilizer location Lens Colour of product Red White balance Auto, Cloudy, Custom modes, Daylight, Fluorescent, Fluorescent H, Tungsten Self-timer 2, 10s Playback zoom (max) 10x Languages support ARA, CHI (SIMPL), CHI (TR), CZE, DAN, DEU, DUT, ENG, ESP, FIN, FRE, GRE, HUN, ITA, JPN, KOR, NOR, POL, POR, RUM, RUS, SWE, THA, TUR, UKR Histogram Yes Direct printing Yes Camera file system DCF Brightness adjustment Yes Battery Battery technology Lithium-Ion (Li-Ion) Battery life (CIPA standard) 190 shots Power source type Battery Technical details Wrist strap included Yes Resolution at capture speed 1280x720@25fps, 640x480@30fps Languages support ARA, CHI (SIMPL), CHI (TR), CZE, DAN, DEU, DUT, ENG, ESP, FIN, FRE, GRE, HUN, ITA, JPN, KOR, NOR, POL, POR, RUM, RUS, SWE, THA, TUR, UKR Direct printing Yes Design Colour of product Red Performance Direct printing Yes Operational conditions Operating temperature (T-T) 0 - 40 \u00b0C Operating relative humidity (H-H) 10 - 90% Weight & dimensions Width 9.54 cm Depth 2.06 cm Height 5.6 cm Weight 133g Packaging content Wrist strap included Yes Cables included AC, USB Battery charger included Yes Batteries included Yes AC adapter included Yes",
    "lensstructureelementsgroups": "8/7",
    "languagessupport": "ARA, CHI (SIMPL), CHI (TR), CZE, DAN, DEU, DUT, ENG, ESP, FIN, FRE, GRE, HUN, ITA, JPN, KOR, NOR, POL, POR, RUM, RUS, SWE, THA, TUR, UKR",
    "displayresolutionnumeric": "460000 pixels",
    "selftimer": "2, 10s",
    "width": "9.54 cm",
    "supportedaspectratios": "1:1, 3:2, 4:3, 16:9",
    "minimumfocallength35mmfilmequiv": "2.8 cm",
    "flashexposurecompensation": "Yes",
    "playbackzoommax": "10x",
    "imagesensorsize": "25.4/58.4 mm (1/2.3\")",
    "maximumvideoresolution": "1280 x 720 pixels",
    "displaydiagonal": "7.62 cm (3\")",
    "shortdescription": "16MP, 8x(4x digital), 7.62 cm (3 \") , TFT, DIGIC 4",
    "sku": "8198B006AA",
    "histogram": "Yes",
    "closestfocusingdistance": "0.01m",
    "combinedzoom": "32x",
    "maximumfocallength35mmfilmequiv": "22.4 cm",
    "batteriesincluded": "Yes",
    "ean": "8714574599151",
    "imagestabilizer": "Yes",
    "autofocusafpoints": "9",
    "autofocusingafmodes": "Centre weighted Auto Focus, Face detection",
    "sensortype": "CCD",
    "batterychargerincluded": "Yes",
    "display": "TFT",
    "batterylifecipastandard": "190 shots",
    "fullhd": "No",
    "wifi": "Yes",
    "extrasmartzoom": "16x",
    "powersourcetype": "Battery",
    "operatingrelativehumidityhh": "10 - 90%",
    "manufacturer": "Canon",
    "brightnessadjustment": "Yes",
    "isosensitivitymin": "100",
    "opticalzoom": "8x",
    "cameratype": "Compact",
    "builtinflash": "Yes",
    "camerashutterspeedmin": "0.0005s",
    "colourofproduct": "Red",
    "batterytechnology": "Lithium-Ion (Li-Ion)",
    "compatiblememorycards": "SD, SDHC, SDXC",
    "wifistandards": "802.11b, 802.11g, 802.11n",
    "isosensitivitymax": "1600",
    "megapixel": "16 MP",
    "flashmodes": "Auto, Flash off, Flash on, Slow synchronization",
    "digitalzoom": "4x",
    "resolutionatcapturespeed": "1280x720@25fps, 640x480@30fps",
    "videoresolutions": "640 x 480, 1280 x 720 pixels",
    "autoexposureaelock": "Yes",
    "directprinting": "Yes",
    "imagestabilizerlocation": "Lens",
    "flashexposurelock": "Yes"
}