{
    "pictbridge": "Yes",
    "lightexposurecontrol": "Program AE",
    "wifi": "Yes",
    "cablesincluded": "USB",
    "weight": "577g",
    "lightexposuremodes": "Aperture priority AE, Manual, Shutter priority AE",
    "isosensitivity": "100, 200, 400, 800, 1600, 3200, 6400, 12800",
    "fieldofview": "97%",
    "focus": "TTL",
    "handstrap": "Yes",
    "megapixel": "16.2 MP",
    "camerashutterspeedmax": "8s",
    "maximumimageresolution": "4608 x 3456 pixels",
    "operatingtemperaturett": "0 - 40 \u00b0C",
    "lightexposurecorrection": "\u00b1 2EV (1/3EV step)",
    "focallengthrangeff": "4.3 - 215 mm",
    "batterytype": "AA",
    "sku": "P10NC12710A",
    "usbversion": "2.0",
    "builtinmicrophone": "Yes",
    "batteriesincluded": "Yes",
    "numberofbatteriessupported": "4",
    "imageformatssupported": "JPG, RAW",
    "lightmetering": "Centre-weighted, Evaluative (Multi-pattern)",
    "specification": "Picture quality Image sensor size 25.4/58.4 mm (1/2.3\") Supported aspect ratios 3:2, 4:3, 16:9 Still image resolution(s) 4608 x 3456 4608 x 3072 4608 x 2592 3456 x 3456 3264 x 2448 3264 x 2176 3264 x 1840 2432 x 2432 2304 x 1728 2304 x 1536 1920 x 1080 1728 x 1728 Image stabilizer Yes Image formats supported JPG, RAW Maximum image resolution 4608 x 3456 pixels Sensor type CMOS Camera type Bridge Megapixel 16.2 MP Lens system Focal length range (f-f) 4.3 - 215 mm Minimum focal length (35mm film equiv) 2.4 cm Maximum focal length (35mm film equiv) 120 cm Minimum aperture 2.9 Maximum aperture 19 Lens structure (elements/groups) 17/12 Lens type High power zoom Combined zoom 100x Digital zoom 2x Optical zoom 50x Focusing Focus TTL Focus adjustment Auto Auto focusing (AF) modes Continuous Auto Focus, Single Auto Focus, Tracking Auto Focus Super Macro focusing range 0.01 - 1m Macro focusing range (wide) 0.07 - 3m Macro focusing range (tele) 3.5 - 5m Light exposure ISO sensitivity 100, 200, 400, 800, 1600, 3200, 6400, 12800 Light exposure modes Aperture priority AE, Manual, Shutter priority AE Light exposure control Program AE Light exposure correction \u00b1 2EV (1/3EV step) Light metering Centre-weighted, Evaluative (Multi-pattern) ISO sensitivity (min) 100 ISO sensitivity (max) 12800 Shutter Camera shutter speed (min) 0.00058s Camera shutter speed (max) 8s Camera shutter type Electronic Flash Flash modes Auto, Red-eye reduction, Slow synchronization Video Video resolutions 640 x 480, 1280 x 720, 1920 x 1080 pixels Video formats supported H.264, MOV Motion JPEG frame rate 30 fps Full HD Yes Maximum video resolution 1920 x 1080 pixels Audio Built-in microphone Yes Voice recording Yes Memory Internal memory 38 MB Compatible memory cards SD, SDHC, SDXC Display Display LCD Display diagonal 7.62 cm (3\") Display resolution (numeric) 460000 pixels Field of view 97% Viewfinder Viewfinder type Electrical Ports & interfaces USB version 2.0 HDMI connector type Mini PictBridge Yes HDMI Yes Networking Wi-Fi standards 802.11b, 802.11g, 802.11n Wi-Fi Yes Camera Colour of product White White balance Auto, Daylight, Fine, Fluorescent, Incandescent, Shade Scene modes Beach, Children, Fireworks, Flower, Landscape, Night, Party (indoor), Portrait, Snow, Sports Self-timer 2, 10s Battery Battery technology Alkaline Battery life (CIPA standard) 300 shots Battery type AA Number of batteries supported 4 Power source type Battery Technical details HDMI Yes Design Colour of product White Operational conditions Operating temperature (T-T) 0 - 40 \u00b0C Operating relative humidity (H-H) 10 - 80% Weight & dimensions Width 12.26 cm Depth 11.62 cm Height 8.69 cm Weight 577g Weight (including battery) 670g Packaging content Hand strap Yes Cables included USB Batteries included Yes",
    "lensstructureelementsgroups": "17/12",
    "depth": "11.62 cm",
    "displayresolutionnumeric": "460000 pixels",
    "selftimer": "2, 10s",
    "width": "12.26 cm",
    "supportedaspectratios": "3:2, 4:3, 16:9",
    "minimumfocallength35mmfilmequiv": "2.4 cm",
    "maximumaperture": "19",
    "imagesensorsize": "25.4/58.4 mm (1/2.3\")",
    "minimumaperture": "2.9",
    "displaydiagonal": "7.62 cm (3\")",
    "voicerecording": "Yes",
    "videoformatssupported": "H.264, MOV",
    "macrofocusingrangetele": "3.5 - 5m",
    "motionjpegframerate": "30 fps",
    "category": "camera",
    "weightincludingbattery": "670g",
    "stillimageresolutions": "4608 x 3456 4608 x 3072 4608 x 2592 3456 x 3456 3264 x 2448 3264 x 2176 3264 x 1840 2432 x 2432 2304 x 1728 2304 x 1536 1920 x 1080 1728 x 1728",
    "combinedzoom": "100x",
    "maximumfocallength35mmfilmequiv": "120 cm",
    "hdmi": "Yes",
    "ean": "4547410262834",
    "isosensitivitymin": "100",
    "imagestabilizer": "Yes",
    "autofocusingafmodes": "Continuous Auto Focus, Single Auto Focus, Tracking Auto Focus",
    "internalmemory": "38 MB",
    "scenemodes": "Beach, Children, Fireworks, Flower, Landscape, Night, Party (indoor), Portrait, Snow, Sports",
    "batterylifecipastandard": "300 shots",
    "fullhd": "Yes",
    "powersourcetype": "Battery",
    "operatingrelativehumidityhh": "10 - 80%",
    "manufacturer": "Fujifilm",
    "sensortype": "CMOS",
    "hdmiconnectortype": "Mini",
    "maximumvideoresolution": "1920 x 1080 pixels",
    "whitebalance": "Auto, Daylight, Fine, Fluorescent, Incandescent, Shade",
    "macrofocusingrangewide": "0.07 - 3m",
    "focusadjustment": "Auto",
    "cameratype": "Bridge",
    "camerashuttertype": "Electronic",
    "camerashutterspeedmin": "0.00058s",
    "colourofproduct": "White",
    "batterytechnology": "Alkaline",
    "compatiblememorycards": "SD, SDHC, SDXC",
    "wifistandards": "802.11b, 802.11g, 802.11n",
    "isosensitivitymax": "12800",
    "height": "8.69 cm",
    "flashmodes": "Auto, Red-eye reduction, Slow synchronization",
    "digitalzoom": "2x",
    "viewfindertype": "Electrical",
    "opticalzoom": "50x",
    "lenstype": "High power zoom",
    "videoresolutions": "640 x 480, 1280 x 720, 1920 x 1080 pixels",
    "shortdescription": "16.2MP BSI-CMOS, 50x, 24 x 1200mm, 7.62 cm (3 \") LCD, 12800 ISO, AA",
    "display": "LCD"
}