{
    "videocapability": "Yes",
    "lensstructureelementsgroups": "11/10",
    "lightexposuremodes": "Auto",
    "isosensitivity": "100, 125, 160, 200, 250, 320, 400, 500, 640, 800, 1000, 1250, 1600, 2000, 2500, 3200, 4000, 5000, 6400, 8000, 10000, 12800, Auto",
    "stillimageresolutions": "384 x 480, 480 x 480, 640 x 360, 640 x 424, 640 x 480, 960 x 1200, 1200 x 1200, 1600 x 1064, 1600 x 1200, 1840 x 2304, 1920 x 1080, 2304 x 2304, 2608 x 3264, 3072 x 1728, 3072 x 2048, 3072 x 2304, 3264 x 3264, 4352 x 2248, 4352 x 2904",
    "focus": "TTL",
    "batterytype": "NB-10L",
    "sku": "5249B011AA",
    "usb20portsquantity": "1",
    "supportedaspectratios": "3:2, 4:3, 16:9",
    "flashexposurecompensation": "Yes",
    "videoformatssupported": "H.264, MOV",
    "touchscreen": "No",
    "imagestabilizer": "Yes",
    "sensortype": "CMOS",
    "batterylifecipastandard": "250 shots",
    "height": "8.05 cm",
    "cameraplayback": "Movie, Single image",
    "multiburstmode": "Yes",
    "focusadjustment": "Auto/Manual",
    "flashexposurecorrection": "\u00b12EV (1/3 EV step)",
    "pictbridge": "Yes",
    "lightexposurecontrol": "Program AE",
    "flashrangetele": "1 - 3.1m",
    "weight": "534 g",
    "autoexposureaelock": "Yes",
    "flashexposurelock": "Yes",
    "combinedzoom": "16x",
    "shootingmodes": "Aperture priority, Manual, Movie, Program, Scene, Shutter priority",
    "category": "camera",
    "lightmetering": "Centre-weighted, Evaluative (Multi-pattern), Spot",
    "specification": "Picture quality Supported aspect ratios 3:2, 4:3, 16:9 Still image resolution(s) 384 x 480, 480 x 480, 640 x 360, 640 x 424, 640 x 480, 960 x 1200, 1200 x 1200, 1600 x 1064, 1600 x 1200, 1840 x 2304, 1920 x 1080, 2304 x 2304, 2608 x 3264, 3072 x 1728, 3072 x 2048, 3072 x 2304, 3264 x 3264, 4352 x 2248, 4352 x 2904 Image stabilizer Yes Image sensor size (W x H) 18.7 x 14 mm Image stabilizer location Lens Maximum image resolution 4352 x 3264 pixels Sensor type CMOS Camera type Bridge Megapixel 14.3 MP Lens system Focal length range (f-f) 15.1 - 60.4 mm Minimum focal length (35mm film equiv) 2.8 cm Maximum focal length (35mm film equiv) 11.2 cm Minimum aperture 2.8 Maximum aperture 5.8 Lens structure (elements/groups) 11/10 Combined zoom 16x Number of aspheric elements 3 Digital zoom 4x Optical zoom 4x Focusing Focus TTL Focus adjustment Auto/Manual Auto focusing (AF) modes Continuous Auto Focus, Face detection, Multi Point Auto Focus, Servo Auto Focus, Single Auto Focus, Tracking Auto Focus Closest focusing distance 0.2m Auto Focus (AF) points 9 Auto Focus (AF) lock Yes Auto Focus (AF) assist beam Yes Light exposure ISO sensitivity 100, 125, 160, 200, 250, 320, 400, 500, 640, 800, 1000, 1250, 1600, 2000, 2500, 3200, 4000, 5000, 6400, 8000, 10000, 12800, Auto Light exposure modes Auto Light exposure control Program AE Light exposure correction \u00b1 3EV (1/3EV step) Light metering Centre-weighted, Evaluative (Multi-pattern), Spot Auto Exposure (AE) lock Yes ISO sensitivity (min) 100 ISO sensitivity (max) 12800 Flash Flash modes Auto, Flash off, Flash on, Red-eye reduction, Slow synchronization Built-in flash Yes Flash sync-speed 1/4000s Flash range (wide) 0.5 - 7m Flash range (tele) 1 - 3.1m Flash exposure lock Yes Flash exposure correction \u00b12EV (1/3 EV step) Flash exposure compensation Yes External flash connector Yes Video Video resolutions 640 x 480, 1280 x 720 pixels Video formats supported H.264, MOV Motion JPEG frame rate 24 fps Full HD Yes Analog signal format system NTSC, PAL Maximum video resolution 1920 x 1080 pixels Audio Built-in microphone Yes Memory Compatible memory cards SD, SDHC, SDXC Memory slots 1 Display Display TFT Display diagonal 7.11 cm (2.8\") Display resolution (numeric) 920000 pixels Vari-angle LCD display Yes Field of view 100% Viewfinder Viewfinder type Optical Ports & interfaces PictBridge Yes USB 2.0 ports quantity 1 USB connector type Mini-USB B HDMI ports quantity 1 Camera Image stabilizer location Lens Colour of product Black White balance Auto, Cloudy, Custom modes, Daylight, Flash, Fluorescent, Fluorescent H, Tungsten, Underwater Scene modes Beach, Children, Fireworks, Landscape, Portrait, Snow, Underwater Shooting modes Aperture priority, Manual, Movie, Program, Scene, Shutter priority Photo effects Black&White, Neutral, Positive film, Sepia, Skin tones, Vivid Self-timer 2, 10s Camera playback Movie, Single image Multi burst mode Yes Playback zoom (max) 10x On Screen Display (OSD) languages ARA, CHI (SIMPL), CHI (TR), CZE, DAN, DEU, DUT, ENG, ESP, FIN, FRE, GRE, HUN, ITA, JPN, KOR, NOR, POL, POR, RUM, RUS, SWE, THA, TUR, UKR Image editing Resizing Histogram Yes Dioptre correction Yes Camera file system DPOF 1.1, Exif 2.3, RAW Built-in processor DIGIC 5 + iSAPS Battery Battery technology Lithium-Ion (Li-Ion) Battery life (CIPA standard) 250 shots Battery type NB-10L Number of batteries supported 1 Power source type Battery Technical details USB 2.0 ports quantity 1 HDMI ports quantity 1 Video memory capacity 29min. 59sec. On/off switch Yes Digital SLR No Processor Built-in processor DIGIC 5 + iSAPS Design Colour of product Black Performance Built-in processor DIGIC 5 + iSAPS Operational conditions Operating temperature (T-T) 0 - 40 \u00b0C Operating relative humidity (H-H) 10 - 90% Weight & dimensions Width 11.67 cm Depth 6.47 cm Height 8.05 cm Weight (including battery) 534g Packaging content Battery charger included Yes Batteries included Yes Other features USB 2.0 ports quantity 1 Video capability Yes HDMI ports quantity 1 Video memory capacity 29min. 59sec. On/off switch Yes Camera shutter speed 1 - 1/4000; 60 - 1/4000s Digital SLR No",
    "autofocusafassistbeam": "Yes",
    "selftimer": "2, 10s",
    "maximumaperture": "5.8",
    "digitalslr": "No",
    "minimumaperture": "2.8",
    "motionjpegframerate": "24 fps",
    "camerashutterspeed": "1 - 1/4000; 60 - 1/4000s",
    "onscreendisplayosdlanguages": "ARA, CHI (SIMPL), CHI (TR), CZE, DAN, DEU, DUT, ENG, ESP, FIN, FRE, GRE, HUN, ITA, JPN, KOR, NOR, POL, POR, RUM, RUS, SWE, THA, TUR, UKR",
    "fullhd": "Yes",
    "displayresolutionnumeric": "920000 pixels",
    "manufacturer": "Canon",
    "isosensitivitymin": "100",
    "analogsignalformatsystem": "NTSC, PAL",
    "externalflashconnector": "Yes",
    "builtinflash": "Yes",
    "compatiblememorycards": "SD, SDHC, SDXC",
    "isosensitivitymax": "12800",
    "videoresolutions": "640 x 480, 1280 x 720 pixels",
    "warranty": "1 Year",
    "photoeffects": "Black&White, Neutral, Positive film, Sepia, Skin tones, Vivid",
    "megapixel": "14.3 MP",
    "hdmiportsquantity": "1",
    "camerafilesystem": "DPOF 1.1, Exif 2.3, RAW",
    "imageediting": "Resizing",
    "builtinmicrophone": "Yes",
    "numberofasphericelements": "3",
    "width": "11.67 cm",
    "playbackzoommax": "10x",
    "dioptrecorrection": "Yes",
    "batteriesincluded": "Yes",
    "memoryslots": "1",
    "closestfocusingdistance": "0.2m",
    "histogram": "Yes",
    "batterychargerincluded": "Yes",
    "powersourcetype": "Battery",
    "operatingrelativehumidityhh": "10 - 90%",
    "flashrangewide": "0.5 - 7m",
    "cameratype": "Bridge",
    "colourofproduct": "Black",
    "lcdscreensize": "3",
    "flashmodes": "Auto, Flash off, Flash on, Red-eye reduction, Slow synchronization",
    "maximumfocallength35mmfilmequiv": "11.2 cm",
    "onoffswitch": "Yes",
    "shortdescription": "PowerShot G1X - 14.3MP, 18.7 x 14.0 mm CMOS, 4352 x 3264, 4x Optical zoom, Full HD Movie, 7.62 cm (3.0 \") TFT LCD, USB 2.0, HDMI, 534g, Black",
    "display": "TFT",
    "imagestabilizerlocation": "Lens",
    "focallengthrangeff": "15.1 - 60.4 mm",
    "flashsyncspeed": "1/4000s",
    "fieldofview": "100%",
    "weightincludingbattery": "534g",
    "autofocusaflock": "Yes",
    "maximumimageresolution": "4352 x 3264 pixels",
    "operatingtemperaturett": "0 - 40 \u00b0C",
    "lightexposurecorrection": "\u00b1 3EV (1/3EV step)",
    "usbconnectortype": "Mini-USB B",
    "ean": "8714574577753",
    "digitalzoom": "4x",
    "minimumfocallength35mmfilmequiv": "2.8 cm",
    "dimensionswxdxh": "116.7 x 64.7 x 80.5 mm",
    "maximumvideoresolution": "1920 x 1080 pixels",
    "builtinprocessor": "DIGIC 5 + iSAPS",
    "displaydiagonal": "7.11 cm (2.8\")",
    "varianglelcddisplay": "Yes",
    "autofocusafpoints": "9",
    "autofocusingafmodes": "Continuous Auto Focus, Face detection, Multi Point Auto Focus, Servo Auto Focus, Single Auto Focus, Tracking Auto Focus",
    "scenemodes": "Beach, Children, Fireworks, Landscape, Portrait, Snow, Underwater",
    "batterytechnology": "Lithium-Ion (Li-Ion)",
    "opticalzoom": "4x",
    "imagesensorsizewxh": "18.7 x 14 mm",
    "numberofbatteriessupported": "1",
    "depth": "6.47 cm",
    "viewfindertype": "Optical",
    "whitebalance": "Auto, Cloudy, Custom modes, Daylight, Flash, Fluorescent, Fluorescent H, Tungsten, Underwater"
}