{
    "pictbridge": "Yes",
    "lightexposurecontrol": "Program AE",
    "wifi": "Yes",
    "focallengthrangeff": "16 - 50 mm",
    "weight": "280g",
    "lightexposuremodes": "Aperture priority AE, Manual, Shutter priority AE",
    "audioformatssupported": "PCM",
    "isosensitivity": "100, 200, 6400, 12800, 25600",
    "stillimageresolutions": "4896 x 2760 3264 x 3264 3456 x 2304 3456 x 1944 2304 x 2304 2496 x 1664 2496 x 1408 1664 x 1664",
    "focus": "TTL",
    "megapixel": "16 MP",
    "camerashutterspeedmax": "30s",
    "maximumimageresolution": "4896 x 3264 pixels",
    "operatingtemperaturett": "0 - 40 \u00b0C",
    "lightexposurecorrection": "\u00b1 2EV (1/3EV step)",
    "batterytype": "NP-W126",
    "sku": "P10NC11660A",
    "selftimer": "2, 10s",
    "builtinmicrophone": "Yes",
    "motionjpegframerate": "30 fps",
    "imageformatssupported": "JPG, RAW",
    "specification": "Picture quality Sensor format Advanced Photo System type-C (APS-C) Supported aspect ratios 1:1, 3:2, 16:9 Still image resolution(s) 4896 x 2760 3264 x 3264 3456 x 2304 3456 x 1944 2304 x 2304 2496 x 1664 2496 x 1408 1664 x 1664 Total megapixels 16.3 MP Image sensor size (W x H) 23.6 x 15.6 mm Image formats supported JPG, RAW Maximum image resolution 4896 x 3264 pixels Sensor type CMOS Camera type MILC Megapixel 16 MP Lens system Focal length range (f-f) 16 - 50 mm Focusing Focus TTL Focus adjustment Auto/Manual Auto focusing (AF) modes Continuous Auto Focus, Multi Point Auto Focus, Tracking Auto Focus Light exposure ISO sensitivity 100, 200, 6400, 12800, 25600 Light exposure modes Aperture priority AE, Manual, Shutter priority AE Light exposure control Program AE Light exposure correction \u00b1 2EV (1/3EV step) Shutter Camera shutter speed (min) 0.00025s Camera shutter speed (max) 30s Flash Flash modes Manual Built-in flash Yes Video Video resolutions 1280 x 720 pixels Video formats supported H.264, MOV Motion JPEG frame rate 30 fps Full HD Yes Maximum video resolution 1920 x 1080 pixels Audio Built-in microphone Yes Audio formats supported PCM Memory Compatible memory cards SD, SDHC, SDXC Memory slots 1 Display Display aspect ratio 3:2 Display LCD Display diagonal 7.62 cm (3\") Display resolution (numeric) 920000 pixels Ports & interfaces USB version 2.0 HDMI connector type Mini PictBridge Yes HDMI Yes Networking Wi-Fi standards 802.11b, 802.11g, 802.11n Wi-Fi Yes Camera Colour of product Black, Silver White balance Auto, Custom modes, Fluorescent, Incandescent Scene modes Landscape, Portrait, Sports Photo effects Negative film, Sepia, Vivid Self-timer 2, 10s Battery Battery technology Lithium-Ion (Li-Ion) Battery life (CIPA standard) 350 shots Battery type NP-W126 Power source type Battery Technical details HDMI Yes Design Colour of product Black, Silver Operational conditions Operating temperature (T-T) 0 - 40 \u00b0C Operating relative humidity (H-H) 10 - 80% Weight & dimensions Width 11.69 cm Depth 3.9 cm Height 6.65 cm Weight 280g Weight (including battery) 330g",
    "memoryslots": "1",
    "displayresolutionnumeric": "920000 pixels",
    "usbversion": "2.0",
    "width": "11.69 cm",
    "supportedaspectratios": "1:1, 3:2, 16:9",
    "maximumvideoresolution": "1920 x 1080 pixels",
    "displayaspectratio": "3:2",
    "videoformatssupported": "H.264, MOV",
    "category": "camera",
    "weightincludingbattery": "330g",
    "displaydiagonal": "7.62 cm (3\")",
    "hdmi": "Yes",
    "ean": "4547410251968",
    "whitebalance": "Auto, Custom modes, Fluorescent, Incandescent",
    "autofocusingafmodes": "Continuous Auto Focus, Multi Point Auto Focus, Tracking Auto Focus",
    "sensortype": "CMOS",
    "scenemodes": "Landscape, Portrait, Sports",
    "batterylifecipastandard": "350 shots",
    "fullhd": "Yes",
    "photoeffects": "Negative film, Sepia, Vivid",
    "powersourcetype": "Battery",
    "operatingrelativehumidityhh": "10 - 80%",
    "manufacturer": "Fujifilm",
    "sensorformat": "Advanced Photo System type-C (APS-C)",
    "hdmiconnectortype": "Mini",
    "focusadjustment": "Auto/Manual",
    "cameratype": "MILC",
    "flashmodes": "Manual",
    "builtinflash": "Yes",
    "camerashutterspeedmin": "0.00025s",
    "colourofproduct": "Black, Silver",
    "batterytechnology": "Lithium-Ion (Li-Ion)",
    "compatiblememorycards": "SD, SDHC, SDXC",
    "wifistandards": "802.11b, 802.11g, 802.11n",
    "imagesensorsizewxh": "23.6 x 15.6 mm",
    "height": "6.65 cm",
    "depth": "3.9 cm",
    "totalmegapixels": "16.3 MP",
    "videoresolutions": "1280 x 720 pixels",
    "shortdescription": "X-M1 + XC16-50mm Kit, 16MP, APS-C X-Trans CMOS, 7.62 cm (3.0 \") LCD, SD/SDHC/SDXC, Full HD Movie, Black/Silver",
    "display": "LCD"
}