{
    "lightexposuremodes": "Aperture priority AE, Auto, Manual, Shutter priority AE",
    "isosensitivity": "100, 3200, 16000",
    "noisereduction": "Yes",
    "batterytype": "NP-FW50",
    "sku": "ILCE3000KB.CE",
    "supportedaspectratios": "3:2, 16:9",
    "videoformatssupported": "AVCHD, H.264, MPEG4",
    "stillimageresolutions": "5456x3064, 3872\u00d72576, 3872x2176, 2736x1824, 2736x1536",
    "sensortype": "CMOS",
    "batterylifecipastandard": "4700 shots",
    "height": "9.09 cm",
    "cameraplayback": "Single image, Slide show",
    "normalfocusingrange": "0.5 - 3m",
    "focusadjustment": "Auto/Manual",
    "camerashutterspeedmin": "0.00025s",
    "batterylevelindicator": "Yes",
    "audiosystem": "Mono",
    "pictbridge": "No",
    "lightexposurecontrol": "Program AE",
    "weight": "353g",
    "audioformatssupported": "AAC, AC3, MP4",
    "autoexposureaelock": "Yes",
    "category": "camera",
    "macoperatingsystemssupported": "Yes",
    "imageformatssupported": "JPG, RAW",
    "lightmetering": "Centre-weighted, Evaluative (Multi-pattern), Spot",
    "specification": "Picture quality Sensor format Advanced Photo System type-C (APS-C) Supported aspect ratios 3:2, 16:9 Still image resolution(s) 5456x3064, 3872\u00d72576, 3872x2176, 2736x1824, 2736x1536 Total megapixels 20.4 MP Image sensor size (W x H) 23.2 x 15.4 mm Image formats supported JPG, RAW Maximum image resolution 5456 x 3632 pixels Sensor type CMOS Camera type SLR Body Megapixel 20.1 MP Lens system Lens mount interface Sony E Digital zoom 4x Focusing Focus adjustment Auto/Manual Auto focusing (AF) modes Centre weighted Auto Focus, Continuous Auto Focus, Contrast Detection Auto Focus, Face detection, Flexible Spot Auto Focus, Multi Point Auto Focus, Single Auto Focus, Tracking Auto Focus Normal focusing range 0.5 - 3m Closest focusing distance 0.25m Auto Focus (AF) points 25 Light exposure ISO sensitivity 100, 3200, 16000 Light exposure modes Aperture priority AE, Auto, Manual, Shutter priority AE Light exposure control Program AE Light exposure correction \u00b1 3EV (1/3EV step) Light metering Centre-weighted, Evaluative (Multi-pattern), Spot Auto Exposure (AE) lock Yes ISO sensitivity (min) 100 ISO sensitivity (max) 16000 Shutter Camera shutter speed (min) 0.00025s Camera shutter speed (max) 30s Camera shutter type Electronic Flash Flash modes Auto, Fill-in, Flash off, Flash on, Pre-flash, Red-eye reduction, Slow synchronization, Flash Off Built-in flash Yes Flash sync-speed 1/160s Flash recharging time 4s Flash exposure correction \u00b12EV (1/3 EV step) Video Video resolutions 640 x 480, 1440 x 1080, 1920 x 1080 pixels Video formats supported AVCHD, H.264, MPEG4 Full HD Yes Analog signal format system NTSC Maximum video resolution 1920 x 1080 pixels Audio Noise reduction Yes Built-in microphone Yes Audio system Mono Audio formats supported AAC, AC3, MP4 Memory Compatible memory cards MS PRO Duo, MS Pro-HG Duo, MSXC, SD, SDHC, SDXC Display Display LCD Display diagonal 7.62 cm (3\") Display resolution (numeric) 230.400 pixels Field of view 100% Viewfinder Viewfinder type Electrical Ports & interfaces USB version 2.0 PictBridge No DC-in jack Yes HDMI No Camera Colour of product Black White balance Auto, Cloudy, Custom modes, Daylight, Flash, Fluorescent, Incandescent, Shade Scene modes Portrait, Landscape, Sunset Self-timer 2, 10s Camera playback Single image, Slide show Histogram Yes Brightness adjustment Yes Anti-dust function Yes Battery Battery technology Lithium-Ion (Li-Ion) Battery life (CIPA standard) 4700 shots Battery capacity 1080 mAh Battery level indicator Yes Power source type AC, Battery Operating system/software Windows operating systems supported Yes Mac operating systems supported Yes Technical details Noise reduction Yes Frame rate 30 fps Shutter priority AE Yes Panorama Yes Manual exposure Yes HDMI No Effective megapixels (image) 20.1 MP Battery level indicator Yes Auto exposure Yes Audio system Mono Aperture priority AE Yes Design Colour of product Black Operational conditions Operating temperature (T-T) 0 - 40 \u00b0C System requirements Windows operating systems supported Yes Mac operating systems supported Yes Weight & dimensions Width 12.8 cm Depth 8.45 cm Height 9.09 cm Weight 353g Other features Frame rate 30 fps Shutter priority AE Yes Panorama Yes Manual exposure Yes Effective megapixels (image) 20.1 MP Auto exposure Yes Aperture priority AE Yes",
    "selftimer": "2, 10s",
    "hdmi": "No",
    "fullhd": "Yes",
    "displayresolutionnumeric": "230.400 pixels",
    "manufacturer": "Sony",
    "isosensitivitymin": "100",
    "analogsignalformatsystem": "NTSC",
    "flashmodes": "Auto, Fill-in, Flash off, Flash on, Pre-flash, Red-eye reduction, Slow synchronization, Flash Off",
    "builtinflash": "Yes",
    "compatiblememorycards": "MS PRO Duo, MS Pro-HG Duo, MSXC, SD, SDHC, SDXC",
    "isosensitivitymax": "16000",
    "videoresolutions": "640 x 480, 1440 x 1080, 1920 x 1080 pixels",
    "warranty": "1 Year",
    "megapixel": "20.1 MP",
    "shutterpriorityae": "Yes",
    "builtinmicrophone": "Yes",
    "panorama": "Yes",
    "width": "12.8 cm",
    "sensorformat": "Advanced Photo System type-C (APS-C)",
    "windowsoperatingsystemssupported": "Yes",
    "antidustfunction": "Yes",
    "ean": "4905524945416",
    "closestfocusingdistance": "0.25m",
    "histogram": "Yes",
    "batterycapacity": "1080 mAh",
    "powersourcetype": "AC, Battery",
    "brightnessadjustment": "Yes",
    "cameratype": "SLR Body",
    "camerashuttertype": "Electronic",
    "colourofproduct": "Black",
    "framerate": "30 fps",
    "lensmountinterface": "Sony E",
    "manualexposure": "Yes",
    "lenstype": "18-55mm",
    "shortdescription": "Digital E-mount 20.1 Mega Pixel Camera with SEL 1855 Lens",
    "display": "LCD",
    "flashsyncspeed": "1/160s",
    "fieldofview": "100%",
    "autoexposure": "Yes",
    "camerashutterspeedmax": "30s",
    "maximumimageresolution": "5456 x 3632 pixels",
    "operatingtemperaturett": "0 - 40 \u00b0C",
    "lightexposurecorrection": "\u00b1 3EV (1/3EV step)",
    "dcinjack": "Yes",
    "depth": "8.45 cm",
    "usbversion": "2.0",
    "dimensionswxdxh": "128 x 84.5 x 90.9 mm",
    "maximumvideoresolution": "1920 x 1080 pixels",
    "displaydiagonal": "7.62 cm (3\")",
    "autofocusafpoints": "25",
    "autofocusingafmodes": "Centre weighted Auto Focus, Continuous Auto Focus, Contrast Detection Auto Focus, Face detection, Flexible Spot Auto Focus, Multi Point Auto Focus, Single Auto Focus, Tracking Auto Focus",
    "scenemodes": "Portrait, Landscape, Sunset",
    "aperturepriorityae": "Yes",
    "flashrechargingtime": "4s",
    "batterytechnology": "Lithium-Ion (Li-Ion)",
    "flashexposurecorrection": "\u00b12EV (1/3 EV step)",
    "imagesensorsizewxh": "23.2 x 15.4 mm",
    "totalmegapixels": "20.4 MP",
    "digitalzoom": "4x",
    "viewfindertype": "Electrical",
    "whitebalance": "Auto, Cloudy, Custom modes, Daylight, Flash, Fluorescent, Incandescent, Shade"
}