{
    "videocapability": "Yes",
    "pictbridge": "Yes",
    "cablesincluded": "AC, USB",
    "autofocusafpointsselection": "Auto, Manual",
    "weight": "480 g",
    "lightexposuremodes": "Auto, Manual",
    "isosensitivity": "100, 125, 160, 200, 250, 320, 400, 500, 640, 800, 1000, 1250, 1600, 2000, 2250, 2500, 3200, 4000, 5000, 6400",
    "stillimageresolutions": "JPEG 3:2: (L) 5184x3456, (M) 3456x2304, (S1) 2592x1728, (S2) 1920x1280, (S3) 720x480 JPEG 4:3: (L) 4608x3456, (M) 3072x2304, (S1) 2304x1728, (S2) 1696x1280, (S3) 640x480 JPEG 16:9: (L) 5184x2912, (M) 3456x1944, (S1) 2592x1456 (S2) 1920x1080, (S3) 720x400 JPEG 1:1: (L) 3456x3456, (M) 2304x2304, (S1) 1728x1728, (S2) 1280x1280, (S3) 480x480",
    "focus": "TTL",
    "height": "9.97 cm",
    "lightexposurecorrection": "\u00b15EV (1/2; 1/3 EV step)",
    "flashexposurelock": "Yes",
    "operatingtemperaturett": "0 - 40 \u00b0C",
    "autofocusaflock": "Yes",
    "isosensitivitymax": "6400",
    "batterytype": "Rechargeable Li-ion Battery LP-E10",
    "flashmodes": "Auto, Flash off, Flash on",
    "camerafilesystem": "DCF 2.0",
    "sku": "9127B020AA",
    "totalmegapixels": "18.7 MP",
    "whitebalance": "Cloudy, Custom modes, Daylight, Flash, Fluorescent L, Shade, Tungsten",
    "mountingtype": "Bayonet",
    "liveview": "Yes",
    "specification": "Picture quality Supported aspect ratios 1:1, 3:2, 4:3, 16:9 Still image resolution(s) JPEG 3:2: (L) 5184x3456, (M) 3456x2304, (S1) 2592x1728, (S2) 1920x1280, (S3) 720x480 JPEG 4:3: (L) 4608x3456, (M) 3072x2304, (S1) 2304x1728, (S2) 1696x1280, (S3) 640x480 JPEG 16:9: (L) 5184x2912, (M) 3456x1944, (S1) 2592x1456 (S2) 1920x1080, (S3) 720x400 JPEG 1:1: (L) 3456x3456, (M) 2304x2304, (S1) 1728x1728, (S2) 1280x1280, (S3) 480x480 Total megapixels 18.7 MP Image sensor size (W x H) 22.3 x 14.9 mm Maximum image resolution 5184 x 3456 pixels Sensor type CMOS Camera type SLR Body Megapixel 18 MP Lens system Mounting type Bayonet Lens mount interface Canon EF, Canon EF-S Focusing Focus TTL Auto Focus (AF) points selection Auto, Manual Auto Focus (AF) points 9 Auto Focus (AF) lock Yes Auto Focus (AF) assist beam Yes Light exposure ISO sensitivity 100, 125, 160, 200, 250, 320, 400, 500, 640, 800, 1000, 1250, 1600, 2000, 2250, 2500, 3200, 4000, 5000, 6400 Light exposure modes Auto, Manual Light exposure correction \u00b15EV (1/2; 1/3 EV step) ISO sensitivity (min) 100 ISO sensitivity (max) 6400 Shutter Camera shutter speed (min) 0.000250s Camera shutter type Electronic Flash Flash modes Auto, Flash off, Flash on Built-in flash Yes Flash recharging time 2s Flash exposure lock Yes Flash exposure correction \u00b12EV (1/2, 1/3 EV step) Flash exposure compensation Yes External flash connector Yes Video Video resolutions 640 x 480, 1280 x 720, 1920 x 1080 pixels Video formats supported H.264 Full HD Yes Maximum video resolution 1920 x 1080 pixels Memory Compatible memory cards SD, SDHC, SDXC Display Display TFT Display diagonal 7.62 cm (3\") Ports & interfaces HDMI connector type Mini PictBridge Yes HDMI Yes Camera Colour of product Black White balance Cloudy, Custom modes, Daylight, Flash, Fluorescent L, Shade, Tungsten Scene modes Close-up (macro), Landscape, Night portrait, Sports Shooting modes Aperture priority, Auto, Manual, Movie, Program, Scene, Shutter priority Self-timer 2, 10s Orientation sensor Yes Live view Yes Languages support ARA, CHI (SIMPL), CHI (TR), CZE, DAN, DEU, DUT, ENG, ESP, FIN, FRE, GRE, HUN, ITA, JPN, KOR, NOR, POL, POR, RUM, RUS, SWE, THA, TUR, UKR Histogram Yes GPS O Direct printing Yes Dioptre correction Yes Camera file system DCF 2.0 Brightness adjustment Yes Battery Battery technology Lithium-Ion (Li-Ion) Battery life (CIPA standard) 500 shots Power source type Battery Technical details Wrist strap included Yes Material Carbon, Glass, Polycarbonate Languages support ARA, CHI (SIMPL), CHI (TR), CZE, DAN, DEU, DUT, ENG, ESP, FIN, FRE, GRE, HUN, ITA, JPN, KOR, NOR, POL, POR, RUM, RUS, SWE, THA, TUR, UKR HDMI Yes GPS O Direct printing Yes Design Material Carbon, Glass, Polycarbonate Colour of product Black Performance GPS O Direct printing Yes Operational conditions Operating temperature (T-T) 0 - 40 \u00b0C Operating relative humidity (H-H) 0 - 85% Weight & dimensions Width 12.96 cm Depth 7.79 cm Height 9.97 cm Weight (including battery) 480g Packaging content Wrist strap included Yes Cables included AC, USB Battery charger included Yes Batteries included Yes",
    "autofocusafassistbeam": "Yes",
    "depth": "7.79 cm",
    "selftimer": "2, 10s",
    "width": "12.96 cm",
    "supportedaspectratios": "1:1, 3:2, 4:3, 16:9",
    "flashrechargingtime": "2s",
    "flashexposurecompensation": "Yes",
    "dimensionswxdxh": "129.6 x 77.9 x 99.7 mm",
    "maximumvideoresolution": "1920 x 1080 pixels",
    "type": "Digital SLR",
    "videoformatssupported": "H.264",
    "compatiblememorycards": "SD, SDHC, SDXC",
    "category": "camera",
    "dioptrecorrection": "Yes",
    "displaydiagonal": "7.62 cm (3\")",
    "hdmi": "Yes",
    "ean": "8714574618166",
    "material": "Carbon, Glass, Polycarbonate",
    "autofocusafpoints": "9",
    "histogram": "Yes",
    "sensortype": "CMOS",
    "batterychargerincluded": "Yes",
    "scenemodes": "Close-up (macro), Landscape, Night portrait, Sports",
    "weightincludingbattery": "480g",
    "fullhd": "Yes",
    "powersourcetype": "Battery",
    "operatingrelativehumidityhh": "0 - 85%",
    "manufacturer": "Canon",
    "brightnessadjustment": "Yes",
    "isosensitivitymin": "100",
    "hdmiconnectortype": "Mini",
    "lcdscreensize": "3",
    "batteriesincluded": "Yes",
    "lensmountinterface": "Canon EF, Canon EF-S",
    "camerashutterspeedmin": "0.000250s",
    "cameratype": "SLR Body",
    "camerashuttertype": "Electronic",
    "directprinting": "Yes",
    "colourofproduct": "Black",
    "batterytechnology": "Lithium-Ion (Li-Ion)",
    "shootingmodes": "Aperture priority, Auto, Manual, Movie, Program, Scene, Shutter priority",
    "flashexposurecorrection": "\u00b12EV (1/2, 1/3 EV step)",
    "imagesensorsizewxh": "22.3 x 14.9 mm",
    "megapixel": "18 MP",
    "externalflashconnector": "Yes",
    "languagessupport": "ARA, CHI (SIMPL), CHI (TR), CZE, DAN, DEU, DUT, ENG, ESP, FIN, FRE, GRE, HUN, ITA, JPN, KOR, NOR, POL, POR, RUM, RUS, SWE, THA, TUR, UKR",
    "orientationsensor": "Yes",
    "builtinflash": "Yes",
    "batterylifecipastandard": "500 shots",
    "videoresolutions": "640 x 480, 1280 x 720, 1920 x 1080 pixels",
    "gps": "O",
    "shortdescription": "18MP, 22.3 x 14.9mm, 3:2, CMOS, TFT, 7.62 cm (3 \")",
    "display": "TFT",
    "maximumimageresolution": "5184 x 3456 pixels"
}