{
    "lightexposuremodes": "Aperture priority AE, Auto, Shutter priority AE",
    "isosensitivity": "100, 200, 400, 800, 1600, 3200, 6400, Auto",
    "stillimageresolutions": "480 x 480, 720 x 400, 720 x 480, 1280 x 1280, 1696 x 1280, 1728 x 1728, 1920 x 1080, 1920 x 1280, 2304 x 1728, 2304 x 2304, 2592 x 1456, 2592 x 1728, 3072 x 2304, 3456 x 1944, 3456 x 2304, 3456 x 3456, 4608 x 3456, 5184 x 2912, 5184 x 3456",
    "focus": "TTL",
    "batterytype": "LP-E12",
    "sku": "8576B014AA",
    "usb20portsquantity": "1",
    "liveview": "Yes",
    "supportedaspectratios": "3:2, 4:3, 16:9",
    "flashexposurecompensation": "Yes",
    "videoformatssupported": "H.264, MOV",
    "weightincludingbattery": "407g",
    "builtinprocessor": "DIGIC 5",
    "sensortype": "CMOS",
    "batterylifecipastandard": "380 shots",
    "height": "9.07 cm",
    "cameraplayback": "Highlights, Movie, Single image, Slide show",
    "focusadjustment": "Auto/Manual",
    "camerashutterspeedmin": "0.00025s",
    "pictbridge": "Yes",
    "weight": "407 g",
    "batterylevelindicator": "Yes",
    "flashexposurelock": "Yes",
    "hdmiportsquantity": "1",
    "flashguidenumber": "9.4m",
    "shootingmodes": "Aperture priority, Auto, Manual, Program, Shutter priority",
    "category": "camera",
    "macoperatingsystemssupported": "Mac OS X 10.6 Snow Leopard, Mac OS X 10.7 Lion, Mac OS X 10.8 Mountain Lion",
    "imageformatssupported": "JPG",
    "lightmetering": "Centre-weighted, Evaluative (Multi-pattern), Spot",
    "specification": "Picture quality Supported aspect ratios 3:2, 4:3, 16:9 Still image resolution(s) 480 x 480, 720 x 400, 720 x 480, 1280 x 1280, 1696 x 1280, 1728 x 1728, 1920 x 1080, 1920 x 1280, 2304 x 1728, 2304 x 2304, 2592 x 1456, 2592 x 1728, 3072 x 2304, 3456 x 1944, 3456 x 2304, 3456 x 3456, 4608 x 3456, 5184 x 2912, 5184 x 3456 Total megapixels 18.5 MP Image formats supported JPG Maximum image resolution 5184 x 3456 pixels Sensor type CMOS Camera type SLR Body Megapixel 18 MP Lens system Lens mount interface Canon EF, Canon EF-S Focusing Focus TTL Focus adjustment Auto/Manual Auto focusing (AF) modes Face detection, Face tracking Auto Focus (AF) points 9 Auto Focus (AF) lock Yes Auto Focus (AF) assist beam Yes Light exposure ISO sensitivity 100, 200, 400, 800, 1600, 3200, 6400, Auto Light exposure modes Aperture priority AE, Auto, Shutter priority AE Light exposure correction \u00b1 5EV (1/3EV step) Light metering Centre-weighted, Evaluative (Multi-pattern), Spot Auto Exposure (AE) lock Yes ISO sensitivity (min) 100 ISO sensitivity (max) 6400 Shutter Camera shutter speed (min) 0.00025s Camera shutter speed (max) 30s Camera shutter type Electronic Flash Flash modes Auto, Manual, Red-eye reduction Built-in flash Yes Flash sync-speed 1/200s Flash recharging time 3s Flash guide number 9.4m Flash exposure lock Yes Flash exposure correction \u00b12EV (1/2, 1/3 EV step) Flash exposure compensation Yes External flash connector Yes Video Video resolutions 640 x 480, 1280 x 720, 1920 x 1080 pixels Video formats supported H.264, MOV Full HD Yes Analog signal format system NTSC, PAL Maximum video resolution 1920 x 1080 pixels Memory Compatible memory cards SD, SDHC, SDXC Memory slots 1 Display Display LCD Display diagonal 7.62 cm (3\") Display resolution (numeric) 1040000 pixels Field of view 100% Viewfinder Viewfinder type Electrical Magnification 0.87x Ports & interfaces USB version 2.0 HDMI connector type Mini Microphone in Yes PictBridge Yes USB 2.0 ports quantity 1 HDMI ports quantity 1 HDMI Yes Camera Colour of product Black White balance Auto, Cloudy, Custom modes, Daylight, Flash, Fluorescent, Shade, Tungsten Scene modes Candlelight, Children, Close-up (macro), Landscape, Night portrait, Portrait, Sports Shooting modes Aperture priority, Auto, Manual, Program, Shutter priority Photo effects Black&White, Neutral Camera playback Highlights, Movie, Single image, Slide show Playback zoom (max) 10x Orientation sensor Yes On Screen Display (OSD) languages ARA, CHI (SIMPL), CHI (TR), CZE, DAN, DEU, DUT, ENG, ESP, FIN, FRE, GRE, HUN, ITA, JPN, KOR, NOR, POL, POR, RUM, RUS, SWE, THA, TUR, UKR Live view Yes Histogram Yes Dioptre correction Yes Custom colour Yes Camera file system DPOF 1.1, Exif 2.3 Built-in processor DIGIC 5 Battery Battery technology Lithium-Ion (Li-Ion) Battery life (CIPA standard) 380 shots Battery type LP-E12 Number of batteries supported 1 Battery level indicator Yes Power source type Battery, USB Operating system/software Windows operating systems supported Windows 7 Home Basic, Windows 7 Home Basic x64, Windows 7 Home Premium, Windows 7 Home Premium x64, Windows 7 Professional, Windows 7 Professional x64, Windows 7 Starter, Windows 7 Starter x64, Windows 7 Ultimate, Windows 7 Ultimate x64, Windows 8, Windows 8 Enterprise, Windows 8 Enterprise x64, Windows 8 Pro, Windows 8 Pro x64, Windows 8 x64, Windows XP Home, Windows XP Home x64, Windows XP Professional, Windows XP Professional x64 Mac operating systems supported Mac OS X 10.6 Snow Leopard, Mac OS X 10.7 Lion, Mac OS X 10.8 Mountain Lion Bundled software ImageBrowser EX, PhotoStitch, EOS Utility, Picture Style Editor Technical details USB 2.0 ports quantity 1 HDMI ports quantity 1 Material Aluminium, Glass, Polycarbonate, Rubber HDMI Yes Battery level indicator Yes Processor Built-in processor DIGIC 5 Design Material Aluminium, Glass, Polycarbonate, Rubber Colour of product Black Performance Built-in processor DIGIC 5 Operational conditions Operating temperature (T-T) 0 - 45 \u00b0C Operating relative humidity (H-H) 5 - 85% System requirements Windows operating systems supported Windows 7 Home Basic, Windows 7 Home Basic x64, Windows 7 Home Premium, Windows 7 Home Premium x64, Windows 7 Professional, Windows 7 Professional x64, Windows 7 Starter, Windows 7 Starter x64, Windows 7 Ultimate, Windows 7 Ultimate x64, Windows 8, Windows 8 Enterprise, Windows 8 Enterprise x64, Windows 8 Pro, Windows 8 Pro x64, Windows 8 x64, Windows XP Home, Windows XP Home x64, Windows XP Professional, Windows XP Professional x64 Mac operating systems supported Mac OS X 10.6 Snow Leopard, Mac OS X 10.7 Lion, Mac OS X 10.8 Mountain Lion Weight & dimensions Width 11.68 cm Depth 6.94 cm Height 9.07 cm Weight (including battery) 407g Packaging content Bundled software ImageBrowser EX, PhotoStitch, EOS Utility, Picture Style Editor Batteries included Yes Other features USB 2.0 ports quantity 1 HDMI ports quantity 1",
    "autofocusafassistbeam": "Yes",
    "customcolour": "Yes",
    "hdmi": "Yes",
    "onscreendisplayosdlanguages": "ARA, CHI (SIMPL), CHI (TR), CZE, DAN, DEU, DUT, ENG, ESP, FIN, FRE, GRE, HUN, ITA, JPN, KOR, NOR, POL, POR, RUM, RUS, SWE, THA, TUR, UKR",
    "fullhd": "Yes",
    "displayresolutionnumeric": "1040000 pixels",
    "manufacturer": "Canon",
    "isosensitivitymin": "100",
    "analogsignalformatsystem": "NTSC, PAL",
    "bundledsoftware": "ImageBrowser EX, PhotoStitch, EOS Utility, Picture Style Editor",
    "externalflashconnector": "Yes",
    "builtinflash": "Yes",
    "compatiblememorycards": "SD, SDHC, SDXC",
    "isosensitivitymax": "6400",
    "hdmiconnectortype": "Mini",
    "warranty": "1 Year",
    "photoeffects": "Black&White, Neutral",
    "megapixel": "18 MP",
    "camerafilesystem": "DPOF 1.1, Exif 2.3",
    "width": "11.68 cm",
    "magnification": "0.87x",
    "windowsoperatingsystemssupported": "Windows 7 Home Basic, Windows 7 Home Basic x64, Windows 7 Home Premium, Windows 7 Home Premium x64, Windows 7 Professional, Windows 7 Professional x64, Windows 7 Starter, Windows 7 Starter x64, Windows 7 Ultimate, Windows 7 Ultimate x64, Windows 8, Windows 8 Enterprise, Windows 8 Enterprise x64, Windows 8 Pro, Windows 8 Pro x64, Windows 8 x64, Windows XP Home, Windows XP Home x64, Windows XP Professional, Windows XP Professional x64",
    "playbackzoommax": "10x",
    "type": "Body Only",
    "dioptrecorrection": "Yes",
    "batteriesincluded": "Yes",
    "memoryslots": "1",
    "histogram": "Yes",
    "powersourcetype": "Battery, USB",
    "operatingrelativehumidityhh": "5 - 85%",
    "cameratype": "SLR Body",
    "camerashuttertype": "Electronic",
    "colourofproduct": "Black",
    "lensmountinterface": "Canon EF, Canon EF-S",
    "lcdscreensize": "3",
    "flashmodes": "Auto, Manual, Red-eye reduction",
    "autofocusaflock": "Yes",
    "shortdescription": "EOS 100D - Body, 18MP, 22.3 x 14.9mm CMOS, DIGIC 5, EF/EF-S, ISO Auto (100-6400), 7.7cm (3.0\") 3:2 Clear View II TFT 1040K, 5184x3456, SD, SDHC, SDXC, 407g",
    "display": "LCD",
    "flashsyncspeed": "1/200s",
    "fieldofview": "100%",
    "microphonein": "Yes",
    "camerashutterspeedmax": "30s",
    "maximumimageresolution": "5184 x 3456 pixels",
    "operatingtemperaturett": "0 - 45 \u00b0C",
    "lightexposurecorrection": "\u00b1 5EV (1/3EV step)",
    "ean": "8714574602653",
    "usbversion": "2.0",
    "dimensionswxdxh": "116.8 x 69.4 x 90.7 mm",
    "maximumvideoresolution": "1920 x 1080 pixels",
    "orientationsensor": "Yes",
    "material": "Aluminium, Glass, Polycarbonate, Rubber",
    "displaydiagonal": "7.62 cm (3\")",
    "autofocusafpoints": "9",
    "autofocusingafmodes": "Face detection, Face tracking",
    "scenemodes": "Candlelight, Children, Close-up (macro), Landscape, Night portrait, Portrait, Sports",
    "videoresolutions": "640 x 480, 1280 x 720, 1920 x 1080 pixels",
    "flashrechargingtime": "3s",
    "batterytechnology": "Lithium-Ion (Li-Ion)",
    "flashexposurecorrection": "\u00b12EV (1/2, 1/3 EV step)",
    "totalmegapixels": "18.5 MP",
    "numberofbatteriessupported": "1",
    "depth": "6.94 cm",
    "viewfindertype": "Electrical",
    "autoexposureaelock": "Yes",
    "whitebalance": "Auto, Cloudy, Custom modes, Daylight, Flash, Fluorescent, Shade, Tungsten"
}