{
    "videocapability": "YES",
    "warranty": "1 Year",
    "photoeffects": "Art, Black&White, Negative film",
    "flashrangetele": "0.55 - 6.3m",
    "cablesincluded": "USB",
    "weight": "240g",
    "lightexposuremodes": "Auto, Manual",
    "isosensitivity": "125, 200, 400, 800, 1600, 3200",
    "stillimageresolutions": "2592 x 1944, 2736 x 1824, 3648 x 2056, 3648 x 2736, 3888 x 2592, 5472 x 3080",
    "handstrap": "Yes",
    "megapixel": "20.2 MP",
    "acadapterincluded": "Yes",
    "camerashutterspeedmax": "30s",
    "maximumimageresolution": "5472 x 3648 pixels",
    "hdmiconnectortype": "Micro",
    "lightexposurecorrection": "\u00b1 3EV (1/3EV step)",
    "focallengthrangeff": "28 - 146 mm",
    "lcdscreensize": "3",
    "batterytype": "NP-BX1",
    "sku": "DSCRX100.CEH",
    "selftimer": "2, 10s",
    "whitebalance": "Auto, Cloudy, Daylight, Fluorescent, Incandescent, Shade",
    "batteriesincluded": "Yes",
    "dcinjack": "Yes",
    "specification": "Picture quality Image sensor size 25.4/50.8 mm (1/2\") Still image resolution(s) 2592 x 1944, 2736 x 1824, 3648 x 2056, 3648 x 2736, 3888 x 2592, 5472 x 3080 Image stabilizer Yes Total megapixels 20.9 MP Image sensor size (W x H) 13.2 x 8.8 mm Maximum image resolution 5472 x 3648 pixels Sensor type CMOS Camera type Compact Megapixel 20.2 MP Lens system Focal length range (f-f) 28 - 146 mm Minimum focal length (35mm film equiv) 2.8 cm Maximum focal length (35mm film equiv) 14.6 cm Minimum aperture 1.8 Maximum aperture 4.9 Lens structure (elements/groups) 7/6 Digital zoom 54x Optical zoom 3.6x Focusing Auto focusing (AF) modes Centre weighted Auto Focus, Face tracking, Flexible Spot Auto Focus, Multi Point Auto Focus Light exposure ISO sensitivity 125, 200, 400, 800, 1600, 3200 Light exposure modes Auto, Manual Light exposure correction \u00b1 3EV (1/3EV step) Shutter Camera shutter speed (min) 0.0005s Camera shutter speed (max) 30s Flash Flash modes Auto, Fill-in, Flash off, Flash on, Slow synchronization Built-in flash Yes Flash range (wide) 0.3 - 17.1m Flash range (tele) 0.55 - 6.3m Video Video resolutions 640 x 480, 1440 x 1080, 1920 x 1080 pixels Video formats supported AVCHD, MP4 Full HD Yes Maximum video resolution 1920 x 1080 pixels Memory Compatible memory cards MS Duo, MS PRO Duo, MS PRO Duo HS, MS Pro-HG Duo, SD, SDHC, SDXC Display Display LCD Display diagonal 7.62 cm (3\") Display resolution (numeric) 1229000 pixels Viewfinder Viewfinder type Electrical Ports & interfaces USB version 2.0 HDMI connector type Micro USB 2.0 ports quantity 1 HDMI ports quantity 1 DC-in jack Yes HDMI Yes Camera Colour of product Black White balance Auto, Cloudy, Daylight, Fluorescent, Incandescent, Shade Scene modes Fireworks, Landscape, Night, Night portrait, Portrait, Sports, Sunset, Twilight Photo effects Art, Black&White, Negative film Self-timer 2, 10s Battery Battery technology Lithium-Ion (Li-Ion) Battery type NP-BX1 Number of batteries supported 1 Power source type Battery Technical details USB 2.0 ports quantity 1 HDMI ports quantity 1 HDMI Yes Design Colour of product Black Weight & dimensions Width 10.16 cm Depth 5.81 cm Height 3.59 cm Weight 240g Packaging content Hand strap Yes Cables included USB Battery charger included Yes Batteries included Yes AC adapter included Yes Other features USB 2.0 ports quantity 1 HDMI ports quantity 1",
    "lensstructureelementsgroups": "7/6",
    "depth": "5.81 cm",
    "displayresolutionnumeric": "1229000 pixels",
    "usbversion": "2.0",
    "width": "10.16 cm",
    "minimumfocallength35mmfilmequiv": "2.8 cm",
    "maximumaperture": "4.9",
    "imagesensorsize": "25.4/50.8 mm (1/2\")",
    "minimumaperture": "1.8",
    "videoformatssupported": "AVCHD, MP4",
    "viewfindertype": "Electrical",
    "category": "camera",
    "touchscreen": "NO",
    "imagestabilizer": "Yes",
    "displaydiagonal": "7.62 cm (3\")",
    "maximumfocallength35mmfilmequiv": "14.6 cm",
    "hdmi": "Yes",
    "ean": "4905524895193",
    "freezeproof": "NO",
    "camerashutterspeed": "iAuto(4 - 1/2000) / Program Auto(1 - 1/2000)",
    "hdmiportsquantity": "1",
    "autofocusingafmodes": "Centre weighted Auto Focus, Face tracking, Flexible Spot Auto Focus, Multi Point Auto Focus",
    "sensortype": "CMOS",
    "batterychargerincluded": "Yes",
    "scenemodes": "Fireworks, Landscape, Night, Night portrait, Portrait, Sports, Sunset, Twilight",
    "fullhd": "Yes",
    "dimensionswxdxh": "101.6 x 35.9 x 58.1 mm",
    "powersourcetype": "Battery",
    "usb20portsquantity": "1",
    "manufacturer": "Sony",
    "waterproof": "NO",
    "maximumvideoresolution": "1920 x 1080 pixels",
    "boxcontents": "rechargeable battery Micro USB cable wrist strap instruction manual AC adaptor",
    "flashrangewide": "0.3 - 17.1m",
    "cameratype": "Compact",
    "flashmodes": "Auto, Fill-in, Flash off, Flash on, Slow synchronization",
    "builtinflash": "Yes",
    "camerashutterspeedmin": "0.0005s",
    "colourofproduct": "Black",
    "batterytechnology": "Lithium-Ion (Li-Ion)",
    "compatiblememorycards": "MS Duo, MS PRO Duo, MS PRO Duo HS, MS Pro-HG Duo, SD, SDHC, SDXC",
    "opticalzoom": "3.6x",
    "imagesensorsizewxh": "13.2 x 8.8 mm",
    "height": "3.59 cm",
    "numberofbatteriessupported": "1",
    "digitalzoom": "54x",
    "totalmegapixels": "20.9 MP",
    "shockproof": "NO",
    "videoresolutions": "640 x 480, 1440 x 1080, 1920 x 1080 pixels",
    "shortdescription": "1.0-type 20.2 megapixels Exmor CMOS, F1.8 lens, 3.6x optical zoom, Full HD 50p, 7.5cm (3.0\") LCD",
    "display": "LCD"
}