{
    "lightexposuremodes": "Aperture priority AE, Auto, Manual, Shutter priority AE",
    "isosensitivity": "100, 200, 400, 800, 1600, 3200, 6400, 12800, Auto",
    "stillimageresolutions": "480 x 480, 640 x 480, 720 x 400, 720 x 480, 1280 x 1280, 1696 x 1280, 1728 x 1728, 1920 x 1080, 1920 x 1280, 2304 x 1728, 2304 x 2304, 2592 x 1456, 2592 x 1728, 3072 x 2304, 3456 x 1944, 3456 x 2304, 3456 x 3456, 4608 x 3456, 5184 x 2912, 5184 x 3456",
    "focus": "TTL",
    "batterytype": "LP-E8",
    "sku": "8596B027AA",
    "usb20portsquantity": "1",
    "liveview": "Yes",
    "supportedaspectratios": "3:2, 4:3, 16:9",
    "flashexposurecompensation": "Yes",
    "videoformatssupported": "H.264",
    "weightincludingbattery": "580g",
    "builtinprocessor": "DIGIC 5",
    "sensortype": "CMOS",
    "height": "9.98 cm",
    "cameraplayback": "Movie, Single image, Slide show",
    "focusadjustment": "Auto/Manual",
    "camerashutterspeedmin": "0.00025s",
    "lenssystem": "Single Lens Kit",
    "pictbridge": "Yes",
    "lightexposurecontrol": "Program AE",
    "weight": "580 g",
    "autoexposureaelock": "Yes",
    "flashexposurelock": "Yes",
    "hdmiportsquantity": "1",
    "category": "camera",
    "hdmi": "Yes",
    "macoperatingsystemssupported": "Mac OS X 10.6 Snow Leopard, Mac OS X 10.7 Lion, Mac OS X 10.8 Mountain Lion",
    "imageformatssupported": "JPG, RAW",
    "lightmetering": "Centre-weighted, Evaluative (Multi-pattern), Spot",
    "specification": "Picture quality Supported aspect ratios 3:2, 4:3, 16:9 Still image resolution(s) 480 x 480, 640 x 480, 720 x 400, 720 x 480, 1280 x 1280, 1696 x 1280, 1728 x 1728, 1920 x 1080, 1920 x 1280, 2304 x 1728, 2304 x 2304, 2592 x 1456, 2592 x 1728, 3072 x 2304, 3456 x 1944, 3456 x 2304, 3456 x 3456, 4608 x 3456, 5184 x 2912, 5184 x 3456 Image stabilizer Yes Total megapixels 18.5 MP Image formats supported JPG, RAW Maximum image resolution 5184 x 3456 pixels Sensor type CMOS Camera type SLR Kit Megapixel 18 MP Lens system Focal length range (f-f) 18 - 55 mm Minimum focal length (35mm film equiv) 2.9 cm Maximum focal length (35mm film equiv) 8.8 cm Minimum aperture 3.5 Maximum aperture 38 Lens structure (elements/groups) 13/11 Number of diaphragm blades 7 Lens mount interface Canon EF, Canon EF-S Filter size 5.8 cm Focusing Focus TTL Focus adjustment Auto/Manual Auto focusing (AF) modes Continuous Auto Focus, Servo Auto Focus, Single Auto Focus Closest focusing distance 0.25m Light exposure ISO sensitivity 100, 200, 400, 800, 1600, 3200, 6400, 12800, Auto Light exposure modes Aperture priority AE, Auto, Manual, Shutter priority AE Light exposure control Program AE Light exposure correction \u00b1 5EV (1/3EV step) Light metering Centre-weighted, Evaluative (Multi-pattern), Spot Auto Exposure (AE) lock Yes ISO sensitivity (min) 100 ISO sensitivity (max) 12800 Shutter Camera shutter speed (min) 0.00025s Camera shutter speed (max) 30s Camera shutter type Electronic Flash Flash modes Auto, Manual, Red-eye reduction Built-in flash Yes Flash sync-speed 1/200s Flash exposure lock Yes Flash exposure correction \u00b12EV (1/2, 1/3 EV step) Flash exposure compensation Yes Video Video resolutions 640 x 480, 1280 x 720, 1920 x 1080 pixels Video formats supported H.264 Motion JPEG frame rate 29.97 fps Full HD Yes Analog signal format system NTSC, PAL Maximum video resolution 1920 x 1080 pixels Memory Compatible memory cards SD, SDHC, SDXC Memory slots 1 Display Display TFT Display diagonal 7.62 cm (3\") Display resolution (numeric) 1040000 pixels Vari-angle LCD display Yes Touch sensitive screen Yes Field of view 100% Viewfinder Viewfinder type Electrical Magnification 0.85x Ports & interfaces USB version 2.0 HDMI connector type Mini Microphone in Yes PictBridge Yes USB 2.0 ports quantity 1 HDMI ports quantity 1 HDMI Yes Camera Colour of product Black White balance Auto, Cloudy, Daylight, Flash, Fluorescent L, Shade, Tungsten Scene modes Close-up (macro), Landscape, Night, Night portrait, Portrait, Sports Shooting modes Aperture priority, Auto, Manual, Movie, Program, Scene, Shutter priority Self-timer 2, 10s Camera playback Movie, Single image, Slide show Playback zoom (max) 10x Live view Yes Histogram Yes Dioptre correction Yes Camera file system DCF 2.0, DPOF 1.1, Exif 2.3, RAW Built-in processor DIGIC 5 Battery Battery technology Lithium-Ion (Li-Ion) Battery type LP-E8 Number of batteries supported 1 Power source type Battery Operating system/software Windows operating systems supported Windows 7 Home Basic, Windows 7 Home Basic x64, Windows 7 Home Premium, Windows 7 Home Premium x64, Windows 7 Professional, Windows 7 Professional x64, Windows 7 Starter, Windows 7 Starter x64, Windows 7 Ultimate, Windows 7 Ultimate x64, Windows 8, Windows 8 Enterprise, Windows 8 Enterprise x64, Windows 8 Pro, Windows 8 Pro x64, Windows 8 x64, Windows Vista Business, Windows Vista Business x64, Windows Vista Enterprise, Windows Vista Enterprise x64, Windows Vista Home Basic, Windows Vista Home Basic x64, Windows Vista Home Premium, Windows Vista Home Premium x64, Windows Vista Ultimate, Windows Vista Ultimate x64, Windows XP Home, Windows XP Home x64, Windows XP Professional, Windows XP Professional x64 Mac operating systems supported Mac OS X 10.6 Snow Leopard, Mac OS X 10.7 Lion, Mac OS X 10.8 Mountain Lion Bundled software ImageBrowser EX Technical details Quick start guide Yes USB 2.0 ports quantity 1 HDMI ports quantity 1 HDMI Yes Processor Built-in processor DIGIC 5 Design Colour of product Black Performance Built-in processor DIGIC 5 Operational conditions Operating temperature (T-T) 0 - 40 \u00b0C Operating relative humidity (H-H) 10 - 85% System requirements Windows operating systems supported Windows 7 Home Basic, Windows 7 Home Basic x64, Windows 7 Home Premium, Windows 7 Home Premium x64, Windows 7 Professional, Windows 7 Professional x64, Windows 7 Starter, Windows 7 Starter x64, Windows 7 Ultimate, Windows 7 Ultimate x64, Windows 8, Windows 8 Enterprise, Windows 8 Enterprise x64, Windows 8 Pro, Windows 8 Pro x64, Windows 8 x64, Windows Vista Business, Windows Vista Business x64, Windows Vista Enterprise, Windows Vista Enterprise x64, Windows Vista Home Basic, Windows Vista Home Basic x64, Windows Vista Home Premium, Windows Vista Home Premium x64, Windows Vista Ultimate, Windows Vista Ultimate x64, Windows XP Home, Windows XP Home x64, Windows XP Professional, Windows XP Professional x64 Mac operating systems supported Mac OS X 10.6 Snow Leopard, Mac OS X 10.7 Lion, Mac OS X 10.8 Mountain Lion Weight & dimensions Width 13.31 cm Depth 7.88 cm Height 9.98 cm Weight (including battery) 580g Packaging content Quick start guide Yes Bundled software ImageBrowser EX Batteries included Yes Other features USB 2.0 ports quantity 1 HDMI ports quantity 1",
    "lensstructureelementsgroups": "13/11",
    "touchsensitivescreen": "Yes",
    "selftimer": "2, 10s",
    "maximumaperture": "38",
    "minimumaperture": "3.5",
    "motionjpegframerate": "29.97 fps",
    "fullhd": "Yes",
    "displayresolutionnumeric": "1040000 pixels",
    "manufacturer": "Canon",
    "isosensitivitymin": "100",
    "analogsignalformatsystem": "NTSC, PAL",
    "bundledsoftware": "ImageBrowser EX",
    "flashmodes": "Auto, Manual, Red-eye reduction",
    "builtinflash": "Yes",
    "compatiblememorycards": "SD, SDHC, SDXC",
    "isosensitivitymax": "12800",
    "hdmiconnectortype": "Mini",
    "quickstartguide": "Yes",
    "megapixel": "18 MP",
    "numberofdiaphragmblades": "7",
    "camerafilesystem": "DCF 2.0, DPOF 1.1, Exif 2.3, RAW",
    "width": "13.31 cm",
    "magnification": "0.85x",
    "windowsoperatingsystemssupported": "Windows 7 Home Basic, Windows 7 Home Basic x64, Windows 7 Home Premium, Windows 7 Home Premium x64, Windows 7 Professional, Windows 7 Professional x64, Windows 7 Starter, Windows 7 Starter x64, Windows 7 Ultimate, Windows 7 Ultimate x64, Windows 8, Windows 8 Enterprise, Windows 8 Enterprise x64, Windows 8 Pro, Windows 8 Pro x64, Windows 8 x64, Windows Vista Business, Windows Vista Business x64, Windows Vista Enterprise, Windows Vista Enterprise x64, Windows Vista Home Basic, Windows Vista Home Basic x64, Windows Vista Home Premium, Windows Vista Home Premium x64, Windows Vista Ultimate, Windows Vista Ultimate x64, Windows XP Home, Windows XP Home x64, Windows XP Professional, Windows XP Professional x64",
    "playbackzoommax": "10x",
    "type": "Single Lens Kit",
    "dioptrecorrection": "Yes",
    "batteriesincluded": "Yes",
    "memoryslots": "1",
    "closestfocusingdistance": "0.25m",
    "histogram": "Yes",
    "powersourcetype": "Battery",
    "operatingrelativehumidityhh": "10 - 85%",
    "cameratype": "SLR Kit",
    "camerashuttertype": "Electronic",
    "colourofproduct": "Black",
    "lensmountinterface": "Canon EF, Canon EF-S",
    "lcdscreensize": "3",
    "shootingmodes": "Aperture priority, Auto, Manual, Movie, Program, Scene, Shutter priority",
    "filtersize": "5.8 cm",
    "maximumfocallength35mmfilmequiv": "8.8 cm",
    "lenstype": "EF-S 18-55mm Lens",
    "shortdescription": "EOS 700D + EF-S 18-55mm IS STM - 18MP/18.5MP, 5184x3456, TTL-CT-SIR, CMOS, DIGIC 5, EF/EF-S, RAW/JPEG, 1920x1080/30fps, SD/SDHC/SDXC, 580g",
    "display": "TFT",
    "focallengthrangeff": "18 - 55 mm",
    "flashsyncspeed": "1/200s",
    "fieldofview": "100%",
    "microphonein": "Yes",
    "camerashutterspeedmax": "30s",
    "maximumimageresolution": "5184 x 3456 pixels",
    "operatingtemperaturett": "0 - 40 \u00b0C",
    "lightexposurecorrection": "\u00b1 5EV (1/3EV step)",
    "ean": "8714574602516",
    "usbversion": "2.0",
    "minimumfocallength35mmfilmequiv": "2.9 cm",
    "dimensionswxdxh": "133.1 x 78.8 x 99.8 mm",
    "maximumvideoresolution": "1920 x 1080 pixels",
    "imagestabilizer": "Yes",
    "displaydiagonal": "7.62 cm (3\")",
    "varianglelcddisplay": "Yes",
    "autofocusingafmodes": "Continuous Auto Focus, Servo Auto Focus, Single Auto Focus",
    "scenemodes": "Close-up (macro), Landscape, Night, Night portrait, Portrait, Sports",
    "videoresolutions": "640 x 480, 1280 x 720, 1920 x 1080 pixels",
    "batterytechnology": "Lithium-Ion (Li-Ion)",
    "flashexposurecorrection": "\u00b12EV (1/2, 1/3 EV step)",
    "totalmegapixels": "18.5 MP",
    "numberofbatteriessupported": "1",
    "depth": "7.88 cm",
    "viewfindertype": "Electrical",
    "whitebalance": "Auto, Cloudy, Daylight, Flash, Fluorescent L, Shade, Tungsten"
}