{
    "focallengthrangeff": "10.4 - 37.1 mm",
    "weight": "165g",
    "isosensitivity": "160, 200, 250, 320, 400, 500, 640, 800, 1000, 1250, 1600, 2000, 2250, 2500, 3200, 4000, 5000, 6400",
    "stillimageresolutions": "5472x3648, 4864x3648, 2592x1944, 5472x3080, 2720x1528, 3648x3648, 1920x1920, 1440x1080",
    "height": "6.25 cm",
    "camerashutterspeedmax": "0.0005s",
    "maximumimageresolution": "5472 x 3648 pixels",
    "batterytype": "NP-BN",
    "manualfocus": "Yes",
    "sku": "DSCQX100B.CE7",
    "specification": "Picture quality Still image resolution(s) 5472x3648, 4864x3648, 2592x1944, 5472x3080, 2720x1528, 3648x3648, 1920x1920, 1440x1080 Maximum image resolution 5472 x 3648 pixels Sensor type CMOS Camera type Compact Megapixel 20.2 MP Lens system Focal length range (f-f) 10.4 - 37.1 mm Minimum focal length (35mm film equiv) 2.8 cm Maximum focal length (35mm film equiv) 10 cm Minimum aperture 1.8 Maximum aperture 11 Optical zoom 3.6x Focusing Auto focusing (AF) modes Centre weighted Auto Focus Light exposure ISO sensitivity 160, 200, 250, 320, 400, 500, 640, 800, 1000, 1250, 1600, 2000, 2250, 2500, 3200, 4000, 5000, 6400 Shutter Camera shutter speed (min) 4s Camera shutter speed (max) 0.0005s Video Video formats supported MP4 Motion JPEG frame rate 30 fps Full HD No Maximum video resolution 1440 x 1080 pixels Memory Compatible memory cards MicroSD (TransFlash), MicroSDHC, MicroSDXC, MS Micro (M2) Memory slots 2 Display Display No Ports & interfaces USB version 2.0 Camera Colour of product Black White balance Auto, Cloudy, Daylight, Fluorescent, Incandescent, Shade Battery Battery technology Lithium-Ion (Li-Ion) Battery type NP-BN Power source type Battery Technical details Manual focus Yes Design Colour of product Black Weight & dimensions Width 6.25 cm Depth 5.55 cm Height 6.25 cm Weight 165g Other features Manual focus Yes",
    "ean": "4905524951264",
    "usbversion": "2.0",
    "width": "6.25 cm",
    "minimumfocallength35mmfilmequiv": "2.8 cm",
    "maximumaperture": "11",
    "minimumaperture": "1.8",
    "videoformatssupported": "MP4",
    "category": "camera",
    "motionjpegframerate": "30 fps",
    "memoryslots": "2",
    "autofocusingafmodes": "Centre weighted Auto Focus",
    "sensortype": "CMOS",
    "fullhd": "No",
    "powersourcetype": "Battery",
    "manufacturer": "Sony",
    "maximumvideoresolution": "1440 x 1080 pixels",
    "cameratype": "Compact",
    "camerashutterspeedmin": "4s",
    "colourofproduct": "Black",
    "batterytechnology": "Lithium-Ion (Li-Ion)",
    "compatiblememorycards": "MicroSD (TransFlash), MicroSDHC, MicroSDXC, MS Micro (M2)",
    "opticalzoom": "3.6x",
    "whitebalance": "Auto, Cloudy, Daylight, Fluorescent, Incandescent, Shade",
    "megapixel": "20.2 MP",
    "depth": "5.55 cm",
    "maximumfocallength35mmfilmequiv": "10 cm",
    "shortdescription": "3.6x Optical zoom, CMOS, 20.2 Mega Pixels, Carl Zeiss optics, Hi-Speed USB, Lithium-ion, 165g",
    "display": "No"
}