{
    "minimumram": "512 MB",
    "lightexposuremodes": "Aperture priority AE, Auto, Manual, Shutter priority AE",
    "isosensitivity": "100, 200, 400, 800, 1600, 3200, 6400, 12800, 25600",
    "stillimageresolutions": "480 x 480, 640 x 360, 640 x 424, 1280 x 1280, 1920 x 1080, 1920 x 1280, 2000 x 2000, 3008 x 1688, 3008 x 2000",
    "batterytype": "BP1130",
    "sku": "EV-NX2000BABGB",
    "operatingrelativehumidityhh": "5 - 85%",
    "supportedaspectratios": "3:2, 16:9",
    "imagequalityadjustment": "Brightness, Colour depth, Contrast, Saturation",
    "videoformatssupported": "H.264, MP4",
    "minimumprocessor": "Intel Core 2 Duo 2.0 GHz / AMD Phenom 2.4 GHz",
    "builtinprocessor": "DRIMe IV",
    "sensortype": "CMOS",
    "batterylifecipastandard": "340 shots",
    "height": "6.45 cm",
    "cameraplayback": "Movie, Single image, Slide show, Thumbnails",
    "camerashutterspeedmin": "30s",
    "batterylifemax": "2.83h",
    "weight": "228g",
    "audioformatssupported": "AAC",
    "autoexposureaelock": "Yes",
    "nearfieldcommunicationnfc": "Yes",
    "hdmiportsquantity": "1",
    "category": "camera",
    "hdmi": "Yes",
    "macoperatingsystemssupported": "Yes",
    "imageformatssupported": "JPG, MPO, RAW",
    "lightmetering": "Centre-weighted, Evaluative (Multi-pattern), Spot",
    "specification": "Picture quality Supported aspect ratios 3:2, 16:9 Still image resolution(s) 480 x 480, 640 x 360, 640 x 424, 1280 x 1280, 1920 x 1080, 1920 x 1280, 2000 x 2000, 3008 x 1688, 3008 x 2000 Image stabilizer Yes Total megapixels 21.6 MP Image sensor size (W x H) 23.5 x 15.7 mm Image formats supported JPG, MPO, RAW Sensor type CMOS Camera type MILC Megapixel 20.3 MP Lens system Focal length range (f-f) 20 - 50 mm Lens mount interface Samsung NX Digital zoom 2x Focusing Auto focusing (AF) modes Continuous Auto Focus, Multi Point Auto Focus, Single Auto Focus Auto Focus (AF) points 21 Light exposure ISO sensitivity 100, 200, 400, 800, 1600, 3200, 6400, 12800, 25600 Light exposure modes Aperture priority AE, Auto, Manual, Shutter priority AE Light exposure correction \u00b1 3EV (1/3EV step) Light metering Centre-weighted, Evaluative (Multi-pattern), Spot Auto Exposure (AE) lock Yes ISO sensitivity (min) 100 ISO sensitivity (max) 25600 Shutter Camera shutter speed (min) 30s Camera shutter speed (max) 0.00025s Flash Flash modes Auto, Fill-in, Flash off, Red-eye reduction Flash sync-speed 0.0055s External flash connector Yes Video Video resolutions 320 x 240, 640 x 480, 1280 x 720, 1920 x 810, 1920 x 1080 pixels Video formats supported H.264, MP4 Motion JPEG frame rate 30 fps Full HD Yes Maximum video resolution 1920 x 1080 pixels Audio Built-in microphone Yes Voice recording Yes Audio formats supported AAC Memory Internal memory 2048 MB Compatible memory cards MicroSD (TransFlash), MicroSDHC, MicroSDXC Display Display LCD Display diagonal 9.4 cm (3.7\") Display resolution 800 x 400 pixels Display resolution (numeric) 1152000 pixels Touch sensitive screen Yes Field of view 100% Ports & interfaces USB version 2.0 USB 2.0 ports quantity 1 HDMI ports quantity 1 HDMI Yes Networking Wi-Fi standards 802.11b, 802.11g, 802.11n Near Field Communication (NFC) Yes Wi-Fi Yes Camera Colour of product Black White balance Auto, Cloudy, Custom modes, Daylight, Flash, Fluorescent, Manual, Tungsten Scene modes Fireworks, Landscape, Night, Panorama, Sunset Photo effects Vivid Self-timer 2, 30s Contrast adjustment Yes Saturation adjustment Yes Camera playback Movie, Single image, Slide show, Thumbnails Image quality adjustment Brightness, Colour depth, Contrast, Saturation Image editing Rotating, Trimming Histogram Yes Camera file system DCF, DPOF 1.1, Exif 2.21, RAW Built-in processor DRIMe IV Brightness adjustment Yes Anti-dust function Yes 3D compatibility Yes Battery Battery technology Lithium-Ion (Li-Ion) Battery voltage 7.6V Battery life (CIPA standard) 340 shots Battery capacity 1130 mAh Battery life (max) 2.83h Battery type BP1130 Number of batteries supported 1 Power source type Battery Operating system/software Windows operating systems supported Yes Mac operating systems supported Yes Bundled software Adobe Photoshop Lightroom 4 iLauncher Technical details USB 2.0 ports quantity 1 HDMI ports quantity 1 HDMI Yes Processor Built-in processor DRIMe IV Design Colour of product Black Performance Built-in processor DRIMe IV Operational conditions Operating temperature (T-T) 0 - 40 \u00b0C Operating relative humidity (H-H) 5 - 85% System requirements Minimum hard disk space 250 MB Minimum RAM 512 MB Minimum processor Intel Core 2 Duo 2.0 GHz / AMD Phenom 2.4 GHz Windows operating systems supported Yes Mac operating systems supported Yes Weight & dimensions Width 11.9 cm Depth 3.57 cm Height 6.45 cm Weight 228g Packaging content Bundled software Adobe Photoshop Lightroom 4 iLauncher Batteries included Yes Other features USB 2.0 ports quantity 1 HDMI ports quantity 1",
    "touchsensitivescreen": "Yes",
    "selftimer": "2, 30s",
    "saturationadjustment": "Yes",
    "motionjpegframerate": "30 fps",
    "autofocusafpoints": "21",
    "displayresolutionnumeric": "1152000 pixels",
    "manufacturer": "Samsung",
    "isosensitivitymin": "100",
    "bundledsoftware": "Adobe Photoshop Lightroom 4 iLauncher",
    "flashmodes": "Auto, Fill-in, Flash off, Red-eye reduction",
    "compatiblememorycards": "MicroSD (TransFlash), MicroSDHC, MicroSDXC",
    "isosensitivitymax": "25600",
    "videoresolutions": "320 x 240, 640 x 480, 1280 x 720, 1920 x 810, 1920 x 1080 pixels",
    "fullhd": "Yes",
    "photoeffects": "Vivid",
    "megapixel": "20.3 MP",
    "camerafilesystem": "DCF, DPOF 1.1, Exif 2.21, RAW",
    "imageediting": "Rotating, Trimming",
    "builtinmicrophone": "Yes",
    "width": "11.9 cm",
    "contrastadjustment": "Yes",
    "windowsoperatingsystemssupported": "Yes",
    "voicerecording": "Yes",
    "antidustfunction": "Yes",
    "batteriesincluded": "Yes",
    "ean": "8806085630741",
    "histogram": "Yes",
    "internalmemory": "2048 MB",
    "batterycapacity": "1130 mAh",
    "powersourcetype": "Battery",
    "usb20portsquantity": "1",
    "brightnessadjustment": "Yes",
    "cameratype": "MILC",
    "colourofproduct": "Black",
    "lensmountinterface": "Samsung NX",
    "attr3dcompatibility": "Yes",
    "externalflashconnector": "Yes",
    "shortdescription": "20.3MP ASP-C CMOS, ISO100 - 25600, 1/4000s, f=20 - 50mm, 9.398 cm (3.7 \") Full Touchscreen (800 x 480), Memory 2GB, MicroSD/MicroSDHC/MicroSDXC, Micro HDMI, USB 2.0, Wi-Fi 802.11b/g/n, NFC, Black",
    "display": "LCD",
    "focallengthrangeff": "20 - 50 mm",
    "flashsyncspeed": "0.0055s",
    "fieldofview": "100%",
    "camerashutterspeedmax": "0.00025s",
    "operatingtemperaturett": "0 - 40 \u00b0C",
    "lightexposurecorrection": "\u00b1 3EV (1/3EV step)",
    "batteryvoltage": "7.6V",
    "depth": "3.57 cm",
    "usbversion": "2.0",
    "displayresolution": "800 x 400 pixels",
    "maximumvideoresolution": "1920 x 1080 pixels",
    "imagestabilizer": "Yes",
    "displaydiagonal": "9.4 cm (3.7\")",
    "minimumharddiskspace": "250 MB",
    "autofocusingafmodes": "Continuous Auto Focus, Multi Point Auto Focus, Single Auto Focus",
    "scenemodes": "Fireworks, Landscape, Night, Panorama, Sunset",
    "wifi": "Yes",
    "batterytechnology": "Lithium-Ion (Li-Ion)",
    "wifistandards": "802.11b, 802.11g, 802.11n",
    "imagesensorsizewxh": "23.5 x 15.7 mm",
    "totalmegapixels": "21.6 MP",
    "numberofbatteriessupported": "1",
    "digitalzoom": "2x",
    "whitebalance": "Auto, Cloudy, Custom modes, Daylight, Flash, Fluorescent, Manual, Tungsten"
}