{
    "pictbridge": "No",
    "batterylifemax": "1.8h",
    "cablesincluded": "USB",
    "weight": "90g",
    "batterytechnology": "Lithium-Ion (Li-Ion)",
    "isosensitivity": "100, 200, 400, 800, 1600, 3200, 12800, Auto",
    "stillimageresolutions": "4864 \u00d7 3648, 2592 \u00d7 1944, 4896 x 2752, 2720 x 1528, 3648 \u00d7 3648, 1920 x 1080, 1440 x 1080",
    "handstrap": "Yes",
    "height": "6.18 cm",
    "nearfieldcommunicationnfc": "Yes",
    "camerashutterspeedmax": "4s",
    "lightexposurecorrection": "\u00b1 2EV (1/3EV step)",
    "focallengthrangeff": "10.4 - 37.1 mm",
    "batterytype": "NP-BN",
    "camerafilesystem": "DCF",
    "category": "camera",
    "totalmegapixels": "18.2 MP",
    "batteriesincluded": "Yes",
    "usbconnectortype": "Micro-USB A",
    "imageformatssupported": "JPG",
    "lightmetering": "Evaluative (Multi-pattern)",
    "specification": "Picture quality Image sensor size 25.4/58.4 mm (1/2.3\") Supported aspect ratios 1:1, 4:3, 16:9 Still image resolution(s) 4864 \u00d7 3648, 2592 \u00d7 1944, 4896 x 2752, 2720 x 1528, 3648 \u00d7 3648, 1920 x 1080, 1440 x 1080 Total megapixels 18.2 MP Image formats supported JPG Sensor type CMOS Camera type Compact Megapixel 18 MP Lens system Focal length range (f-f) 10.4 - 37.1 mm Minimum focal length (35mm film equiv) 2.5 cm Maximum focal length (35mm film equiv) 25 cm Minimum aperture 3.3 Maximum aperture 5.9 Optical zoom 10x Focusing Focus adjustment Manual Auto focusing (AF) modes Centre weighted Auto Focus, Face detection Macro focusing range (wide) 0.05 - ? Macro focusing range (tele) 1.5 - ? Light exposure ISO sensitivity 100, 200, 400, 800, 1600, 3200, 12800, Auto Light exposure correction \u00b1 2EV (1/3EV step) Light metering Evaluative (Multi-pattern) ISO sensitivity (min) 100 ISO sensitivity (max) 12800 Shutter Camera shutter speed (min) 1s Camera shutter speed (max) 4s Flash Built-in flash No Video Video resolutions 1440 x 1080 pixels Video formats supported MP4 Motion JPEG frame rate 30 fps Full HD No Maximum video resolution 1440 x 1080 pixels Memory Compatible memory cards microSD (TransFlash), microSDHC, microSDXC, MS Micro (M2) Memory slots 1 Display Display No Ports & interfaces USB version 2.0 PictBridge No USB connector type Micro-USB A HDMI No Networking Near Field Communication (NFC) Yes Wi-Fi Yes Camera Colour of product White White balance Auto, Cloudy, Daylight, Fluorescent, Shade, Tungsten On Screen Display (OSD) languages BUL, CZE, DAN, DEU, DUT, ENG, ESP, FIN, FRE, GRE, HUN, ITA, NOR, POL, POR, RUM, RUS, SWE, TUR Camera file system DCF Built-in processor BIONZ Battery Battery technology Lithium-Ion (Li-Ion) Battery life (CIPA standard) 220 shots Battery life (max) 1.8h Battery type NP-BN Number of batteries supported 1 Battery level indicator Yes Power source type Battery Operating system/software Bundled software PlayMemories Home Technical details HDMI No Battery level indicator Yes Processor Built-in processor BIONZ Design Colour of product White Performance Built-in processor BIONZ Weight & dimensions Width 6.24 cm Depth 3.33 cm Height 6.18 cm Weight 90g Weight (including battery) 105g Packaging content Bundled software PlayMemories Home Hand strap Yes Cables included USB Batteries included Yes",
    "memoryslots": "1",
    "usbversion": "2.0",
    "width": "6.24 cm",
    "supportedaspectratios": "1:1, 4:3, 16:9",
    "minimumfocallength35mmfilmequiv": "2.5 cm",
    "macrofocusingrangetele": "1.5 - ?",
    "imagesensorsize": "25.4/58.4 mm (1/2.3\")",
    "maximumvideoresolution": "1440 x 1080 pixels",
    "videoformatssupported": "MP4",
    "maximumaperture": "5.9",
    "motionjpegframerate": "30 fps",
    "sku": "DSCQX10W.CE7",
    "weightincludingbattery": "105g",
    "hdmi": "No",
    "ean": "4905524951240",
    "builtinprocessor": "BIONZ",
    "autofocusingafmodes": "Centre weighted Auto Focus, Face detection",
    "sensortype": "CMOS",
    "display": "No",
    "batterylifecipastandard": "220 shots",
    "fullhd": "No",
    "wifi": "Yes",
    "powersourcetype": "Battery",
    "manufacturer": "Sony",
    "isosensitivitymin": "100",
    "minimumaperture": "3.3",
    "bundledsoftware": "PlayMemories Home",
    "macrofocusingrangewide": "0.05 - ?",
    "focusadjustment": "Manual",
    "cameratype": "Compact",
    "onscreendisplayosdlanguages": "BUL, CZE, DAN, DEU, DUT, ENG, ESP, FIN, FRE, GRE, HUN, ITA, NOR, POL, POR, RUM, RUS, SWE, TUR",
    "camerashutterspeedmin": "1s",
    "colourofproduct": "White",
    "batterylevelindicator": "Yes",
    "compatiblememorycards": "microSD (TransFlash), microSDHC, microSDXC, MS Micro (M2)",
    "opticalzoom": "10x",
    "isosensitivitymax": "12800",
    "megapixel": "18 MP",
    "numberofbatteriessupported": "1",
    "depth": "3.33 cm",
    "maximumfocallength35mmfilmequiv": "25 cm",
    "builtinflash": "No",
    "videoresolutions": "1440 x 1080 pixels",
    "shortdescription": "A wireless lens that connects to your smartphone with an 18MP Exmor R CMOS sensor & 10x optical zoom",
    "whitebalance": "Auto, Cloudy, Daylight, Fluorescent, Shade, Tungsten"
}