{
    "warranty": "1 Year",
    "videocapability": "Yes",
    "photoeffects": "Antique, Black&White",
    "flashrangetele": "2.4 - 3.5m",
    "cablesincluded": "AC, USB",
    "weight": "633g",
    "lightexposuremodes": "Auto",
    "isosensitivity": "80, 100, 125, 160, 200, 250, 320, 400, 500, 640, 800, 1000, 1250, 1600, 2000, 2500, 3200, 6400, 12800, Auto",
    "stillimageresolutions": "3:2 - 18M(5184\u00d73456) / 8.9M(3648\u00d72432) / 4.5M(2592\u00d71728) 4:3 - 20M(5184\u00d73888) / 10M(3648\u00d72736) / 5M(2592\u00d71944) / VGA 16:9 - 15M(5184\u00d72920) / 7.5M(3648\u00d72056) / 2.1M(1920\u00d71080) 1:1 - 15M(3888\u00d73888) / 7.5M(2736\u00d72736) / 3.7M(1920\u00d71920) 7152\u00d71080 / 4912\u00d71920 / 4912\u00d71080 / 3424\u00d71920 / 11520\u00d71080",
    "megapixel": "20.4 MP",
    "acadapterincluded": "Yes",
    "camerashutterspeedmax": "0.00025s",
    "wifistandards": "802.11b, 802.11g, 802.11n",
    "lightexposurecorrection": "\u00b1 2EV (1/3EV step)",
    "focallengthrangeff": "4.3 - 215 mm",
    "lcdscreensize": "3",
    "lightmetering": "Centre-weighted, Evaluative (Multi-pattern), Spot",
    "flashmodes": "Auto, Fill-in, Flash off, Slow synchronization",
    "camerafilesystem": "Exif, DCF, DPOF, MPF",
    "sku": "DSCHX400VB.CEH",
    "selftimer": "2, 10s",
    "imageprocessor": "BIONZ X",
    "builtinmicrophone": "Yes",
    "hdmi": "Yes",
    "automodefocusingrangewide": "0.01 - ?",
    "imageformatssupported": "JPG",
    "batterytype": "NP-BX1",
    "specification": "Picture quality Image sensor size 25.4/58.4 mm (1/2.3\") Still image resolution(s) 3:2 - 18M(5184\u00d73456) / 8.9M(3648\u00d72432) / 4.5M(2592\u00d71728) 4:3 - 20M(5184\u00d73888) / 10M(3648\u00d72736) / 5M(2592\u00d71944) / VGA 16:9 - 15M(5184\u00d72920) / 7.5M(3648\u00d72056) / 2.1M(1920\u00d71080) 1:1 - 15M(3888\u00d73888) / 7.5M(2736\u00d72736) / 3.7M(1920\u00d71920) 7152\u00d71080 / 4912\u00d71920 / 4912\u00d71080 / 3424\u00d71920 / 11520\u00d71080 Image stabilizer Yes Image formats supported JPG Maximum image resolution 5184 x 3888 pixels Sensor type CMOS Camera type Bridge Megapixel 20.4 MP Lens system Focal length range (f-f) 4.3 - 215 mm Lens structure (elements/groups) 15/10 Number of aspheric elements 3 Filter size 5.5 cm Digital zoom 810x Optical zoom 50x Focusing Focus adjustment Auto/Manual Auto focusing (AF) modes Continuous Auto Focus, Single Auto Focus Auto Mode focusing range (wide) 0.01 - ? Auto Mode focusing range (tele) 2.4 - ? Light exposure ISO sensitivity 80, 100, 125, 160, 200, 250, 320, 400, 500, 640, 800, 1000, 1250, 1600, 2000, 2500, 3200, 6400, 12800, Auto Light exposure modes Auto Light exposure correction \u00b1 2EV (1/3EV step) Light metering Centre-weighted, Evaluative (Multi-pattern), Spot ISO sensitivity (min) 80 ISO sensitivity (max) 12800 Shutter Camera shutter speed (min) 30s Camera shutter speed (max) 0.00025s Flash Flash modes Auto, Fill-in, Flash off, Slow synchronization Built-in flash Yes Flash range (wide) 0.5 - 8.5m Flash range (tele) 2.4 - 3.5m External flash connector Yes Video Video resolutions 640 x 480, 1440 x 1080, 1920 x 1080 pixels Motion JPEG frame rate 50 fps Full HD Yes Maximum video resolution 1920 x 1080 pixels Audio Built-in microphone Yes Memory Compatible memory cards MicroSD (TransFlash), MicroSDHC, MicroSDXC, MS Duo, MS Micro (M2), MS PRO Duo, MS Pro-HG Duo, MS XC-HG Duo, SD, SDHC, SDXC Display Display LCD Display diagonal 7.62 cm (3\") Display resolution (numeric) 921600 pixels Ports & interfaces USB version 2.0 HDMI connector type Micro HDMI Yes Networking Wi-Fi standards 802.11b, 802.11g, 802.11n Wi-Fi Yes Camera Colour of product Black White balance Auto, Cloudy, Custom modes, Daylight, Flash, Fluorescent, Incandescent Scene modes Beach, Fireworks, Food, Landscape, Night, Night portrait, Pet, Portrait, Snow, Sports, Twilight Shooting modes Aperture priority, Auto, Manual, Movie, Program, Scene, Shutter priority Photo effects Antique, Black&White Self-timer 2, 10s GPS Yes Camera file system Exif, DCF, DPOF, MPF Battery Battery life (CIPA standard) 300 shots Battery life (max) 2.5h Battery type NP-BX1 Power source type Battery Technical details HDMI Yes GPS Yes Design Colour of product Black Performance GPS Yes Weight & dimensions Width 12.96 cm Depth 10.32 cm Height 9.32 cm Weight 633g Weight (including battery) 660g Packaging content Cables included AC, USB Batteries included Yes AC adapter included Yes Technical details Image processor BIONZ X",
    "lensstructureelementsgroups": "15/10",
    "depth": "10.32 cm",
    "usbversion": "2.0",
    "width": "12.96 cm",
    "colourofproduct": "Black",
    "compatiblememorycards": "MicroSD (TransFlash), MicroSDHC, MicroSDXC, MS Duo, MS Micro (M2), MS PRO Duo, MS Pro-HG Duo, MS XC-HG Duo, SD, SDHC, SDXC",
    "imagesensorsize": "25.4/58.4 mm (1/2.3\")",
    "maximumvideoresolution": "1920 x 1080 pixels",
    "gps": "Yes",
    "motionjpegframerate": "50 fps",
    "category": "camera",
    "weightincludingbattery": "660g",
    "imagestabilizer": "Yes",
    "displaydiagonal": "7.62 cm (3\")",
    "automodefocusingrangetele": "2.4 - ?",
    "ean": "4905524981483",
    "camerashutterspeed": "iAuto (4 - 1/4000) / Program Auto (1 - 1/4000) / Aperture Priority (8 - 1/2000) / Shutter Priority (30 - 1/4000) / Manual (30 - 1/4000)",
    "autofocusingafmodes": "Continuous Auto Focus, Single Auto Focus",
    "sensortype": "CMOS",
    "scenemodes": "Beach, Fireworks, Food, Landscape, Night, Night portrait, Pet, Portrait, Snow, Sports, Twilight",
    "batterylifecipastandard": "300 shots",
    "fullhd": "Yes",
    "dimensionswxdxh": "129.6 x 103.2 x 93.2 mm",
    "wifi": "Yes",
    "powersourcetype": "Battery",
    "displayresolutionnumeric": "921600 pixels",
    "manufacturer": "Sony",
    "isosensitivitymin": "80",
    "hdmiconnectortype": "Micro",
    "batteriesincluded": "Yes",
    "flashrangewide": "0.5 - 8.5m",
    "focusadjustment": "Auto/Manual",
    "cameratype": "Bridge",
    "externalflashconnector": "Yes",
    "builtinflash": "Yes",
    "camerashutterspeedmin": "30s",
    "batterylifemax": "2.5h",
    "shootingmodes": "Aperture priority, Auto, Manual, Movie, Program, Scene, Shutter priority",
    "opticalzoom": "50x",
    "isosensitivitymax": "12800",
    "height": "9.32 cm",
    "digitalzoom": "810x",
    "filtersize": "5.5 cm",
    "whitebalance": "Auto, Cloudy, Custom modes, Daylight, Flash, Fluorescent, Incandescent",
    "videoresolutions": "640 x 480, 1440 x 1080, 1920 x 1080 pixels",
    "numberofasphericelements": "3",
    "shortdescription": "20.4MP, 1/2.3\" Exmor R CMOS, ZEISS Vario Sonnar T*, f=4.3-215mm, F2.8 (W) - 6.3 (T), Wi-Fi, GPS",
    "display": "LCD",
    "maximumimageresolution": "5184 x 3888 pixels"
}