{
    "videocapability": "Yes",
    "focallengthrangeff": "4.4 - 277 mm",
    "weight": "655 g",
    "flashtype": "Sorry, this data isn\u2032t available",
    "isosensitivity": "Auto: (ISO100-ISO800 Level) ISO 80-3200",
    "megapixel": "20.1",
    "pictureeffects": "Still: Toy camera / Pop Color / Partial Color / Soft High-key, Movie: Toy camera, Pop Color, Partial Color, Soft High-key",
    "batterytype": "NP-BX1",
    "builtinwifi": "?",
    "sku": "DSCH400B.CEH",
    "selftimer": "Off / 10sec. / 2sec. / portrait1 / portrait2",
    "batterylife": "Up to 300 shots / 150 minutes",
    "display": "3.0'' (7.5 cm) (4:3) / 460,800 dots / Xtra Fine / TFT LCD",
    "lightmetering": "Multi Pattern",
    "specification": "Picture quality Sensor type 1/2.3\" type (7.76mm) Super HAD CCD Lens system Focal length range (f-f) 4.4 - 277 mm Filter size Yes Optical zoom 63x Light exposure ISO sensitivity Auto: (ISO100-ISO800 Level) ISO 80-3200 Light metering Multi Pattern Flash Flash modes Auto,Flash On,Flash Off Auto / Flash On / Slow Synchro / Flash Off / Advanced Flash Flash exposure compensation +/- 2.0 EV (1/3 EV steps) Memory Compatible memory cards Memory Stick\u2122 Duo;Memory Stick PRO Duo\u2122;Memory Stick PRO Duo\u2122(high speed);Memory Stick PRO HG Duo\u2122;Memory Stick XC-HG Duo\u2122;Memory Stick Micro;Memory Stick Micro (Mark2);SD Memory Card;SDHC Memory Card;SDXC Memory Card;microSD Memory Card;microSDHC Memory Card;microSDXC Memory Card Display Display 3.0'' (7.5 cm) (4:3) / 460,800 dots / Xtra Fine / TFT LCD Viewfinder Viewfinder type 0.2-type electronic viewfinder Camera Playback modes Date view, Slideshow with Music White balance Auto, Daylight, Cloudy, Incandescent, Flash Scene modes Night Portrait, Portrait, Landscape, Portrait, Beach, Snow, Fireworks Shooting modes Aperture Priority Technical details Playback modes Date view, Slideshow with Music Accessories included Rechargeable Battery Pack NP-BX1;AC AdaptorAC-UB10C;Multi USB cable;Shoulder Strap;Lens Cap;Instruction Manual Recording format Still Images: JPEG (DCF, Exif, MPF Baseline) compliant, DPOF compatible Lens system Sony Lens Picture effects Still: Toy camera / Pop Color / Partial Color / Soft High-key, Movie: Toy camera, Pop Color, Partial Color, Soft High-key Self-timer Off / 10sec. / 2sec. / portrait1 / portrait2 Image processor Sorry, this data isn\u2032t available F-number (relative aperture) F3.4  - 6.5 Flash type Sorry, this data isn\u2032t available SteadyShot Optical Shutter speed iAuto (2 - 1/2000) / Program Auto (1 - 1/2000) / Manual (30 - 1/2000) Display brightness control 5(Bright) / 4 / 3 / 2 / 1(Dark) Built-in WiFi ? Effective megapixels 20.1 MP Dimensions (WxHxD) 129.6 x 95 x 122.3 mm Battery life Up to 300 shots / 150 minutes Internal memory Approx. 55MB Other features Accessories included Rechargeable Battery Pack NP-BX1;AC AdaptorAC-UB10C;Multi USB cable;Shoulder Strap;Lens Cap;Instruction Manual Recording format Still Images: JPEG (DCF, Exif, MPF Baseline) compliant, DPOF compatible Lens system Sony Lens Picture effects Still: Toy camera / Pop Color / Partial Color / Soft High-key, Movie: Toy camera, Pop Color, Partial Color, Soft High-key",
    "playbackmodes": "Date view, Slideshow with Music",
    "recordingformat": "Still Images: JPEG (DCF, Exif, MPF Baseline) compliant, DPOF compatible",
    "flashexposurecompensation": "+/- 2.0 EV (1/3 EV steps)",
    "steadyshot": "Optical",
    "dimensionswxhxd": "129.6 x 95 x 122.3 mm",
    "lenssystem": "Sony Lens",
    "category": "camera",
    "accessoriesincluded": "Rechargeable Battery Pack NP-BX1;AC AdaptorAC-UB10C;Multi USB cable;Shoulder Strap;Lens Cap;Instruction Manual",
    "ean": "4905524981650",
    "camerashutterspeed": "iAuto (2 - 1/2000) / Program Auto (1 - 1/2000) / Manual (30 - 1/2000)",
    "sensortype": "1/2.3\" type (7.76mm) Super HAD CCD",
    "scenemodes": "Night Portrait, Portrait, Landscape, Portrait, Beach, Snow, Fireworks",
    "dimensionswxdxh": "129.6 x 122.3 x 95 mm",
    "imageprocessor": "Sorry, this data isn\u2032t available",
    "shutterspeed": "iAuto (2 - 1/2000) / Program Auto (1 - 1/2000) / Manual (30 - 1/2000)",
    "manufacturer": "Sony",
    "internalmemory": "Approx. 55MB",
    "flashmodes": "Auto,Flash On,Flash Off Auto / Flash On / Slow Synchro / Flash Off / Advanced Flash",
    "builtinflash": "Yes",
    "colourofproduct": "Black",
    "compatiblememorycards": "Memory Stick\u2122 Duo;Memory Stick PRO Duo\u2122;Memory Stick PRO Duo\u2122(high speed);Memory Stick PRO HG Duo\u2122;Memory Stick XC-HG Duo\u2122;Memory Stick Micro;Memory Stick Micro (Mark2);SD Memory Card;SDHC Memory Card;SDXC Memory Card;microSD Memory Card;microSDHC Memory Card;microSDXC Memory Card",
    "opticalzoom": "63x",
    "lcdscreensize": "3",
    "shootingmodes": "Aperture Priority",
    "digitalzoom": "Approx. 126 x",
    "filtersize": "Yes",
    "viewfindertype": "0.2-type electronic viewfinder",
    "effectivemegapixels": "20.1 MP",
    "shortdescription": "H400 compact camera with a 20.1MP sensor, 63x optical zoom, Optical SteadyShot, & X Type lithium-ion battery",
    "whitebalance": "Auto, Daylight, Cloudy, Incandescent, Flash"
}