{
    "videocapability": "Yes",
    "lightexposuremodes": "Aperture priority AE, Auto, Manual, Shutter priority AE",
    "isosensitivity": "100, 200, 400, 800, 1600, 3200, 6400, 12800, 25600, Auto",
    "stillimageresolutions": "480 x 480, 640 x 480, 720 x 480, 1280 x 1280, 1696 x 1280, 1920 x 1080, 1920 x 1280, 2736 x 1824, 2736 x 2736, 3648 x 2048, 3648 x 2432, 3648 x 2736, 3648 x 3648, 5472 x 3080, 5472 x 3648",
    "focus": "TTL",
    "batterytype": "LP-E6",
    "sku": "8469B031AA",
    "liveview": "Yes",
    "supportedaspectratios": "1:1, 3:2, 16:9",
    "flashexposurecompensation": "Yes",
    "videoformatssupported": "H.264, MOV",
    "builtinprocessor": "DIGIC 5+",
    "sensortype": "CMOS",
    "batterylifecipastandard": "920 shots",
    "height": "10.43 cm",
    "focusadjustment": "Auto/Manual",
    "camerashutterspeedmin": "0.000125s",
    "lenssystem": "18-55mm Lens Included",
    "pictbridge": "Yes",
    "lightexposurecontrol": "Program AE",
    "weight": "755g",
    "batterylevelindicator": "Yes",
    "weatherproof": "No",
    "flashexposurelock": "Yes",
    "flashguidenumber": "12m",
    "category": "camera",
    "hdmi": "Yes",
    "imageformatssupported": "JPG, RAW",
    "lightmetering": "Centre-weighted, Evaluative (Multi-pattern), Spot",
    "specification": "Picture quality Supported aspect ratios 1:1, 3:2, 16:9 Still image resolution(s) 480 x 480, 640 x 480, 720 x 480, 1280 x 1280, 1696 x 1280, 1920 x 1080, 1920 x 1280, 2736 x 1824, 2736 x 2736, 3648 x 2048, 3648 x 2432, 3648 x 2736, 3648 x 3648, 5472 x 3080, 5472 x 3648 Total megapixels 20.9 MP Image sensor size (W x H) 22.5 x 15 mm Image formats supported JPG, RAW Maximum image resolution 5472 x 3648 pixels Sensor type CMOS Camera type SLR Kit Megapixel 20.2 MP Lens system Lens mount interface Canon EF, Canon EF-S Focusing Focus TTL Focus adjustment Auto/Manual Auto focusing (AF) modes Face detection, Single Auto Focus Auto Focus (AF) points selection Auto Auto Focus (AF) points 19 Auto Focus (AF) lock Yes Auto Focus (AF) assist beam Yes Light exposure ISO sensitivity 100, 200, 400, 800, 1600, 3200, 6400, 12800, 25600, Auto Light exposure modes Aperture priority AE, Auto, Manual, Shutter priority AE Light exposure control Program AE Light exposure correction \u00b15EV (1/2; 1/3 EV step) Light metering Centre-weighted, Evaluative (Multi-pattern), Spot Auto Exposure (AE) lock Yes ISO sensitivity (min) 100 ISO sensitivity (max) 25600 Shutter Camera shutter speed (min) 0.000125s Camera shutter speed (max) 30s Flash Flash modes Auto, Manual, Red-eye reduction Built-in flash Yes Flash recharging time 3s Flash guide number 12m Flash exposure lock Yes Flash exposure correction \u00b13EV (1/2; 1/3 EV step) Flash exposure compensation Yes Video Video resolutions 640 x 480, 1280 x 720, 1920 x 1080 pixels Video formats supported H.264, MOV Motion JPEG frame rate 50 fps Full HD Yes Analog signal format system NTSC, PAL Maximum video resolution 1920 x 1080 pixels Audio Built-in microphone Yes Memory Compatible memory cards SD, SDHC, SDXC Memory slots 1 Display Display aspect ratio 3:2 Display LCD Display diagonal 7.62 cm (3\") Display resolution (numeric) 1040000 pixels Vari-angle LCD display Yes Touch sensitive screen Yes Second display No Field of view 98% Ports & interfaces USB version 2.0 HDMI connector type Mini PictBridge Yes HDMI Yes Networking Wi-Fi Yes Camera Colour of product Black White balance Auto, Cloudy, Custom modes, Flash, Fluorescent, Shade, Tungsten Scene modes Close-up (macro), Landscape, Night, Night portrait, Portrait, Sports, Sunset, Twilight Self-timer 2, 10s Multi-shot Yes Live view Yes Languages support ARA, CHI (SIMPL), CHI (TR), CZE, DAN, DEU, DUT, ENG, ESP, FIN, FRE, GRE, HUN, ITA, JPN, KOR, NOR, POL, POR, RUS, SWE, THA, TUR, UKR Histogram Yes Dioptre correction Yes Camera file system DCF 2.0, DPOF 1.1, Exif 2.3 Built-in processor DIGIC 5+ Battery Battery life (CIPA standard) 920 shots Battery type LP-E6 Number of batteries supported 1 Battery level indicator Yes Power source type Battery Technical details Languages support ARA, CHI (SIMPL), CHI (TR), CZE, DAN, DEU, DUT, ENG, ESP, FIN, FRE, GRE, HUN, ITA, JPN, KOR, NOR, POL, POR, RUS, SWE, THA, TUR, UKR HDMI Yes Battery level indicator Yes Processor Built-in processor DIGIC 5+ Design Colour of product Black Performance Built-in processor DIGIC 5+ Operational conditions Operating temperature (T-T) 0 - 40 \u00b0C Operating relative humidity (H-H) 0 - 85% Weight & dimensions Width 13.9 cm Depth 7.85 cm Height 10.43 cm Weight 755g Packaging content Hand strap Yes Cables included USB Battery charger included Yes Batteries included Yes",
    "autofocusafassistbeam": "Yes",
    "touchsensitivescreen": "Yes",
    "selftimer": "2, 10s",
    "displayaspectratio": "3:2",
    "multishot": "Yes",
    "motionjpegframerate": "50 fps",
    "fullhd": "Yes",
    "displayresolutionnumeric": "1040000 pixels",
    "manufacturer": "Canon",
    "isosensitivitymin": "100",
    "analogsignalformatsystem": "NTSC, PAL",
    "flashmodes": "Auto, Manual, Red-eye reduction",
    "builtinflash": "Yes",
    "compatiblememorycards": "SD, SDHC, SDXC",
    "isosensitivitymax": "25600",
    "languagessupport": "ARA, CHI (SIMPL), CHI (TR), CZE, DAN, DEU, DUT, ENG, ESP, FIN, FRE, GRE, HUN, ITA, JPN, KOR, NOR, POL, POR, RUS, SWE, THA, TUR, UKR",
    "hdmiconnectortype": "Mini",
    "warranty": "1 Year",
    "cablesincluded": "USB",
    "handstrap": "Yes",
    "megapixel": "20.2 MP",
    "camerafilesystem": "DCF 2.0, DPOF 1.1, Exif 2.3",
    "builtinmicrophone": "Yes",
    "width": "13.9 cm",
    "type": "Single Lens Kit",
    "dioptrecorrection": "Yes",
    "batteriesincluded": "Yes",
    "memoryslots": "1",
    "histogram": "Yes",
    "batterychargerincluded": "Yes",
    "powersourcetype": "Battery",
    "operatingrelativehumidityhh": "0 - 85%",
    "cameratype": "SLR Kit",
    "colourofproduct": "Black",
    "lensmountinterface": "Canon EF, Canon EF-S",
    "lcdscreensize": "3",
    "shortdescription": "EOS 70D + 18-55mm IS STM - 20.2MP, CMOS, 3:2 Native, 5472 x 3648 max, 1/8000 - 30 sec, AF, AE, ISO 100-12800 (H: 25600), Video Full HD, PictBridge, USB, HDMI Type C, SD/SDHC /SDXC, WiFi, 7.62 cm (3.0 \") TFT LCD Touchscreen",
    "display": "LCD",
    "autofocusafpointsselection": "Auto",
    "fieldofview": "98%",
    "lightexposurecorrection": "\u00b15EV (1/2; 1/3 EV step)",
    "camerashutterspeedmax": "30s",
    "maximumimageresolution": "5472 x 3648 pixels",
    "operatingtemperaturett": "0 - 40 \u00b0C",
    "autofocusaflock": "Yes",
    "seconddisplay": "No",
    "ean": "8714574610665",
    "usbversion": "2.0",
    "dimensionswxdxh": "139 x 78.5 x 104.3 mm",
    "maximumvideoresolution": "1920 x 1080 pixels",
    "displaydiagonal": "7.62 cm (3\")",
    "varianglelcddisplay": "Yes",
    "autofocusafpoints": "19",
    "autofocusingafmodes": "Face detection, Single Auto Focus",
    "scenemodes": "Close-up (macro), Landscape, Night, Night portrait, Portrait, Sports, Sunset, Twilight",
    "videoresolutions": "640 x 480, 1280 x 720, 1920 x 1080 pixels",
    "flashrechargingtime": "3s",
    "wifi": "Yes",
    "flashexposurecorrection": "\u00b13EV (1/2; 1/3 EV step)",
    "imagesensorsizewxh": "22.5 x 15 mm",
    "totalmegapixels": "20.9 MP",
    "numberofbatteriessupported": "1",
    "depth": "7.85 cm",
    "autoexposureaelock": "Yes",
    "whitebalance": "Auto, Cloudy, Custom modes, Flash, Fluorescent, Shade, Tungsten"
}