{
    "autofocusafassistbeam": "Yes",
    "lightexposuremodes": "Auto, Manual",
    "isosensitivity": "100, 6400, 12800",
    "stillimageresolutions": "640 x 480, 720 x 400, 720 x 480, 1280 x 1280, 1712 x 1712, 1920 x 1080, 1920 x 1280, 2304 x 1728, 2304 x 2304, 2592 x 1456, 2592 x 1728, 3072 x 2304, 3456 x 1944, 3456 x 2304, 3456 x 3456, 4608 x 3456, 5184 x 2912, 5184 x 3456",
    "acadapterincluded": "Yes",
    "batterytype": "LP-E12",
    "sku": "6609B065AA",
    "supportedaspectratios": "1:1, 3:2, 4:3, 16:9",
    "flashexposurecompensation": "Yes",
    "videoformatssupported": "H.264, MOV",
    "weightincludingbattery": "298g",
    "builtinprocessor": "DIGIC 5",
    "sensortype": "CMOS",
    "batterylifecipastandard": "230 shots",
    "height": "6.65 cm",
    "cameraplayback": "Movie, Single image, Slide show",
    "focusadjustment": "Auto/Manual",
    "camerashutterspeedmin": "0.00025s",
    "pictbridge": "Yes",
    "lightexposurecontrol": "Program AE",
    "autoexposureaelock": "Yes",
    "flashexposurelock": "Yes",
    "displaydiagonal": "7.62 cm (3\")",
    "category": "camera",
    "macoperatingsystemssupported": "Mac OS X 10.6 Snow Leopard, Mac OS X 10.7 Lion",
    "imageformatssupported": "JPG, RAW",
    "specification": "Picture quality Supported aspect ratios 1:1, 3:2, 4:3, 16:9 Still image resolution(s) 640 x 480, 720 x 400, 720 x 480, 1280 x 1280, 1712 x 1712, 1920 x 1080, 1920 x 1280, 2304 x 1728, 2304 x 2304, 2592 x 1456, 2592 x 1728, 3072 x 2304, 3456 x 1944, 3456 x 2304, 3456 x 3456, 4608 x 3456, 5184 x 2912, 5184 x 3456 Image stabilizer Yes Total megapixels 18.5 MP Image formats supported JPG, RAW Maximum image resolution 5184 x 3456 pixels Sensor type CMOS Camera type SLR Kit Megapixel 18 MP Lens system Minimum aperture 22 Lens structure (elements/groups) 7/6 Number of diaphragm blades 7 Lens mount interface Canon EF-M Filter size 4.3 cm Focusing Focus adjustment Auto/Manual Auto focusing (AF) modes Face detection, Face tracking Auto Focus (AF) points selection Auto, Manual Auto Focus (AF) points 31 Auto Focus (AF) lock Yes Auto Focus (AF) assist beam Yes Light exposure ISO sensitivity 100, 6400, 12800 Light exposure modes Auto, Manual Light exposure control Program AE Light exposure correction \u00b1 3EV (1/3EV step) Auto Exposure (AE) lock Yes ISO sensitivity (min) 100 ISO sensitivity (max) 12800 Shutter Camera shutter speed (min) 0.00025s Camera shutter speed (max) 30s Camera shutter type Electronic, Mechanical Flash Built-in flash No Flash sync-speed 0.005s Flash exposure lock Yes Flash exposure correction \u00b12EV (1/2, 1/3 EV step) Flash exposure compensation Yes External flash connector Yes Video Video resolutions 640 x 480, 1280 x 720, 1920 x 1080 pixels Video formats supported H.264, MOV Motion JPEG frame rate 30 fps Full HD Yes Analog signal format system NTSC, PAL Maximum video resolution 1920 x 1080 pixels Audio Built-in microphone Yes Memory Compatible memory cards SD, SDHC, SDXC Display Display aspect ratio 3:2 Display LCD Display diagonal 7.62 cm (3\") Display resolution (numeric) 1040000 pixels Touch sensitive screen Yes Ports & interfaces Microphone in Yes PictBridge Yes USB 2.0 ports quantity 1 HDMI ports quantity 1 DC-in jack Yes Camera Colour of product Black White balance Cloudy, Custom modes, Daylight, Flash, Fluorescent L, Shade, Tungsten Scene modes Close-up (macro), Landscape, Night portrait, Portrait, Sports Shooting modes Aperture priority, Auto, Manual, Shutter priority Self-timer 2, 10s Camera playback Movie, Single image, Slide show Playback zoom (max) 10x Direct printing Yes Camera file system Exif 2.3 Built-in processor DIGIC 5 Battery Battery technology Lithium-Ion (Li-Ion) Battery life (CIPA standard) 230 shots Battery type LP-E12 Number of batteries supported 1 Power source type AC, Battery Operating system/software Windows operating systems supported Yes Mac operating systems supported Mac OS X 10.6 Snow Leopard, Mac OS X 10.7 Lion Technical details USB 2.0 ports quantity 1 HDMI ports quantity 1 Direct printing Yes Processor Built-in processor DIGIC 5 Design Colour of product Black Performance Direct printing Yes Built-in processor DIGIC 5 Operational conditions Operating temperature (T-T) 0 - 40 \u00b0C System requirements Windows operating systems supported Yes Mac operating systems supported Mac OS X 10.6 Snow Leopard, Mac OS X 10.7 Lion Weight & dimensions Width 10.86 cm Depth 3.23 cm Height 6.65 cm Weight (including battery) 298g Packaging content Battery charger included Yes Batteries included Yes AC adapter included Yes Other features USB 2.0 ports quantity 1 HDMI ports quantity 1",
    "lensstructureelementsgroups": "7/6",
    "touchsensitivescreen": "Yes",
    "selftimer": "2, 10s",
    "minimumaperture": "22",
    "displayaspectratio": "3:2",
    "motionjpegframerate": "30 fps",
    "fullhd": "Yes",
    "displayresolutionnumeric": "1040000 pixels",
    "manufacturer": "Canon",
    "isosensitivitymin": "100",
    "analogsignalformatsystem": "NTSC, PAL",
    "externalflashconnector": "Yes",
    "builtinflash": "No",
    "compatiblememorycards": "SD, SDHC, SDXC",
    "isosensitivitymax": "12800",
    "videoresolutions": "640 x 480, 1280 x 720, 1920 x 1080 pixels",
    "megapixel": "18 MP",
    "numberofdiaphragmblades": "7",
    "camerafilesystem": "Exif 2.3",
    "builtinmicrophone": "Yes",
    "width": "10.86 cm",
    "windowsoperatingsystemssupported": "Yes",
    "playbackzoommax": "10x",
    "batteriesincluded": "Yes",
    "ean": "8714574590561",
    "batterychargerincluded": "Yes",
    "powersourcetype": "AC, Battery",
    "usb20portsquantity": "1",
    "cameratype": "SLR Kit",
    "camerashuttertype": "Electronic, Mechanical",
    "colourofproduct": "Black",
    "lensmountinterface": "Canon EF-M",
    "shootingmodes": "Aperture priority, Auto, Manual, Shutter priority",
    "autofocusaflock": "Yes",
    "filtersize": "4.3 cm",
    "shortdescription": "EOS-M + EF-M 22mm + EF Adapter, 3:2, 18MP, 22.3 x 14.9mm CMOS, 5184 x 3456, PictBridge, 298g",
    "display": "LCD",
    "autofocusafpointsselection": "Auto, Manual",
    "flashsyncspeed": "0.005s",
    "microphonein": "Yes",
    "camerashutterspeedmax": "30s",
    "maximumimageresolution": "5184 x 3456 pixels",
    "operatingtemperaturett": "0 - 40 \u00b0C",
    "lightexposurecorrection": "\u00b1 3EV (1/3EV step)",
    "dcinjack": "Yes",
    "maximumvideoresolution": "1920 x 1080 pixels",
    "imagestabilizer": "Yes",
    "hdmiportsquantity": "1",
    "autofocusafpoints": "31",
    "autofocusingafmodes": "Face detection, Face tracking",
    "scenemodes": "Close-up (macro), Landscape, Night portrait, Portrait, Sports",
    "directprinting": "Yes",
    "batterytechnology": "Lithium-Ion (Li-Ion)",
    "flashexposurecorrection": "\u00b12EV (1/2, 1/3 EV step)",
    "totalmegapixels": "18.5 MP",
    "numberofbatteriessupported": "1",
    "depth": "3.23 cm",
    "whitebalance": "Cloudy, Custom modes, Daylight, Flash, Fluorescent L, Shade, Tungsten"
}