{
    "lightexposurecontrol": "Program AE",
    "flashrangetele": "0.5 - 5.1m",
    "focallengthrangeff": "4.1 - 86.1 mm",
    "weight": "300g",
    "lightexposuremodes": "Aperture priority AE, Auto, Manual, Shutter priority AE",
    "audioformatssupported": "3GA, AAC, AMR, FLAC, M4A, MP3, OGG, WAV, WMA",
    "bluetoothversion": "4.0",
    "stillimageresolutions": "16M : 4608 x 3456, 14MP : 4608 x 3072, 12M W : 4608 x 2592, 10M : 3648 x 2736, 5M : 2592 x 1944, 3M : 1984 x 1488, 2MW : 1920 x 1080, 1M : 1024 x 768",
    "focus": "TTL",
    "height": "1.91 cm",
    "datanetwork": "3G, GSM, HSPA+",
    "camerashutterspeedmax": "16s",
    "maximumimageresolution": "4608 x 3456 pixels",
    "lightexposurecorrection": "\u00b1 2EV (1/3EV step)",
    "wifistandards": "802.11a, 802.11b, 802.11n",
    "bluetooth": "Yes",
    "lightmetering": "Centre-weighted, Evaluative (Multi-pattern), Spot",
    "sku": "EK-GC100ZWABTU",
    "totalmegapixels": "17 MP",
    "whitebalance": "Auto, Cloudy, Custom modes, Daylight, Fluorescent H, Fluorescent L, Tungsten",
    "hdmi": "No",
    "usbconnectortype": "Micro-USB A",
    "specification": "Picture quality Image sensor size 25.4/58.4 mm (1/2.3\") Still image resolution(s) 16M : 4608 x 3456, 14MP : 4608 x 3072, 12M W : 4608 x 2592, 10M : 3648 x 2736, 5M : 2592 x 1944, 3M : 1984 x 1488, 2MW : 1920 x 1080, 1M : 1024 x 768 Image stabilizer Yes Total megapixels 17 MP Image stabilizer location Lens Maximum image resolution 4608 x 3456 pixels Sensor type CMOS Camera type Compact Megapixel 16.3 MP Lens system Focal length range (f-f) 4.1 - 86.1 mm Minimum focal length (35mm film equiv) 2.3 cm Maximum focal length (35mm film equiv) 48.3 cm Optical zoom 21x Focusing Focus TTL Focus adjustment Auto/Manual Auto focusing (AF) modes Centre weighted Auto Focus, Face detection, Multi Point Auto Focus Normal focusing range 0.8m Manual focusing range (wide) 0.1m Manual focusing range (tele) 1.5m Macro focusing range (wide) 0.8m Macro focusing range (tele) 10m Light exposure ISO sensitivity 100, 200, 400, 800, 1600, 3200, Auto Light exposure modes Aperture priority AE, Auto, Manual, Shutter priority AE Light exposure control Program AE Light exposure correction \u00b1 2EV (1/3EV step) Light metering Centre-weighted, Evaluative (Multi-pattern), Spot ISO sensitivity (min) 100 ISO sensitivity (max) 3200 Shutter Camera shutter speed (min) 0.0005s Camera shutter speed (max) 16s Flash Flash modes Auto, Fill-in, Flash off, Red-eye reduction, Slow synchronization Built-in flash Yes Flash recharging time 4s Flash range (wide) 0.2 - 6.2m Flash range (tele) 0.5 - 5.1m Flash exposure correction \u00b11EV (1/2 EV step) Video Video resolutions 320 x 240, 640 x 480, 768 x 512, 1280 x 720, 1920 x 1080 pixels Video formats supported 3GP, AVI, FLV, MKV, MP4, WEBM, WMV Motion JPEG frame rate 30 fps Full HD Yes Maximum video resolution 1920 x 1080 pixels Audio Audio formats supported 3GA, AAC, AMR, FLAC, M4A, MP3, OGG, WAV, WMA Memory Internal memory 3690.72 MB Compatible memory cards MicroSD (TransFlash) Maximum memory card size 64 GB Display Display TFT Display diagonal 12.19 cm (4.8\") Display resolution 1280 x 720 pixels Ports & interfaces USB version 2.0 Headphone outputs 1 USB 2.0 ports quantity 1 USB connector type Micro-USB A HDMI No Networking Data network 3G, GSM, HSPA+ Wi-Fi standards 802.11a, 802.11b, 802.11n Bluetooth Yes Bluetooth version 4.0 Wi-Fi Yes Camera Image stabilizer location Lens Colour of product Grey White balance Auto, Cloudy, Custom modes, Daylight, Fluorescent H, Fluorescent L, Tungsten Scene modes Backlight, Close-up (macro), Fireworks, Landscape, Night, Panorama, Portrait, Sunset Photo effects Antique, Black&White, Fader, Negative film, Pastel, Solarisation Processor clock speed 1400 MHz Built-in processor Quad Core Application Processor Battery Battery capacity 1650 mAh Battery life (max) 280h Power source type Battery Technical details USB 2.0 ports quantity 1 HDMI No Processor Processor clock speed 1400 MHz Built-in processor Quad Core Application Processor Design Colour of product Grey Performance Processor clock speed 1400 MHz Built-in processor Quad Core Application Processor Weight & dimensions Width 7.08 cm Depth 12.87 cm Height 1.91 cm Weight 300g Other features USB 2.0 ports quantity 1",
    "isosensitivitymin": "100",
    "manualfocusingrangetele": "1.5m",
    "usbversion": "2.0",
    "width": "7.08 cm",
    "colourofproduct": "Grey",
    "minimumfocallength35mmfilmequiv": "2.3 cm",
    "macrofocusingrangetele": "10m",
    "imagesensorsize": "25.4/58.4 mm (1/2.3\")",
    "maximumvideoresolution": "1920 x 1080 pixels",
    "processorclockspeed": "1400 MHz",
    "isosensitivity": "100, 200, 400, 800, 1600, 3200, Auto",
    "videoformatssupported": "3GP, AVI, FLV, MKV, MP4, WEBM, WMV",
    "displayresolution": "1280 x 720 pixels",
    "category": "camera",
    "maximummemorycardsize": "64 GB",
    "displaydiagonal": "12.19 cm (4.8\")",
    "maximumfocallength35mmfilmequiv": "48.3 cm",
    "motionjpegframerate": "30 fps",
    "ean": "8806085298682",
    "macrofocusingrangewide": "0.8m",
    "builtinprocessor": "Quad Core Application Processor",
    "autofocusingafmodes": "Centre weighted Auto Focus, Face detection, Multi Point Auto Focus",
    "sensortype": "CMOS",
    "scenemodes": "Backlight, Close-up (macro), Fireworks, Landscape, Night, Panorama, Portrait, Sunset",
    "batterycapacity": "1650 mAh",
    "fullhd": "Yes",
    "wifi": "Yes",
    "photoeffects": "Antique, Black&White, Fader, Negative film, Pastel, Solarisation",
    "powersourcetype": "Battery",
    "usb20portsquantity": "1",
    "manufacturer": "Samsung",
    "flashrechargingtime": "4s",
    "internalmemory": "3690.72 MB",
    "imagestabilizer": "Yes",
    "normalfocusingrange": "0.8m",
    "flashrangewide": "0.2 - 6.2m",
    "focusadjustment": "Auto/Manual",
    "cameratype": "Compact",
    "builtinflash": "Yes",
    "camerashutterspeedmin": "0.0005s",
    "batterylifemax": "280h",
    "compatiblememorycards": "MicroSD (TransFlash)",
    "flashexposurecorrection": "\u00b11EV (1/2 EV step)",
    "isosensitivitymax": "3200",
    "megapixel": "16.3 MP",
    "flashmodes": "Auto, Fill-in, Flash off, Red-eye reduction, Slow synchronization",
    "depth": "12.87 cm",
    "opticalzoom": "21x",
    "videoresolutions": "320 x 240, 640 x 480, 768 x 512, 1280 x 720, 1920 x 1080 pixels",
    "manualfocusingrangewide": "0.1m",
    "shortdescription": "Galaxy, Wi-Fi, 3G, 17MP, 21x Zoom",
    "display": "TFT",
    "imagestabilizerlocation": "Lens"
}