{
    "lensstructureelementsgroups": "11/9",
    "lightexposuremodes": "Auto, Manual",
    "isosensitivity": "100, 125, 160, 200, 250, 320, 400, 500, 640, 800, 1000, 1250, 1600, 2000, 2250, 2500, 3200, 4000, 5000, 6400",
    "stillimageresolutions": "JPEG 3:2: (L) 5184x3456, (M) 3456x2304, (S1) 2592x1728, (S2) 1920x1280, (S3) 720x480 JPEG 4:3: (L) 4608x3456, (M) 3072x2304, (S1) 2304x1728, (S2) 1696x1280, (S3) 640x480 JPEG 16:9: (L) 5184x2912, (M) 3456x1944, (S1) 2592x1456 (S2) 1920x1080, (S3) 720x400 JPEG 1:1: (L) 3456x3456, (M) 2304x2304, (S1) 1728x1728, (S2) 1280x1280, (S3) 480x480",
    "focus": "TTL",
    "batterytype": "Rechargeable Li-ion Battery LP-E10",
    "sku": "9127B027AA",
    "liveview": "Yes",
    "sensorformat": "Advanced Photo System type-C (APS-C)",
    "flashexposurecompensation": "Yes",
    "videoformatssupported": "H.264",
    "weightincludingbattery": "680g",
    "material": "Carbon, Glass, Polycarbonate",
    "sensortype": "CMOS",
    "batterylifecipastandard": "500 shots",
    "imageprocessor": "DIGIC 4+",
    "camerashutterspeedmin": "0.000250s",
    "lenssystem": "EF/EF-S",
    "pictbridge": "Yes",
    "externalflashconnector": "Yes",
    "weight": "480 g",
    "flashexposurelock": "Yes",
    "category": "camera",
    "imageformatssupported": "JPEG XR, RAW",
    "lightmetering": "Centre-weighted, Evaluative (Multi-pattern)",
    "specification": "Picture quality Sensor format Advanced Photo System type-C (APS-C) Supported aspect ratios 1:1, 3:2, 4:3, 16:9 Still image resolution(s) JPEG 3:2: (L) 5184x3456, (M) 3456x2304, (S1) 2592x1728, (S2) 1920x1280, (S3) 720x480 JPEG 4:3: (L) 4608x3456, (M) 3072x2304, (S1) 2304x1728, (S2) 1696x1280, (S3) 640x480 JPEG 16:9: (L) 5184x2912, (M) 3456x1944, (S1) 2592x1456 (S2) 1920x1080, (S3) 720x400 JPEG 1:1: (L) 3456x3456, (M) 2304x2304, (S1) 1728x1728, (S2) 1280x1280, (S3) 480x480 Image stabilizer Yes Total megapixels 18.7 MP Image sensor size (W x H) 22.3 x 14.9 mm Image stabilizer location Lens Image formats supported JPEG XR, RAW Maximum image resolution 5184 x 3456 pixels Sensor type CMOS Camera type SLR Kit Megapixel 18 MP Lens system Mounting type Bayonet Minimum focal length (35mm film equiv) 2.9 cm Maximum focal length (35mm film equiv) 8.8 cm Minimum aperture 22 Maximum aperture 38 Lens structure (elements/groups) 11/9 Number of diaphragm blades 6 Lens mount interface Canon EF, Canon EF-S Filter size 5.8 cm Focusing Focus TTL Auto focusing (AF) modes Servo Auto Focus Closest focusing distance 0.25m Auto Focus (AF) points selection Auto, Manual Auto Focus (AF) points 9 Auto Focus (AF) lock Yes Auto Focus (AF) assist beam No Light exposure ISO sensitivity 100, 125, 160, 200, 250, 320, 400, 500, 640, 800, 1000, 1250, 1600, 2000, 2250, 2500, 3200, 4000, 5000, 6400 Light exposure modes Auto, Manual Light metering Centre-weighted, Evaluative (Multi-pattern) ISO sensitivity (min) 100 ISO sensitivity (max) 6400 Shutter Camera shutter speed (min) 0.000250s Camera shutter type Electronic Flash Flash modes Auto, Flash off, Flash on Built-in flash Yes Flash recharging time 2s Flash exposure lock Yes Flash exposure correction \u00b12EV (1/2, 1/3 EV step) Flash exposure compensation Yes External flash connector Yes Video Video resolutions 640 x 480, 1280 x 720, 1920 x 1080 pixels Video formats supported H.264 Full HD Yes Maximum video resolution 1920 x 1080 pixels Memory Compatible memory cards SD, SDHC, SDXC Display Display TFT Display diagonal 7.62 cm (3\") Viewfinder Magnification 0.34x Ports & interfaces HDMI connector type Mini PictBridge Yes HDMI Yes Camera Image stabilizer location Lens Colour of product Black White balance Cloudy, Custom modes, Daylight, Flash, Fluorescent L, Shade, Tungsten Scene modes Close-up (macro), Landscape, Night portrait, Sports Shooting modes Aperture priority, Auto, Manual, Movie, Program, Scene, Shutter priority Self-timer 2, 10s Orientation sensor Yes Live view Yes Languages support ARA, CHI (SIMPL), CHI (TR), CZE, DAN, DEU, DUT, ENG, ESP, FIN, FRE, GRE, HUN, ITA, JPN, KOR, NOR, POL, POR, RUM, RUS, SWE, THA, TUR, UKR Histogram Yes Direct printing Yes Dioptre correction Yes Camera file system DCF 2.0 Brightness adjustment Yes Battery Battery technology Lithium-Ion (Li-Ion) Battery life (CIPA standard) 500 shots Power source type Battery Technical details Wrist strap included Yes Material Carbon, Glass, Polycarbonate Languages support ARA, CHI (SIMPL), CHI (TR), CZE, DAN, DEU, DUT, ENG, ESP, FIN, FRE, GRE, HUN, ITA, JPN, KOR, NOR, POL, POR, RUM, RUS, SWE, THA, TUR, UKR HDMI Yes Direct printing Yes Design Material Carbon, Glass, Polycarbonate Colour of product Black Performance Direct printing Yes Operational conditions Operating temperature (T-T) 0 - 40 \u00b0C Operating relative humidity (H-H) 0 - 85% Weight & dimensions Width 12.96 cm Depth 7.79 cm Height 9.97 cm Weight (including battery) 680g Packaging content Wrist strap included Yes Cables included AC, USB Battery charger included Yes Batteries included Yes Technical details Image processor DIGIC 4+",
    "autofocusafassistbeam": "No",
    "selftimer": "2, 10s",
    "maximumaperture": "38",
    "minimumaperture": "22",
    "hdmi": "Yes",
    "fullhd": "Yes",
    "manufacturer": "Canon",
    "isosensitivitymin": "100",
    "flashmodes": "Auto, Flash off, Flash on",
    "builtinflash": "Yes",
    "compatiblememorycards": "SD, SDHC, SDXC",
    "isosensitivitymax": "6400",
    "languagessupport": "ARA, CHI (SIMPL), CHI (TR), CZE, DAN, DEU, DUT, ENG, ESP, FIN, FRE, GRE, HUN, ITA, JPN, KOR, NOR, POL, POR, RUM, RUS, SWE, THA, TUR, UKR",
    "videoresolutions": "640 x 480, 1280 x 720, 1920 x 1080 pixels",
    "videocapability": "Yes",
    "cablesincluded": "AC, USB",
    "megapixel": "18 MP",
    "numberofdiaphragmblades": "6",
    "camerafilesystem": "DCF 2.0",
    "mountingtype": "Bayonet",
    "width": "12.96 cm",
    "magnification": "0.34x",
    "supportedaspectratios": "1:1, 3:2, 4:3, 16:9",
    "type": "Digital SLR",
    "dioptrecorrection": "Yes",
    "batteriesincluded": "Yes",
    "ean": "8714574618234",
    "closestfocusingdistance": "0.25m",
    "histogram": "Yes",
    "batterychargerincluded": "Yes",
    "powersourcetype": "Battery",
    "operatingrelativehumidityhh": "0 - 85%",
    "brightnessadjustment": "Yes",
    "cameratype": "SLR Kit",
    "camerashuttertype": "Electronic",
    "colourofproduct": "Black",
    "lensmountinterface": "Canon EF, Canon EF-S",
    "lcdscreensize": "3",
    "shootingmodes": "Aperture priority, Auto, Manual, Movie, Program, Scene, Shutter priority",
    "filtersize": "5.8 cm",
    "maximumfocallength35mmfilmequiv": "8.8 cm",
    "shortdescription": "18MP, 22.3 x 14.9mm, 3:2, CMOS, APS-C, TFT, 7.62 cm (3 \")",
    "display": "TFT",
    "imagestabilizerlocation": "Lens",
    "autofocusafpointsselection": "Auto, Manual",
    "lenstype": "18-55mm",
    "maximumimageresolution": "5184 x 3456 pixels",
    "operatingtemperaturett": "0 - 40 \u00b0C",
    "autofocusaflock": "Yes",
    "totalmegapixels": "18.7 MP",
    "minimumfocallength35mmfilmequiv": "2.9 cm",
    "dimensionswxdxh": "129.6 x 77.9 x 99.7 mm",
    "maximumvideoresolution": "1920 x 1080 pixels",
    "imagestabilizer": "Yes",
    "displaydiagonal": "7.62 cm (3\")",
    "autofocusafpoints": "9",
    "autofocusingafmodes": "Servo Auto Focus",
    "scenemodes": "Close-up (macro), Landscape, Night portrait, Sports",
    "hdmiconnectortype": "Mini",
    "flashrechargingtime": "2s",
    "directprinting": "Yes",
    "batterytechnology": "Lithium-Ion (Li-Ion)",
    "flashexposurecorrection": "\u00b12EV (1/2, 1/3 EV step)",
    "imagesensorsizewxh": "22.3 x 14.9 mm",
    "height": "9.97 cm",
    "depth": "7.79 cm",
    "orientationsensor": "Yes",
    "whitebalance": "Cloudy, Custom modes, Daylight, Flash, Fluorescent L, Shade, Tungsten"
}