{
    "autofocusafassistbeam": "Yes",
    "lightexposuremodes": "Aperture priority AE, Auto, Manual, Shutter priority AE",
    "isosensitivity": "100, 200, 400, 800, 1600, 3200, Auto",
    "stillimageresolutions": "4608 x 3456, 3264 x 2448, 2048 x 1536, 640 x 480, 4608 x 2592, 3264 x 1832, 1920 x 1080, 640 x 360, 4608 x 3072, 3264 x 2176, 2048 x 1368, 640 x 424, 3456 x 3456, 2448 x 2448, 1536 x 1536, 480 x 480",
    "focus": "TTL",
    "batterytype": "Rechargeable Li-ion Battery NB-6LH",
    "sku": "9339B014AA",
    "supportedaspectratios": "1:1, 3:2, 4:3, 16:9",
    "flashexposurecompensation": "Yes",
    "videoformatssupported": "MP4",
    "weightincludingbattery": "269g",
    "builtinprocessor": "DIGIC 6",
    "sensortype": "CMOS",
    "batterylifecipastandard": "250 shots",
    "height": "6.58 cm",
    "focusadjustment": "Auto/Manual",
    "camerashutterspeedmin": "15s",
    "pictbridge": "Yes",
    "flashrangetele": "1 - 2m",
    "weight": "269 g",
    "autoexposureaelock": "Yes",
    "flashexposurelock": "Yes",
    "displaydiagonal": "7.62 cm (3\")",
    "category": "camera",
    "macoperatingsystemssupported": "Mac OS X 10.7 Lion, Mac OS X 10.8 Mountain Lion, Mac OS X 10.9 Mavericks",
    "lightmetering": "Centre-weighted, Evaluative (Multi-pattern), Spot",
    "specification": "Picture quality Image sensor size 25.4/58.4 mm (1/2.3\") Supported aspect ratios 1:1, 3:2, 4:3, 16:9 Still image resolution(s) 4608 x 3456, 3264 x 2448, 2048 x 1536, 640 x 480, 4608 x 2592, 3264 x 1832, 1920 x 1080, 640 x 360, 4608 x 3072, 3264 x 2176, 2048 x 1368, 640 x 424, 3456 x 3456, 2448 x 2448, 1536 x 1536, 480 x 480 Image stabilizer Yes Maximum image resolution 4608 x 3456 pixels Sensor type CMOS Camera type Compact Megapixel 16.1 MP Lens system Focal length range (f-f) 4.5 - 135 mm Minimum focal length (35mm film equiv) 2.5 cm Maximum focal length (35mm film equiv) 75 cm Minimum aperture 3.2 Maximum aperture 6.9 Lens structure (elements/groups) 13/10 Combined zoom 120x Digital zoom 4x Optical zoom 30x Focusing Focus TTL Focus adjustment Auto/Manual Auto focusing (AF) modes Continuous Auto Focus, Face detection, Servo Auto Focus, Single Auto Focus, Tracking Auto Focus Closest focusing distance 0.01m Auto Focus (AF) lock Yes Auto Focus (AF) assist beam Yes Light exposure ISO sensitivity 100, 200, 400, 800, 1600, 3200, Auto Light exposure modes Aperture priority AE, Auto, Manual, Shutter priority AE Light exposure correction \u00b1 2EV (1/3EV step) Light metering Centre-weighted, Evaluative (Multi-pattern), Spot Auto Exposure (AE) lock Yes ISO sensitivity (min) 100 ISO sensitivity (max) 3200 Shutter Camera shutter speed (min) 15s Camera shutter speed (max) 0.0003125s Flash Flash modes Auto, Flash off, Flash on, Manual, Red-eye reduction, Slow synchronization Built-in flash Yes Flash sync-speed 0.0005s Flash range (wide) 0.5 - 3.5m Flash range (tele) 1 - 2m Flash exposure lock Yes Flash exposure compensation Yes Video Video resolutions 320 x 240, 640 x 480, 1280 x 720, 1920 x 1080 pixels Resolution at capture speed 1280\u00d7720@30fps, 1920x1080@30fps, 1920x1080@60fps, 640x480@30fps Video formats supported MP4 Full HD Yes Maximum video resolution 1920 x 1080 pixels Audio Built-in microphone Yes Memory Compatible memory cards SD, SDHC, SDXC Memory slots 1 Display Display TFT Display diagonal 7.62 cm (3\") Ports & interfaces USB version 2.0 HDMI connector type Micro PictBridge Yes USB connector type Mini-USB B HDMI Yes Networking Wi-Fi standards 802.11b, 802.11g, 802.11n Wi-Fi Yes Camera Colour of product Red White balance Auto, Cloudy, Custom modes, Daylight, Fluorescent, Fluorescent H, Tungsten Scene modes Fireworks, Portrait, Snow, Sports Photo effects Black&White, Neutral, Positive film, Sepia, Skin tones, Vivid Self-timer 2, 10s Languages support Multi Histogram Yes Camera file system DPOF 1.1, Exif 2.3 Built-in processor DIGIC 6 Battery Battery technology Lithium-Ion (Li-Ion) Battery life (CIPA standard) 250 shots Number of batteries supported 1 Power source type Battery Operating system/software Windows operating systems supported Windows 7 Home Basic, Windows 7 Home Basic x64, Windows 7 Home Premium, Windows 7 Home Premium x64, Windows 7 Professional, Windows 7 Professional x64, Windows 7 Starter, Windows 7 Starter x64, Windows 7 Ultimate, Windows 7 Ultimate x64, Windows 8, Windows 8 Enterprise, Windows 8 Enterprise x64, Windows 8 Pro, Windows 8 Pro x64, Windows 8 x64, Windows 8.1, Windows 8.1 Enterprise, Windows 8.1 Enterprise x64, Windows 8.1 Pro, Windows 8.1 Pro x64, Windows 8.1 x64, Windows Vista Business, Windows Vista Business x64, Windows Vista Enterprise, Windows Vista Enterprise x64, Windows Vista Home Basic, Windows Vista Home Basic x64, Windows Vista Home Premium, Windows Vista Home Premium x64, Windows Vista Ultimate, Windows Vista Ultimate x64, Windows XP Home, Windows XP Home x64, Windows XP Professional, Windows XP Professional x64 Mac operating systems supported Mac OS X 10.7 Lion, Mac OS X 10.8 Mountain Lion, Mac OS X 10.9 Mavericks Technical details Resolution at capture speed 1280\u00d7720@30fps, 1920x1080@30fps, 1920x1080@60fps, 640x480@30fps Languages support Multi HDMI Yes Processor Built-in processor DIGIC 6 Design Colour of product Red Performance Built-in processor DIGIC 6 Operational conditions Operating temperature (T-T) 0 - 40 \u00b0C Operating relative humidity (H-H) 10 - 90% System requirements Windows operating systems supported Windows 7 Home Basic, Windows 7 Home Basic x64, Windows 7 Home Premium, Windows 7 Home Premium x64, Windows 7 Professional, Windows 7 Professional x64, Windows 7 Starter, Windows 7 Starter x64, Windows 7 Ultimate, Windows 7 Ultimate x64, Windows 8, Windows 8 Enterprise, Windows 8 Enterprise x64, Windows 8 Pro, Windows 8 Pro x64, Windows 8 x64, Windows 8.1, Windows 8.1 Enterprise, Windows 8.1 Enterprise x64, Windows 8.1 Pro, Windows 8.1 Pro x64, Windows 8.1 x64, Windows Vista Business, Windows Vista Business x64, Windows Vista Enterprise, Windows Vista Enterprise x64, Windows Vista Home Basic, Windows Vista Home Basic x64, Windows Vista Home Premium, Windows Vista Home Premium x64, Windows Vista Ultimate, Windows Vista Ultimate x64, Windows XP Home, Windows XP Home x64, Windows XP Professional, Windows XP Professional x64 Mac operating systems supported Mac OS X 10.7 Lion, Mac OS X 10.8 Mountain Lion, Mac OS X 10.9 Mavericks Weight & dimensions Width 11.27 cm Depth 3.48 cm Height 6.58 cm Weight (including battery) 269g",
    "lensstructureelementsgroups": "13/10",
    "selftimer": "2, 10s",
    "maximumaperture": "6.9",
    "minimumaperture": "3.2",
    "resolutionatcapturespeed": "1280\u00d7720@30fps, 1920x1080@30fps, 1920x1080@60fps, 640x480@30fps",
    "hdmi": "Yes",
    "camerashutterspeed": "1 \u2013 1/3200 sec. (factory default)  15 \u2013 1/3200 sec. (total range \u2013 varies by shooting mode)",
    "fullhd": "Yes",
    "manufacturer": "Canon",
    "isosensitivitymin": "100",
    "flashmodes": "Auto, Flash off, Flash on, Manual, Red-eye reduction, Slow synchronization",
    "builtinflash": "Yes",
    "compatiblememorycards": "SD, SDHC, SDXC",
    "isosensitivitymax": "3200",
    "languagessupport": "Multi",
    "videoresolutions": "320 x 240, 640 x 480, 1280 x 720, 1920 x 1080 pixels",
    "videocapability": "Yes",
    "photoeffects": "Black&White, Neutral, Positive film, Sepia, Skin tones, Vivid",
    "megapixel": "16.1 MP",
    "wifistandards": "802.11b, 802.11g, 802.11n",
    "camerafilesystem": "DPOF 1.1, Exif 2.3",
    "builtinmicrophone": "Yes",
    "width": "11.27 cm",
    "windowsoperatingsystemssupported": "Windows 7 Home Basic, Windows 7 Home Basic x64, Windows 7 Home Premium, Windows 7 Home Premium x64, Windows 7 Professional, Windows 7 Professional x64, Windows 7 Starter, Windows 7 Starter x64, Windows 7 Ultimate, Windows 7 Ultimate x64, Windows 8, Windows 8 Enterprise, Windows 8 Enterprise x64, Windows 8 Pro, Windows 8 Pro x64, Windows 8 x64, Windows 8.1, Windows 8.1 Enterprise, Windows 8.1 Enterprise x64, Windows 8.1 Pro, Windows 8.1 Pro x64, Windows 8.1 x64, Windows Vista Business, Windows Vista Business x64, Windows Vista Enterprise, Windows Vista Enterprise x64, Windows Vista Home Basic, Windows Vista Home Basic x64, Windows Vista Home Premium, Windows Vista Home Premium x64, Windows Vista Ultimate, Windows Vista Ultimate x64, Windows XP Home, Windows XP Home x64, Windows XP Professional, Windows XP Professional x64",
    "imagesensorsize": "25.4/58.4 mm (1/2.3\")",
    "memoryslots": "1",
    "closestfocusingdistance": "0.01m",
    "histogram": "Yes",
    "powersourcetype": "Battery",
    "operatingrelativehumidityhh": "10 - 90%",
    "flashrangewide": "0.5 - 3.5m",
    "cameratype": "Compact",
    "colourofproduct": "Red",
    "lcdscreensize": "3",
    "maximumfocallength35mmfilmequiv": "75 cm",
    "shortdescription": "16.1 MP (4608 x 3456 max.), 1/2.3\" CMOS, 30x optical/4x digital zoom, ISO 100-3200, 7.62 cm (3 \") TFT, USB 2.0, HDMI, 269 g, Red",
    "display": "TFT",
    "focallengthrangeff": "4.5 - 135 mm",
    "flashsyncspeed": "0.0005s",
    "lightexposurecorrection": "\u00b1 2EV (1/3EV step)",
    "camerashutterspeedmax": "0.0003125s",
    "maximumimageresolution": "4608 x 3456 pixels",
    "operatingtemperaturett": "0 - 40 \u00b0C",
    "autofocusaflock": "Yes",
    "usbconnectortype": "Mini-USB B",
    "ean": "8714574617534",
    "digitalzoom": "4x",
    "usbversion": "2.0",
    "minimumfocallength35mmfilmequiv": "2.5 cm",
    "dimensionswxdxh": "112.7 x 34.8 x 65.8 mm",
    "maximumvideoresolution": "1920 x 1080 pixels",
    "imagestabilizer": "Yes",
    "combinedzoom": "120x",
    "autofocusingafmodes": "Continuous Auto Focus, Face detection, Servo Auto Focus, Single Auto Focus, Tracking Auto Focus",
    "scenemodes": "Fireworks, Portrait, Snow, Sports",
    "hdmiconnectortype": "Micro",
    "wifi": "Yes",
    "batterytechnology": "Lithium-Ion (Li-Ion)",
    "opticalzoom": "30x",
    "numberofbatteriessupported": "1",
    "depth": "3.48 cm",
    "whitebalance": "Auto, Cloudy, Custom modes, Daylight, Fluorescent, Fluorescent H, Tungsten"
}