{
    "photoeffects": "Antique, Black&White",
    "flashrangetele": "1.5 - 2.2m",
    "cablesincluded": "AC, USB",
    "weight": "105g",
    "lightexposuremodes": "Auto",
    "isosensitivity": "100, 200, 400, 800, 1600, 3200, 6400, Auto",
    "stillimageresolutions": "3:2 - 16M(4896\u00d73264) / 8.9M(3648\u00d72432) / 4.5M(2592\u00d71728) 4:3 - 18M(4896\u00d73672) / 10M(3648\u00d72736) / 5M(2592\u00d71944) / VGA 16:9 - 13M(4896\u00d72752) / 7.5M(3648\u00d72056) / 2.1M(1920\u00d71080) 1:1 - 13M(3664\u00d73664) / 7.5M(2736\u00d72736) / 3.7M(1920\u00d71920) 7152\u00d71080 / 4912\u00d71920 / 4912\u00d71080 / 3424\u00d7192 / 11520\u00d71080",
    "megapixel": "18.2 MP",
    "nearfieldcommunicationnfc": "Yes",
    "camerashutterspeedmax": "0.000625s",
    "wifistandards": "802.11b, 802.11g, 802.11n",
    "lightexposurecorrection": "\u00b1 2EV (1/3EV step)",
    "focallengthrangeff": "4.45 - 44.5 mm",
    "batterytype": "NP-BN",
    "sku": "DSCWX220B.CEH",
    "selftimer": "2, 10s",
    "imageprocessor": "BIONZ X",
    "builtinmicrophone": "Yes",
    "automodefocusingrangetele": "1.5 - ?",
    "automodefocusingrangewide": "0.05 - ?",
    "imageformatssupported": "JPG",
    "lightmetering": "Centre-weighted, Evaluative (Multi-pattern), Spot",
    "specification": "Picture quality Image sensor size 25.4/58.4 mm (1/2.3\") Still image resolution(s) 3:2 - 16M(4896\u00d73264) / 8.9M(3648\u00d72432) / 4.5M(2592\u00d71728) 4:3 - 18M(4896\u00d73672) / 10M(3648\u00d72736) / 5M(2592\u00d71944) / VGA 16:9 - 13M(4896\u00d72752) / 7.5M(3648\u00d72056) / 2.1M(1920\u00d71080) 1:1 - 13M(3664\u00d73664) / 7.5M(2736\u00d72736) / 3.7M(1920\u00d71920) 7152\u00d71080 / 4912\u00d71920 / 4912\u00d71080 / 3424\u00d7192 / 11520\u00d71080 Image stabilizer Yes Image formats supported JPG Maximum image resolution 4896 x 3672 pixels Sensor type CMOS Camera type Compact Megapixel 18.2 MP Lens system Focal length range (f-f) 4.45 - 44.5 mm Lens structure (elements/groups) 9/7 Digital zoom 153x Optical zoom 10x Focusing Focus adjustment Auto Auto focusing (AF) modes Centre weighted Auto Focus, Multi Point Auto Focus, Single Auto Focus Auto Mode focusing range (wide) 0.05 - ? Auto Mode focusing range (tele) 1.5 - ? Light exposure ISO sensitivity 100, 200, 400, 800, 1600, 3200, 6400, Auto Light exposure modes Auto Light exposure correction \u00b1 2EV (1/3EV step) Light metering Centre-weighted, Evaluative (Multi-pattern), Spot ISO sensitivity (min) 100 ISO sensitivity (max) 12800 Shutter Camera shutter speed (min) 1s Camera shutter speed (max) 0.000625s Flash Flash modes Auto, Flash off, Flash on, Slow synchronization Built-in flash Yes Flash range (wide) 0.2 - 3.7m Flash range (tele) 1.5 - 2.2m Video Video resolutions 640 x 480, 1440 x 1080, 1920 x 1080 pixels Video formats supported AVCHD, MP4 Motion JPEG frame rate 50 fps Full HD Yes Maximum video resolution 1920 x 1080 pixels Audio Built-in microphone Yes Memory Compatible memory cards MicroSD (TransFlash), MicroSDHC, MicroSDXC, MS Duo, MS Micro (M2), MS PRO Duo, MS Pro-HG Duo, MS XC-HG Duo, SD, SDHC, SDXC Display Display LCD Display diagonal 6.86 cm (2.7\") Display resolution (numeric) 460800 pixels Ports & interfaces USB version 2.0 HDMI connector type Micro HDMI Yes Networking Wi-Fi standards 802.11b, 802.11g, 802.11n Near Field Communication (NFC) Yes Wi-Fi Yes Camera Colour of product Black White balance Auto, Cloudy, Custom modes, Daylight, Flash, Fluorescent, Incandescent Scene modes Beach, Fireworks, Food, Landscape, Night, Night portrait, Pet, Portrait, Snow, Twilight Shooting modes Auto, Movie, Scene Photo effects Antique, Black&White Self-timer 2, 10s Camera playback Movie, Single image, Slide show Battery Battery life (CIPA standard) 210 shots Battery life (max) 1.75h Battery type NP-BN Power source type Battery Technical details HDMI Yes Design Colour of product Black Weight & dimensions Width 9.23 cm Depth 2.16 cm Height 5.24 cm Weight 105g Weight (including battery) 121g Packaging content Cables included AC, USB Batteries included Yes AC adapter included Yes Technical details Image processor BIONZ X",
    "lensstructureelementsgroups": "9/7",
    "depth": "2.16 cm",
    "usbversion": "2.0",
    "width": "9.23 cm",
    "colourofproduct": "Black",
    "imagesensorsize": "25.4/58.4 mm (1/2.3\")",
    "maximumvideoresolution": "1920 x 1080 pixels",
    "videoformatssupported": "AVCHD, MP4",
    "motionjpegframerate": "50 fps",
    "category": "camera",
    "weightincludingbattery": "121g",
    "displaydiagonal": "6.86 cm (2.7\")",
    "hdmi": "Yes",
    "ean": "4905524980745",
    "isosensitivitymin": "100",
    "imagestabilizer": "Yes",
    "autofocusingafmodes": "Centre weighted Auto Focus, Multi Point Auto Focus, Single Auto Focus",
    "sensortype": "CMOS",
    "scenemodes": "Beach, Fireworks, Food, Landscape, Night, Night portrait, Pet, Portrait, Snow, Twilight",
    "batterylifecipastandard": "210 shots",
    "fullhd": "Yes",
    "wifi": "Yes",
    "powersourcetype": "Battery",
    "displayresolutionnumeric": "460800 pixels",
    "manufacturer": "Sony",
    "cameraplayback": "Movie, Single image, Slide show",
    "acadapterincluded": "Yes",
    "hdmiconnectortype": "Micro",
    "batteriesincluded": "Yes",
    "flashrangewide": "0.2 - 3.7m",
    "focusadjustment": "Auto",
    "cameratype": "Compact",
    "shootingmodes": "Auto, Movie, Scene",
    "builtinflash": "Yes",
    "camerashutterspeedmin": "1s",
    "batterylifemax": "1.75h",
    "compatiblememorycards": "MicroSD (TransFlash), MicroSDHC, MicroSDXC, MS Duo, MS Micro (M2), MS PRO Duo, MS Pro-HG Duo, MS XC-HG Duo, SD, SDHC, SDXC",
    "opticalzoom": "10x",
    "isosensitivitymax": "12800",
    "height": "5.24 cm",
    "flashmodes": "Auto, Flash off, Flash on, Slow synchronization",
    "digitalzoom": "153x",
    "videoresolutions": "640 x 480, 1440 x 1080, 1920 x 1080 pixels",
    "whitebalance": "Auto, Cloudy, Custom modes, Daylight, Flash, Fluorescent, Incandescent",
    "shortdescription": "18.2MP, 1/2.3\" Exmor R CMOS, Sony G lens, f = 4.45 - 44.5 mm, F3.3(W) - 5.9(T), NFC, Wi-Fi",
    "display": "LCD",
    "maximumimageresolution": "4896 x 3672 pixels"
}