{
    "focallengthrangeff": "4.6 - 23 mm",
    "weight": "125 g",
    "flashtype": "Sorry, this data isn\u2032t available",
    "isosensitivity": "Auto: (ISO100-800 level) ISO 100-3200",
    "megapixel": "20.1",
    "pictureeffects": "Still: Toy camera / Pop Color / Partial Color / Soft High-key, Movie: Toy camera, Pop Color, Partial Color, Soft High-key",
    "batterytype": "Rechargeable Battery Pack NP-BN",
    "builtinwifi": "?",
    "sku": "DSCW800B.CEH",
    "playbackmodes": "Slideshow with Music",
    "batterylife": "Up to 200 shots / 100 minutes",
    "display": "2.7'' (6.7 cm) (4:3) / 230,400 dots / Xtra Fine / TFT LCD",
    "lightmetering": "Multi Pattern",
    "specification": "Picture quality Sensor type 1/2.3\" type (7.76mm) Super HAD CCD Lens system Focal length range (f-f) 4.6 - 23 mm Optical zoom 5x Light exposure ISO sensitivity Auto: (ISO100-800 level) ISO 100-3200 Light metering Multi Pattern Flash Flash modes Auto,Flash On,Flash Off Auto / Flash On / Slow Synchro / Flash Off / Advanced Flash Flash exposure compensation +/- 2.0 EV (1/3 EV steps) Memory Compatible memory cards Memory Stick\u2122 Duo;Memory Stick PRO Duo\u2122;Memory Stick PRO Duo\u2122(high speed);Memory Stick PRO HG Duo\u2122;Memory Stick XC-HG Duo\u2122;Memory Stick Micro;Memory Stick Micro (Mark2);SD Memory Card;SDHC Memory Card;SDXC Memory Card;microSD Memory Card;microSDHC Memory Card;microSDXC Memory Card Display Display 2.7'' (6.7 cm) (4:3) / 230,400 dots / Xtra Fine / TFT LCD Viewfinder Viewfinder type ? Camera Colour of product Black Playback modes Slideshow with Music White balance Auto, Daylight, Cloudy, Incandescent, Flash Scene modes Night Portrait, Landscape, Portrait, Beach, Snow Shooting modes Intelligent Auto, Panorama, Program Auto, Easy Shooting, Picture Effect, Scene Selection, Steady shot, Party Technical details Playback modes Slideshow with Music Accessories included Rechargeable Battery Pack NP-BN;AC AdaptorAC-UB10C;Wrist Strap;Multi USB cable;Instruction Manual Recording format Still Images: JPEG (DCF, Exif, MPF Baseline) compliant, DPOF compatible Lens system Sony Lens Picture effects Still: Toy camera / Pop Color / Partial Color / Soft High-key, Movie: Toy camera, Pop Color, Partial Color, Soft High-key Design Colour of product Black Technical details Self-timer Off / 10sec. / 2sec. / portrait1 / portrait2 Image processor Sorry, this data isn\u2032t available F-number (relative aperture) F3.2  - 6.4 Flash type Sorry, this data isn\u2032t available SteadyShot EIS (without GYRO) Shutter speed iAuto (2 - 1/1500) / Program Auto (1 - 1/1500) Display brightness control 5(Bright) / 4 / 3 / 2 / 1(Dark) Built-in WiFi ? Effective megapixels 20.1 MP Dimensions (WxHxD) 96.8 x 55.5 x 20.8 mm Battery life Up to 200 shots / 100 minutes Internal memory Approx. 29MB Other features Accessories included Rechargeable Battery Pack NP-BN;AC AdaptorAC-UB10C;Wrist Strap;Multi USB cable;Instruction Manual Recording format Still Images: JPEG (DCF, Exif, MPF Baseline) compliant, DPOF compatible Lens system Sony Lens Picture effects Still: Toy camera / Pop Color / Partial Color / Soft High-key, Movie: Toy camera, Pop Color, Partial Color, Soft High-key",
    "selftimer": "Off / 10sec. / 2sec. / portrait1 / portrait2",
    "recordingformat": "Still Images: JPEG (DCF, Exif, MPF Baseline) compliant, DPOF compatible",
    "flashexposurecompensation": "+/- 2.0 EV (1/3 EV steps)",
    "steadyshot": "EIS (without GYRO)",
    "dimensionswxhxd": "96.8 x 55.5 x 20.8 mm",
    "lenssystem": "Sony Lens",
    "category": "camera",
    "accessoriesincluded": "Rechargeable Battery Pack NP-BN;AC AdaptorAC-UB10C;Wrist Strap;Multi USB cable;Instruction Manual",
    "ean": "4905524978681",
    "camerashutterspeed": "iAuto (2 - 1/1500) / Program Auto (1 - 1/1500)",
    "sensortype": "1/2.3\" type (7.76mm) Super HAD CCD",
    "scenemodes": "Night Portrait, Landscape, Portrait, Beach, Snow",
    "dimensionswxdxh": "96.8 x 20.8 x 55.5 mm",
    "imageprocessor": "Sorry, this data isn\u2032t available",
    "shutterspeed": "iAuto (2 - 1/1500) / Program Auto (1 - 1/1500)",
    "manufacturer": "Sony",
    "internalmemory": "Approx. 29MB",
    "flashmodes": "Auto,Flash On,Flash Off Auto / Flash On / Slow Synchro / Flash Off / Advanced Flash",
    "builtinflash": "Yes",
    "colourofproduct": "Black",
    "compatiblememorycards": "Memory Stick\u2122 Duo;Memory Stick PRO Duo\u2122;Memory Stick PRO Duo\u2122(high speed);Memory Stick PRO HG Duo\u2122;Memory Stick XC-HG Duo\u2122;Memory Stick Micro;Memory Stick Micro (Mark2);SD Memory Card;SDHC Memory Card;SDXC Memory Card;microSD Memory Card;microSDHC Memory Card;microSDXC Memory Card",
    "opticalzoom": "5x",
    "lcdscreensize": "2.7",
    "reviews": "No",
    "shootingmodes": "Intelligent Auto, Panorama, Program Auto, Easy Shooting, Picture Effect, Scene Selection, Steady shot, Party",
    "viewfindertype": "?",
    "effectivemegapixels": "20.1 MP",
    "shortdescription": "Digital compact camera with 5x optical zoom, a 26mm wide-angle lens, a 20.1MP sensor, & SteadyShot",
    "whitebalance": "Auto, Daylight, Cloudy, Incandescent, Flash"
}