{
    "category": "camera",
    "internationalbuyerspleasenoteimportdutiesandbrokeragefeesarenotincludedintheitempriceorshippingchargesthesechargesarethebuyersresponsibilityallusbuyersmustincludetheirphoneintheirshippingdetailspleasecheckwithyourlocalcustomsofficetodeterminewhattheseadditionalcostswillbepriortobiddingbuyingwearenotabletoestimatequotethesechargesthesechargesarenormallycollectedbythedeliveringfreightshippingcompanyorwhenyoupicktheitemupwedonotmarkmerchandisevaluesbelowvalueormarkitemsasgiftsuscanadianandinternationalgovernmentregulationsprohibitsuchbehaviourthankyounoticepleasebeawaretaxeswillbechargedonallcanadianpurchasestaxesandratesarenonnegotiablerateswillbereflectiveofyourprovinceofresidenceandareoutlinedhereatsurplusbydesignitemssoldasisorworkingasisarenoteligibleforreturnsrefundsandorexchangesasisorworkingasisitemsarefinalsaleupondiscoveryofissueswithasisandworkingasisitemswestoptestingandissuesmaynotbelimitedtothoseoutlinedinourlistingwecannotguaranteethefullfunctionalityofallpartsonasisandworkingasisitemspleasebidcarefully": "SPECIFICATIONS: Type: Point & Shoot Brand: Canon Model: SX500 IS Megapixels: 16.0 MP Optical Zoom: 30x Colour: Black Additional Features: 16 effective megapixel,  1/2.3-inch CCD sensor 3-inch TFT color LCD with wide viewing angle DIGIC 4 image processor 720p HD video in stereo sound with a dedicated movie button 24mm wide-angle lens with powerful 30x optical zoom and optical image stabilizer 30x Optical Zoom and 24mm Wide-Angle lens with Optical Image Stabilizer MPN: SX500IS Country/Region of Manufacture: China Screen Size: 3.0\" INCLUDES: Battery Battery Charger Lens Cap Manual OEM Box Software Disc Strap (Neck or Wrist) USB Cable(s) EXCLUDES: ITEM DETAILS: This product has been used, we have tested all components and all of them work as they are supposed to. PHYSICAL CONDITION: Great There are no marks on the unit. FUNCTIONAL CONDITION: Used We have stress-tested all product components  and they work as they are supposed to. Product has been reset to near factory condition. 26974",
    "mpn": "SX500IS",
    "colour": "Black",
    "megapixels": "16.0 MP",
    "opticalzoom": "30x",
    "additionalfeatures": "16 effective megapixel,  1/2.3-inch CCD sensor 3-inch TFT color LCD with wide viewing angle DIGIC 4 image processor 720p HD video in stereo sound with a dedicated movie button 24mm wide-angle lens with powerful 30x optical zoom and optical image stabilizer 30x Optical Zoom and 24mm Wide-Angle lens with Optical Image Stabilizer",
    "screensize": "3.0\"",
    "wevemadeafewchangestobidding": "Were these helpful?",
    "model": "SX500 IS",
    "type": "Point & Shoot",
    "brand": "Canon",
    "countryregionofmanufacture": "China"
}