{
    "category": "camera",
    "internationalbuyerspleasenoteimportdutiesandbrokeragefeesarenotincludedintheitempriceorshippingchargesthesechargesarethebuyersresponsibilityallusbuyersmustincludetheirphoneintheirshippingdetailspleasecheckwithyourlocalcustomsofficetodeterminewhattheseadditionalcostswillbepriortobiddingbuyingwearenotabletoestimatequotethesechargesthesechargesarenormallycollectedbythedeliveringfreightshippingcompanyorwhenyoupicktheitemupwedonotmarkmerchandisevaluesbelowvalueormarkitemsasgiftsuscanadianandinternationalgovernmentregulationsprohibitsuchbehaviourthankyounoticepleasebeawaretaxeswillbechargedonallcanadianpurchasestaxesandratesarenonnegotiablerateswillbereflectiveofyourprovinceofresidenceandareoutlinedhereatsurplusbydesignitemssoldasisorworkingasisarenoteligibleforreturnsrefundsandorexchangesasisorworkingasisitemsarefinalsaleupondiscoveryofissueswithasisandworkingasisitemswestoptestingandissuesmaynotbelimitedtothoseoutlinedinourlistingwecannotguaranteethefullfunctionalityofallpartsonasisandworkingasisitemspleasebidcarefully": "SPECIFICATIONS: Type: Digital SLR Brand: Canon Model: EOS REBEL T2i Megapixels: 18.0 MP Lens: EF-S18-55mm IS Video Resolution: HD Colour: Black Additional Features: Sensor Resolution 18.0 Megapixel Optical Sensor Type CMOS Total Pixels 18, 700, 000 pixels pixels Effective Sensor Resolution 18, 000, 000 pixels pixels Optical Sensor Size 14.9 x 22.3mm Field of View Crop Factor 1.6 Sensor Dust Reduction Yes Sensor Features EOS Integrated Cleaning System Optical Zoom 7.5 x Image Processor DIGIC 4 Image Stabilizer optical Auto Focus TTL phase detection Auto Focus Points (Zones) Qty 9 Digital Video Format H.264 Image Recording Format RAW AV Interfaces composite video/audio Manufacturer Canon Country/Region of Manufacture: China Screen Size: 3\" INCLUDES: A/V Cable(s) Battery Battery Charger OEM Box Strap (Neck or Wrist) USB Cable(s) EXCLUDES: ITEM DETAILS: Although this unit has been previously used, it is in complete working order. Physically the unit is in great condition without any marks on it. PHYSICAL CONDITION: Great Physically the unit is in great condition without any marks on it. FUNCTIONAL CONDITION: Used Although this unit has been previously used, it is in complete working order. 29993",
    "videoresolution": "HD",
    "colour": "Black",
    "megapixels": "18.0 MP",
    "lens": "EF-S18-55mm IS",
    "additionalfeatures": "Sensor Resolution 18.0 Megapixel Optical Sensor Type CMOS Total Pixels 18, 700, 000 pixels pixels Effective Sensor Resolution 18, 000, 000 pixels pixels Optical Sensor Size 14.9 x 22.3mm Field of View Crop Factor 1.6 Sensor Dust Reduction Yes Sensor Features EOS Integrated Cleaning System Optical Zoom 7.5 x Image Processor DIGIC 4 Image Stabilizer optical Auto Focus TTL phase detection Auto Focus Points (Zones) Qty 9 Digital Video Format H.264 Image Recording Format RAW AV Interfaces composite video/audio Manufacturer Canon",
    "screensize": "3\"",
    "wevemadeafewchangestobidding": "Were these helpful?",
    "model": "EOS REBEL T2i",
    "type": "Digital SLR",
    "brand": "Canon",
    "countryregionofmanufacture": "China"
}