{
    "externalflashconnection": "Hot Shoe",
    "leftbardescstart": "Left Bar Desc //End !Right Bar Desc //Start !Nikon D5200 Red SLR Camera + 18-55 VR + 3 Lens Kit +16GB +Filters +Case +Battery Click an Image to Enlarge This item is 100% brand new. 52mm Professional HD 2x Telephoto lens + Carry Case fit Nikon Canon Sony Lens 52mm Wide-Angle 45x Digital High Definition Lens with Macro fit Nikon Canon Sony 3-Piece Filter Kit 16 GB Secure Digital (SD) Memory Card High Speed External USB All in One Memory Card Reader & Writer SD SDHC CF MS XD Deluxe Soft Medium SLR Camera Case / Bag fit Canon EOS, Nikon, Sony Alpha Camera Multi Memory Card Wallet Digital Auto Slave Flash with Bracket EN-EL14 Replacement Rechargeable Li-ion Battery f/ Nikon D3100 D3200 D5100 D5200 ENEL14 Camera Battery Quick Charger f/ Nikon D3100 D3200 D5100 D5200 P7700 P7000 Full Size 50-inch Tripod With Leveler 360 adjust & Carryng Case for SLR Cameras Mini Flexible Taple Top Travel Tripod  with Pocket clip Deluxe Screen Protector Pro Pack (Clear ) Deluxe Camera , Screen & Lens 5pc cleaning Kit Lens Cap Keeper Showcase your artistry Vari-angle display, built-in HDR, special effects and filters Creativity and flexibility were considered in every aspect of the D5200. It has a 921,000-dot Vari-angle display that lets you shoot from just about any position\u2014hold the camera overhead for a view above a crowd, at ground level for an interesting close-up of a flower, or just enjoy easier video recording and self portraits. For shots that have both very dark and very bright areas, D5200 includes built-in HDR (high-dynamic range). It takes two shots at different exposures and blends them into one amazing image. And an exciting collection of built-in effects and filters opens new possibilities for expression: isolate a single color, explore black & white, posterize, miniaturize\u2014the creative techniques pros spend years mastering are now conveniently at your command. Capture life's brilliance 24.1 MP DX-format CMOS sensor and renowned NIKKOR lenses Perhaps   your greatest inspiration will be the spectacular quality of every   photo and video you shoot with the D5200. Its highly sensitive   24.1-megapixel DX-format CMOS image sensor captures your vision with   lifelike brilliance\u2014marvel at the vibrant colors and razor-sharp detail,   even in low light. Legendary NIKKOR lenses, marvels of clarity and   quality, are the perfect companion for the D5200, drawing peak   performance out of the sensor. Our intelligent Scene Recognition System   compares your shot against an onboard database for optimum exposure, and   EXPEED 3, the processing power in our acclaimed D4, makes it all happen   in an instant. Share your creations in an instant Optional WU-1a Wireless Adapter for Wi-Fi photo sharing and camera control The   thrill of creating a great photo is topped only by the excitement of   sharing it. With the D5200, you'll have many great photos to share, so   we made it easy. Just add the optional WU-1a Wireless Mobile Adapter and   instantly transfer your shots to a smartphone or tablet via Wi-Fi. Then   share your favorites online as usual: email them, upload them to your   favorite social networks or photo-sharing site like Nikon's my   Picturetown. You can even use your smartphone or tablet as an external   \u201clive view\u201d monitor to see what the camera sees and fire the   shutter\u2014perfect for getting into photos instead of always shooting them. Note:   These functions require an Android or iOS device and Nikon's free   Wireless Mobile Adapter Utility app, available on Google Play and the   iTunes App Store. Take your vision to video High-quality Full HD (1080p) video recording capabilities The   D5200 includes Nikon's latest innovations for creating beautiful videos   with virtually no choppiness. D-Movie mode now features Full HD 1080p   60i for visibly smoother sequences, a first for Nikon HD-SLRs.   Full-time-servo AF (AF-F) and subject-tracking AF work together to keep   moving subjects sharp and in focus, and face-priority AF instantly   detects and tracks up to 35 faces in a scene. D5200 also has a built-in   stereo microphone that can be controlled automatically or manually via   20 incremental steps, another first for Nikon HD-SLRs. Whether you shoot   short clips or cinema-style movies, the D5200 makes it easy to take   your projects to the next level. Ultra-fast, accurate shooting No   matter where your subject is within the frame, the D5200\u2019s 39-point   wide-area autofocus system keeps it in focus so you can fire up to 5   fps. 3D Subject Tracking, powered by a 2,016-pixel RGB sensor, locks   onto your subject and tracks it with exceptional accuracy. Improvements   to the D5200's optical viewfinder make it easier to identify and capture   fast-moving subjects, even when panning the camera. Included 18-55mm NIKKOR lens When   asked why they choose Nikon gear, pros and serious shooters   consistently mention NIKKOR lenses among their reasons. The D5200 comes   equipped with the AF-S DX NIKKOR 18-55mm f/3.5-5.6G VR lens\u2014an excellent   lightweight, multipurpose lens for nearly all shooting situations and   an ideal match for the camera's DX-format sensor. Simple, intuitive operation You'll   be at home with the D5200 in no time. Using visual representations of   each setting to show you exactly what's changing with each adjustment, a   redesigned display groups your most frequently adjusted camera settings   for faster access. Long range remote control Whether   you're shooting a group portrait (that includes you) or an intricate   macro shot, a remote control is one of the most convenient accessories   you can have. The new WR-R10 and WR-T10 Wireless Remote Controllers   communicate using radio frequencies instead of Infrared, so you'll have   control even when there's no direct line of sight between devices. Imaging Camera Type Digital SLR with Interchangeable lenses Lens Mount Nikon F Camera Format DX / (1.5x Crop Factor) Pixels Actual: 24.71 Megapixel Effective: 24.1 Megapixel Max Resolution 6000 x 4000 Other Resolutions 4496 x 3000 2992 x 2000 Aspect Ratio 3:2 Sensor Type / Size CMOS, 23.5 x 15.6 mm File Formats Still Images: JPEG, RAW Movies: MPEG-4 AVC/H.264, MOV Audio: Linear PCM Bit Depth 14-bit Noise Reduction Yes Memory Card Type SD SDHC SDXC Focus Control Focus Type Auto & Manual Focus Mode Single-servo AF (S), Continuous-servo AF (C), Manual Focus (M) , Focus Lock AF Area Mode Autofocus Points 39 Viewfinder/Display Viewfinder Type Pentamirror Viewfinder Coverage 95% Viewfinder Magnification Approx. 0.78x Diopter Adjustment - 1.7 to +0.7 m Display Screen 3\"\u00a0Rear Screen\u00a0Swivel\u00a0\u00a0LCD (921,000) Screen Coverage 100% Angle of View 170.0\u00b0 Live View Yes Exposure Control ISO Sensitivity Auto, 100-6400 (Extended Mode: 100-25600) Shutter Type: Charge-coupled Electronic Speed: 30 - 1/4000\u00a0sec Remote Control ML-L3 (Optional) Metering Method 3D Color Matrix Metering, Center-weighted average metering, Spot metering Exposure Modes Modes: Aperture Priority, Auto, Flash Off, Manual, Program, Shutter Priority Compensation: -5 EV to +5 EV (in .3 or .5 EV steps) White Balance Modes Auto, Cloudy, Custom, Daylight, Flash, Fluorescent, Incandescent, Preset Manual, Shade Flash Flash Modes Auto Auto/Red-eye Reduction Fill-in Off Red-eye Reduction Second-curtain Sync Slow Sync Slow Sync./Red-eye Reduction Built-in Flash Yes Guide No. 39'\u00a0(11.89 m)\u00a0ISO100 Max Sync Speed Electronic Shutter: 1 / 200 sec Flash Compensation -3 EV to +1 EV (in .3 or .5 EV steps) Dedicated Flash System iTTL External Flash Connection Hot Shoe AV Recording Video Recording Yes, NTSC/PAL File Size 1920 x 1080i\u00a0(Full HD) 1920 x 1080p\u00a0(Full HD) 1280 x 720p\u00a0(HD) 640 x 424p\u00a0(SD) Frame Rate @ 1920 x 1080: 60 fps, 30 fps, 24 fps @ 1920 x 1080: 50 fps, 25 fps @ 1280 x 720: 60 fps, 50 fps @ 640 x 424: 30 fps, 25 fps Exposure Control Auto:\u00a0Shutter Speed, Aperture, ISO Manual:\u00a0Shutter Speed, ISO ISO Sensitivity Auto, 200 - 6400 Exposure Compensation -0 EV to +2 EV (in .3, .7 or 1 EV steps) Focus Auto Manual Continuous Auto Audio Recording With Video, Stereo, Via Optional External Mic Performance Continuous Shooting Up to 5 fps Self Timer 2 sec, 5 sec, 10 sec, 20 sec Number of Shots: 1-9 Interval Recording Yes Date & Time Stamp Yes Connectivity 1/8\" Microphone, HDMI C (Mini), USB 2.0 Wi-Fi Capable Yes Power Battery 1x  EN-EL14\u00a0 Rechargeable Lithium-Ion Battery Pack, 7.4VDC, 1030mAh Operating/Storage Temperature Operating 32 to 104\u00b0F (0 to 40\u00b0C) Humidity: 0 - 85% Physical Dimensions (WxHxD) 5.1 x 3.9 x 3.1\"\u00a0/\u00a0129.0 x 98.0 x 78.0 mm Weight 1.22 lb\u00a0/\u00a0555 g Kit Lens Focal Length 18 - 55 mm Comparable  DX  Focal Length: 27 - 82.5 mm Aperture Maximum: f/3.5 Minimum: f/22 Angle of View 76\u00b0 - 25.5\u00b0 Minimum Focus Distance 11.02\"\u00a0(28 cm) Magnification 0.31x Groups/Elements 5/7 Diaphragm Blades 7 Autofocus Yes Image Stabilization Yes Filter Thread Front: 52 mm Dimensions (DxL) Approx. 2.78 x 2.91\" (70.5 x 74 mm) Weight 7.23 oz (205 g) Nikon D5200 Digital SLR Camera with 18-55mm Lens (Red) 18-55mm f/3.5-5.6G VR AF-S DX Nikkor Lens EN-EL14 Lithium-Ion Battery (1030mAh) MH-24 Quick Charger for EN-EL14 Battery DK-5 Eyepiece Shield (Replacement) DK-20 Rubber Eyecup UC-E17 USB Cable EG-CP16 Nikon Audio/Video Cable AN-DC3 Camera Strap (Black) BF-1B Body Cap BS-1 Hot-Shoe Cover ViewNX 2 CD-ROM Professional HD 2x 52mm  telephoto lens When your camera can't get you close enough to capture the action in detail, this 2x Telephoto lens will bring the action to you! Optically multiplying the focal length of your camera's lens by a factor of 2, it more than doubles your telephoto magnification and detail without any pixelization. This is dramatically better than the \"Digital Zoom\" feature of many cameras where the magnification is obtained by merely enlarging the existing image, resulting in a loss of sharpness. This 2x telephoto attachment is perfect for all your long-distance imaging including sports, surveillance, nature and wildlife. You will also be able to utilize your camera's macro capability at over twice the usual distance, allowing for easier subject lighting with less shadows and intrusion.. High Speed Auto-Focus / Infrared Compatible (IR) Maximize day and night shots by providing maximum light and image transmission High Definition Optical Resolution Infrared Compatibility High Quality Precision Optics\u00a0Glass 45x 52mm Wide-Angle Digital High Definition Lens with Maro This 0.45x Wide Angle adapter will allow you to capture it all! This attachment more than doubles your camera's wide angle field-of-view . Scenic shots will be more panoramic and you'll be able to take outstanding group photos, even in tight places. In addition, the detachable Macro Lens enables you to photograph small objects up close. Great for jewelry, coins, stamps, flowers, and more. Even if your camera already has macro capability, this macro lens will get you even closer for truly amazing close-up photos. High speed Auto-Focus/ Infrared compatible 0.45x high definition wide angle lens with macro Marco 4:1 ratio Premium Rimmed Glass Include Protective Lens Case Digital Multi Coated 52mm Glass Filter Kit (UV-CPL-FLD) 3pc Filter kit The UV filter protects your camera's lens from scratches, dust,  dirt, moisture and fingerprints, while removing unwanted ultraviolet  light.The UV filter reduces blue haze caused by UV light by absorbing  71% of UV. The CPL filter deepens and  intensifies blue skies, achieves vibrant colors and reduces glare and  reflections from non-metallic objects & glass surfaces. Great for  video. The Fluorescent Light Correction Filter gives  you the prefect solution for shooting without a flash under a  fluorescent light.This filter gives true-to-life colors and pleasing  skin tones by removing the harsh yellow-green cast created by flouriest  lightning. Lens filter set is a must-have for photographers 52mm filters improve photographs by giving photographers control over light and allowing them to emphasize certain features Filter kit features UV, CPL, and FLD filters Set comes with hard carrying case and filters UV Protector Filter protected the lens from damage 16 GB Secure Digital (SD) Memory Card Get The Best SD Card for your product When getting an SD memory card there are hundreds of options for your item this can get confusing and costly \u00a0, When purchasing one of our handpicked memory cards for your item you receive a \u00a0Memory card at the highest quality. We go to every extent to handpick cards to provide \u00a0you as a bonus with your purchase that are not only guaranteed to work with your item but have the best performance with your item. This is a Onetime purchase that will help you capture a memory for a lifetime. Our memory card offers are High performance cards that are made reliable with long life spans \u00a0created to handle real life motions and real time transfers. There will be \u00a0no delay time in transferring information from your device to this card. Get Quality at the top of its class with\u00a0 SD memory. High Speed USB  All  One Card Reader Access a multitude of memory cards with this USB 2.0 All-in-One card reader! This portable memory card reader supports the most popular memory cards such as Compact Flash I/II, Secure Digital, SD, Memory Stick, Micro Drive and Multimedia Card. Deluxe Medium Camera and Video Bag The Deluxe Medium Camera and Video Bag  is the perfect compliment to hold all of your equipment. It features a shock proof nylon material and is water resistant. It has 1 removable divider, rubber feet, shoulder strap and a handle grip. Easy access closure flap Mesh pockets for accessory storage compartment with interior   mesh pockets for spare batteries, flash-memory cards, diskettes,cords,   cables and more Shoulder strap/1 re moveable divider ,rubber feet, shoulder strap and a handle grip nylon material and is water resistant Dimensions: Size: 10.8 x 6.5 x 7.5 inches Multi Memory Card Wallet Don\u00e2\u0080\u0099t lose your life\u00e2\u0080\u0099s Memories Memory Cards are the Insert that holds your life\u00e2\u0080\u0099s memory\u00e2\u0080\u0099s. A little card that easily lost but so important to you and your family. Always keep \u00a0your memory cards together at any cost. One lost card can lose decades of Memories. A memory card wallet is someplace for you to keep these memory\u00e2\u0080\u0099s together. Memory Card Wallet Keeps multiple memory cards protected and organized with this durable storage wallet. Sturdy memory card wallet case holds memory cards of any type securely, keeping them from contact with other accessories and makes them easily accessible in larger luggage bags. Features Memory Card Wallet Holds up to Multi \u00a0memory Cards (SD,CF,MS) 1 Year Limited Warranty Pro Digital Auto Slave Flash with Bracket for All SLR/DSLR Digital Camera & Camcorders Every photographer knows that a quality flash unit is an essential component to taking great pictures. Built-in flashes simply don't have enough power to properly illuminate most subjects, and typically produce harsh shadows, red-eye, and other undesirable effects. An external flash offers far more power and versatility , resulting in consistently better pictures! The Flash is a high-power flash unit that works seamlessly with a wide variety of camera models and provides exceptional light coverage , at a price that doesn't break the bank! The Flash features automatic exposure control , which syncs with your camera to provide just the right amount of light. The zoom function allows you to light subjects as far away as 50 feet , and the bounce head tilts and swivels to give you full creative control. EN-EL14 Replacement rechargeable Li-ion Battery Pack for Nikon D3100, D3200 & D5100 generic Compatible Li-ion Battery for Nikon EN-EL14 *Never run out of battery power when you're about to capture the perfect moment with this Nikon EN-EL14 compatible li-ion battery *Extra power for your digital video camera / camcorder *High capacity / rechargeable li-ion battery with premium cell *Type: Generic / aftermarket *Color: Black *Voltage: 7.4V *Replacement for the original Nikon EN-EL14 battery pack *Accessory ONLY, camera not included *Compatible with: Nikon Coolpix P7000 fit for Nikon Coolpix P7000, Coolpix P7100, Coolpix P7700, D3100, D3200, D5100 & D5200 * Quantity: 1 Battery Charger For Nikon EN-EL14 D3100 D3200 D5100 NOTE: For a success and safe charge to your battery, please make sure to line up the correct polarity (positive / negative) before inserting the battery onto the charger. A/C power supply input voltage: AC100V~240V. Output voltage: DC 8.4v 600mA. Charger Compatible with Nikon EN-EL14 battery. Accessory ONLY, camera not included. Full Size 50-inch Tripod With Leveler  360 adjust & Case Want to relax and take time shooting ? \u00a0Not worry about your shots being leveled ?\u00a0 adjust shots with a swivel instead of an adjustment ? If the answer to all these Questions are YES this is the item for you!! The 50-Inch Photo and Video tripod features a special carrying handle as well as a professional grip. With its \u00a0self leveling rubber leg tips \u00a0it offers a great floor grip for positioning and\u00a0 built in bubble leveler to give you a leveled shot. Capability\u00a0 for a 360 degree spin with its 3 way pan head doesn\u2019t hurt for convenience. There are bracing sections to adjust Tripod size and an additional Bonus of Tripod case. What else can you ask for as a free bonus with your purchase. Features Extends to 50 Inch \u00a0and under Non slip handle Mid level bracing system for adjustable sizes Bubble leveler Tripod fitted case Compact Carry Size Mini Flexible Taple Top Travel Tripod  with Pocket clip We realized to take a quick snap shot anywhere with your camera is a hassle to keep the camera sturdy with a table top tripod you can pull it out instantly or leave attached to your product for that Quick Snap and Go picture. A focused leveled camera\u00e2\u0080\u0099s shot and a wobbled shot is a big difference. This handy little tripod also can keep you in the picture. Place your camera on the Tripod and use the camera's self-timer, or a remote shutter release and you are in the picture for a great crisp-sharp shot. It easy to use and it is small enough to be ideal for carry in travel. Featuring an adjustable head and hard Flexible legs, this Tripod is an ideal accessory for photographers on the run. This lightweight, yet durable tripod stands at a height of up to 5\". Perfect for most digital, video and still cameras . Features Fits all 35mm Digital and Video camera with Tripod Socket Sturdy Ultra Compact Convenient Pocket Clip Travel Sized Deluxe Screen Protector Pro Pack (Clear ) Be safe scratches aren\u00e2\u0080\u0099t appealing . Save your screen it takes a second to apply and \u00a0will give you longer usage with your product Purchasing any item everyone always knows the LCD screen or glass screen is an imperative part of the electronic device always the first to get damaged. Easy solution for you !! Deluxe screen protectors are perfect for digital camera screens, cell phone screens and game player screens. screen protectors are included with \u00a0a squeegee to smooth them out and remove air bubbles. They can be cut down to size to fit any screen from 1\" to 5\". The extra clear layer on your device will not only protect it from Sun damage but will also protect from \u00a0Nail Scratches, finger smudges and many other contact damage to the screen point of your device. The Clear Quality Kit touch safes \u00a0your device. Universal Screen Guard The Greatest \u00a0Guarder for LCD Screens Multi 3pcs 3x5\u00e2\u0080\u0099\u00e2\u0080\u0099 Deluxe Screen Guard 1 Squeegee Card Deluxe Camera , Screen & Lens 5pc cleaning Kit Be clean Be Safe use something Approved for your product : It's obvious that the cleaner the lens and camera sensor, the sharper your pictures will be. Dirt, dust, and fingerprints will degrade the image quality of even the finest optics. However, it's equally important to avoid using incorrect cleaning materials which can permanently damage your photo equipment. The 5 Piece Camera and lens Cleaning Kit. consists of soft-texture fiber cloth, 5 cotton swabs, a bottle of cleaning fluid, soft lens tissue paper, and top quality blower brush. It easily fits in your camera bag so you can take it anywhere with you easily. It is perfect for an on-the-spot camera or lens cleaning and is approved by the manufacture to use with your item Screen Camera and Lens Cleaning kit Soft Texture Fiber Cloth Five Quality Cotton Swabs Top Quality cleaning Fluid Quality Blower and Brush Full Pack Lens Cleaning Tissue Lens Cap Keeper Keep Your lens safe its one of the Eyes of your purchase: Its always the little things that we lose that are a pain to replace . Why go through the hassle we found the perfect solution. Your cameras lens is a vital part of the pathway that captures an image from external reality\u00a0and stores it onto a memory card film device or other \u00a0Keeping this lens free of dust smudges and contact with other items is imperative. A Lens Cap holder as simple as it sounds is the solution. The \u00a0perfect way to keep track of your lens caps. A small button tapes onto the front of your lens cap and the elastic loop goes around the barrel of your lens so that your lens cap always remains attached, hanging from the lens. Lens caps can be pricey and hard to find\u00a0 with this you will \u00a0Never lose a lens cap again ! NIKON D5200R/18-55KIT10 We usually ship within 1-2 business days after receiving payment. Please be aware that weekends are not business days. At our discretion; large or expensive packages may receive a free upgrade to FedEx Ground with signature confirmation. \u00a0If this applies to you, please assure that your address is able to receive FedEx packages & that an adult is available to sign for & accept the shipment. All express methods of shipment as long as verified take 1 business day to ship We ship everything professionally in our state of the art warehouse boxed and shipped with perfection. \"Free Shipping\" applies to orders shipped within the USA (48 states) We do not ship to APO or FPO address Orders shipping to PR/HI/AK Will have an additional shipping charge and a longer process time to ship order Credit Cards: We can only ship to addresses that are noted with your credit card account. We may contact you for additional verification after you check out. PayPal: We prefer to ship to confirmed addresses. We may contact you for additional verification for payments made by unconfirmed PayPal addresses. We do not accept PayPal payments from accounts outside the USA and Canada. \u00b7 When necessary, we may contact you via Direct Message or telephone to obtain additional verification. We offer our customer's a 14 day return for replacement policy if item is defective other then that all sales are final . A Return Merchandise Authorization (RMA) number must be obtained for any return. To obtain an RMA number, please call us toll free at 877-254-6155 Returned packages without proper RMA demarcations will be refused by our warehouse and returned to you. Customers who refuse a delivery, will be subject to charges for return shipping to us. If the item was advertised as Free Shipping, then we will charge the amount of shipping as determined by Our Shipping Station . Defective Item An item that was discovered to be defective upon receipt can be replaced with the same model only. Return Shipping Return shipping cost (the cost to send an item back to our store) is like or comparable to your cost of driving to any store for returning an item, which is not reimbursable. Therefore, we do not reimburse any return shipping cost. If an item you received is defective, we will certainly replace the item with a new one, however we do not cover or reimburse the shipping cost for returning defective merchandise back to our store. We will ship the replacement product to you at our cost, and use every good measure to ensure that the replacement order is processed quickly. Replacement We will send a product replacement after the authorized return has completed our receiving/inspection process. The replacement will ship within four business days following our receipt of your return. Please allow additional processing time after Holidays. Although it is our goal to ship a replacement as quickly as possible, we do not send replacements before we receive and inspect the returned merchandise. All items are sold with Manufacture Warranty so there is another avenue for assistance. All returns must be packed with all contents which came with the original package including, cables, software, plastic and cardboard packaging, and unregistered warranty card. This return policy excludes Televisions, Home Theater Projectors or any Home audio Product . For further questions please call us toll free at 877-254-6155 We encourage any questions or concerns you may have for us, but we request that all communication be done through eBay messages only or over the phone. Our dedicated customer support team is available Monday-Friday 10AM - 6PM (EST) TOLL FREE: +1-877-254-6155 LOCAL: +1-908-967-5155 Click here to send us your email inquiry now through eBay messages.Right Bar Desc //End !",
    "exposurecontrol": "Auto:\u00a0Shutter Speed, Aperture, ISO Manual:\u00a0Shutter Speed, ISO",
    "weight": "7.23 oz (205 g)",
    "maxsyncspeed": "Electronic Shutter: 1 / 200 sec",
    "battery": "1x  EN-EL14\u00a0 Rechargeable Lithium-Ion Battery Pack, 7.4VDC, 1030mAh",
    "exposuremodes": "Modes: Aperture Priority, Auto, Flash Off, Manual, Program, Shutter Priority Compensation: -5 EV to +5 EV (in .3 or .5 EV steps)",
    "isosensitivity": "Auto, 200 - 6400",
    "noisereduction": "Yes",
    "memorycardtype": "SD SDHC SDXC",
    "diaphragmblades": "7",
    "imagestabilization": "Yes",
    "dimensionsdxl": "Approx. 2.78 x 2.91\" (70.5 x 74 mm)",
    "shutter": "Type: Charge-coupled Electronic Speed: 30 - 1/4000\u00a0sec",
    "aspectratio": "3:2",
    "viewfindermagnification": "Approx. 0.78x",
    "maxvideoresolution": "6000 x 4000",
    "category": "camera",
    "datetimestamp": "Yes",
    "minimumfocusdistance": "11.02\"\u00a0(28 cm)",
    "continuousshooting": "Up to 5 fps",
    "focustype": "Auto & Manual",
    "bitdepth": "14-bit",
    "operatingstoragetemperature": "Operating 32 to 104\u00b0F (0 to 40\u00b0C) Humidity: 0 - 85%",
    "lensforsd": "AF-S DX G VR 18-55mm",
    "pixels": "Actual: 24.71 Megapixel Effective: 24.1 Megapixel",
    "selftimer": "2 sec, 5 sec, 10 sec, 20 sec Number of Shots: 1-9",
    "liveview": "Yes",
    "magnification": "0.31x",
    "guideno": "39'\u00a0(11.89 m)\u00a0ISO100",
    "filesize": "1920 x 1080i\u00a0(Full HD) 1920 x 1080p\u00a0(Full HD) 1280 x 720p\u00a0(HD) 640 x 424p\u00a0(SD)",
    "aperture": "Maximum: f/3.5 Minimum: f/22",
    "dimensionswxhxd": "5.1 x 3.9 x 3.1\"\u00a0/\u00a0129.0 x 98.0 x 78.0 mm",
    "autofocus": "Yes",
    "viewfindercoverage": "95%",
    "meteringmethod": "3D Color Matrix Metering, Center-weighted average metering, Spot metering",
    "audiorecording": "With Video, Stereo, Via Optional External Mic",
    "whitebalancemodes": "Auto, Cloudy, Custom, Daylight, Flash, Fluorescent, Incandescent, Preset Manual, Shade",
    "flashcompensation": "-3 EV to +1 EV (in .3 or .5 EV steps)",
    "focallength": "18 - 55 mm Comparable  DX  Focal Length: 27 - 82.5 mm",
    "brand": "Nikon",
    "sensortypesize": "CMOS, 23.5 x 15.6 mm",
    "filterthread": "Front: 52 mm",
    "focus": "Auto Manual Continuous Auto",
    "connectivity": "1/8\" Microphone, HDMI C (Mini), USB 2.0",
    "storecategoriesstorehomeipadtabletipadsipadminiipodmp3playersdigitalslrcamerascanonnikonsonydigitalpscameraspanasonicdigitalcameralensescanonnikonsonydigitalcameraaccessoriescameracasesmemorycardmemorycardreadermemorycardholderbatterieschargerwarrantyserviceplanslensfiltertripodsmonopodslenshoodcapslearningdvdotherstarterkitipodmp3accessoriesspeakers": "Nikon D5200 Red SLR Camera + 18-55 VR + 3 Lens Kit +16GB +Filters +Case +Battery Click an Image to Enlarge This item is 100% brand new. 52mm Professional HD 2x Telephoto lens + Carry Case fit Nikon Canon Sony Lens 52mm Wide-Angle 45x Digital High Definition Lens with Macro fit Nikon Canon Sony 3-Piece Filter Kit 16 GB Secure Digital (SD) Memory Card High Speed External USB All in One Memory Card Reader & Writer SD SDHC CF MS XD Deluxe Soft Medium SLR Camera Case / Bag fit Canon EOS, Nikon, Sony Alpha Camera Multi Memory Card Wallet Digital Auto Slave Flash with Bracket EN-EL14 Replacement Rechargeable Li-ion Battery f/ Nikon D3100 D3200 D5100 D5200 ENEL14 Camera Battery Quick Charger f/ Nikon D3100 D3200 D5100 D5200 P7700 P7000 Full Size 50-inch Tripod With Leveler 360 adjust & Carryng Case for SLR Cameras Mini Flexible Taple Top Travel Tripod  with Pocket clip Deluxe Screen Protector Pro Pack (Clear ) Deluxe Camera , Screen & Lens 5pc cleaning Kit Lens Cap Keeper Showcase your artistry Vari-angle display, built-in HDR, special effects and filters Creativity and flexibility were considered in every aspect of the D5200. It has a 921,000-dot Vari-angle display that lets you shoot from just about any position\u2014hold the camera overhead for a view above a crowd, at ground level for an interesting close-up of a flower, or just enjoy easier video recording and self portraits. For shots that have both very dark and very bright areas, D5200 includes built-in HDR (high-dynamic range). It takes two shots at different exposures and blends them into one amazing image. And an exciting collection of built-in effects and filters opens new possibilities for expression: isolate a single color, explore black & white, posterize, miniaturize\u2014the creative techniques pros spend years mastering are now conveniently at your command. Capture life's brilliance 24.1 MP DX-format CMOS sensor and renowned NIKKOR lenses Perhaps   your greatest inspiration will be the spectacular quality of every   photo and video you shoot with the D5200. Its highly sensitive   24.1-megapixel DX-format CMOS image sensor captures your vision with   lifelike brilliance\u2014marvel at the vibrant colors and razor-sharp detail,   even in low light. Legendary NIKKOR lenses, marvels of clarity and   quality, are the perfect companion for the D5200, drawing peak   performance out of the sensor. Our intelligent Scene Recognition System   compares your shot against an onboard database for optimum exposure, and   EXPEED 3, the processing power in our acclaimed D4, makes it all happen   in an instant. Share your creations in an instant Optional WU-1a Wireless Adapter for Wi-Fi photo sharing and camera control The   thrill of creating a great photo is topped only by the excitement of   sharing it. With the D5200, you'll have many great photos to share, so   we made it easy. Just add the optional WU-1a Wireless Mobile Adapter and   instantly transfer your shots to a smartphone or tablet via Wi-Fi. Then   share your favorites online as usual: email them, upload them to your   favorite social networks or photo-sharing site like Nikon's my   Picturetown. You can even use your smartphone or tablet as an external   \u201clive view\u201d monitor to see what the camera sees and fire the   shutter\u2014perfect for getting into photos instead of always shooting them. Note:   These functions require an Android or iOS device and Nikon's free   Wireless Mobile Adapter Utility app, available on Google Play and the   iTunes App Store. Take your vision to video High-quality Full HD (1080p) video recording capabilities The   D5200 includes Nikon's latest innovations for creating beautiful videos   with virtually no choppiness. D-Movie mode now features Full HD 1080p   60i for visibly smoother sequences, a first for Nikon HD-SLRs.   Full-time-servo AF (AF-F) and subject-tracking AF work together to keep   moving subjects sharp and in focus, and face-priority AF instantly   detects and tracks up to 35 faces in a scene. D5200 also has a built-in   stereo microphone that can be controlled automatically or manually via   20 incremental steps, another first for Nikon HD-SLRs. Whether you shoot   short clips or cinema-style movies, the D5200 makes it easy to take   your projects to the next level. Ultra-fast, accurate shooting No   matter where your subject is within the frame, the D5200\u2019s 39-point   wide-area autofocus system keeps it in focus so you can fire up to 5   fps. 3D Subject Tracking, powered by a 2,016-pixel RGB sensor, locks   onto your subject and tracks it with exceptional accuracy. Improvements   to the D5200's optical viewfinder make it easier to identify and capture   fast-moving subjects, even when panning the camera. Included 18-55mm NIKKOR lens When   asked why they choose Nikon gear, pros and serious shooters   consistently mention NIKKOR lenses among their reasons. The D5200 comes   equipped with the AF-S DX NIKKOR 18-55mm f/3.5-5.6G VR lens\u2014an excellent   lightweight, multipurpose lens for nearly all shooting situations and   an ideal match for the camera's DX-format sensor. Simple, intuitive operation You'll   be at home with the D5200 in no time. Using visual representations of   each setting to show you exactly what's changing with each adjustment, a   redesigned display groups your most frequently adjusted camera settings   for faster access. Long range remote control Whether   you're shooting a group portrait (that includes you) or an intricate   macro shot, a remote control is one of the most convenient accessories   you can have. The new WR-R10 and WR-T10 Wireless Remote Controllers   communicate using radio frequencies instead of Infrared, so you'll have   control even when there's no direct line of sight between devices. Imaging Camera Type Digital SLR with Interchangeable lenses Lens Mount Nikon F Camera Format DX / (1.5x Crop Factor) Pixels Actual: 24.71 Megapixel Effective: 24.1 Megapixel Max Resolution 6000 x 4000 Other Resolutions 4496 x 3000 2992 x 2000 Aspect Ratio 3:2 Sensor Type / Size CMOS, 23.5 x 15.6 mm File Formats Still Images: JPEG, RAW Movies: MPEG-4 AVC/H.264, MOV Audio: Linear PCM Bit Depth 14-bit Noise Reduction Yes Memory Card Type SD SDHC SDXC Focus Control Focus Type Auto & Manual Focus Mode Single-servo AF (S), Continuous-servo AF (C), Manual Focus (M) , Focus Lock AF Area Mode Autofocus Points 39 Viewfinder/Display Viewfinder Type Pentamirror Viewfinder Coverage 95% Viewfinder Magnification Approx. 0.78x Diopter Adjustment - 1.7 to +0.7 m Display Screen 3\"\u00a0Rear Screen\u00a0Swivel\u00a0\u00a0LCD (921,000) Screen Coverage 100% Angle of View 170.0\u00b0 Live View Yes Exposure Control ISO Sensitivity Auto, 100-6400 (Extended Mode: 100-25600) Shutter Type: Charge-coupled Electronic Speed: 30 - 1/4000\u00a0sec Remote Control ML-L3 (Optional) Metering Method 3D Color Matrix Metering, Center-weighted average metering, Spot metering Exposure Modes Modes: Aperture Priority, Auto, Flash Off, Manual, Program, Shutter Priority Compensation: -5 EV to +5 EV (in .3 or .5 EV steps) White Balance Modes Auto, Cloudy, Custom, Daylight, Flash, Fluorescent, Incandescent, Preset Manual, Shade Flash Flash Modes Auto Auto/Red-eye Reduction Fill-in Off Red-eye Reduction Second-curtain Sync Slow Sync Slow Sync./Red-eye Reduction Built-in Flash Yes Guide No. 39'\u00a0(11.89 m)\u00a0ISO100 Max Sync Speed Electronic Shutter: 1 / 200 sec Flash Compensation -3 EV to +1 EV (in .3 or .5 EV steps) Dedicated Flash System iTTL External Flash Connection Hot Shoe AV Recording Video Recording Yes, NTSC/PAL File Size 1920 x 1080i\u00a0(Full HD) 1920 x 1080p\u00a0(Full HD) 1280 x 720p\u00a0(HD) 640 x 424p\u00a0(SD) Frame Rate @ 1920 x 1080: 60 fps, 30 fps, 24 fps @ 1920 x 1080: 50 fps, 25 fps @ 1280 x 720: 60 fps, 50 fps @ 640 x 424: 30 fps, 25 fps Exposure Control Auto:\u00a0Shutter Speed, Aperture, ISO Manual:\u00a0Shutter Speed, ISO ISO Sensitivity Auto, 200 - 6400 Exposure Compensation -0 EV to +2 EV (in .3, .7 or 1 EV steps) Focus Auto Manual Continuous Auto Audio Recording With Video, Stereo, Via Optional External Mic Performance Continuous Shooting Up to 5 fps Self Timer 2 sec, 5 sec, 10 sec, 20 sec Number of Shots: 1-9 Interval Recording Yes Date & Time Stamp Yes Connectivity 1/8\" Microphone, HDMI C (Mini), USB 2.0 Wi-Fi Capable Yes Power Battery 1x  EN-EL14\u00a0 Rechargeable Lithium-Ion Battery Pack, 7.4VDC, 1030mAh Operating/Storage Temperature Operating 32 to 104\u00b0F (0 to 40\u00b0C) Humidity: 0 - 85% Physical Dimensions (WxHxD) 5.1 x 3.9 x 3.1\"\u00a0/\u00a0129.0 x 98.0 x 78.0 mm Weight 1.22 lb\u00a0/\u00a0555 g Kit Lens Focal Length 18 - 55 mm Comparable  DX  Focal Length: 27 - 82.5 mm Aperture Maximum: f/3.5 Minimum: f/22 Angle of View 76\u00b0 - 25.5\u00b0 Minimum Focus Distance 11.02\"\u00a0(28 cm) Magnification 0.31x Groups/Elements 5/7 Diaphragm Blades 7 Autofocus Yes Image Stabilization Yes Filter Thread Front: 52 mm Dimensions (DxL) Approx. 2.78 x 2.91\" (70.5 x 74 mm) Weight 7.23 oz (205 g) Nikon D5200 Digital SLR Camera with 18-55mm Lens (Red) 18-55mm f/3.5-5.6G VR AF-S DX Nikkor Lens EN-EL14 Lithium-Ion Battery (1030mAh) MH-24 Quick Charger for EN-EL14 Battery DK-5 Eyepiece Shield (Replacement) DK-20 Rubber Eyecup UC-E17 USB Cable EG-CP16 Nikon Audio/Video Cable AN-DC3 Camera Strap (Black) BF-1B Body Cap BS-1 Hot-Shoe Cover ViewNX 2 CD-ROM Professional HD 2x 52mm  telephoto lens When your camera can't get you close enough to capture the action in detail, this 2x Telephoto lens will bring the action to you! Optically multiplying the focal length of your camera's lens by a factor of 2, it more than doubles your telephoto magnification and detail without any pixelization. This is dramatically better than the \"Digital Zoom\" feature of many cameras where the magnification is obtained by merely enlarging the existing image, resulting in a loss of sharpness. This 2x telephoto attachment is perfect for all your long-distance imaging including sports, surveillance, nature and wildlife. You will also be able to utilize your camera's macro capability at over twice the usual distance, allowing for easier subject lighting with less shadows and intrusion.. High Speed Auto-Focus / Infrared Compatible (IR) Maximize day and night shots by providing maximum light and image transmission High Definition Optical Resolution Infrared Compatibility High Quality Precision Optics\u00a0Glass 45x 52mm Wide-Angle Digital High Definition Lens with Maro This 0.45x Wide Angle adapter will allow you to capture it all! This attachment more than doubles your camera's wide angle field-of-view . Scenic shots will be more panoramic and you'll be able to take outstanding group photos, even in tight places. In addition, the detachable Macro Lens enables you to photograph small objects up close. Great for jewelry, coins, stamps, flowers, and more. Even if your camera already has macro capability, this macro lens will get you even closer for truly amazing close-up photos. High speed Auto-Focus/ Infrared compatible 0.45x high definition wide angle lens with macro Marco 4:1 ratio Premium Rimmed Glass Include Protective Lens Case Digital Multi Coated 52mm Glass Filter Kit (UV-CPL-FLD) 3pc Filter kit The UV filter protects your camera's lens from scratches, dust,  dirt, moisture and fingerprints, while removing unwanted ultraviolet  light.The UV filter reduces blue haze caused by UV light by absorbing  71% of UV. The CPL filter deepens and  intensifies blue skies, achieves vibrant colors and reduces glare and  reflections from non-metallic objects & glass surfaces. Great for  video. The Fluorescent Light Correction Filter gives  you the prefect solution for shooting without a flash under a  fluorescent light.This filter gives true-to-life colors and pleasing  skin tones by removing the harsh yellow-green cast created by flouriest  lightning. Lens filter set is a must-have for photographers 52mm filters improve photographs by giving photographers control over light and allowing them to emphasize certain features Filter kit features UV, CPL, and FLD filters Set comes with hard carrying case and filters UV Protector Filter protected the lens from damage 16 GB Secure Digital (SD) Memory Card Get The Best SD Card for your product When getting an SD memory card there are hundreds of options for your item this can get confusing and costly \u00a0, When purchasing one of our handpicked memory cards for your item you receive a \u00a0Memory card at the highest quality. We go to every extent to handpick cards to provide \u00a0you as a bonus with your purchase that are not only guaranteed to work with your item but have the best performance with your item. This is a Onetime purchase that will help you capture a memory for a lifetime. Our memory card offers are High performance cards that are made reliable with long life spans \u00a0created to handle real life motions and real time transfers. There will be \u00a0no delay time in transferring information from your device to this card. Get Quality at the top of its class with\u00a0 SD memory. High Speed USB  All  One Card Reader Access a multitude of memory cards with this USB 2.0 All-in-One card reader! This portable memory card reader supports the most popular memory cards such as Compact Flash I/II, Secure Digital, SD, Memory Stick, Micro Drive and Multimedia Card. Deluxe Medium Camera and Video Bag The Deluxe Medium Camera and Video Bag  is the perfect compliment to hold all of your equipment. It features a shock proof nylon material and is water resistant. It has 1 removable divider, rubber feet, shoulder strap and a handle grip. Easy access closure flap Mesh pockets for accessory storage compartment with interior   mesh pockets for spare batteries, flash-memory cards, diskettes,cords,   cables and more Shoulder strap/1 re moveable divider ,rubber feet, shoulder strap and a handle grip nylon material and is water resistant Dimensions: Size: 10.8 x 6.5 x 7.5 inches Multi Memory Card Wallet Don\u00e2\u0080\u0099t lose your life\u00e2\u0080\u0099s Memories Memory Cards are the Insert that holds your life\u00e2\u0080\u0099s memory\u00e2\u0080\u0099s. A little card that easily lost but so important to you and your family. Always keep \u00a0your memory cards together at any cost. One lost card can lose decades of Memories. A memory card wallet is someplace for you to keep these memory\u00e2\u0080\u0099s together. Memory Card Wallet Keeps multiple memory cards protected and organized with this durable storage wallet. Sturdy memory card wallet case holds memory cards of any type securely, keeping them from contact with other accessories and makes them easily accessible in larger luggage bags. Features Memory Card Wallet Holds up to Multi \u00a0memory Cards (SD,CF,MS) 1 Year Limited Warranty Pro Digital Auto Slave Flash with Bracket for All SLR/DSLR Digital Camera & Camcorders Every photographer knows that a quality flash unit is an essential component to taking great pictures. Built-in flashes simply don't have enough power to properly illuminate most subjects, and typically produce harsh shadows, red-eye, and other undesirable effects. An external flash offers far more power and versatility , resulting in consistently better pictures! The Flash is a high-power flash unit that works seamlessly with a wide variety of camera models and provides exceptional light coverage , at a price that doesn't break the bank! The Flash features automatic exposure control , which syncs with your camera to provide just the right amount of light. The zoom function allows you to light subjects as far away as 50 feet , and the bounce head tilts and swivels to give you full creative control. EN-EL14 Replacement rechargeable Li-ion Battery Pack for Nikon D3100, D3200 & D5100 generic Compatible Li-ion Battery for Nikon EN-EL14 *Never run out of battery power when you're about to capture the perfect moment with this Nikon EN-EL14 compatible li-ion battery *Extra power for your digital video camera / camcorder *High capacity / rechargeable li-ion battery with premium cell *Type: Generic / aftermarket *Color: Black *Voltage: 7.4V *Replacement for the original Nikon EN-EL14 battery pack *Accessory ONLY, camera not included *Compatible with: Nikon Coolpix P7000 fit for Nikon Coolpix P7000, Coolpix P7100, Coolpix P7700, D3100, D3200, D5100 & D5200 * Quantity: 1 Battery Charger For Nikon EN-EL14 D3100 D3200 D5100 NOTE: For a success and safe charge to your battery, please make sure to line up the correct polarity (positive / negative) before inserting the battery onto the charger. A/C power supply input voltage: AC100V~240V. Output voltage: DC 8.4v 600mA. Charger Compatible with Nikon EN-EL14 battery. Accessory ONLY, camera not included. Full Size 50-inch Tripod With Leveler  360 adjust & Case Want to relax and take time shooting ? \u00a0Not worry about your shots being leveled ?\u00a0 adjust shots with a swivel instead of an adjustment ? If the answer to all these Questions are YES this is the item for you!! The 50-Inch Photo and Video tripod features a special carrying handle as well as a professional grip. With its \u00a0self leveling rubber leg tips \u00a0it offers a great floor grip for positioning and\u00a0 built in bubble leveler to give you a leveled shot. Capability\u00a0 for a 360 degree spin with its 3 way pan head doesn\u2019t hurt for convenience. There are bracing sections to adjust Tripod size and an additional Bonus of Tripod case. What else can you ask for as a free bonus with your purchase. Features Extends to 50 Inch \u00a0and under Non slip handle Mid level bracing system for adjustable sizes Bubble leveler Tripod fitted case Compact Carry Size Mini Flexible Taple Top Travel Tripod  with Pocket clip We realized to take a quick snap shot anywhere with your camera is a hassle to keep the camera sturdy with a table top tripod you can pull it out instantly or leave attached to your product for that Quick Snap and Go picture. A focused leveled camera\u00e2\u0080\u0099s shot and a wobbled shot is a big difference. This handy little tripod also can keep you in the picture. Place your camera on the Tripod and use the camera's self-timer, or a remote shutter release and you are in the picture for a great crisp-sharp shot. It easy to use and it is small enough to be ideal for carry in travel. Featuring an adjustable head and hard Flexible legs, this Tripod is an ideal accessory for photographers on the run. This lightweight, yet durable tripod stands at a height of up to 5\". Perfect for most digital, video and still cameras . Features Fits all 35mm Digital and Video camera with Tripod Socket Sturdy Ultra Compact Convenient Pocket Clip Travel Sized Deluxe Screen Protector Pro Pack (Clear ) Be safe scratches aren\u00e2\u0080\u0099t appealing . Save your screen it takes a second to apply and \u00a0will give you longer usage with your product Purchasing any item everyone always knows the LCD screen or glass screen is an imperative part of the electronic device always the first to get damaged. Easy solution for you !! Deluxe screen protectors are perfect for digital camera screens, cell phone screens and game player screens. screen protectors are included with \u00a0a squeegee to smooth them out and remove air bubbles. They can be cut down to size to fit any screen from 1\" to 5\". The extra clear layer on your device will not only protect it from Sun damage but will also protect from \u00a0Nail Scratches, finger smudges and many other contact damage to the screen point of your device. The Clear Quality Kit touch safes \u00a0your device. Universal Screen Guard The Greatest \u00a0Guarder for LCD Screens Multi 3pcs 3x5\u00e2\u0080\u0099\u00e2\u0080\u0099 Deluxe Screen Guard 1 Squeegee Card Deluxe Camera , Screen & Lens 5pc cleaning Kit Be clean Be Safe use something Approved for your product : It's obvious that the cleaner the lens and camera sensor, the sharper your pictures will be. Dirt, dust, and fingerprints will degrade the image quality of even the finest optics. However, it's equally important to avoid using incorrect cleaning materials which can permanently damage your photo equipment. The 5 Piece Camera and lens Cleaning Kit. consists of soft-texture fiber cloth, 5 cotton swabs, a bottle of cleaning fluid, soft lens tissue paper, and top quality blower brush. It easily fits in your camera bag so you can take it anywhere with you easily. It is perfect for an on-the-spot camera or lens cleaning and is approved by the manufacture to use with your item Screen Camera and Lens Cleaning kit Soft Texture Fiber Cloth Five Quality Cotton Swabs Top Quality cleaning Fluid Quality Blower and Brush Full Pack Lens Cleaning Tissue Lens Cap Keeper Keep Your lens safe its one of the Eyes of your purchase: Its always the little things that we lose that are a pain to replace . Why go through the hassle we found the perfect solution. Your cameras lens is a vital part of the pathway that captures an image from external reality\u00a0and stores it onto a memory card film device or other \u00a0Keeping this lens free of dust smudges and contact with other items is imperative. A Lens Cap holder as simple as it sounds is the solution. The \u00a0perfect way to keep track of your lens caps. A small button tapes onto the front of your lens cap and the elastic loop goes around the barrel of your lens so that your lens cap always remains attached, hanging from the lens. Lens caps can be pricey and hard to find\u00a0 with this you will \u00a0Never lose a lens cap again ! NIKON D5200R/18-55KIT10 We usually ship within 1-2 business days after receiving payment. Please be aware that weekends are not business days. At our discretion; large or expensive packages may receive a free upgrade to FedEx Ground with signature confirmation. \u00a0If this applies to you, please assure that your address is able to receive FedEx packages & that an adult is available to sign for & accept the shipment. All express methods of shipment as long as verified take 1 business day to ship We ship everything professionally in our state of the art warehouse boxed and shipped with perfection. \"Free Shipping\" applies to orders shipped within the USA (48 states) We do not ship to APO or FPO address Orders shipping to PR/HI/AK Will have an additional shipping charge and a longer process time to ship order Credit Cards: We can only ship to addresses that are noted with your credit card account. We may contact you for additional verification after you check out. PayPal: We prefer to ship to confirmed addresses. We may contact you for additional verification for payments made by unconfirmed PayPal addresses. We do not accept PayPal payments from accounts outside the USA and Canada. \u00b7 When necessary, we may contact you via Direct Message or telephone to obtain additional verification. We offer our customer's a 14 day return for replacement policy if item is defective other then that all sales are final . A Return Merchandise Authorization (RMA) number must be obtained for any return. To obtain an RMA number, please call us toll free at 877-254-6155 Returned packages without proper RMA demarcations will be refused by our warehouse and returned to you. Customers who refuse a delivery, will be subject to charges for return shipping to us. If the item was advertised as Free Shipping, then we will charge the amount of shipping as determined by Our Shipping Station . Defective Item An item that was discovered to be defective upon receipt can be replaced with the same model only. Return Shipping Return shipping cost (the cost to send an item back to our store) is like or comparable to your cost of driving to any store for returning an item, which is not reimbursable. Therefore, we do not reimburse any return shipping cost. If an item you received is defective, we will certainly replace the item with a new one, however we do not cover or reimburse the shipping cost for returning defective merchandise back to our store. We will ship the replacement product to you at our cost, and use every good measure to ensure that the replacement order is processed quickly. Replacement We will send a product replacement after the authorized return has completed our receiving/inspection process. The replacement will ship within four business days following our receipt of your return. Please allow additional processing time after Holidays. Although it is our goal to ship a replacement as quickly as possible, we do not send replacements before we receive and inspect the returned merchandise. All items are sold with Manufacture Warranty so there is another avenue for assistance. All returns must be packed with all contents which came with the original package including, cables, software, plastic and cardboard packaging, and unregistered warranty card. This return policy excludes Televisions, Home Theater Projectors or any Home audio Product . For further questions please call us toll free at 877-254-6155 We encourage any questions or concerns you may have for us, but we request that all communication be done through eBay messages only or over the phone. Our dedicated customer support team is available Monday-Friday 10AM - 6PM (EST) TOLL FREE: +1-877-254-6155 LOCAL: +1-908-967-5155 Click here to send us your email inquiry now through eBay messages.",
    "cameraformat": "DX / (1.5x Crop Factor)",
    "groupselements": "5/7",
    "angleofview": "76\u00b0 - 25.5\u00b0",
    "maxresolution": "6000 x 4000",
    "wevemadeafewchangestobidding": "Were these helpful?",
    "videorecording": "Yes, NTSC/PAL",
    "lensmount": "Nikon F",
    "displayscreen": "3\"\u00a0Rear Screen\u00a0Swivel\u00a0\u00a0LCD (921,000)",
    "fileformats": "Still Images: JPEG, RAW Movies: MPEG-4 AVC/H.264, MOV Audio: Linear PCM",
    "intervalrecording": "Yes",
    "otherresolutions": "4496 x 3000 2992 x 2000",
    "remotecontrol": "ML-L3 (Optional)",
    "diopteradjustment": "- 1.7 to +0.7 m",
    "displaytype": "LCD",
    "builtinflash": "Yes",
    "cameratype": "Digital SLR with Interchangeable lenses",
    "framerate": "@ 1920 x 1080: 60 fps, 30 fps, 24 fps @ 1920 x 1080: 50 fps, 25 fps @ 1280 x 720: 60 fps, 50 fps @ 640 x 424: 30 fps, 25 fps",
    "dedicatedflashsystem": "iTTL",
    "displaysize": "3\"",
    "exposurecompensation": "-0 EV to +2 EV (in .3, .7 or 1 EV steps)",
    "focusmode": "Single-servo AF (S), Continuous-servo AF (C), Manual Focus (M) , Focus Lock AF Area Mode",
    "flashmodes": "Auto Auto/Red-eye Reduction Fill-in Off Red-eye Reduction Second-curtain Sync Slow Sync Slow Sync./Red-eye Reduction",
    "sensorresolution": "24.1 MP",
    "viewfindertype": "Pentamirror",
    "autofocuspoints": "39",
    "mpn": "1507",
    "supportedflashmemory": "SD Memory Card, SDHC Memory Card, SDXC Card",
    "model": "D5200",
    "screencoverage": "100%",
    "wificapable": "Yes",
    "screensize": "3\""
}