{
    "category": "camera",
    "internationalbuyerspleasenoteimportdutiesandbrokeragefeesarenotincludedintheitempriceorshippingchargesthesechargesarethebuyersresponsibilityallusbuyersmustincludetheirphoneintheirshippingdetailspleasecheckwithyourlocalcustomsofficetodeterminewhattheseadditionalcostswillbepriortobiddingbuyingwearenotabletoestimatequotethesechargesthesechargesarenormallycollectedbythedeliveringfreightshippingcompanyorwhenyoupicktheitemupwedonotmarkmerchandisevaluesbelowvalueormarkitemsasgiftsuscanadianandinternationalgovernmentregulationsprohibitsuchbehaviourthankyounoticepleasebeawaretaxeswillbechargedonallcanadianpurchasestaxesandratesarenonnegotiablerateswillbereflectiveofyourprovinceofresidenceandareoutlinedhereatsurplusbydesignitemssoldasisorworkingasisarenoteligibleforreturnsrefundsandorexchangesasisorworkingasisitemsarefinalsaleupondiscoveryofissueswithasisandworkingasisitemswestoptestingandissuesmaynotbelimitedtothoseoutlinedinourlistingwecannotguaranteethefullfunctionalityofallpartsonasisandworkingasisitemspleasebidcarefully": "SPECIFICATIONS: Type: Digital Still Camera Brand: Sony Model: Cyber-Shot DSC-W560 Megapixels: 14.1 Lens: Carl Zeiss Vario-Tessar Wide-Angle Video Resolution: 720p Optical Zoom: 4x Colour: Red Additional Features: Capture your videos in HD Movie mode (720p) Capture breathtaking images in Sweep Panorama Mode 14.1 megapixel 3-inch LCD screen for easy viewing Optical SteadyShot image stabilization reduces blur iAuto mode automatically optimizes camera settings Country/Region of Manufacture: China Screen Size: 3.0-inch INCLUDES: A/V Cable(s) Battery Manual OEM Box Software Disc Strap (Neck or Wrist) USB Cable(s) EXCLUDES: ITEM DETAILS: This used product has been tested showing that all components work as they are supposed to. PHYSICAL CONDITION: Great There are no marks on the unit. FUNCTIONAL CONDITION: Used This used product has been tested showing that all components work as they are supposed to. 38094",
    "videoresolution": "720p",
    "colour": "Red",
    "megapixels": "14.1",
    "opticalzoom": "4x",
    "lens": "Carl Zeiss Vario-Tessar Wide-Angle",
    "additionalfeatures": "Capture your videos in HD Movie mode (720p) Capture breathtaking images in Sweep Panorama Mode 14.1 megapixel 3-inch LCD screen for easy viewing Optical SteadyShot image stabilization reduces blur iAuto mode automatically optimizes camera settings",
    "screensize": "3.0-inch",
    "wevemadeafewchangestobidding": "Were these helpful?",
    "model": "Cyber-Shot DSC-W560",
    "type": "Digital Still Camera",
    "brand": "Sony",
    "countryregionofmanufacture": "China"
}