{
    "warranty": "6 Months",
    "color": "Black",
    "powersource": "Li-ion battery",
    "mainfeatures": "This digital camera is designed with small size and it is easy to carry The HD digital video camcorder has 2.0 inch LCD screen, you can see the images clearly The digital video camera capture vibrant still photos that are as clear as your own memories Compact, attractive and easy to use, this best digital video camcorder can go with you anywhere The HD digital video camera can be used as PC camera, voice and picture recorder, music player and video camcorder",
    "size": "102 x 54 x 31mm / 4.0 x 2.1 x 1.2in",
    "category": "camera",
    "flash": "Auto/off",
    "selftimer": "10s/20s delay",
    "osdlanguage": "Chinese / English / Japan / France / Germany / Spain / Italy / Russian",
    "internalspeaker": "Yes",
    "shootingmode": "Single shot / self-time shot / sequence",
    "imageresolution": "640 x 480Pixels, 1600 x 1200Pixels, 2592 x 1944Pixels, 4032 x 3024 Pixels",
    "specifications": "Color: Black Max. Resolution: 12Megapixel (interpolation) Image Sensor: 5.0Megapixel CMOS Image Resolution: 640 x 480Pixels, 1600 x 1200Pixels, 2592 x 1944Pixels, 4032 x 3024 Pixels Internal Memory: 16MB Flash, External: MMC or SD card (Extend up to 8GB) Resolution: 4032 x 3024 Pixels(12.0MP), 2592 x 1944 Pixels(5.0MP), 2048 x 1536 Pixels(3.0MP), 1600 x 1200 Pixels(2.0MP), 1280 x 960 Pixels(1.3MP), 640 x 480 Pixels(0.3MP) Video Recording mode: 640 x 480pixels, Frame rate:30fps or 15fps, -320x240pixels, Frame rate: 30fps or 15fps PC Camera: Yes MP3 Player: Yes, MP3 MP4 Player: Yes, AVI Audio Record: Yes, WAV Digital Zoom: 8X File Formats: JPEG /AVI /MP3 / WAV LCD Viewfinder: 2.0\u2033TFT LCD(270 degree eddy) Exposure: Auto or EV +2.0 ~ -2.0 White Balance: Automatic / daylight / tungsten / fluorescent / cloudy Flash: Auto/off Internal Microphone: Yes Internal Speaker: Yes Direct Print System: compatible with \"PictBridge\" system Scenery: Auto / scenery / flower / night scene Shooting Mode: Single shot / self-time shot / sequence Self-Timer: 10s/20s delay Interface: USB1.1 / TV out/MP3 Lens: Fixed f=9.3mm , F=2.8 Focus Range: 20cm ~30cm(macro) / 1.2m~\u221e(normal) Shutter Speed: 1/30second OSD Language: Chinese / English / Japan / France / Germany / Spain / Italy / Russian Power Source: Li-ion battery Automatic Energy Saving: 60s, 120s, always on Size: 102 x 54 x 31mm / 4.0 x 2.1 x 1.2in System Requirement for PC: Windows 98 / 2000 / ME / XP",
    "lens": "Fixed f=9.3mm , F=2.8",
    "focusrange": "20cm ~30cm(macro) / 1.2m~\u221e(normal)",
    "packagecontents": "1 x Digital Camcorder 1 x Li-ion Battery 1 x USB / AV Cable 1 x Earphone 1 x AC Adapter 1 x Pouch 1 x User Manual",
    "interface": "USB1.1 / TV out/MP3",
    "shutterspeed": "1/30second",
    "fileformats": "JPEG /AVI /MP3 / WAV",
    "exposure": "Auto or EV +2.0 ~ -2.0",
    "internalmemory": "16MB Flash, External",
    "imagesensor": "5.0Megapixel CMOS",
    "internalmicrophone": "Yes",
    "digitalzoom": "8X",
    "pccamera": "Yes",
    "maxresolution": "12Megapixel (interpolation)",
    "resolution": "4032 x 3024 Pixels(12.0MP), 2592 x 1944 Pixels(5.0MP), 2048 x 1536 Pixels(3.0MP), 1600 x 1200 Pixels(2.0MP), 1280 x 960 Pixels(1.3MP), 640 x 480 Pixels(0.3MP)",
    "whitebalance": "Automatic / daylight / tungsten / fluorescent / cloudy"
}