{
    "warranty": "12 Months",
    "pictbridge": "Yes",
    "weight": "247.6g(without batteries)",
    "battery": "NP-40 Lithium",
    "scene": "Auto/Landscape/Portrait/Night Portrait/Beach/Sport/Dinner/High",
    "externalmemory": "SD card(Up to 64GB)",
    "label13": "Sensitivity",
    "mainfeatures": "5 Mega pixels CMOS sensor 1080P HD digital camera 12x Optical zoom SD card(Up to 64GB) 2.7\" TFT screen, can rotate a maximum of 270 degree",
    "category": "camera",
    "microphone": "Yes",
    "flash": "2 x LED",
    "selftimer": "5S/10S",
    "speaker": "Yes",
    "workingtemperature": "0 - 40 \u2103",
    "imageresolution": "3264x2448\uff088MP\uff094",
    "specifications": "Image Sensor: 5 Mega Pixels CMOS Sensor Image Resolution: 3264x2448\uff088MP\uff094:3 2592x1944 (5MP) 4:3 2048x1536 (3MP) 4:3 640x480 (VGA) 4:3 3648x2048\uff087MP\uff0916:9 HD 1920x1080 (2MP) 16:9 HD Video Resolution: 1440x1080(Full HD: 15fps) 1280x720(HD: 15/30fps )  640x480 (VGA: 15/30/60fps)  320x240(QVGA: 15/30/60fps) LCD Display: 2.7\u2033TFT (270\u00b0) Internal Memory: 64MB DDR2(Buffer) External Memory: SD card(Up to 64GB) Lens: 12x Optical Zoom Digital Zoom: N/A Shutter Speed: 1/7.5~1/2000S Exposure: EV-2.0/EV-1.5/EV-1.0/0/EV1.0/EV1.5/EV 2.0 ISO: ISOAUTO/100/200/400/800/1600/3200 White Balance: Auto/Daylight/Cloudy/Tungsten/Fluorescent Scene: Auto/Landscape/Portrait/Night Portrait/Beach/Sport/Dinner/High Sensitivity Self-timer: 5S/10S File Format: JPEG ( Still Image),MOV ( Video) Anti-shake: Yes Flash: 2 x LED TV out: Yes Microphone: Yes Speaker: Yes PictBridge: Yes MSDC: Yes Interface: USB 2.0 High Speed System Requirements: Windows XP/VISTA,MAC Continue Shot: Yes Smile Capture: Yes Face Detaction: Yes Battery: NP-40 Lithium Working Temperature: 0 - 40 \u2103 Weight: 247.6g(without batteries) Dimension: 12.3 x 6.2 x 7.3cm",
    "whitebalance": "Auto/Daylight/Cloudy/Tungsten/Fluorescent",
    "lens": "12x Optical Zoom",
    "interface": "USB 2.0 High Speed",
    "shutterspeed": "1/7.5~1/2000S",
    "exposure": "EV-2.0/EV-1.5/EV-1.0/0/EV1.0/EV1.5/EV 2.0",
    "internalmemory": "64MB DDR2(Buffer)",
    "tvout": "Yes",
    "imagesensor": "5 Mega Pixels CMOS Sensor",
    "antishake": "Yes",
    "dimension": "12.3 x 6.2 x 7.3cm",
    "digitalzoom": "N/A",
    "iso": "ISOAUTO/100/200/400/800/1600/3200",
    "systemrequirements": "Windows XP/VISTA,MAC",
    "packagecontents": "1 x Digital camcorder HD-150Z 1 x HDMI cable 1 x USB cable 1 x AC cable 1 x Li-ion battery 1 x CD-Rom 1 x pouch 1 x User Manual",
    "lcddisplay": "2.7\u2033TFT (270\u00b0)",
    "videoresolution": "1440x1080(Full HD",
    "fileformat": "JPEG ( Still Image),MOV ( Video)"
}