{
    "warranty": "12 Months",
    "pictbridge": "Yes",
    "weight": "110g(without battery)",
    "battery": "Built-in Battery",
    "externalmemory": "Support up to 32GB SD Card (SD card is not included)",
    "mainfeatures": "DC-720 high definition digital camera Features face tracking technology, blur reduction and digital image stabilization for crisp, detailed shots of friends and family up to 14.0MP 2.7\" TFT LCD CMOS HD display 14.0 Mega pixels effectual resolution 4x digital zoom 3x optical zoom 9.1MP CMOS sensor Built-in rechargeable lithium battery With flash light Exterior SD/SDHC card up to 32GB (not included) Light weight, exquisite size and fashionable design A great travel assistant",
    "dimension": "100*60*20mm",
    "category": "camera",
    "flash": "Auto/Force/Off/Red Eye Reduction",
    "selftimer": "10s/5s/2s",
    "color": "Silver",
    "imageresolution": "4416 x 3312 (14M), 4000 x 3000 (12M), 3648 x 2736 (10M), 3456 x 2448 (8M), 3648 x 2048 (7M) HD, 2592 x 1944 (5M), 2048 x 1536 (3M), 1920 x 1080 (HD 2M), 640 x 480 (VGA)",
    "specifications": "Model: DC-720 Color: Silver Image Sensor: 9.1MP Mage Pixels CMOS Sensor LCD Display: 2.7\" TFT LCD Zoom: 3X optical zoom; 4X digital zoom Video Resolution: 320 x 240, 640 x 480,1280x720 Image Resolution: 4416 x 3312 (14M), 4000 x 3000 (12M), 3648 x 2736 (10M), 3456 x 2448 (8M), 3648 x 2048 (7M) HD, 2592 x 1944 (5M), 2048 x 1536 (3M), 1920 x 1080 (HD 2M), 640 x 480 (VGA) System Requirement: Windows7 /XP/ Vista / OS X (10.5X or later) External Memory: Support up to 32GB SD Card (SD card is not included) Lens: Optical Zoom Lens File Format: JPEG(Still Image) & AVI(Video) Battery: Built-in Battery Flash: Auto/Force/Off/Red Eye Reduction Exposure: +/-3.0 EV Self-Timer: 10s/5s/2s White balance: Auto, Daylight, Cloudy, Incandescent, Fluorescent Scene Modes: Auto, Night Portrait, Night Scenery, Portrait, Scenery, Sport, Party, Beach, High Sensitivity Connection Interface: USB 2.0 ISO: Auto/100/200/400 Anti-Shake: Yes Face Detecting: Yes PictBridge: Yes Dimension: 100*60*20mm Weight: 110g(without battery)",
    "systemrequirement": "Windows7 /XP/ Vista / OS X (10.5X or later)",
    "lens": "Optical Zoom Lens",
    "scenemodes": "Auto, Night Portrait, Night Scenery, Portrait, Scenery, Sport, Party, Beach, High Sensitivity",
    "exposure": "+/-3.0 EV",
    "imagesensor": "9.1MP Mage Pixels CMOS Sensor",
    "antishake": "Yes",
    "zoom": "3X optical zoom; 4X digital zoom",
    "whitebalance": "Auto, Daylight, Cloudy, Incandescent, Fluorescent",
    "iso": "Auto/100/200/400",
    "packagecontents": "1 x Digital camera 1 x USB cable 1 x Lithium-ion battery 1 x Battery charger 1 x CD disk 1 x User manual",
    "model": "DC-720",
    "lcddisplay": "2.7\" TFT LCD",
    "videoresolution": "320 x 240, 640 x 480,1280x720",
    "fileformat": "JPEG(Still Image) & AVI(Video)"
}