{
    "warranty": "12 Months",
    "weight": "110g(without battery)",
    "battery": "lithium-ion",
    "label13": "Support SDHC card (up tp 32GB)",
    "mainfeatures": "1/2.3\" 1400MP CCD(SONY)COMS 3 Inch TFT LCD touch display 4x Optical zoom Support optical image stabilization, face tracking, smile detection",
    "category": "camera",
    "tvoutput": "NTSC / PAL",
    "system": "Win 2000, Win XP, Vista,Win7",
    "connector": "USB 2.0",
    "focuslength": "Micropur",
    "specifications": "Sence: 1/2.3\" 1400MP CCD(SONY)COMS Static pixels: 12 M : 4000 x 3000 / ( 3 : 2 ): 4000 x 2672 / 8M : 3264x2448 / 5M : 2592 x 1944 / 3M : 2048 x 1536 / HD: 1920 x 1080 / VGA : 640 x 480 Dynamic pixels: 1280x780(16:9), 640x480, 320x240, 640x480(web) LCD display: 3 Inch LCD display touch screem Focus length: Micropur:12cm~100cm; Nomal: 12cm~limitless(W) & 70cm~limitless(T) ISO/ASA sensitivity: Auto/ 50 / 100 / 200 / 400 / 800 / 1600 / 3200(within 3 meter) Storage medium: 32MB flash memory Zoom: 4x Optical zoom Shutter speed: Electronic shutter(speed:1/2000~15mins) Exposure: -2.0EV ~ +2.0EV Flashlight(pic): Auto/open/close/bloodshot eyes/slow sync White balance: Auto/sunny/cloudy/fluorescent/tungsten Memory,External: SD card (up to 4GB) Support SDHC card (up tp 32GB) TV output: NTSC / PAL Autodyne: 2/10 / SEC/continuous shooting exposure/fast/around even pat Connector: USB 2.0 Support form: JPEG / AVI / WAV Language: English / Japanese / Indonesian /Malay / Thai / Spanish / Italian / Arabic / Russian / Portuguese / The Czech / Hungary / polish / Turkey... 31 countries Battery: lithium-ion Dimensions: 91.57 x 57.77 x 18.23 mm Weight: 110g(without battery) System: Win 2000, Win XP, Vista,Win7",
    "dimensions": "91.57 x 57.77 x 18.23 mm",
    "shutterspeed": "Electronic shutter(speed",
    "exposure": "-2.0EV ~ +2.0EV",
    "storagemedium": "32MB flash memory",
    "language": "English / Japanese / Indonesian /Malay / Thai / Spanish / Italian / Arabic / Russian / Portuguese / The Czech / Hungary / polish / Turkey... 31 countries",
    "zoom": "4x Optical zoom",
    "packagecontents": "1 x Digital camera 1 x USB cable 1 x Lithium-ion battery 1 x Battery charger 1 x CD disk 1 x User manul",
    "lcddisplay": "3 Inch LCD display touch screem",
    "whitebalance": "Auto/sunny/cloudy/fluorescent/tungsten"
}