{
    "externalflashconnection": "Hot Shoe",
    "leftbardescstart": "8035B002 Browse Our Store Store                                                                                                                         home Point & Shoot Cameras Pro. SLR Cameras Digital Camera Lenses Camcorders Projectors GPS Navigation Home audio Blu-ray / DVD PlayersLeft Bar Desc //End !Right Bar Desc //Start !Canon EOS 6D Digital SLR Camera (Body) Brand New, Never Been Used 20.2MP Full-Frame CMOS Sensor 3.0\" Clear View High Resolution LCD DIGIC 5+ Image Processor Built-In Wi-Fi and GPS Connectivity Full HD 1080p with Manual Controls 11-Point AF with Center Cross-Type Point 63-Zone Dual Layer Metering Sensor Extended ISO Range of 50-102400 Up to 4.5 Full Resolution FPS Built-In HDR and Multiple Exposure Modes Canon             EOS 6D DSLR Camera (Body Only) Eyecup Eb R-F-3 Camera Cover Wide Neck Strap EW-EOS 6D LC-E6 Charger for LP-E6 Battery Pack LP-E6 Rechargeable Lithium-Ion Battery Pack (7.2V, 1800mAh) AVC-DC400ST Stereo AV Cable IFC-200U USB Interface Cable - 6.9' (1.9 m) NOTE: This camera may be an imported model. It is completely  identical to the USA model and is produced by the same factories. This  product comes set in English as a standard, with USA connections. Imported models do not carry a USA manufacturer  warranty card. Your purchase is covered by a BigValueInc store warranty  which covers you for 1 Year. Please view below in our terms and  conditions for details. NOTE: Please note that we purchase DSLR camera kits and separate the camera body and lens for individual sale. If purchasing a DSLR camera kit or camera body, you may receive a box that once contained a lens. The box may specify a lens is included; this lens will not be included unless it was part of your purchase. If purchasing a DSLR lens, it may come in a white box if it was separated from a DSLR camera body and lens kit. Rest assured all items are brand new and untouched during the separation process. Canon EOS 6D Digital SLR Camera (B ... SPECIFICATIONS Imaging Camera Type Digital SLR with Interchangeable lenses Lens Mount Canon EF Camera Format Full-Frame Pixels Actual: 20.6 MegapixelEffective: 20.2 Megapixel Max Resolution 20MP: 5472 x 3648 at 3:2 Other Resolutions 11MP: 4104 x 2736 at 3:2 8.9MP: 3648 x 2432 at 3:2 5MP: 2736 x 1824 at 3:2 2.5MP: 1920 x 1280 at 3:2 0.35MP: 720 x 480 at 3:2 Sensor Type / Size CMOS, 35.8 x 23.9 mm File Formats Still Images: JPEG, RAW Movies: MOV, MPEG-4 AVC/H.264 Audio: Linear PCM Bit Depth 14-bit Noise Reduction Yes Memory Card Type SD SDHC SDXC Focus Control Focus Type Auto & Manual Focus Mode Single-servo AF (S), Continuous-servo AF (C), Manual Focus (M) Autofocus Points 11 Viewfinder/Display Viewfinder Type Pentaprism Viewfinder Coverage 97% Viewfinder Magnification Approx. 0.71x Diopter Adjustment - 3.0 to +1.0 m Display Screen 3\"\u00a0Rear Screen\u00a0\u00a0\u00a0LCD (1,040,000) Screen Coverage 100% Live View Yes Exposure Control ISO Sensitivity 100-25600 (Extended Mode: 50-102400) Shutter Type: Electronic & MechanicalSpeed: 30 - 1/4000\u00a0sec Metering Method Average metering, Center-weighted average metering, Spot metering Exposure Modes Modes: Aperture Priority, Manual, Program, Program Shift, Programmed Auto, Shutter PriorityCompensation: -5 EV to +5 EV White Balance Modes Auto, Cloudy, Custom, Daylight, Flash, Fluorescent (White), Manual, Shade, Tungsten Flash Built-in Flash No Max Sync Speed 1 / 180 sec Flash Compensation -3 EV to +3 EV (in 1/3 or 1/2 EV steps) Dedicated Flash System eTTL External Flash Connection Hot Shoe AV Recording Video Recording Yes, NTSC/PAL File Size 1920 x 1080p\u00a0(Full HD) 1280 x 720p\u00a0(HD) 640 x 480p\u00a0(SD) Frame Rate at 1920 x 1080: 30 fps, 24 fps, 25 fps at 1280 x 720: 60 fps, 50 fps at 640 x 480: 30 fps, 25 fps Exposure Control Manual:\u00a0Shutter Speed, Aperture, ISO Auto ISO Sensitivity 100 - 12800, Expandable to 25600 Exposure Compensation -3 EV to +3 EV (in 1/3 EV steps) Focus Auto Manual Continuous Shooting Time 1920 x 1080 (with 8GB memory card)at 30 fps\u00a0IPB: 32 min. (235 MB / min.) / ALL-I: 11 min. (685 MB / min.) 1280 x 720 (with 8GB memory card)at 60 fps\u00a0IPB: 37 min. (205 MB / min.) / ALL-I: 12 min. (610 MB / min.) 640 x 480 (with 8GB memory card)at 30 fps\u00a0ALL-I: 97 min. (78 MB / min.) Audio Recording Optional External Mic: With Video, Stereo, Performance Continuous Shooting Up to 4.5 fps Start-up Time 0.1 Seconds Self Timer 2 sec, 10 sec Connectivity AV Output HDMI C (Mini) USB 2.0 Wi-Fi Capable Yes 1 Please Note: Built-in close Power Battery 1x  LP-E6\u00a0 Rechargeable Lithium-Ion Battery Pack, 7.2VDC, 1800mAh Operating/Storage Temperature Operating 32 to 104\u00c2\u00b0F (0 to 40\u00c2\u00b0C)Humidity: 0 - 85% Physical Dimensions (WxHxD) 5.7 x 4.4 x 2.8\"\u00a0/\u00a014.5 x 11.2 x 7.1 cm Weight 27.16 oz\u00a0/\u00a0770 g Back to Top CANEOS6DDD TERMS AND CONDITIONS We usually ship within 1 business day after receiving payment. Please be aware                                                                                                                                         that weekends are not business days. All express methods of shipment still may require 1 day of processing time. Canadians and international buyers are responsible for all duties, customs                                                                                                                                         charges, and/or brokerage fees. We cannot ship as a gift, or claim as lower value. New Jersey buyers are responsible for applicable sales tax. We ship everything professionally in our state of the art warehouse. All products we sell are brand new and includes warranty coverage unless clearly                                                                                                                                         specified on the listing. \"Free Shipping\" applies to orders shipped within the continental                                                                                                                                         US. Domestic orders ship FedEx, UPS, and USPS. Our packages are insured and may require a signature. In accordance with PayPal                                                                                                                                         and eBay policies, we cannot reroute your package to a different address or hold                                                                                                                                         your shipment at the local hub for pick up, your order must be delivered to the                                                                                                                                         confirmed PayPal address received with your purchase. We cannot change your address                                                                                                                                         before the order ships. Please do not submit handling instructions in the notes                                                                                                                                         of your order requesting special handling, a specific courier or a change of address,                                                                                                                                         as we will be unable to meet these requests. We reserve the right to cancel any orders addressed to P.O. boxes, freight                                                                                                                                         forwarders, or resellers. We do not offer price protection if the price of an item                                                                                                                                         that you purchased. Prices do change frequently. We reserve the right to cancel orders placed without a registered eBay or                                                                                                                                         PayPal account. Orders placed by eBay guest checkout require additional verification                                                                                                                                         and may be delayed. Orders placed without a registered PayPal account cannot be                                                                                                                                         accepted and will be cancelled and refunded upon receipt. We offer a customer 30 day return privilege policy. A Return Merchandise Authorization                                                                                                                                             (RMA) number must be obtained for any return. To obtain an RMA number, please call                                                                                                                                             us toll free at 866-673-7187 . Returned packages without proper RMA demarcations will be refused by our warehouse                                                                                                                                             and returned to you. Customers who refuse a delivery, will be subject to charges                                                                                                                                             for return shipping to us. If the item was advertised as Free Shipping, then we                                                                                                                                             will charge the amount of shipping as determined by the FedEx shipping calculator. Some returns are subject to a restocking fee. The restocking percentage will depend                                                                                                                                             on the condition of the returned product. Defective products are eligible for exchange,                                                                                                                                             and no restock fee will apply. All returns must be packed with all contents which came with the original package                                                                                                                                             including, cables, software, plastic and cardboard packaging, and unregistered warranty                                                                                                                                             card. This return policy excludes Televisions and Home Theater Projectors. For further                                                                                                                                             questions please call us toll free at 866-673-7187 . You can also                                                                                                                                             contact us using the contact form found                                                                                                                                                  here. Return shipping costs are not reimbursable. International Customers: All electronic products are packaged for sale in the US with US Voltage. View International Policies Back to Top CONTACT INFO AND STORE HOURS ANY QUESTIONS? CALL US TOLL FREE: +1-866-673-7187 STORE HOURS: Monday - Friday 10:00AM to 3:00PM EST Email us anytime! Back to TopRight Bar Desc //End !",
    "exposurecontrol": "Manual:\u00a0Shutter Speed, Aperture, ISO Auto",
    "weight": "27.16 oz\u00a0/\u00a0770 g",
    "maxsyncspeed": "1 / 180 sec",
    "battery": "1x  LP-E6\u00a0 Rechargeable Lithium-Ion Battery Pack, 7.2VDC, 1800mAh",
    "exposuremodes": "Modes: Aperture Priority, Manual, Program, Program Shift, Programmed Auto, Shutter PriorityCompensation: -5 EV to +5 EV",
    "isosensitivity": "100 - 12800, Expandable to 25600",
    "noisereduction": "Yes",
    "focus": "Auto Manual",
    "memorycardtype": "SD SDHC SDXC",
    "viewfindercoverage": "97%",
    "category": "camera",
    "shutter": "Type: Electronic & MechanicalSpeed: 30 - 1/4000\u00a0sec",
    "startuptime": "0.1 Seconds",
    "continuousshooting": "Up to 4.5 fps",
    "operatingstoragetemperature": "Operating 32 to 104\u00c2\u00b0F (0 to 40\u00c2\u00b0C)Humidity: 0 - 85%",
    "pixels": "Actual: 20.6 MegapixelEffective: 20.2 Megapixel",
    "selftimer": "2 sec, 10 sec",
    "liveview": "Yes",
    "filesize": "1920 x 1080p\u00a0(Full HD) 1280 x 720p\u00a0(HD) 640 x 480p\u00a0(SD)",
    "videorecording": "Yes, NTSC/PAL",
    "dimensionswxhxd": "5.7 x 4.4 x 2.8\"\u00a0/\u00a014.5 x 11.2 x 7.1 cm",
    "otherresolutions": "11MP: 4104 x 2736 at 3:2 8.9MP: 3648 x 2432 at 3:2 5MP: 2736 x 1824 at 3:2 2.5MP: 1920 x 1280 at 3:2 0.35MP: 720 x 480 at 3:2",
    "meteringmethod": "Average metering, Center-weighted average metering, Spot metering",
    "audiorecording": "Optional External Mic: With Video, Stereo,",
    "whitebalancemodes": "Auto, Cloudy, Custom, Daylight, Flash, Fluorescent (White), Manual, Shade, Tungsten",
    "sensortypesize": "CMOS, 35.8 x 23.9 mm",
    "viewfindermagnification": "Approx. 0.71x",
    "flashcompensation": "-3 EV to +3 EV (in 1/3 or 1/2 EV steps)",
    "continuousshootingtime": "1920 x 1080 (with 8GB memory card)at 30 fps\u00a0IPB: 32 min. (235 MB / min.) / ALL-I: 11 min. (685 MB / min.) 1280 x 720 (with 8GB memory card)at 60 fps\u00a0IPB: 37 min. (205 MB / min.) / ALL-I: 12 min. (610 MB / min.) 640 x 480 (with 8GB memory card)at 30 fps\u00a0ALL-I: 97 min. (78 MB / min.)",
    "connectivity": "AV Output HDMI C (Mini) USB 2.0",
    "cameraformat": "Full-Frame",
    "focustype": "Auto & Manual",
    "bitdepth": "14-bit",
    "lensmount": "Canon EF",
    "displayscreen": "3\"\u00a0Rear Screen\u00a0\u00a0\u00a0LCD (1,040,000)",
    "fileformats": "Still Images: JPEG, RAW Movies: MOV, MPEG-4 AVC/H.264 Audio: Linear PCM",
    "diopteradjustment": "- 3.0 to +1.0 m",
    "exposurecompensation": "-3 EV to +3 EV (in 1/3 EV steps)",
    "builtinflash": "No",
    "cameratype": "Digital SLR with Interchangeable lenses",
    "framerate": "at 1920 x 1080: 30 fps, 24 fps, 25 fps at 1280 x 720: 60 fps, 50 fps at 640 x 480: 30 fps, 25 fps",
    "focusmode": "Single-servo AF (S), Continuous-servo AF (C), Manual Focus (M)",
    "viewfindertype": "Pentaprism",
    "autofocuspoints": "11",
    "dedicatedflashsystem": "eTTL",
    "maxresolution": "20MP: 5472 x 3648 at 3:2",
    "screencoverage": "100%",
    "wificapable": "Yes 1 Please Note: Built-in close"
}