{
    "category": "camera",
    "internationalbuyerspleasenoteimportdutiesandbrokeragefeesarenotincludedintheitempriceorshippingchargesthesechargesarethebuyersresponsibilityallusbuyersmustincludetheirphoneintheirshippingdetailspleasecheckwithyourlocalcustomsofficetodeterminewhattheseadditionalcostswillbepriortobiddingbuyingwearenotabletoestimatequotethesechargesthesechargesarenormallycollectedbythedeliveringfreightshippingcompanyorwhenyoupicktheitemupwedonotmarkmerchandisevaluesbelowvalueormarkitemsasgiftsuscanadianandinternationalgovernmentregulationsprohibitsuchbehaviourthankyounoticepleasebeawaretaxeswillbechargedonallcanadianpurchasestaxesandratesarenonnegotiablerateswillbereflectiveofyourprovinceofresidenceandareoutlinedhereatsurplusbydesignitemssoldasisorworkingasisarenoteligibleforreturnsrefundsandorexchangesasisorworkingasisitemsarefinalsaleupondiscoveryofissueswithasisandworkingasisitemswestoptestingandissuesmaynotbelimitedtothoseoutlinedinourlistingwecannotguaranteethefullfunctionalityofallpartsonasisandworkingasisitemspleasebidcarefully": "SPECIFICATIONS: Type: Digital Camera Brand: Canon Model: Powershot A1400HD Megapixels: 16.0 Video Resolution: 720p Optical Zoom: 5x Colour: Black Additional Features: 2.7-inch TFT color LCD with wide-viewing angle monitor 16.0 megapixel 1/2.3-inch CCD sensor DIGIC 4 image processor for exceptional performance 5x optical zoom with 28mm wide-angle lens delivers stunning images Shoot brilliant 720p HD video with a dedicated movie button Country/Region of Manufacture: Unknown Screen Size: 2.7\" INCLUDES: Battery Manual OEM Box Strap (Neck or Wrist) EXCLUDES: ITEM DETAILS: This product has been used, we have tested all components and all of them work as they are supposed to. PHYSICAL CONDITION: Great There are no marks on the unit. FUNCTIONAL CONDITION: Used We have stress-tested all product components  and they work as they are supposed to. Product has been reset to near factory condition. 29402",
    "videoresolution": "720p",
    "colour": "Black",
    "megapixels": "16.0",
    "opticalzoom": "5x",
    "additionalfeatures": "2.7-inch TFT color LCD with wide-viewing angle monitor 16.0 megapixel 1/2.3-inch CCD sensor DIGIC 4 image processor for exceptional performance 5x optical zoom with 28mm wide-angle lens delivers stunning images Shoot brilliant 720p HD video with a dedicated movie button",
    "screensize": "2.7\"",
    "model": "Powershot A1400HD",
    "type": "Digital Camera",
    "brand": "Canon",
    "countryregionofmanufacture": "Unknown"
}