{
    "category": "camera",
    "internationalbuyerspleasenoteimportdutiesandbrokeragefeesarenotincludedintheitempriceorshippingchargesthesechargesarethebuyersresponsibilityallusbuyersmustincludetheirphoneintheirshippingdetailspleasecheckwithyourlocalcustomsofficetodeterminewhattheseadditionalcostswillbepriortobiddingbuyingwearenotabletoestimatequotethesechargesthesechargesarenormallycollectedbythedeliveringfreightshippingcompanyorwhenyoupicktheitemupwedonotmarkmerchandisevaluesbelowvalueormarkitemsasgiftsuscanadianandinternationalgovernmentregulationsprohibitsuchbehaviourthankyounoticepleasebeawaretaxeswillbechargedonallcanadianpurchasestaxesandratesarenonnegotiablerateswillbereflectiveofyourprovinceofresidenceandareoutlinedhereatsurplusbydesignitemssoldasisorworkingasisarenoteligibleforreturnsrefundsandorexchangesasisorworkingasisitemsarefinalsaleupondiscoveryofissueswithasisandworkingasisitemswestoptestingandissuesmaynotbelimitedtothoseoutlinedinourlistingwecannotguaranteethefullfunctionalityofallpartsonasisandworkingasisitemspleasebidcarefully": "SPECIFICATIONS: Type: Digital Camera Brand: Fujifilm Model: Finepix XP150 Megapixels: 14 Video Resolution: 1080p Optical Zoom: 5x Colour: SILVER/BLACK Additional Features: Proof Protection: Waterproof 33',  Shockproof 6.5',  Freezeproof 14,  Dustproof.                                                                       Full HD Movies. GPS with Compass and Photo navigation Country/Region of Manufacture: China Screen Size: 2.7\" INCLUDES: AC Adapter Battery Manual OEM Box Software Disc Strap (Neck or Wrist) USB Cable(s) EXCLUDES: ITEM DETAILS: The packing has been opened, but the contents remain unused. PHYSICAL CONDITION: New / sealed The packing has been opened, but the contents remain unused. FUNCTIONAL CONDITION: Sealed unit - open box The packing has been opened, but the contents remain unused. 32192",
    "videoresolution": "1080p",
    "colour": "SILVER/BLACK",
    "megapixels": "14",
    "opticalzoom": "5x",
    "additionalfeatures": "Proof Protection: Waterproof 33',  Shockproof 6.5',  Freezeproof 14,  Dustproof.                                                                       Full HD Movies. GPS with Compass and Photo navigation",
    "screensize": "2.7\"",
    "model": "Finepix XP150",
    "type": "Digital Camera",
    "brand": "Fujifilm",
    "countryregionofmanufacture": "China"
}