{
    "category": "camera",
    "internationalbuyerspleasenoteimportdutiesandbrokeragefeesarenotincludedintheitempriceorshippingchargesthesechargesarethebuyersresponsibilityallusbuyersmustincludetheirphoneintheirshippingdetailspleasecheckwithyourlocalcustomsofficetodeterminewhattheseadditionalcostswillbepriortobiddingbuyingwearenotabletoestimatequotethesechargesthesechargesarenormallycollectedbythedeliveringfreightshippingcompanyorwhenyoupicktheitemupwedonotmarkmerchandisevaluesbelowvalueormarkitemsasgiftsuscanadianandinternationalgovernmentregulationsprohibitsuchbehaviourthankyounoticepleasebeawaretaxeswillbechargedonallcanadianpurchasestaxesandratesarenonnegotiablerateswillbereflectiveofyourprovinceofresidenceandareoutlinedhereatsurplusbydesignitemssoldasisorworkingasisarenoteligibleforreturnsrefundsandorexchangesasisorworkingasisitemsarefinalsaleupondiscoveryofissueswithasisandworkingasisitemswestoptestingandissuesmaynotbelimitedtothoseoutlinedinourlistingwecannotguaranteethefullfunctionalityofallpartsonasisandworkingasisitemspleasebidcarefully": "SPECIFICATIONS: Type: Point & Shoot Brand: Fuji Model: Finepix JX680 Megapixels: 16 MP Lens: Fujinon lens Optical Zoom: 5x wide Colour: white Country/Region of Manufacture: China Screen Size: 3\" INCLUDES: AC Adapter Battery Manual Software Disc USB Cable(s) EXCLUDES: Strap (Neck or Wrist) ITEM DETAILS: This product has been used, we have tested all components and all of them work as they are supposed to. There are no marks on the unit. PHYSICAL CONDITION: Great There are no marks on the unit. FUNCTIONAL CONDITION: Used This product has been used, we have tested all components and all of them work as they are supposed to. 32176",
    "colour": "white",
    "megapixels": "16 MP",
    "opticalzoom": "5x wide",
    "lens": "Fujinon lens",
    "screensize": "3\"",
    "model": "Finepix JX680",
    "type": "Point & Shoot",
    "brand": "Fuji",
    "countryregionofmanufacture": "China"
}