{
    "category": "camera",
    "internationalbuyerspleasenoteimportdutiesandbrokeragefeesarenotincludedintheitempriceorshippingchargesthesechargesarethebuyersresponsibilityallusbuyersmustincludetheirphoneintheirshippingdetailspleasecheckwithyourlocalcustomsofficetodeterminewhattheseadditionalcostswillbepriortobiddingbuyingwearenotabletoestimatequotethesechargesthesechargesarenormallycollectedbythedeliveringfreightshippingcompanyorwhenyoupicktheitemupwedonotmarkmerchandisevaluesbelowvalueormarkitemsasgiftsuscanadianandinternationalgovernmentregulationsprohibitsuchbehaviourthankyounoticepleasebeawaretaxeswillbechargedonallcanadianpurchasestaxesandratesarenonnegotiablerateswillbereflectiveofyourprovinceofresidenceandareoutlinedhereatsurplusbydesignitemssoldasisorworkingasisarenoteligibleforreturnsrefundsandorexchangesasisorworkingasisitemsarefinalsaleupondiscoveryofissueswithasisandworkingasisitemswestoptestingandissuesmaynotbelimitedtothoseoutlinedinourlistingwecannotguaranteethefullfunctionalityofallpartsonasisandworkingasisitemspleasebidcarefully": "SPECIFICATIONS: Type: Mini Digital Camera Brand: Nikon Model: Coolpix S3500 Megapixels: 20.1MP Lens: NIKKOR 7x Wide Optical Zoom ED VR 4.7-32.9mm 1:3.4-6.4 Video Resolution: 1280 x 720 Optical Zoom: 7x Colour: Black MPN: S3500(CN)BK Country/Region of Manufacture: China Screen Size: 2.7\" INCLUDES: AC Adapter Battery Manual OEM Box Software Disc Strap (Neck or Wrist) USB Cable(s) EXCLUDES: ITEM DETAILS: This digital camera has been used before.  It has been tested and it is in working condition. PHYSICAL CONDITION: Very good There are some minor scuffs on the body of the camera. FUNCTIONAL CONDITION: Used Everything has been tested and works the way it should. 36855",
    "mpn": "S3500(CN)BK",
    "videoresolution": "1280 x 720",
    "colour": "Black",
    "megapixels": "20.1MP",
    "opticalzoom": "7x",
    "lens": "NIKKOR 7x Wide Optical Zoom ED VR 4.7-32.9mm 1:3.4-6.4",
    "screensize": "2.7\"",
    "model": "Coolpix S3500",
    "type": "Mini Digital Camera",
    "brand": "Nikon",
    "countryregionofmanufacture": "China"
}