{
    "category": "camera",
    "internationalbuyerspleasenoteimportdutiesandbrokeragefeesarenotincludedintheitempriceorshippingchargesthesechargesarethebuyersresponsibilityallusbuyersmustincludetheirphoneintheirshippingdetailspleasecheckwithyourlocalcustomsofficetodeterminewhattheseadditionalcostswillbepriortobiddingbuyingwearenotabletoestimatequotethesechargesthesechargesarenormallycollectedbythedeliveringfreightshippingcompanyorwhenyoupicktheitemupwedonotmarkmerchandisevaluesbelowvalueormarkitemsasgiftsuscanadianandinternationalgovernmentregulationsprohibitsuchbehaviourthankyounoticepleasebeawaretaxeswillbechargedonallcanadianpurchasestaxesandratesarenonnegotiablerateswillbereflectiveofyourprovinceofresidenceandareoutlinedhereatsurplusbydesignitemssoldasisorworkingasisarenoteligibleforreturnsrefundsandorexchangesasisorworkingasisitemsarefinalsaleupondiscoveryofissueswithasisandworkingasisitemswestoptestingandissuesmaynotbelimitedtothoseoutlinedinourlistingwecannotguaranteethefullfunctionalityofallpartsonasisandworkingasisitemspleasebidcarefully": "SPECIFICATIONS: Type: Digital Camera Brand: Canon Model: Powershot A1400HD Megapixels: 16.0 Video Resolution: 720p Optical Zoom: 5x Colour: Black Additional Features: 2.7-inch TFT color LCD with wide-viewing angle monitor 16.0 megapixel 1/2.3-inch CCD sensor DIGIC 4 image processor for exceptional performance 5x optical zoom with 28mm wide-angle lens delivers stunning images Shoot brilliant 720p HD video with a dedicated movie button Country/Region of Manufacture: Unknown INCLUDES: Manual OEM Box EXCLUDES: AC Adapter Battery Strap (Neck or Wrist) USB Cable(s) ITEM DETAILS: This item is used. The item has been tested and everything is working the way it should. There are no visible imperfections on the unit. PHYSICAL CONDITION: Great There are no visible imperfections on the unit. FUNCTIONAL CONDITION: Used This item is used. The item has been tested and everything is working the way it should. 29649",
    "videoresolution": "720p",
    "colour": "Black",
    "megapixels": "16.0",
    "opticalzoom": "5x",
    "additionalfeatures": "2.7-inch TFT color LCD with wide-viewing angle monitor 16.0 megapixel 1/2.3-inch CCD sensor DIGIC 4 image processor for exceptional performance 5x optical zoom with 28mm wide-angle lens delivers stunning images Shoot brilliant 720p HD video with a dedicated movie button",
    "model": "Powershot A1400HD",
    "type": "Digital Camera",
    "brand": "Canon",
    "countryregionofmanufacture": "Unknown"
}