{
    "category": "camera",
    "internationalbuyerspleasenoteimportdutiesandbrokeragefeesarenotincludedintheitempriceorshippingchargesthesechargesarethebuyersresponsibilityallusbuyersmustincludetheirphoneintheirshippingdetailspleasecheckwithyourlocalcustomsofficetodeterminewhattheseadditionalcostswillbepriortobiddingbuyingwearenotabletoestimatequotethesechargesthesechargesarenormallycollectedbythedeliveringfreightshippingcompanyorwhenyoupicktheitemupwedonotmarkmerchandisevaluesbelowvalueormarkitemsasgiftsuscanadianandinternationalgovernmentregulationsprohibitsuchbehaviourthankyounoticepleasebeawaretaxeswillbechargedonallcanadianpurchasestaxesandratesarenonnegotiablerateswillbereflectiveofyourprovinceofresidenceandareoutlinedhereatsurplusbydesignitemssoldasisorworkingasisarenoteligibleforreturnsrefundsandorexchangesasisorworkingasisitemsarefinalsaleupondiscoveryofissueswithasisandworkingasisitemswestoptestingandissuesmaynotbelimitedtothoseoutlinedinourlistingwecannotguaranteethefullfunctionalityofallpartsonasisandworkingasisitemspleasebidcarefully": "SPECIFICATIONS: Type: Point & Shoot Brand: Canon Model: SX240 HS Megapixels: 12.1 MP Video Resolution: 720p Optical Zoom: 20x Colour: Blaqck Additional Features: 12 .1 effective megapixel,  1/2.3-inch high-sensitivity CMOS sensor 3-inch TFT color LCD with wide viewing angle 25mm wide-angle lens with optical image stabilizer 20x optical zoom,  4x digital zoom and 80x combined zoom Full 1080p HD video with stereo sound Country/Region of Manufacture: China Screen Size: 3.0\" INCLUDES: Battery Battery Charger Strap (Neck or Wrist) USB Cable(s) EXCLUDES: Manual Non-OEM Box OEM Box Software Disc ITEM DETAILS: This product has been used, we have tested all components and all of them work as they are supposed to. PHYSICAL CONDITION: Good There are few small scratches and scuffs on screen and randomly on unit. FUNCTIONAL CONDITION: Used This product has been used, we have tested all components and all of them work as they are supposed to. 40465",
    "videoresolution": "720p",
    "colour": "Blaqck",
    "megapixels": "12.1 MP",
    "opticalzoom": "20x",
    "additionalfeatures": "12 .1 effective megapixel,  1/2.3-inch high-sensitivity CMOS sensor 3-inch TFT color LCD with wide viewing angle 25mm wide-angle lens with optical image stabilizer 20x optical zoom,  4x digital zoom and 80x combined zoom Full 1080p HD video with stereo sound",
    "screensize": "3.0\"",
    "model": "SX240 HS",
    "type": "Point & Shoot",
    "brand": "Canon",
    "countryregionofmanufacture": "China"
}