{
    "externalflashconnection": "Hot Shoe, PC Terminal, Wireless",
    "leftbardescstart": "5253B002 Browse Our Store Store                                                                                                                         home Point & Shoot Cameras Pro. SLR Cameras Digital Camera Lenses Camcorders Projectors GPS Navigation Home audio Blu-ray / DVD PlayersLeft Bar Desc //End !Right Bar Desc //Start !Canon EOS-1D X 18.1MP Full Frame CMOS Digital SLR Camera New, Open Box 18.1Mp CMOS Sensor Dual DIGIC 5+ Image Processors 3.2\" LCD Screen Eye-Level Pentaprism Viewfinder Dual CF Card Recording Media Canon EF Lens Mount Magnesium Alloy Body 1920 x 1080 HD Video Capture Live View Still and Video Recording 61-Point High Density Auto Focus Canon EOS-1D X Digital SLR Camera (Body Only) Eyecup Eg LP-E4N Battery Pack LC-E4N Battery Charger With Cable Wide Neck Strap L7 Cable Protector AVC-DC400ST Stereo AV Cable IFC-200U USB Interface Cable - 6.9' (1.9 m) EOS Digital Solution Disc Software Instruction Manual Canon EOS-1D X 18.1MP Full Frame C ... SPECIFICATIONS Imaging Lens Mount Canon EF Camera Format Full-Frame (1.0x Crop Factor) Pixels Actual: 19.3 MegapixelEffective: 18.1 Megapixel Max Resolution 17.9MP: 5184 x 3456 Aspect Ratio 3:2 Sensor Type / Size CMOS, 36 x 24 mm File Formats Still Images: JPEG, RAW Movies: MOV, MPEG-4 AVC/H.264 Audio: Linear PCM Bit Depth 14-bit Memory Card Type CompactFlash Focus Control Focus Type Auto & Manual Focus Mode Single-servo AF (S), Continuous-servo AF (C), Manual Focus (M) Autofocus Points 61 Viewfinder/Display Viewfinder Type Pentaprism Viewfinder Coverage 100% Viewfinder Magnification Approx. 0.76x Diopter Adjustment - 3.0 to +1.0 m Display Screen 3.2\"\u00a0Rear Screen\u00a0\u00a0\u00a0LCD (1,040,000) Screen Coverage 100% Exposure Control ISO Sensitivity Auto, 100-51200 (Extended Mode: 50-204800) Shutter Type: Electronic & MechanicalSpeed: 30 - 1/8000\u00a0seconds Remote Control RS-80N3 (Optional) Mirror Lock-Up Yes Metering Method Average metering, Center-weighted average metering, Multi-zone metering, Spot metering Exposure Modes Modes: Aperture Priority, Manual, Program, Shutter PriorityCompensation: -5 EV to +5 EV (in 1/3 EV steps) White Balance Modes Auto, Cloudy, Custom, Daylight, Flash, Fluorescent (White), Manual, Shade, Tungsten Flash Max Sync Speed 1 / 250 sec Flash Compensation -3 EV to +3 EV (in 1/3 or 1/2 EV steps) Dedicated Flash System eTTL External Flash Connection Hot Shoe, PC Terminal, Wireless AV Recording Video Recording Yes File Size 1920 x 1080\u00a0(Full HD) 1280 x 720 640 x 480 Frame Rate at 1920 x 1080: 30 fps, 25 fps, 24 fps at 1280 x 720: 60 fps, 50 fps at 640 x 480: 30 fps, 25 fps Exposure Control Manual:\u00a0Shutter Speed, Aperture, ISO ISO Sensitivity Not Specified By Manufacturer Exposure Compensation -3 EV to +3 EV (in 1/3 or 1/2 EV steps) Focus Auto Manual Continuous Auto Audio Recording Optional External Mic: With Video, Stereo Performance Continuous Shooting Up to 14 fps Self Timer 10 sec, 2 sec Connectivity AV Output HDMI C (Mini) USB 2.0 Power Battery 1x  LP-E4N\u00a0 Rechargeable Lithium-Ion Battery Pack, 11.1VDC, 2450mAh AC Power Adapter ACK-E4 (Optional) Operating/Storage Temperature Operating 32 to 104\u00b0F (0 to 40\u00b0C)Humidity: 0 - 85% Physical Dimensions (WxHxD) 6.2 x 6.4 x 3.3\"\u00a0/\u00a0157.5 x 162.6 x 83.8 mm Weight 3.4 lb\u00a0/\u00a01.54 kg With battery Back to Top CNEOS1DXOB TERMS AND CONDITIONS We usually ship within 1 business day after receiving payment. Please be aware                                                                                                                                         that weekends are not business days. All express methods of shipment still may require 1 day of processing time. Canadians and international buyers are responsible for all duties, customs                                                                                                                                         charges, and/or brokerage fees. We cannot ship as a gift, or claim as lower value. New Jersey buyers are responsible for applicable sales tax. We ship everything professionally in our state of the art warehouse. All products we sell are brand new and includes warranty coverage unless clearly                                                                                                                                         specified on the listing. \"Free Shipping\" applies to orders shipped within the continental                                                                                                                                         US. Domestic orders ship FedEx, UPS, and USPS. Our packages are insured and may require a signature. In accordance with PayPal                                                                                                                                         and eBay policies, we cannot reroute your package to a different address or hold                                                                                                                                         your shipment at the local hub for pick up, your order must be delivered to the                                                                                                                                         confirmed PayPal address received with your purchase. We cannot change your address                                                                                                                                         before the order ships. Please do not submit handling instructions in the notes                                                                                                                                         of your order requesting special handling, a specific courier or a change of address,                                                                                                                                         as we will be unable to meet these requests. We reserve the right to cancel any orders addressed to P.O. boxes, freight                                                                                                                                         forwarders, or resellers. We do not offer price protection if the price of an item                                                                                                                                         that you purchased. Prices do change frequently. We reserve the right to cancel orders placed without a registered eBay or                                                                                                                                         PayPal account. Orders placed by eBay guest checkout require additional verification                                                                                                                                         and may be delayed. Orders placed without a registered PayPal account cannot be                                                                                                                                         accepted and will be cancelled and refunded upon receipt. We offer a customer 30 day return privilege policy. A Return Merchandise Authorization                                                                                                                                             (RMA) number must be obtained for any return. To obtain an RMA number, please call                                                                                                                                             us toll free at 866-673-7187 . Returned packages without proper RMA demarcations will be refused by our warehouse                                                                                                                                             and returned to you. Customers who refuse a delivery, will be subject to charges                                                                                                                                             for return shipping to us. If the item was advertised as Free Shipping, then we                                                                                                                                             will charge the amount of shipping as determined by the FedEx shipping calculator. Some returns are subject to a restocking fee. The restocking percentage will depend                                                                                                                                             on the condition of the returned product. Defective products are eligible for exchange,                                                                                                                                             and no restock fee will apply. All returns must be packed with all contents which came with the original package                                                                                                                                             including, cables, software, plastic and cardboard packaging, and unregistered warranty                                                                                                                                             card. This return policy excludes Televisions and Home Theater Projectors. For further                                                                                                                                             questions please call us toll free at 866-673-7187 . You can also                                                                                                                                             contact us using the contact form found here . Return shipping costs are not reimbursable. International Customers: All electronic products are packaged for sale in the US with US Voltage. View International Policies Back to Top CONTACT INFO AND STORE HOURS ANY QUESTIONS? CALL US TOLL FREE: +1-866-673-7187 STORE HOURS: Monday - Friday 10:00AM to 3:00PM EST Email us anytime! Back to TopRight Bar Desc //End !",
    "exposurecontrol": "Manual:\u00a0Shutter Speed, Aperture, ISO",
    "weight": "3.4 lb\u00a0/\u00a01.54 kg With battery",
    "mirrorlockup": "Yes",
    "battery": "1x  LP-E4N\u00a0 Rechargeable Lithium-Ion Battery Pack, 11.1VDC, 2450mAh",
    "exposuremodes": "Modes: Aperture Priority, Manual, Program, Shutter PriorityCompensation: -5 EV to +5 EV (in 1/3 EV steps)",
    "isosensitivity": "Not Specified By Manufacturer",
    "focus": "Auto Manual Continuous Auto",
    "height": "6.4 in.",
    "displaytype": "LCD",
    "cameraflashfeatures": "Auto Flash",
    "additionalfeatures": "HDMI, Interchangeable Lenses, USB 2.0",
    "acpoweradapter": "ACK-E4 (Optional)",
    "lensmount": "Canon EF",
    "viewfindercoverage": "100%",
    "category": "camera",
    "shutter": "Type: Electronic & MechanicalSpeed: 30 - 1/8000\u00a0seconds",
    "videorecording": "Yes",
    "lightsensitivitymax": "50100",
    "operatingstoragetemperature": "Operating 32 to 104\u00b0F (0 to 40\u00b0C)Humidity: 0 - 85%",
    "lensforsd": "Body Only",
    "pixels": "Actual: 19.3 MegapixelEffective: 18.1 Megapixel",
    "selftimer": "10 sec, 2 sec",
    "width": "6.2 in.",
    "viewfindermagnification": "Approx. 0.76x",
    "maxvideoresolution": "1920 x 1080",
    "filesize": "1920 x 1080\u00a0(Full HD) 1280 x 720 640 x 480",
    "dimensionswxhxd": "6.2 x 6.4 x 3.3\"\u00a0/\u00a0157.5 x 162.6 x 83.8 mm",
    "continuousshooting": "Up to 14 fps",
    "meteringmethod": "Average metering, Center-weighted average metering, Multi-zone metering, Spot metering",
    "audiorecording": "Optional External Mic: With Video, Stereo",
    "whitebalancemodes": "Auto, Cloudy, Custom, Daylight, Flash, Fluorescent (White), Manual, Shade, Tungsten",
    "maxresolution": "17.9MP: 5184 x 3456",
    "flashcompensation": "-3 EV to +3 EV (in 1/3 or 1/2 EV steps)",
    "mpn": "5253B002",
    "brand": "Canon",
    "sensortypesize": "CMOS, 36 x 24 mm",
    "sensortype": "CMOS",
    "connectivity": "AV Output HDMI C (Mini) USB 2.0",
    "cameraformat": "Full-Frame (1.0x Crop Factor)",
    "screensize": "3.2\"",
    "focustype": "Auto & Manual",
    "wevemadeafewchangestobidding": "Were these helpful?",
    "bitdepth": "14-bit",
    "aspectratio": "3:2",
    "displayscreen": "3.2\"\u00a0Rear Screen\u00a0\u00a0\u00a0LCD (1,040,000)",
    "fileformats": "Still Images: JPEG, RAW Movies: MOV, MPEG-4 AVC/H.264 Audio: Linear PCM",
    "microphonetype": "With Built-in Microphone",
    "remotecontrol": "RS-80N3 (Optional)",
    "diopteradjustment": "- 3.0 to +1.0 m",
    "memorycardtype": "CompactFlash",
    "cameratype": "Digital SLR",
    "framerate": "at 1920 x 1080: 30 fps, 25 fps, 24 fps at 1280 x 720: 60 fps, 50 fps at 640 x 480: 30 fps, 25 fps",
    "upc": "013803145410",
    "displaysize": "3.2\"",
    "dedicatedflashsystem": "eTTL",
    "focusmode": "Single-servo AF (S), Continuous-servo AF (C), Manual Focus (M)",
    "depth": "3.3 in.",
    "sensorresolution": "18.1 MP",
    "viewfindertype": "Pentaprism",
    "maxsyncspeed": "1 / 250 sec",
    "autofocuspoints": "61",
    "exposurecompensation": "-3 EV to +3 EV (in 1/3 or 1/2 EV steps)",
    "supportedflashmemory": "CompactFlash Card Type I, CompactFlash Card Type II, CompactFlash I, CompactFlash II",
    "model": "1D X",
    "screencoverage": "100%",
    "whitebalance": "Auto"
}