{
    "category": "camera",
    "internationalbuyerspleasenoteimportdutiesandbrokeragefeesarenotincludedintheitempriceorshippingchargesthesechargesarethebuyersresponsibilityallusbuyersmustincludetheirphoneintheirshippingdetailspleasecheckwithyourlocalcustomsofficetodeterminewhattheseadditionalcostswillbepriortobiddingbuyingwearenotabletoestimatequotethesechargesthesechargesarenormallycollectedbythedeliveringfreightshippingcompanyorwhenyoupicktheitemupwedonotmarkmerchandisevaluesbelowvalueormarkitemsasgiftsuscanadianandinternationalgovernmentregulationsprohibitsuchbehaviourthankyounoticepleasebeawaretaxeswillbechargedonallcanadianpurchasestaxesandratesarenonnegotiablerateswillbereflectiveofyourprovinceofresidenceandareoutlinedhereatsurplusbydesignitemssoldasisorworkingasisarenoteligibleforreturnsrefundsandorexchangesasisorworkingasisitemsarefinalsaleupondiscoveryofissueswithasisandworkingasisitemswestoptestingandissuesmaynotbelimitedtothoseoutlinedinourlistingwecannotguaranteethefullfunctionalityofallpartsonasisandworkingasisitemspleasebidcarefully": "SPECIFICATIONS: Type: Mirrorlesss digital camera Brand: Sony Model: Alpha NEX F3K Megapixels: 16.1 Lens: 18-55mm OSS Lens Video Resolution: Full HD movie shooting 60i/24p Optical Zoom: 3 x Digital Zoom: 8x Colour: Black Additional Features: 16.1 MP Exmor APS HD CMOS image sensor \u00e2\u0080\u00a2       Full HD movie shooting 60i/24p \u00e2\u0080\u00a2       LCD tilts down 13\u00c2\u00b0,  up 180\u00c2\u00b0 for low-angle and self-portrait shots \u00e2\u0080\u00a2       Optical Zoom 3 x \u00e2\u0080\u00a2       Digital Zoom 8x \u00e2\u0080\u00a2       SDXC  MSPD \u00e2\u0080\u00a2       3\" LCD display - tiltable Country/Region of Manufacture: China Screen Size: 3\" INCLUDES: Lens Manual OEM Box Software Disc EXCLUDES: AC Adapter Battery Lens Cap Strap (Neck or Wrist) USB Cable(s) ITEM DETAILS: We have stress-tested all product components  and they work as they are supposed to. Product has been reset to near factory condition. PHYSICAL CONDITION: Very good There are only one or two minor scuffs randomly on the screen. FUNCTIONAL CONDITION: Used We have stress-tested all product components  and they work as they are supposed to. Product has been reset to near factory condition. 30569",
    "videoresolution": "Full HD movie shooting 60i/24p",
    "colour": "Black",
    "megapixels": "16.1",
    "opticalzoom": "3 x",
    "lens": "18-55mm OSS Lens",
    "digitalzoom": "8x",
    "additionalfeatures": "16.1 MP Exmor APS HD CMOS image sensor \u00e2\u0080\u00a2       Full HD movie shooting 60i/24p \u00e2\u0080\u00a2       LCD tilts down 13\u00c2\u00b0,  up 180\u00c2\u00b0 for low-angle and self-portrait shots \u00e2\u0080\u00a2       Optical Zoom 3 x \u00e2\u0080\u00a2       Digital Zoom 8x \u00e2\u0080\u00a2       SDXC  MSPD \u00e2\u0080\u00a2       3\" LCD display - tiltable",
    "screensize": "3\"",
    "model": "Alpha NEX F3K",
    "type": "Mirrorlesss digital camera",
    "brand": "Sony",
    "countryregionofmanufacture": "China"
}