{
    "category": "camera",
    "internationalbuyerspleasenoteimportdutiesandbrokeragefeesarenotincludedintheitempriceorshippingchargesthesechargesarethebuyersresponsibilityallusbuyersmustincludetheirphoneintheirshippingdetailspleasecheckwithyourlocalcustomsofficetodeterminewhattheseadditionalcostswillbepriortobiddingbuyingwearenotabletoestimatequotethesechargesthesechargesarenormallycollectedbythedeliveringfreightshippingcompanyorwhenyoupicktheitemupwedonotmarkmerchandisevaluesbelowvalueormarkitemsasgiftsuscanadianandinternationalgovernmentregulationsprohibitsuchbehaviourthankyounoticepleasebeawaretaxeswillbechargedonallcanadianpurchasestaxesandratesarenonnegotiablerateswillbereflectiveofyourprovinceofresidenceandareoutlinedhereatsurplusbydesignitemssoldasisorworkingasisarenoteligibleforreturnsrefundsandorexchangesasisorworkingasisitemsarefinalsaleupondiscoveryofissueswithasisandworkingasisitemswestoptestingandissuesmaynotbelimitedtothoseoutlinedinourlistingwecannotguaranteethefullfunctionalityofallpartsonasisandworkingasisitemspleasebidcarefully": "SPECIFICATIONS: Type: Digital Camera Brand: Sony Model: Cyber-shot DSC-W690 Megapixels: 16.1 Lens: Sony Lens G Video Resolution: 720p Optical Zoom: 10x Colour: Silver Additional Features: 720p MP4 HD Movie Mode Sweep Panorama mode-up to 360\u00c2\u00b0 Country/Region of Manufacture: China Screen Size: 3\" INCLUDES: Battery Battery Charger OEM Box Strap (Neck or Wrist) USB Cable(s) EXCLUDES: ITEM DETAILS: Although this unit has been previously used, it is in complete working order. Physically, the unit is in very good condition with some minor marks on the screen and throughout the body. PHYSICAL CONDITION: Very good Physically, the unit is in very good condition with some minor marks on the screen and throughout the body. FUNCTIONAL CONDITION: Used Although this unit has been previously used, it is in complete working order. 41874",
    "videoresolution": "720p",
    "colour": "Silver",
    "megapixels": "16.1",
    "opticalzoom": "10x",
    "lens": "Sony Lens G",
    "additionalfeatures": "720p MP4 HD Movie Mode Sweep Panorama mode-up to 360\u00c2\u00b0",
    "screensize": "3\"",
    "model": "Cyber-shot DSC-W690",
    "type": "Digital Camera",
    "brand": "Sony",
    "countryregionofmanufacture": "China"
}