{
    "category": "camera",
    "internationalbuyerspleasenoteimportdutiesandbrokeragefeesarenotincludedintheitempriceorshippingchargesthesechargesarethebuyersresponsibilityallusbuyersmustincludetheirphoneintheirshippingdetailspleasecheckwithyourlocalcustomsofficetodeterminewhattheseadditionalcostswillbepriortobiddingbuyingwearenotabletoestimatequotethesechargesthesechargesarenormallycollectedbythedeliveringfreightshippingcompanyorwhenyoupicktheitemupwedonotmarkmerchandisevaluesbelowvalueormarkitemsasgiftsuscanadianandinternationalgovernmentregulationsprohibitsuchbehaviourthankyounoticepleasebeawaretaxeswillbechargedonallcanadianpurchasestaxesandratesarenonnegotiablerateswillbereflectiveofyourprovinceofresidenceandareoutlinedhereatsurplusbydesignitemssoldasisorworkingasisarenoteligibleforreturnsrefundsandorexchangesasisorworkingasisitemsarefinalsaleupondiscoveryofissueswithasisandworkingasisitemswestoptestingandissuesmaynotbelimitedtothoseoutlinedinourlistingwecannotguaranteethefullfunctionalityofallpartsonasisandworkingasisitemspleasebidcarefully": "SPECIFICATIONS: Type: Digital Camera Brand: Canon Model: SX160 IS Megapixels: 16.0 Optical Zoom: 16x Colour: black Additional Features: 16 effective megapixel,  1/2.3-inch CCD sensor 3-inch TFT color LCD with wide viewing angle DIGIC 4 image processor 720p HD video with dedicated movie button 28mm wide-angle lens with powerful 16x optical zoom and optical image stabilizer 16x Optical Zoom with 28mm Wide-Angle lens DIGIC 4 Image Processor Manufacturer Warranty: no Country/Region of Manufacture: Malaysia Screen Size: 3.0 INCLUDES: Strap (Neck or Wrist) USB Cable(s) EXCLUDES: Battery Manual OEM Box ITEM DETAILS: We have stress-tested all product components  and they work as they are supposed to. Product has been reset to near factory condition. PHYSICAL CONDITION: Good There are only a few slight scratches or scuffs on screen and a few randomly on other sides. FUNCTIONAL CONDITION: Used We have stress-tested all product components  and they work as they are supposed to. Product has been reset to near factory condition. 30597",
    "colour": "black",
    "megapixels": "16.0",
    "opticalzoom": "16x",
    "additionalfeatures": "16 effective megapixel,  1/2.3-inch CCD sensor 3-inch TFT color LCD with wide viewing angle DIGIC 4 image processor 720p HD video with dedicated movie button 28mm wide-angle lens with powerful 16x optical zoom and optical image stabilizer 16x Optical Zoom with 28mm Wide-Angle lens DIGIC 4 Image Processor",
    "screensize": "3.0",
    "manufacturerwarranty": "no",
    "model": "SX160 IS",
    "type": "Digital Camera",
    "brand": "Canon",
    "countryregionofmanufacture": "Malaysia"
}