{
    "itemid": "PKDK50300KB",
    "externalflashconnection": "Hot Shoe, Wireless",
    "features": "No",
    "weight": "17.71 oz (502 g)",
    "maxsyncspeed": "Electronic Shutter: 1 / 180 sec",
    "battery": "1x D-LI109\u00a0 Rechargeable               Lithium-Ion Battery Pack,               7.4VDC, 1050mAh 4x AA",
    "framerate": "@ 1920 x 1080: 30 fps, 25 fps,               24 fps @ 1280 x 720: 60 fps, 50 fps, 30               fps, 25 fps, 24 fps @ 640 x 480: 30 fps, 25 fps, 24               fps",
    "isosensitivity": "Auto, 100-51200",
    "focallength": "55-300mm Comparable 35mm Focal Length:               84.5-460 mm",
    "memorycardtype": "SD SDHC SDXC",
    "diaphragmblades": "6",
    "acpoweradapter": "K-AC128 (Optional)",
    "aspectratio": "16:9",
    "viewfindercoverage": "100%",
    "attr1star": "2 stars3 stars4 stars5 stars",
    "shutter": "Type: Electronic Speed: 30 - 1/6000\u00a0sec",
    "videorecording": "Yes, NTSC/PAL",
    "minimumfocusdistance": "4.6'\u00a0(1.40 m)",
    "operatingstoragetemperature": "Operating 14 to 104\u00b0F (-10 to 40\u00b0C)",
    "dimensionsdxl": "Approx. 2.80 x 4.39\" (71 x 111.5               mm)",
    "pixels": "Actual: 16.5 Megapixel Effective: 16.3 Megapixel",
    "selftimer": "12 sec, 2 sec",
    "specifications": "Imaging Lens Mount Pentax K Camera Format APS-C / (1.5x Crop Factor) Pixels Actual: 16.5 Megapixel Effective: 16.3 Megapixel Max Resolution 16MP: 4928 x 3264 Aspect Ratio 3:2 Sensor Type / Size CMOS, 23.7 x 15.7 mm File Formats Still Images: DNG, JPEG, RAW Movies: MOV, MPEG-4 AVC/H.264 Bit Depth 12-bit Dust Reduction System Yes Memory Card Type SD SDHC SDXC Image Stabilization Sensor-Shift Focus Control Focus Type Auto & Manual Focus Mode Continuous-servo AF (C), Focus Lock AF Area Mode, Manual Focus (M),      Single-servo AF (S) Autofocus Points Phase Detection: 11 Viewfinder/Display Viewfinder Type Pentaprism Viewfinder Coverage 100% Viewfinder Magnification Approx. 0.92x Diopter Adjustment - 2.5 to +1.5 m Display Screen 3\"\u00a0Rear Screen\u00a0\u00a0\u00a0LCD (921,000) Screen Coverage 100% Exposure Control ISO Sensitivity Auto, 100-51200 Shutter Type: Electronic Speed: 30 - 1/6000\u00a0sec Remote Control Remote Control F or O-RC1 (Optional) Metering Method Center-weighted average metering, Multi-zone metering, Spot metering Exposure Modes Modes: Aperture Priority, Auto, Bulb, Manual, Movie, Program, Scene      Modes, Sensitivity Priority, Shutter Priority, Shutter/Aperture      Priority Metering Range: EV 0.0 - EV 22.0 Compensation: -5 EV to +5 EV (in 1/3 or 1/2 EV steps) White Balance Modes Auto, Cloudy, Cool White, Daylight, Daylight Color, Daylight White,      Flash, Kelvin, Manual, Shade, Tungsten, Warm White Flash Flash Modes Red-eye Reduction Second-curtain Sync Slow Sync TTL Auto Built-in Flash Yes Guide No. 39.37'\u00a0(12 m)\u00a0ISO100 Max Sync Speed Electronic Shutter: 1 / 180 sec Flash Compensation -2 EV to +1 EV (in 1/3 EV steps) Dedicated Flash System P-TTL\u00a0Remote Firing External Flash Connection Hot Shoe, Wireless AV Recording Video Recording Yes, NTSC/PAL File Size 1920 x 1080p\u00a0(Full HD) 1280 x 720p\u00a0(HD) 640 x 480p\u00a0(SD) Aspect Ratio 16:9 Frame Rate @ 1920 x 1080: 30 fps, 25 fps,               24 fps @ 1280 x 720: 60 fps, 50 fps, 30               fps, 25 fps, 24 fps @ 640 x 480: 30 fps, 25 fps, 24               fps Video Clip Length 1920 x 1080 25 min. 1280 x 720 25 min. 640 x 480 25 min. Audio Recording With Video, Mono Performance Continuous Shooting Up to 6 fps Self Timer 12 sec, 2 sec Interval Recording Yes Connectivity AV Output USB 2.0 Software System Requirements Windows: XP (SP3), Vista, 7, 8 Mac: OS X 10.5 or later Power Battery 1x D-LI109\u00a0 Rechargeable               Lithium-Ion Battery Pack,               7.4VDC, 1050mAh 4x AA AC Power Adapter K-AC128 (Optional) Operating/Storage Temperature Operating 14 to 104\u00b0F (-10 to 40\u00b0C) Physical Dimensions (WxHxD) 5.1 x 3.8 x 2.8\"\u00a0/\u00a013.0 x 9.7 x               7.1 cm Weight 22.9 oz\u00a0/\u00a0649 g With li-ion               battery and memory card Kit Lens Focal Length 18 - 55mm Comparable 35mm Focal Length:               27.5 - 82.5 mm Aperture Maximum: f/3.5 - 5.6 Minimum: f/22 - 38 Angle of View 76\u00b0 - 29\u00b0 Minimum Focus Distance 9.84\"\u00a0(25 cm) Magnification 0.34x Elements/Groups 11/8 Diaphragm Blades 6 Autofocus Yes Filter Thread Front:52 mm Dimensions (DxL) Approx. 2.70 x 2.66\" (68.5 x               67.5 mm) Weight 8.99 oz (255 g) Kit Lens Focal Length 55-300mm Comparable 35mm Focal Length:               84.5-460 mm Aperture Maximum: f/4 - 5.8 Minimum: f/22 - 32 Viewing Angle 29\u00b0 - 5.4\u00b0 Minimum Focus Distance 4.6'\u00a0(1.40 m) Magnification 0.28x Diaphragm Blades 6 Autofocus Yes Filter Thread Front: \u00a058 mm Dimensions (DxL) Approx. 2.80 x 4.39\" (71 x 111.5               mm) Weight 17.71 oz (502 g) Item ID PKDK50300KB Write Your Own Review You're reviewing: Pentax K-50 DSLR Camera with 18-55mm f/3.5-5.6 and 55-300mm f/4-5.8 Lenses 10874 Black How do you rate this product? * 1 star 2 stars 3 stars 4 stars 5 stars Price Value Quality * Nickname * Summary of Your Review * Review Submit Review Go Daddy About Us Privacy Policy Privacy Policy Site Map Search Terms Advanced Search Contact Us Manufacturers Prices, specifications, and images are subject to change without notice. We are not responsible for typographical or illustrative errors. \u00a9 2014 CameraBox.com Loading...",
    "magnification": "0.28x",
    "filesize": "1920 x 1080p\u00a0(Full HD) 1280 x 720p\u00a0(HD) 640 x 480p\u00a0(SD)",
    "aperture": "Maximum: f/4 - 5.8 Minimum: f/22 - 32",
    "dimensionswxhxd": "5.1 x 3.8 x 2.8\"\u00a0/\u00a013.0 x 9.7 x               7.1 cm",
    "autofocus": "Yes",
    "continuousshooting": "Up to 6 fps",
    "meteringmethod": "Center-weighted average metering, Multi-zone metering, Spot metering",
    "audiorecording": "With Video, Mono",
    "softwaresystemrequirements": "Windows: XP (SP3), Vista, 7, 8 Mac: OS X 10.5 or later",
    "dustreductionsystem": "Yes",
    "category": "camera",
    "viewfindermagnification": "Approx. 0.92x",
    "whitebalancemodes": "Auto, Cloudy, Cool White, Daylight, Daylight Color, Daylight White,      Flash, Kelvin, Manual, Shade, Tungsten, Warm White",
    "freeshipping": "Yes",
    "brand": "Pentax",
    "sensortypesize": "CMOS, 23.7 x 15.7 mm",
    "filterthread": "Front: \u00a058 mm",
    "connectivity": "AV Output USB 2.0",
    "cameraformat": "APS-C / (1.5x Crop Factor)",
    "elementsgroups": "11/8",
    "angleofview": "76\u00b0 - 29\u00b0",
    "focustype": "Auto & Manual",
    "included": "Pentax K-50 DSLR Camera with 18-55mm f/3.5-5.6 and 55-300mm f/4-5.8 Lenses Black DA 18-55mm f/3.5-5.6 AL WR Zoom Lens smc Pentax DA L 55-300mm f/4-5.8 ED Lens Rechargeable Li-Ion Battery D-Li109 for The KR Digital SLR Camera K-BC109 Battery Charger Kit for D-LI109 Battery AC Plug Cord I-USB7 USB Interface Cable Hotshoe Cover FK Eyecup FR for K7 Digital SLR Camera (replacement) SLR Body Mount Cover O-ST132 Strap for Pentax K-5 II DSLR Software CD-ROM Limited 1-Year Warranty",
    "bitdepth": "12-bit",
    "lensmount": "Pentax K",
    "displayscreen": "3\"\u00a0Rear Screen\u00a0\u00a0\u00a0LCD (921,000)",
    "fileformats": "Still Images: DNG, JPEG, RAW Movies: MOV, MPEG-4 AVC/H.264",
    "condition": "New",
    "intervalrecording": "Yes",
    "imagestabilization": "Sensor-Shift",
    "remotecontrol": "Remote Control F or O-RC1 (Optional)",
    "diopteradjustment": "- 2.5 to +1.5 m",
    "videocliplength": "1920 x 1080 25 min. 1280 x 720 25 min. 640 x 480 25 min.",
    "builtinflash": "Yes",
    "exposuremodes": "Modes: Aperture Priority, Auto, Bulb, Manual, Movie, Program, Scene      Modes, Sensitivity Priority, Shutter Priority, Shutter/Aperture      Priority Metering Range: EV 0.0 - EV 22.0 Compensation: -5 EV to +5 EV (in 1/3 or 1/2 EV steps)",
    "focusmode": "Continuous-servo AF (C), Focus Lock AF Area Mode, Manual Focus (M),      Single-servo AF (S)",
    "flashmodes": "Red-eye Reduction Second-curtain Sync Slow Sync TTL Auto",
    "flashcompensation": "-2 EV to +1 EV (in 1/3 EV steps)",
    "viewfindertype": "Pentaprism",
    "autofocuspoints": "Phase Detection: 11",
    "dedicatedflashsystem": "P-TTL\u00a0Remote Firing",
    "maxresolution": "16MP: 4928 x 3264",
    "guideno": "39.37'\u00a0(12 m)\u00a0ISO100",
    "screencoverage": "100%",
    "viewingangle": "29\u00b0 - 5.4\u00b0"
}