{
    "itemid": "NIDJ2DKP",
    "acpoweradapter": "EH-5b   (Optional)",
    "weight": "6.2 oz (176   g)",
    "battery": "1x EN-EL20\u00a0   Rechargeable Lithium-Ion Battery   Pack",
    "isosensitivity": "100-6400",
    "focallength": "30-110 mm Comparable Nikon CX Format Focal   Length: 81-297 mm",
    "memorycardtype": "SD SDHC SDXC",
    "diaphragmblades": "7",
    "imagestabilization": "Yes",
    "aspectratio": "3:2, 16:9",
    "attr1star": "2 stars3 stars4 stars5 stars",
    "shutter": "Type:   Electronic Speed: 30 - 1/16000\u00a0sec",
    "maxsyncspeed": "1 / 60 sec",
    "dimensions": "No",
    "minimumfocusdistance": "3.3'\u00a0(1.01 m)",
    "operatingstoragetemperature": "32 to 104\u00b0F   (0 to 40\u00b0C) Humidity: 0 - 85%",
    "dimensionsdxl": "Approx. 2.4 x   2.4\" (6.10 x 6.10 cm)",
    "pixels": "10.1   Megapixel",
    "selftimer": "2 sec, 5 sec,   10 sec",
    "specifications": "Imaging Lens Mount Nikon 1 Camera Format Nikon CX   (2.7x Crop Factor) Pixels 10.1   Megapixel Sensor Type /   Size CMOS, 13.2 x   8.8 mm File Formats Still   Images: JPEG, RAW Movies: MPEG-4 AVC/H.264, MOV Audio: AAC Dust Reduction   System Yes Memory Card   Type SD SDHC SDXC AV Recording Video   Recording Yes Aspect Ratio 3:2, 16:9 Audio   Recording With Video,   Stereo Focus Control Focus Type Auto & Manual Focus Mode Single-servo   AF (S), Continuous-servo AF (C),   Manual Focus (M) Autofocus   Points 41 Viewfinder/Display Viewfinder   Type None Display Screen 3\"\u00a0Rear   Screen\u00a0\u00a0\u00a0LCD (921,000) Screen   Coverage 100% Exposure Control ISO   Sensitivity 100-6400 Shutter Type:   Electronic Speed: 30 - 1/16000\u00a0sec Metering   Method Spot   metering, Center-weighted average   metering, Multi-zone metering Exposure Modes Modes:   Aperture Priority, Auto, Manual,   Programmed Auto, Shutter Priority Compensation: -3 EV to +3 EV (in .33   EV steps) White Balance   Modes Auto, Cloudy,   Daylight, Flash, Fluorescent,   Incandescent, Preset Manual, Shade Burst Rate Up to 10 fps   at 10.1 MP for up to 13 frames Flash Flash Modes Fill-in Red-eye Reduction Second-curtain Sync Slow Sync Slow Sync./Red-eye Reduction Built-in Flash Yes Max Sync Speed 1 / 60 sec Performance Continuous   Shooting Up to 60 fps Self Timer 2 sec, 5 sec,   10 sec Interval   Recording Yes Connectivity HDMI C (Mini) USB 2.0 Power Battery 1x EN-EL20\u00a0   Rechargeable Lithium-Ion Battery   Pack AC Power   Adapter EH-5b   (Optional) Operating/Storage Temperature 32 to 104\u00b0F   (0 to 40\u00b0C) Humidity: 0 - 85% Physical Dimensions   (WxHxD) 4.2 x 2.4 x   1.2\"\u00a0/\u00a010.7 x 6.1 x 3.0 cm Weight 8.4 oz\u00a0/\u00a0238\u00a0   g Body only Kit Lens Focal Length 10 - 30 mm Comparable Nikon CX Format Focal   Length: 27 - 81 mm Aperture Maximum:   f/3.5 - 5.5 Minimum: f/16 - 16 Angle of View 77\u00b0 - 29.4\u00b0 Minimum Focus   Distance 7.87\"\u00a0(19.99   cm) Magnification 0.21x Groups/Elements 9/12 Diaphragm   Blades 7 Autofocus Yes Image   Stabilization Yes Filter Thread Front: 40.5   mm Dimensions   (DxL) Approx. 2.3 x   7.1\" (5.84 x 18.03 cm) Weight 4.1 oz (116   g) Kit Lens Focal Length 30-110 mm Comparable Nikon CX Format Focal   Length: 81-297 mm Aperture Maximum:   f/3.8 - 5.6 Minimum: f/16 - 16 Angle of View 29.4\u00b0 - 8.2\u00b0 Minimum Focus   Distance 3.3'\u00a0(1.01 m) Groups/Elements 12/18 Diaphragm   Blades 7 Autofocus Yes Image   Stabilization Yes Filter Thread Front: 40.5   mm Dimensions (DxL) Approx. 2.4 x   2.4\" (6.10 x 6.10 cm) Weight 6.2 oz (176   g)",
    "magnification": "0.21x",
    "aperture": "Maximum:   f/3.8 - 5.6 Minimum: f/16 - 16",
    "focustype": "Auto & Manual",
    "autofocus": "Yes",
    "continuousshooting": "Up to 60 fps",
    "meteringmethod": "Spot   metering, Center-weighted average   metering, Multi-zone metering",
    "audiorecording": "With Video,   Stereo",
    "whitebalancemodes": "Auto, Cloudy,   Daylight, Flash, Fluorescent,   Incandescent, Preset Manual, Shade",
    "dustreductionsystem": "Yes",
    "category": "camera",
    "screencoverage": "100%",
    "freeshipping": "Yes",
    "brand": "Nikon",
    "sensortypesize": "CMOS, 13.2 x   8.8 mm",
    "filterthread": "Front: 40.5   mm",
    "connectivity": "HDMI C (Mini) USB 2.0",
    "cameraformat": "Nikon CX   (2.7x Crop Factor)",
    "groupselements": "12/18",
    "angleofview": "29.4\u00b0 - 8.2\u00b0",
    "dimensionswxhxd": "4.2 x 2.4 x   1.2\"\u00a0/\u00a010.7 x 6.1 x 3.0 cm",
    "included": "Nikon 1 J2 Mirrorless Digital Camera (Pink) 1 Nikkor VR 10-30 mm f/3.5-5.6 Lens for CX Format (Pink) 1 Nikkor VR 30-110mm f/3.8-5.6 Lens for CX Format (Pink) EN-EL20 Rechargeable Li-ion Battery MH-27 Battery Charger UC-E15 USB Cable BF-N1000 Body Cap AN-N1000 Strap ViewNX 2 Short Movie Creator CD User Manual Reference Manual CD 1-Year Limited Warranty",
    "videorecording": "Yes",
    "lensmount": "Nikon 1",
    "displayscreen": "3\"\u00a0Rear   Screen\u00a0\u00a0\u00a0LCD (921,000)",
    "fileformats": "Still   Images: JPEG, RAW Movies: MPEG-4 AVC/H.264, MOV Audio: AAC",
    "condition": "New",
    "burstrate": "Up to 10 fps   at 10.1 MP for up to 13 frames",
    "intervalrecording": "Yes",
    "builtinflash": "Yes",
    "exposuremodes": "Modes:   Aperture Priority, Auto, Manual,   Programmed Auto, Shutter Priority Compensation: -3 EV to +3 EV (in .33   EV steps)",
    "opticalzoom": "Interchangable Lens",
    "focusmode": "Single-servo   AF (S), Continuous-servo AF (C),   Manual Focus (M)",
    "flashmodes": "Fill-in Red-eye Reduction Second-curtain Sync Slow Sync Slow Sync./Red-eye Reduction",
    "viewfindertype": "None",
    "autofocuspoints": "41",
    "resolution": "10 Megapixels"
}