{
    "itemid": "nidd4s",
    "externalflashconnection": "Hot Shoe, PC Terminal",
    "exposurecontrol": "Manual:\u00a0Shutter Speed, Aperture, ISO Auto:\u00a0ISO",
    "weight": "2.65 lb\u00a0/\u00a01.20 kg",
    "mirrorlockup": "Yes",
    "battery": "1x EN-EL18a\u00a0 Rechargeable Lithium-Ion Battery Pack, 10.8VDC, 2500mAh",
    "exposuremodes": "Modes: Aperture Priority, Manual, Programmed Auto, Shutter Priority Metering Range: EV -1.0 - EV 20.0 Compensation: -5 EV to +5 EV (in 1/3, 1/2 or 1 EV steps)",
    "isosensitivity": "Auto/Manual, 200 - 25600, Expandable to 409600",
    "focus": "Auto Manual Continuous Auto",
    "memorycardtype": "CompactFlash XQD",
    "acpoweradapter": "EH-6b (Optional)",
    "lensmount": "Nikon F",
    "viewfindercoverage": "100%",
    "attr1star": "2 stars3 stars4 stars5 stars",
    "shutter": "Type: Electronic & Mechanical Speed: 30 - 1/8000\u00a0sec, Bulb Mode",
    "videorecording": "Yes, NTSC/PAL",
    "dimensions": "No",
    "operatingstoragetemperature": "Operating 32 to 104\u00b0F (0 to 40\u00b0C) Humidity: 0 - 85%",
    "viewfindereyepoint": "18.00 mm",
    "pixels": "Actual: 16.6 Megapixel Effective: 16.2 Megapixel",
    "selftimer": "2 sec, 5 sec, 10 sec, 20 sec",
    "specifications": "Imaging Lens Mount Nikon F Camera Format Full-Frame (1.0x Crop Factor) Pixels Actual: 16.6 Megapixel Effective: 16.2 Megapixel Max Resolution 16.2MP: 4928 x 3280 Aspect Ratio 3:2, 4:5, 16:9 Sensor Type / Size CMOS, 36.0 x 23.9 mm File Formats Still Images: JPEG, RAW, TIFF Movies: MOV, MPEG-4 AVC/H.264 Audio: Linear PCM Bit Depth 14-bit Dust Reduction System Yes Memory Card Type CompactFlash XQD Focus Control Focus Type Auto & Manual Focus Mode Automatic (A), Continuous-servo AF (C), Full-time Servo (F), Manual Focus (M), Single-servo AF (S) Autofocus Points Phase Detection: 51 Viewfinder/Display Viewfinder Type Pentaprism Viewfinder Eye Point 18.00 mm Viewfinder Coverage 100% Viewfinder Magnification Approx. 0.70x Diopter Adjustment - 3 to +1 m Display Screen 3.2\"\u00a0Rear Screen\u00a0\u00a0\u00a0LCD (921,000) Screen Coverage 100% Diagonal Angle of View 170.0\u00b0 Exposure Control ISO Sensitivity 100-25600 (Extended Mode: 50-409600) Shutter Type: Electronic & Mechanical Speed: 30 - 1/8000\u00a0sec, Bulb Mode Remote Control MC-37, 36A, 30A, 25A, 23A, 22A, 21A, DC2, ML-3, WR-T10, 10, A10, 1, (Optional) Mirror Lock-Up Yes Metering Method 3D Color Matrix Metering, Center-weighted average metering, Spot metering Exposure Modes Modes: Aperture Priority, Manual, Programmed Auto, Shutter Priority Metering Range: EV -1.0 - EV 20.0 Compensation: -5 EV to +5 EV (in 1/3, 1/2 or 1 EV steps) White Balance Modes Auto, Cloudy, Color Temperature, Direct Sunlight, Flash, Fluorescent, Incandescent, Preset Manual, Shade Flash Flash Modes 1st Curtain Sync Hi-Speed Sync Off Rear Curtain/Slow Sync Rear Sync Red-eye Reduction Slow Sync Slow Sync/Red-eye Reduction Max Sync Speed 1 / 250 sec Flash Compensation -3 EV to +1 EV (in 1/3, 1/2 or 1 EV steps) Dedicated Flash System iTTL External Flash Connection Hot Shoe, PC Terminal AV Recording Video Recording Yes, NTSC/PAL File Size 1920 x 1080p\u00a0(Full HD) Aspect Ratio 16:9 Frame Rate @ 1920 x 1080: 60 fps, 50 fps, 30 fps, 25 fps, 24 fps @ 1280 x 720: 60 fps, 50 fps @ 640 x 424: 30 fps, 25 fps Exposure Control Manual:\u00a0Shutter Speed, Aperture, ISO Auto:\u00a0ISO ISO Sensitivity Auto/Manual, 200 - 25600, Expandable to 409600 Focus Auto Manual Continuous Auto Video Clip Length 1920 x 1080 29 min.\u00a059 sec. Audio Recording Built-in Mic: With Video + Voice Memo, Mono Optional External Mic: With Video + Voice Memo, Stereo Performance Continuous Shooting Up to 11 fps Self Timer 2 sec, 5 sec, 10 sec, 20 sec Interval Recording Yes Connectivity 1/8\" Headphone, 1/8\" Microphone, HDMI C (Mini), NIkon 10-Pin, USB 2.0, X-Sync Socket Wi-Fi Capable Yes (with Optional Transmitter) Power Battery 1x EN-EL18a\u00a0 Rechargeable Lithium-Ion Battery Pack, 10.8VDC, 2500mAh AC Power Adapter EH-6b (Optional) Operating/Storage Temperature Operating 32 to 104\u00b0F (0 to 40\u00b0C) Humidity: 0 - 85% Physical Dimensions (WxHxD) 6.3 x 6.2 x 3.6\"\u00a0/\u00a0160.0 x 156.5 x 90.5 mm Weight 2.65 lb\u00a0/\u00a01.20 kg",
    "filesize": "1920 x 1080p\u00a0(Full HD)",
    "dimensionswxhxd": "6.3 x 6.2 x 3.6\"\u00a0/\u00a0160.0 x 156.5 x 90.5 mm",
    "continuousshooting": "Up to 11 fps",
    "meteringmethod": "3D Color Matrix Metering, Center-weighted average metering, Spot metering",
    "audiorecording": "Built-in Mic: With Video + Voice Memo, Mono Optional External Mic: With Video + Voice Memo, Stereo",
    "whitebalancemodes": "Auto, Cloudy, Color Temperature, Direct Sunlight, Flash, Fluorescent, Incandescent, Preset Manual, Shade",
    "dustreductionsystem": "Yes",
    "category": "camera",
    "viewfindermagnification": "Approx. 0.70x",
    "freeshipping": "Yes",
    "brand": "Nikon",
    "sensortypesize": "CMOS, 36.0 x 23.9 mm",
    "connectivity": "1/8\" Headphone, 1/8\" Microphone, HDMI C (Mini), NIkon 10-Pin, USB 2.0, X-Sync Socket",
    "cameraformat": "Full-Frame (1.0x Crop Factor)",
    "diagonalangleofview": "170.0\u00b0",
    "focustype": "Auto & Manual",
    "included": "Nikon D4S DSLR Camera (Body Only) EN-EL18a Rechargeable Lithium-Ion Battery MH-26a Battery Charger UF-2 Connector Cover for Stereo Mini Plug Cable UC-E15 USB Cable AN-DC11 Strap BF-1B Body Cap BS-2 Accessory Shoe Cover BL-6 Battery Chamber Cover ViewNX 2 Software 1-Year CameraBox Warranty",
    "bitdepth": "14-bit",
    "aspectratio": "16:9",
    "displayscreen": "3.2\"\u00a0Rear Screen\u00a0\u00a0\u00a0LCD (921,000)",
    "fileformats": "Still Images: JPEG, RAW, TIFF Movies: MOV, MPEG-4 AVC/H.264 Audio: Linear PCM",
    "condition": "New",
    "intervalrecording": "Yes",
    "remotecontrol": "MC-37, 36A, 30A, 25A, 23A, 22A, 21A, DC2, ML-3, WR-T10, 10, A10, 1, (Optional)",
    "diopteradjustment": "- 3 to +1 m",
    "videocliplength": "1920 x 1080 29 min.\u00a059 sec.",
    "flashmodes": "1st Curtain Sync Hi-Speed Sync Off Rear Curtain/Slow Sync Rear Sync Red-eye Reduction Slow Sync Slow Sync/Red-eye Reduction",
    "screencoverage": "100%",
    "framerate": "@ 1920 x 1080: 60 fps, 50 fps, 30 fps, 25 fps, 24 fps @ 1280 x 720: 60 fps, 50 fps @ 640 x 424: 30 fps, 25 fps",
    "opticalzoom": "Interchangable Lens",
    "focusmode": "Automatic (A), Continuous-servo AF (C), Full-time Servo (F), Manual Focus (M), Single-servo AF (S)",
    "flashcompensation": "-3 EV to +1 EV (in 1/3, 1/2 or 1 EV steps)",
    "viewfindertype": "Pentaprism",
    "maxsyncspeed": "1 / 250 sec",
    "autofocuspoints": "Phase Detection: 51",
    "dedicatedflashsystem": "iTTL",
    "maxresolution": "16.2MP: 4928 x 3280",
    "resolution": "16 Megapixels",
    "wificapable": "Yes (with Optional Transmitter)"
}