{
    "itemid": "NIDS1KWT",
    "externalflashconnection": "None",
    "imagestabilization": "No",
    "weight": "3 oz (85 g)",
    "maxsyncspeed": "Electronic Shutter: 1 / 60 sec",
    "battery": "1x EN-EL20\u00a0 Rechargeable Lithium-Ion Battery Pack",
    "isosensitivity": "Auto, 100-6400",
    "focallength": "11 - 27.5 mm Comparable 35mm Focal Length: 30 - 74 mm",
    "memorycardtype": "SD SDHC SDXC",
    "diaphragmblades": "7",
    "acpoweradapter": "EH-5b AC Adapter (Optional)",
    "aspectratio": "3:2, 16:9",
    "attr1star": "2 stars3 stars4 stars5 stars",
    "shutter": "Type: Electronic Speed: 30 - 1/16000\u00a0sec",
    "videorecording": "Yes, NTSC",
    "dimensions": "No",
    "minimumfocusdistance": "1.0'\u00a0(30.48 cm)",
    "operatingstoragetemperature": "Operating 32 to 104\u00b0F (0 to 40\u00b0C) Humidity: 0 - 85%",
    "dimensionsdxl": "Approx. 2.26 x 1.22\" (5.74 x 3.10 cm)",
    "pixels": "Actual: 12.0 Megapixel Effective: 10.1 Megapixel",
    "selftimer": "2 sec, 5 sec, 10 sec",
    "specifications": "Untitled 4 Imaging Lens Mount Nikon 1 Camera Format Nikon CX (2.7x Crop Factor) Pixels Actual: 12.0 Megapixel Effective: 10.1 Megapixel Max Resolution 3872 x 2592 Sensor Type / Size CMOS, 13.2 x 8.8 mm File Formats Still Images: JPEG,      RAW Movies: MOV, MPEG-4      AVC/H.264 Audio: AAC Bit Depth 12-bit Dust Reduction System Yes Memory Card Type SD SDHC SDXC AV Recording Video Recording Yes, NTSC Resolution 1920 x 1080: 60 fps, 30 fps 1280 x 720: 60 fps, 30 fps 640 x 240: 400 fps 320 x 120: 1200 fps Aspect Ratio 3:2, 16:9 Audio Recording With Video, Stereo Focus Control Focus Type Auto & Manual Focus Mode Continuous-servo AF (C), Focus Lock AF Area Mode, Manual Focus (M),      Single-servo AF (S) Autofocus Points 135 Viewfinder/Display Viewfinder Type LCD Display Display Screen 3\"\u00a0Rear Screen\u00a0\u00a0Live Preview\u00a0LCD (460,000) Exposure Control ISO Sensitivity Auto, 100-6400 Shutter Type: Electronic Speed: 30 - 1/16000\u00a0sec Metering Method 3D Color Matrix Metering, Center-weighted average metering, Spot      metering Exposure Modes Modes: Aperture Priority, Auto, Manual, Programmed Auto, Shutter      Priority Compensation: -3 EV to +3 EV (in 1/3 EV steps) White Balance Modes Auto, Cloudy, Daylight, Flash, Fluorescent (Day White),      Incandescent, Preset Manual, Shade, Underwater Burst Rate Up to 15 fps at 10.1 MP Flash Flash Modes Auto Auto/Red-eye Reduction Fill-flash/Slow Sync Fill-in Off Rear Curtain/Slow Sync Red-eye Reduction Second-curtain Sync Slow Sync/Red-eye Reduction Built-in Flash Yes Guide No. 16'\u00a0(4.88 m)\u00a0ISO100 Max Sync Speed Electronic Shutter: 1 / 60 sec Flash Compensation -3 EV to +1 EV (in 1/3 EV steps) Dedicated Flash System iTTL External Flash Connection None Performance Continuous Shooting Up to 15 fps Self Timer 2 sec, 5 sec, 10 sec Connectivity HDMI C (Mini) USB 2.0 Wi-Fi Capable Yes Power Battery 1x EN-EL20\u00a0 Rechargeable Lithium-Ion Battery Pack AC Power Adapter EH-5b AC Adapter (Optional) Operating/Storage Temperature Operating 32 to 104\u00b0F (0 to 40\u00b0C) Humidity: 0 - 85% Physical Dimensions (WxHxD) 4.0 x 2.4 x 1.2\"\u00a0/\u00a0101.6 x 61.0 x 30.5 mm Weight 6.9 oz\u00a0/\u00a0196 g body      only Kit Lens Focal Length 11 - 27.5 mm Comparable 35mm Focal Length: 30 - 74 mm Aperture Maximum: f/3.5 - 5.6 Minimum: f/16 - 16 Angle of View 72\u00b0 - 32\u00b0 Minimum Focus Distance 1.0'\u00a0(30.48 cm) Magnification 0.1x Elements/Groups 8/6 Diaphragm Blades 7 Autofocus Yes Image Stabilization No Filter Thread Front:40.5 mm Dimensions (DxL) Approx. 2.26 x 1.22\" (5.74 x 3.10 cm) Weight 3 oz (85 g)",
    "magnification": "0.1x",
    "aperture": "Maximum: f/3.5 - 5.6 Minimum: f/16 - 16",
    "dimensionswxhxd": "4.0 x 2.4 x 1.2\"\u00a0/\u00a0101.6 x 61.0 x 30.5 mm",
    "autofocus": "Yes",
    "continuousshooting": "Up to 15 fps",
    "meteringmethod": "3D Color Matrix Metering, Center-weighted average metering, Spot      metering",
    "audiorecording": "With Video, Stereo",
    "whitebalancemodes": "Auto, Cloudy, Daylight, Flash, Fluorescent (Day White),      Incandescent, Preset Manual, Shade, Underwater",
    "dustreductionsystem": "Yes",
    "category": "camera",
    "flashcompensation": "-3 EV to +1 EV (in 1/3 EV steps)",
    "freeshipping": "Yes",
    "brand": "Nikon",
    "sensortypesize": "CMOS, 13.2 x 8.8 mm",
    "filterthread": "Front:40.5 mm",
    "connectivity": "HDMI C (Mini) USB 2.0",
    "cameraformat": "Nikon CX (2.7x Crop Factor)",
    "elementsgroups": "8/6",
    "angleofview": "72\u00b0 - 32\u00b0",
    "focustype": "Auto & Manual",
    "included": "Nikon 1 S1 Mirrorless Digital Camera with 11-27.5mm Lens (White) Nikkor 11-27.5mm f/3.5-5.6 Lens for CX Format (White) EN-EL20 Rechargeable Li-ion Battery (1020mAh) MH-27 Battery Charger UC-E15 USB Cable AN-N1000 Neck Strap for Nikon 1 Series Digital Camera (Silver) BF-N1000 Body Cap for Nikon 1 Cameras LC-N40.5 Front Lens Cap for 1 Nikkor Lenses LF-N1000 Rear Lens Cap for 1 Nikkor Lenses ViewNX 2 Software Short Movie Creator CD User's Manual Reference Manual CD One Year CameraBox Warranty",
    "bitdepth": "12-bit",
    "lensmount": "Nikon 1",
    "displayscreen": "3\"\u00a0Rear Screen\u00a0\u00a0Live Preview\u00a0LCD (460,000)",
    "fileformats": "Still Images: JPEG,      RAW Movies: MOV, MPEG-4      AVC/H.264 Audio: AAC",
    "condition": "New",
    "burstrate": "Up to 15 fps at 10.1 MP",
    "builtinflash": "Yes",
    "exposuremodes": "Modes: Aperture Priority, Auto, Manual, Programmed Auto, Shutter      Priority Compensation: -3 EV to +3 EV (in 1/3 EV steps)",
    "opticalzoom": "Interchangable Lens",
    "focusmode": "Continuous-servo AF (C), Focus Lock AF Area Mode, Manual Focus (M),      Single-servo AF (S)",
    "flashmodes": "Auto Auto/Red-eye Reduction Fill-flash/Slow Sync Fill-in Off Rear Curtain/Slow Sync Red-eye Reduction Second-curtain Sync Slow Sync/Red-eye Reduction",
    "viewfindertype": "LCD Display",
    "autofocuspoints": "135",
    "dedicatedflashsystem": "iTTL",
    "maxresolution": "3872 x 2592",
    "guideno": "16'\u00a0(4.88 m)\u00a0ISO100",
    "resolution": "1920 x 1080: 60 fps, 30 fps 1280 x 720: 60 fps, 30 fps 640 x 240: 400 fps 320 x 120: 1200 fps",
    "wificapable": "Yes"
}