{
    "itemid": "NIDCPABK",
    "externalflashconnection": "Hot Shoe",
    "weight": "10.6 oz\u00a0/\u00a0301\u00a0 g including   battery and memory card",
    "battery": "EN-EL20\u00a0Rechargeable Lithium-Ion Battery Pack, 7.2VDC, 1020mAh",
    "isosensitivity": "100-25600",
    "memorycardtype": "SD SDHC SDXC",
    "acpoweradapter": "EH-5b (Optional)",
    "flashmodes": "TTL Auto",
    "attr1star": "2 stars3 stars4 stars5 stars",
    "videorecording": "Yes",
    "dimensions": "No",
    "operatingstoragetemperature": "Operating 32 to 104\u00b0F (0 to 40\u00b0C) Humidity: 0 - 85%",
    "fileformats": "Still Images: JPEG, RAW Movies: MOV, MPEG-4 AVC/H.264 Audio: Linear PCM",
    "selftimer": "5\u00a0Sec, 10\u00a0Sec, 20\u00a0Sec",
    "specifications": "New Page 2 Imaging Pixels Actual: 16.93 Megapixel Effective: 16.2 Megapixel Sensor DX\u00a0(23.6 x 15.6 mm) CMOS File Formats Still Images: JPEG, RAW Movies: MOV, MPEG-4 AVC/H.264 Audio: Linear PCM Max Resolution 16.1MP: 4928 x 3264 @ 3:2 Other Resolutions 9MP: 3696 x 2448 @ 3:2 4MP: 2464 x 1632 @ 3:2 Aspect Ratio 3:2 Optics Lens NIKKOR, 7 elements in 5 groups EFL: 18.5 mm\u00a0(35 mm equivalent: 28 mm) Aperture: f/2.8 (W) - 22 (T) Focus Range Auto: 19.69\" (50 cm) - Infinity Macro: 3.94\" (10 cm) - Infinity Exposure Control ISO Sensitivity 100-25600 Shutter Type: Electronic & Mechanical Speed: 30 - 1/2000\u00a0sec Exposure Metering Center-weighted, Matrix, Spot Exposure Modes Modes: AE Bracketing, AE Lock, Aperture Priority, Auto, Manual, Programmed Auto,   Shutter Priority Compensation: -5 EV to +5 EV (in 1/3 EV steps) Shooting Modes Landscape Monochrome Portrait Vivid Color White Balance Modes Auto Burst Rate Up to 4 fps at 16 MP for up to 26 frames Self Timer 5\u00a0Sec, 10\u00a0Sec, 20\u00a0Sec Remote Control ML-L3 (Optional) Flash Flash Modes TTL Auto Built-in Flash Yes Effective Flash Range 1.64 - 37.73' (0.5 - 11.5 m) External Flash Connection Hot Shoe Memory Memory Card Type SD SDHC SDXC Recording Video Recording Yes Resolution 1920 x 1080: 30 fps, 25 fps, 24 fps 1280 x 720: 30 fps, 25 fps, 24 fps Video Video Clip Length Up to 29\u00a0Min\u00a059\u00a0Sec Audio Recording With Video, Stereo Viewfinder/Display Screen 3.0\" LCD\u00a0Widescreen\u00a0(921,000 pixels) Connectivity/System Requirements Connectivity HDMI C (Mini) USB 2.0 Wi-Fi Yes via   optional adapter Environmental Operating/Storage Temperature Operating 32 to 104\u00b0F (0 to 40\u00b0C) Humidity: 0 - 85% Power Battery EN-EL20\u00a0Rechargeable Lithium-Ion Battery Pack, 7.2VDC, 1020mAh AC Power Adapter EH-5b (Optional) Physical Dimensions (WxHxD) 4.4 x 2.5 x 1.6\"\u00a0/\u00a0111.0 x 64.3 x 40.3 mm excluding   projections Weight 10.6 oz\u00a0/\u00a0301\u00a0 g including   battery and memory card",
    "dimensionswxhxd": "4.4 x 2.5 x 1.6\"\u00a0/\u00a0111.0 x 64.3 x 40.3 mm excluding   projections",
    "otherresolutions": "9MP: 3696 x 2448 @ 3:2 4MP: 2464 x 1632 @ 3:2",
    "sensor": "DX\u00a0(23.6 x 15.6 mm) CMOS",
    "screen": "3.0\" LCD\u00a0Widescreen\u00a0(921,000 pixels)",
    "whitebalancemodes": "Auto",
    "category": "camera",
    "freeshipping": "Yes",
    "brand": "Nikon",
    "lens": "NIKKOR, 7 elements in 5 groups EFL: 18.5 mm\u00a0(35 mm equivalent: 28 mm) Aperture: f/2.8 (W) - 22 (T)",
    "connectivity": "HDMI C (Mini) USB 2.0",
    "focusrange": "Auto: 19.69\" (50 cm) - Infinity Macro: 3.94\" (10 cm) - Infinity",
    "included": "Nikon COOLPIX A Digital Camera (Black) EN-EL20 Rechargeable Li-ion Battery (1020mAh) MH-27 Battery Charger UC-E16 Replacement USB Cable for CoolPix S30 and L26 Camera Strap BS-1 Hot-Shoe Cover ViewNX 2 Software CD-ROM 1-Year CameraBox Warranty",
    "aspectratio": "3:2",
    "pixels": "Actual: 16.93 Megapixel Effective: 16.2 Megapixel",
    "condition": "New",
    "burstrate": "Up to 4 fps at 16 MP for up to 26 frames",
    "remotecontrol": "ML-L3 (Optional)",
    "builtinflash": "Yes",
    "wifi": "Yes via   optional adapter",
    "exposuremodes": "Modes: AE Bracketing, AE Lock, Aperture Priority, Auto, Manual, Programmed Auto,   Shutter Priority Compensation: -5 EV to +5 EV (in 1/3 EV steps)",
    "opticalzoom": "18x Zoom",
    "audiorecording": "With Video, Stereo",
    "shutter": "Type: Electronic & Mechanical Speed: 30 - 1/2000\u00a0sec",
    "shootingmodes": "Landscape Monochrome Portrait Vivid Color",
    "effectiveflashrange": "1.64 - 37.73' (0.5 - 11.5 m)",
    "videocliplength": "Up to 29\u00a0Min\u00a059\u00a0Sec",
    "maxresolution": "16.1MP: 4928 x 3264 @ 3:2",
    "exposuremetering": "Center-weighted, Matrix, Spot",
    "resolution": "1920 x 1080: 30 fps, 25 fps, 24 fps 1280 x 720: 30 fps, 25 fps, 24 fps"
}