{
    "itemid": "PKDXG1B",
    "features": "No",
    "weight": "19 oz\u00a0/\u00a0539 g without battery               or memory card",
    "battery": "1x LB-060\u00a0Rechargeable               Lithium-Ion Battery Pack",
    "isosensitivity": "Auto, 100-3200",
    "memorycardtype": "SD SDHC",
    "acpoweradapter": "Yes (Optional)",
    "flashmodes": "Auto Flash On Off Red-eye Reduction Slow Sync Slow Sync/Red-eye Reduction",
    "maximumeffectiveflashrange": "Wide: 1.64 - 20' (0.50 - 6.10 m) Telephoto: 3.9 - 12' (1.19 -               3.66 m)",
    "attr1star": "2 stars3 stars4 stars5 stars",
    "stillimagespergb": "JPEG: 210 @ Highest Resolution",
    "videorecording": "Yes",
    "burstrate": "Up to .67 fps at 16 MP Up to 4.7 fps at 16 MP for up to               10 frames Up to 10 fps at 16 MP for up to               20 frames Up to 30 fps at 4 MP Up to 60 fps at .3 MP",
    "operatingstoragetemperature": "Operating 32 to 104\u00b0F (0 to 40\u00b0C)",
    "fileformats": "Still Images : JPEG Movies : MOV Audio : Linear PCM               (Stereo)",
    "specifications": "Imaging Pixels Actual: 16.79 Megapixel Effective: 16 Megapixel Sensor 1/2.3\" CMOS File Formats Still Images : JPEG Movies : MOV Audio : Linear PCM               (Stereo) Max Resolution 16MP: 4608 x 3456 Aspect Ratio 3:2, 4:3, 16:9 Image Stabilization Sensor-Shift Optics Lens 15 elements in 13 groups 6 Aspherical EFL: 4.3-223.6 mm\u00a0(35 mm               equivalent: 24-1248 mm) Aperture: f/2.8 (W) - 5.6 (T) Zoom Optical: 52x Digital: 4x Focus Range Wide: 1.97' (0.60 m) - Infinity Telephoto: 9.8' (2.99 m) -               Infinity Macro: 0.98' (29.87 cm) - Super-Macro: 0.4\" (1.02 cm) - Exposure Control ISO Sensitivity Auto, 100-3200 Shutter Type: Electronic Speed: 4 - 1/2000\u00a0sec Type: Electronic Speed: 30 - 1/2000\u00a0sec in Manual               Mode Exposure Metering Center-weighted, Face Detection,               Spot Exposure Modes Modes: Aperture Priority, Auto,               Manual, Movie, Program, Scene               Modes, Shutter Priority Compensation: -2 EV to +2 EV (in               1/3 EV steps) Shooting Modes Auto Face Beautifier Filter (Advanced Filter) Fireworks Handheld Night Scene Kids Landscape Movie Multi-Exposure Night Portrait Party/Indoor Pet Mode Portrait Smile Snow Sports Sunset White Balance Modes Auto, Cloudy, Color Temperature,               Daylight, Fluorescent,               Fluorescent CWF, Incandescent,               Manual Burst Rate Up to .67 fps at 16 MP Up to 4.7 fps at 16 MP for up to               10 frames Up to 10 fps at 16 MP for up to               20 frames Up to 30 fps at 4 MP Up to 60 fps at .3 MP Interval Recording Yes Remote Control O-RC1 (Optional) Flash Flash Modes Auto Flash On Off Red-eye Reduction Slow Sync Slow Sync/Red-eye Reduction Built-in Flash Yes Maximum Effective Flash Range Wide: 1.64 - 20' (0.50 - 6.10 m) Telephoto: 3.9 - 12' (1.19 -               3.66 m) Memory Built-in Memory 15.4MB Memory Card Type SD SDHC Still Images per GB JPEG: 210 @ Highest Resolution Recording Video Recording Yes Resolution 1920 x 1080: 30 fps 1280 x 720: 60 fps, 30 fps 640 x 480: 30 fps, 120 fps Video Video Clip Length Up to 25\u00a0Min Audio Recording Built-in Mic: With Video, Stereo Viewfinder/Display Viewfinder Type Electronic Diopter Adjustment Not               Specified By Manufacturer Screen .2\" LCD\u00a0(200,000 pixels) 3\" LCD\u00a0Rear Screen\u00a0(460,000               pixels) Connectivity/System Requirements Connectivity AV Output, DC Input, HDMI D               (Micro), USB 2.0 Wi-Fi None Software System Requirements Windows: Vista, 7, 8, 8.1 Mac: OS X 10.6.8, 10.7, 10.8 Environmental Operating/Storage Temperature Operating 32 to 104\u00b0F (0 to 40\u00b0C) Waterproofing None Power Battery 1x LB-060\u00a0Rechargeable               Lithium-Ion Battery Pack AC Power Adapter Yes (Optional) Physical Dimensions (WxHxD) 4.7 x 3.5 x 3.8\"\u00a0/\u00a011.9 x 8.9 x               9.7 cm Weight 19 oz\u00a0/\u00a0539 g without battery               or memory card Item ID PKDXG1B Write Your Own Review You're reviewing: Pentax XG-1 Digital Camera 52x Optical Zoom f/2.8-5.6 Lens 16MP (Black) #07988 How do you rate this product? * 1 star 2 stars 3 stars 4 stars 5 stars Price Value Quality * Nickname * Summary of Your Review * Review Submit Review Go Daddy About Us Privacy Policy Privacy Policy Site Map Search Terms Advanced Search Contact Us Manufacturers Prices, specifications, and images are subject to change without notice. We are not responsible for typographical or illustrative errors. \u00a9 2014 CameraBox.com Loading...",
    "builtinmemory": "15.4MB",
    "dimensionswxhxd": "4.7 x 3.5 x 3.8\"\u00a0/\u00a011.9 x 8.9 x               9.7 cm",
    "sensor": "1/2.3\" CMOS",
    "screen": ".2\" LCD\u00a0(200,000 pixels) 3\" LCD\u00a0Rear Screen\u00a0(460,000               pixels)",
    "softwaresystemrequirements": "Windows: Vista, 7, 8, 8.1 Mac: OS X 10.6.8, 10.7, 10.8",
    "category": "camera",
    "whitebalancemodes": "Auto, Cloudy, Color Temperature,               Daylight, Fluorescent,               Fluorescent CWF, Incandescent,               Manual",
    "freeshipping": "Yes",
    "brand": "Pentax",
    "imagestabilization": "Sensor-Shift",
    "lens": "15 elements in 13 groups 6 Aspherical EFL: 4.3-223.6 mm\u00a0(35 mm               equivalent: 24-1248 mm) Aperture: f/2.8 (W) - 5.6 (T)",
    "connectivity": "AV Output, DC Input, HDMI D               (Micro), USB 2.0",
    "focusrange": "Wide: 1.97' (0.60 m) - Infinity Telephoto: 9.8' (2.99 m) -               Infinity Macro: 0.98' (29.87 cm) - Super-Macro: 0.4\" (1.02 cm) -",
    "diopteradjustment": "Not               Specified By Manufacturer",
    "included": "Pentax 07988  XG-1 Digital Camera 52x Optical Zoom f/2.8-5.6 Lens 16MP (Black) LB-060 Rechargeable Li-Ion Battery Power Adapter USB Cable Strap Lens Cap Documentation CD-ROM Limited 1-Year Warranty",
    "aspectratio": "3:2, 4:3, 16:9",
    "pixels": "Actual: 16.79 Megapixel Effective: 16 Megapixel",
    "condition": "New",
    "intervalrecording": "Yes",
    "remotecontrol": "O-RC1 (Optional)",
    "waterproofing": "None",
    "builtinflash": "Yes",
    "wifi": "None",
    "exposuremodes": "Modes: Aperture Priority, Auto,               Manual, Movie, Program, Scene               Modes, Shutter Priority Compensation: -2 EV to +2 EV (in               1/3 EV steps)",
    "zoom": "Optical: 52x Digital: 4x",
    "audiorecording": "Built-in Mic: With Video, Stereo",
    "shutter": "Type: Electronic Speed: 4 - 1/2000\u00a0sec Type: Electronic Speed: 30 - 1/2000\u00a0sec in Manual               Mode",
    "shootingmodes": "Auto Face Beautifier Filter (Advanced Filter) Fireworks Handheld Night Scene Kids Landscape Movie Multi-Exposure Night Portrait Party/Indoor Pet Mode Portrait Smile Snow Sports Sunset",
    "viewfindertype": "Electronic",
    "videocliplength": "Up to 25\u00a0Min",
    "maxresolution": "16MP: 4608 x 3456",
    "exposuremetering": "Center-weighted, Face Detection,               Spot",
    "resolution": "1920 x 1080: 30 fps 1280 x 720: 60 fps, 30 fps 640 x 480: 30 fps, 120 fps"
}