{
    "itemid": "NIDD3200BKKE",
    "externalflashconnection": "Hot Shoe",
    "features": "No",
    "weight": "9.52 oz",
    "battery": "1x EN-EL14\u00a0 Rechargeable                Lithium-Ion Battery Pack,                7.4VDC, 1030mAh",
    "isosensitivity": "100-6400 (High Sensitivity                Mode: 100-12800)",
    "focallength": "18 - 55 mm",
    "memorycardtype": "SD SDHC SDXC",
    "diaphragmblades": "7",
    "acpoweradapter": "EH-5b (Optional)",
    "incameraimageediting": "Color Balance, Color                Outline, Distortion Control,                Edit Movie, Filter Effects,                Fisheye, Image Overlay,                Miniature Effect,                Monochrome, NEF (RAW)                Processing, Perspective                Control, Quick Retouch,                Red-eye Correction,                Straighten, Trim",
    "lensmount": "Nikon F",
    "viewfindercoverage": "95%",
    "attr1star": "2 stars3 stars4 stars5 stars",
    "shutter": "Type: Electronic Speed: 1/4000 - 30\u00a0sec",
    "minimumfocusdistance": "0.92'\u00a0(0.28 m)",
    "maxsyncspeed": "1 / 200 sec",
    "liveview": "Yes",
    "operatingstoragetemperature": "Operating 32 to 104 \u00b0F (0 to 40 \u00b0C)",
    "selftimer": "2 sec, 5 sec, 10 sec, 20 sec",
    "specifications": "New Page 2 Imaging Camera Type Digital SLR with                Interchangeable lenses Lens Mount Nikon F Camera Format DX / (1.5x Crop Factor) Resolution Actual Pixels: 24.2                Megapixels Max Resolution: 24.2 MP:                6016 x 4000 Aspect Ratio 3:2 Sensor Type / Size CMOS, 23.2 x 15.4 mm File Formats Still Images: JPEG,                RAW Movies: MPEG-4                AVC/H.264, MOV Audio: Linear                PCM Memory Card Type SD SDHC SDXC Focus Control Focus Type Auto & Manual Focus Mode Single-servo AF (S),                Continuous-servo AF (C),                Manual Focus (M) , Focus                Lock AF Area Mode Autofocus Points 11 Viewfinder/Display Viewfinder Type Pentamirror, LCD Display Viewfinder Coverage 95% Viewfinder Magnification Approx. 0.8x Diopter Adjustment - -1.7 to +0.5 m Display Screen 3.0\"\u00a0Rear Screen\u00a0\u00a0\u00a0LCD                (921000) Screen Coverage 100% Live View Yes Exposure Control ISO Sensitivity 100-6400 (High Sensitivity                Mode: 100-12800) Shutter Type: Electronic Speed: 1/4000 - 30\u00a0sec Remote Control ML-L3 (Optional) Metering Method Spot metering,                Center-weighted average                metering, 3D Color Matrix                Metering Exposure Modes Modes: Aperture Priority,                Auto, Manual, Programmed                Auto, Shutter Priority Compensation: -5 EV to +5 EV                (in 1/3 EV steps) White Balance Modes Auto, Cloudy, Daylight,                Flash, Fluorescent,                Incandescent, Preset Manual,                Shade Flash Built-in Flash Yes: Auto, Auto/Red-eye                Reduction, Off,                Second-curtain Sync, Slow                Sync, Slow Sync./Red-eye                Reduction Max Sync Speed 1 / 200 sec Continuous Shooting Up to 4 fps Dedicated Flash System iTTL External Flash Connection Hot Shoe AV Recording Video Recording Yes, NTSC/PAL Audio Recording With Video, Stereo, Via                Optional External Mic Performance In-Camera Image Editing Color Balance, Color                Outline, Distortion Control,                Edit Movie, Filter Effects,                Fisheye, Image Overlay,                Miniature Effect,                Monochrome, NEF (RAW)                Processing, Perspective                Control, Quick Retouch,                Red-eye Correction,                Straighten, Trim Self Timer 2 sec, 5 sec, 10 sec, 20 sec Connectivity HDMI C (Mini), USB 2.0 Wi-Fi Capable (With Optional                Transmitter) Yes Power Battery 1x EN-EL14\u00a0 Rechargeable                Lithium-Ion Battery Pack,                7.4VDC, 1030mAh AC Power Adapter EH-5b (Optional) Operating/Storage                Temperature Operating 32 to 104 \u00b0F (0 to 40 \u00b0C) Physical Dimensions (WxHxD) 5.0 x 3.8 x 3.1\" Weight 1.0 lb Kit Lens Focal Length 18 - 55 mm Aperture Maximum: f/3.5 - 5.6 Minimum: f/22 - 36 Angle of View 76\u00b0 - 28\u00b0 Minimum Focus Distance 0.92'\u00a0(0.28 m) Magnification 3x Maximum Reproduction Ratio 1:3.2 Groups/Elements 8/11 Diaphragm Blades 7 Autofocus Yes Image Stabilization Yes Filter Thread 52 mm Dimensions (DxL) Approx. 2.87 x 3.13\" Weight 9.52 oz",
    "magnification": "3x",
    "videorecording": "Yes, NTSC/PAL",
    "aperture": "Maximum: f/3.5 - 5.6 Minimum: f/22 - 36",
    "dimensionswxhxd": "5.0 x 3.8 x 3.1\"",
    "autofocus": "Yes",
    "meteringmethod": "Spot metering,                Center-weighted average                metering, 3D Color Matrix                Metering",
    "audiorecording": "With Video, Stereo, Via                Optional External Mic",
    "whitebalancemodes": "Auto, Cloudy, Daylight,                Flash, Fluorescent,                Incandescent, Preset Manual,                Shade",
    "category": "camera",
    "screencoverage": "100%",
    "viewfindermagnification": "Approx. 0.8x",
    "freeshipping": "Yes",
    "brand": "Nikon",
    "sensortypesize": "CMOS, 23.2 x 15.4 mm",
    "filterthread": "52 mm",
    "connectivity": "HDMI C (Mini), USB 2.0",
    "cameraformat": "DX / (1.5x Crop Factor)",
    "groupselements": "8/11",
    "angleofview": "76\u00b0 - 28\u00b0",
    "focustype": "Auto & Manual",
    "included": "Nikon D3200 Digital SLR Camera With AF-S DX NIKKOR 18-55mm 3.5-5.6G VR Lens (Black) 18-55 F/3.5-5.6G VR AF-S DX Nikkor Lens Front & Rear Lens Caps 52mm Snap-On Lens Cap Bundled Software: ViewNX 2 CD-ROM EN-EL14 Lithium-Ion Battery (1030mAh) MH-24 Quick Charger for EN-EL14 Battery EG-CP14 A/V Cable AN-DC3 Camera Strap (Black) BF-1B Body Cap BS-1 Hot-Shoe Cover DK-5 Eyepiece Shield (Replacement) DK-20 Rubber Eyecup UC-E17 USB Cable 1-Year Camera Box Warranty",
    "continuousshooting": "Up to 4 fps",
    "aspectratio": "3:2",
    "displayscreen": "3.0\"\u00a0Rear Screen\u00a0\u00a0\u00a0LCD                (921000)",
    "fileformats": "Still Images: JPEG,                RAW Movies: MPEG-4                AVC/H.264, MOV Audio: Linear                PCM",
    "condition": "New",
    "imagestabilization": "Yes",
    "remotecontrol": "ML-L3 (Optional)",
    "diopteradjustment": "- -1.7 to +0.5 m",
    "cameratype": "Digital SLR with                Interchangeable lenses",
    "builtinflash": "Yes: Auto, Auto/Red-eye                Reduction, Off,                Second-curtain Sync, Slow                Sync, Slow Sync./Red-eye                Reduction",
    "exposuremodes": "Modes: Aperture Priority,                Auto, Manual, Programmed                Auto, Shutter Priority Compensation: -5 EV to +5 EV                (in 1/3 EV steps)",
    "maximumreproductionratio": "1:3.2",
    "focusmode": "Single-servo AF (S),                Continuous-servo AF (C),                Manual Focus (M) , Focus                Lock AF Area Mode",
    "dimensionsdxl": "Approx. 2.87 x 3.13\"",
    "wificapablewithoptionaltransmitter": "Yes",
    "viewfindertype": "Pentamirror, LCD Display",
    "autofocuspoints": "11",
    "dedicatedflashsystem": "iTTL",
    "resolution": "Actual Pixels: 24.2                Megapixels Max Resolution: 24.2 MP:                6016 x 4000"
}