{
    "itemid": "NIDD7000K",
    "externalflashconnection": "Hot shoe or Wireless            Commander support",
    "weight": "1 lb 11.5 oz (779g)",
    "durability": "Dust sealed Magnesium-alloy top and rear covers",
    "sensitivity": "100-6400 ISO Can be set up            to approximately 2 EV above ISO 6400; auto            ISO sensitivity control available",
    "multichannelplayback": "Yes",
    "weatherproofing": "Moisture sealed",
    "shutterspeeds": "1/8,000 to 30 s in steps of            1/3 or 1/2 EV Bulb time - requires optional remote control",
    "memorycardtype": "SD/SDHC/SDXC Twin memory card slots",
    "poweradapter": "AC adapter optional",
    "imagestabilization": "Yes",
    "colorspaces": "Not specified by            manufacturer",
    "batterytype": "EN-EL15 rechargeable            lithium-ion battery",
    "viewfindercoverage": "Approximately 100% -            Approximately 0.95x magnification",
    "attr1star": "2 stars3 stars4 stars5 stars",
    "maxsyncspeed": "1/250",
    "dimensions": "5.2 x 4.2 x 3\" (13.2 x 10.6            x 7.6cm)",
    "specifications": "New Page 1 Camera Type DSLR (with 1080p video) Imaging Resolution 16.2MP Sensor Nikon DX-Format (23.6 x            15.6mm) CMOS Sensor With Nikon's dust reduction system Bit Depth 14-bit File Formats Stills: RAW, JPEG, RAW +            JPEG File Size Large: 4,928 x 3,262 Medium: 3,696 x 2,448 Small: 2,464 x 1,632 Color Spaces Not specified by            manufacturer Image Stabilization Yes Optics NIKKOR AF-S DX NIKKOR            18-105mm f/3.5-5.6G ED VR Lens Zoom Two-touch Lens Mount Nikon F bayonet mount (With            AF coupling and AF contacts) Compatible with DX AF, D/G type AF            (excluding IX), AF (other than D/G type,            excluding lenses for F3AF, all functions            supported except 3D Color Matrix Metering            II), AI-P (all functions supported except 3D            Color Matrix Metering II), Non-CPU (can be            used in modes A and M; Color Matrix Metering            and aperture value display supported if user            provides lens data (AI lenses only),            Electronic rangefinder can be used if            maximum aperture is f/5.6 or faster) Focus Type Auto and manual Focus Range 1.5' (0.45m) throughout Shooting Controls Sensitivity 100-6400 ISO Can be set up            to approximately 2 EV above ISO 6400; auto            ISO sensitivity control available Shutter Speeds 1/8,000 to 30 s in steps of            1/3 or 1/2 EV Bulb time - requires optional remote control Metering Matrix Burst Capability 6 frames per second; up to            100 images Remote Control Optional ML-L3 remote Flash Built-in Flash Yes External Flash Connection Hot shoe or Wireless            Commander support Max Sync Speed 1/250 Memory Memory Card Type SD/SDHC/SDXC Twin memory card slots A/V Recording Video Recording Yes Recording Formats H.264/MPEG 4, MOV Video Resolution NTSC: 1920 x 1080/24p 1280 x 720/30p 1280 x 720/24p 640 x 424/30p PAL: 1920 x 1080/24p 1280 x 720/25p 1280 x 720/24p 640 x 424/25p Video Clip Length Maximum recording time:            approximately 20 minutes Audio Recording Built-in monaural or            external stereo microphone recording Viewfinder/Display Viewfinder Type Pentaprism optical            viewfinder Viewfinder Coverage Approximately 100% -            Approximately 0.95x magnification Display 3\" LCD with 170\u00b0 viewing Multi-Channel Playback Yes Connectivity/System            Requirements Connectivity USB 2.0 A/V out HDMI Mic input GPS connection System & Software            Requirements For ViewNX 2 Software Windows CPU Display, playback, and editing of still            images and movies (MotionJPEG): Intel Celeron / Pentium 4 / Core Series,            1.6GHz or above Playback and editing of H.264 movies: Pentium D 3.0GHz or above (during playback) Core 2 Duo 2.6GHz or above (during editing) OS Windows 7 Home Basic/Home Premium/Professional/Enterprise/Ultimate Windows Vista Home Basic/Home            Premium/Business/Enterprise/Ultimate            (Service Pack 2) Windows XP Home Edition/Professional            (Service Pack 3) This application requires a computer with a            pre-installed operating system. If you use            64-bit version Windows 7 or 64-bit version            Windows Vista, operation takes place under            32-bit compatibility environment Hard Disk Space 500MB or above for OS startup disk unit (1GB            or above is recommended) For OS installation: 50 MB or above Installed RAM Windows 7 or Windows Vista: 1GB or above            (1.5GB or above is recommended) Windows XP: 512MB or above (1GB or above is            recommended) Display Resolution: 1024 x 768 pixels (XGA) or more Display color: 24-bit color or above Interface USB: Only built-in USB ports supported Connect the camera directly to the computer;            do not use a hub or USB keyboard Miscellaneous An internet environment is required to use            \"Nikon Message Center 2\", the [GeoTag]            feature and my Picturetown The installation requires the CD-ROM drive            on your PC To use all the functions, you need Google            Earth Plug-in, QuickTime 7 (or later), and            DirectX 9 (or later) For playback and            editing of H.264 movies A computer with a graphics board of 128MB or            above installed is recommended Macintosh Processor Display, playback, and editing of still            images and movies (MotionJPEG): Power PC G4            1GHz or above / PowerPC G5 / Intel Core            series / Intel Xeon series Playback and editing of H.264 movies:            PowerPC G5 Dual 2GHz or above / Core Duo            2GHz or above (during playback) Core 2 Duo 2.6GHz or above (during editing) OS Mac OS X (Version 10.4.11, 10.5.8, 10.6.4) RAM 512MB or above (1GB or above is recommended) Hard Disk Space 500MB or above for OS startup disk unit (1GB            or above is recommended) For OS installation: 50 MB or above Monitor Resolution Resolution: 1024 x 768 pixels (XGA) or more Display color: Millions or above Interface USB: Built-in USB ports and FireWire ports            supported Connect the camera directly to the computer;            do not use a hub or USB keyboard Miscellaneous An internet environment is required to use            \"Nikon Message Center 2\", the [GeoTag]            feature and my Picturetown The installation requires the CD-ROM drive            on your PC For playback and editing of H.264 movies A computer with a graphics board of 128MB or            above installed is recommended During editing or playing of a            high-definition movie using Nikon Movie            Editor on a PowerPC model, the performance            of the computer might become extremely slow Environmental Weatherproofing Moisture sealed Durability Dust sealed Magnesium-alloy top and rear covers Power Battery Type EN-EL15 rechargeable            lithium-ion battery Power Adapter AC adapter optional Physical Dimensions 5.2 x 4.2 x 3\" (13.2 x 10.6            x 7.6cm) Weight 1 lb 11.5 oz (779g)",
    "filesize": "Large: 4,928 x 3,262 Medium: 3,696 x 2,448 Small: 2,464 x 1,632",
    "videorecording": "Yes",
    "focustype": "Auto and manual",
    "sensor": "Nikon DX-Format (23.6 x            15.6mm) CMOS Sensor With Nikon's dust reduction system",
    "audiorecording": "Built-in monaural or            external stereo microphone recording",
    "category": "camera",
    "systemsoftwarerequirements": "For ViewNX 2 Software Windows CPU Display, playback, and editing of still            images and movies (MotionJPEG): Intel Celeron / Pentium 4 / Core Series,            1.6GHz or above Playback and editing of H.264 movies: Pentium D 3.0GHz or above (during playback) Core 2 Duo 2.6GHz or above (during editing) OS Windows 7 Home Basic/Home Premium/Professional/Enterprise/Ultimate Windows Vista Home Basic/Home            Premium/Business/Enterprise/Ultimate            (Service Pack 2) Windows XP Home Edition/Professional            (Service Pack 3) This application requires a computer with a            pre-installed operating system. If you use            64-bit version Windows 7 or 64-bit version            Windows Vista, operation takes place under            32-bit compatibility environment Hard Disk Space 500MB or above for OS startup disk unit (1GB            or above is recommended) For OS installation: 50 MB or above Installed RAM Windows 7 or Windows Vista: 1GB or above            (1.5GB or above is recommended) Windows XP: 512MB or above (1GB or above is            recommended) Display Resolution: 1024 x 768 pixels (XGA) or more Display color: 24-bit color or above Interface USB: Only built-in USB ports supported Connect the camera directly to the computer;            do not use a hub or USB keyboard Miscellaneous An internet environment is required to use            \"Nikon Message Center 2\", the [GeoTag]            feature and my Picturetown The installation requires the CD-ROM drive            on your PC To use all the functions, you need Google            Earth Plug-in, QuickTime 7 (or later), and            DirectX 9 (or later) For playback and            editing of H.264 movies A computer with a graphics board of 128MB or            above installed is recommended Macintosh Processor Display, playback, and editing of still            images and movies (MotionJPEG): Power PC G4            1GHz or above / PowerPC G5 / Intel Core            series / Intel Xeon series Playback and editing of H.264 movies:            PowerPC G5 Dual 2GHz or above / Core Duo            2GHz or above (during playback) Core 2 Duo 2.6GHz or above (during editing) OS Mac OS X (Version 10.4.11, 10.5.8, 10.6.4) RAM 512MB or above (1GB or above is recommended) Hard Disk Space 500MB or above for OS startup disk unit (1GB            or above is recommended) For OS installation: 50 MB or above Monitor Resolution Resolution: 1024 x 768 pixels (XGA) or more Display color: Millions or above Interface USB: Built-in USB ports and FireWire ports            supported Connect the camera directly to the computer;            do not use a hub or USB keyboard Miscellaneous An internet environment is required to use            \"Nikon Message Center 2\", the [GeoTag]            feature and my Picturetown The installation requires the CD-ROM drive            on your PC For playback and editing of H.264 movies A computer with a graphics board of 128MB or            above installed is recommended During editing or playing of a            high-definition movie using Nikon Movie            Editor on a PowerPC model, the performance            of the computer might become extremely slow",
    "freeshipping": "Yes",
    "brand": "Nikon",
    "metering": "Matrix",
    "connectivity": "USB 2.0 A/V out HDMI Mic input GPS connection",
    "focusrange": "1.5' (0.45m) throughout",
    "recordingformats": "H.264/MPEG 4, MOV",
    "included": "Nikon D7000 DSLR Camera Kit with Nikon 18-105mm DX VR Lens 18-105mm f/3.5-5.6G ED VR AF-S DX Nikkor Autofocus Lens EN-EL15 Lithium-Ion Battery MH-25 QuickCharger Camera Strap USB Cable Audio Video Cable DK-5 Eyepiece Shield (Replacement) DK-21 Rubber Eyecup for Nikon D80, D90, D200 & D7000 Digital Cameras BM-11 LCD Monitor Cover BF-1B Body Cap BS-1 Hot-Shoe Cover ViewNX 2 CD-ROM User's Manual",
    "bitdepth": "14-bit",
    "lensmount": "Nikon F bayonet mount (With            AF coupling and AF contacts) Compatible with DX AF, D/G type AF            (excluding IX), AF (other than D/G type,            excluding lenses for F3AF, all functions            supported except 3D Color Matrix Metering            II), AI-P (all functions supported except 3D            Color Matrix Metering II), Non-CPU (can be            used in modes A and M; Color Matrix Metering            and aperture value display supported if user            provides lens data (AI lenses only),            Electronic rangefinder can be used if            maximum aperture is f/5.6 or faster)",
    "burstcapability": "6 frames per second; up to            100 images",
    "fileformats": "Stills: RAW, JPEG, RAW +            JPEG",
    "condition": "New",
    "remotecontrol": "Optional ML-L3 remote",
    "optics": "NIKKOR AF-S DX NIKKOR            18-105mm f/3.5-5.6G ED VR",
    "resolution": "16.2MP",
    "zoom": "Two-touch",
    "opticalzoom": "Interchangable Lens",
    "videocliplength": "Maximum recording time:            approximately 20 minutes",
    "viewfindertype": "Pentaprism optical            viewfinder",
    "builtinflash": "Yes",
    "videoresolution": "NTSC: 1920 x 1080/24p 1280 x 720/30p 1280 x 720/24p 640 x 424/30p PAL: 1920 x 1080/24p 1280 x 720/25p 1280 x 720/24p 640 x 424/25p",
    "display": "3\" LCD with 170\u00b0 viewing"
}