{
    "itemid": "PKDK50B",
    "externalflashconnection": "Hot Shoe, Wireless",
    "acpoweradapter": "K-AC128 (Optional)",
    "weight": "22.9 oz\u00a0/\u00a0649\u00a0 g With   li-ion battery and memory card",
    "maxsyncspeed": "1 / 180 sec",
    "battery": "1x D-LI109\u00a0 Rechargeable Lithium-Ion Battery Pack, 7.4VDC, 1050mAh 4x AA",
    "exposuremodes": "Modes: Aperture Priority, Auto, Bulb, Manual, Movie, Program, Scene Modes,   Sensitivity Priority, Shutter Priority, Shutter/Aperture Priority Metering Range: EV 0.0 - EV 22.0 Compensation: -5 EV to +5 EV (in .3 or .5 EV steps)",
    "isosensitivity": "Auto, 100-51200",
    "focus": "Auto Manual",
    "screencoverage": "100%",
    "memorycardtype": "SD SDHC SDXC",
    "imagestabilization": "Sensor-Shift",
    "incameraimageediting": "Base Parameter Adjustment, Color, Extract Color, Fisheye, High Contrast, Invert   Color, Miniature Effect, Monochrome, Pastel, Posterization, Retro, Shading,   Sketch Filter, Slim, Soft Focus, Tone Expansion, Toy Camera, Watercolor",
    "lensmount": "Pentax K",
    "softwarerequirements": "Windows: XP (SP3), Vista, 7, 8 Mac: OS X 10.5 or later",
    "attr1star": "2 stars3 stars4 stars5 stars",
    "shutter": "Type: Electronic Speed: 30 - 1/6000 sec",
    "bitdepth": "12-bit",
    "dimensions": "5.1 x 3.8 x 2.8\" / 13.0 x 9.7 x 7.1 cm",
    "operatingstoragetemperature": "Operating 14 to 104 \u00b0F (-10 to 40 \u00b0C)",
    "pixels": "Actual: 16.5 Megapixel Effective: 16.3 Megapixel",
    "selftimer": "2 sec, 12 sec",
    "liveview": "Yes",
    "filesize": "1920 x 1080 (Full HD) 1280 x 720 (HD) 640 x 480 (SD)",
    "continuousshootingtime": "1920 x 1080 25 min. 1280 x 720 25 min. 640 x 480 25 min.",
    "dimensionswxhxd": "5.1 x 3.8 x 2.8\"\u00a0/\u00a013.0 x 9.7 x 7.1 cm",
    "viewfindercoverage": "100%",
    "meteringmethod": "Center-weighted average metering, Multi-zone metering, Spot metering",
    "audiorecording": "With Video, Mono",
    "whitebalancemodes": "Auto, Cloudy, Cool White, Daylight, Daylight Color, Daylight White, Flash,   Kelvin, Manual, Shade, Tungsten, Warm White",
    "dustreductionsystem": "Yes",
    "category": "camera",
    "specifications": "New Page 1 Imaging Camera Type Digital SLR with Interchangeable lenses Lens Mount Pentax K Camera Format APS-C / (1.5x Crop Factor) Pixels Actual: 16.5 Megapixel Effective: 16.3 Megapixel Max Resolution 16MP: 4928 x 3264 @ 3:2 Other Resolutions 12MP: 4224 x 2816 @ 3:2 8MP: 3456 x 2304 @ 3:2 5MP: 2688 x 1792 @ 3:2 Aspect Ratio 3:2 Sensor Type / Size CMOS, 23.7 x 15.7 mm File Formats Still Images: DNG, JPEG, RAW Movies: MOV, MPEG-4 AVC/H.264 Bit Depth 12-bit Dust Reduction System Yes Memory Card Type SD SDHC SDXC Image Stabilization Sensor-Shift Focus Control Focus Type Auto\u00a0   & Manual Focus Mode Single-servo AF (S), Continuous-servo AF (C), Manual Focus (M),   Focus Lock AF Area Mode Autofocus Points 11 Viewfinder/Display Viewfinder Type Pentaprism Viewfinder Coverage 100% Viewfinder Magnification Approx. 0.92x Diopter Adjustment - 2.5 to +1.5 m Display Screen 3.0\" Rear Screen Live Preview LCD (921,000) Screen Coverage 100% Live View Yes Exposure Control ISO Sensitivity Auto, 100-51200 Shutter Type: Electronic Speed: 30 - 1/6000 sec Remote Control Remote Control F or O-RC1 (Optional) Metering Method Center-weighted average metering, Multi-zone metering, Spot metering Exposure Modes Modes: Aperture Priority, Auto, Bulb, Manual, Movie, Program, Scene Modes,   Sensitivity Priority, Shutter Priority, Shutter/Aperture Priority Metering Range: EV 0.0 - EV 22.0 Compensation: -5 EV to +5 EV (in .3 or .5 EV steps) White Balance Modes Auto, Cloudy, Cool White, Daylight, Daylight Color, Daylight White, Flash,   Kelvin, Manual, Shade, Tungsten, Warm White Flash Flash Modes Red-eye Reduction Second-curtain Sync Slow Sync TTL Auto Built-in Flash Yes Guide No. 39.37' (12 m) ISO100 Max Sync Speed 1 / 180 sec Flash Compensation -2 EV to +1 EV (in 0.5 EV steps) Dedicated Flash System P-TTL Remote Firing External Flash Connection Hot Shoe, Wireless AV Recording Video Recording Yes, NTSC/PAL File Size 1920 x 1080 (Full HD) 1280 x 720 (HD) 640 x 480 (SD) Aspect Ratio 16:9 Frame Rate @ 1920 x 1080: 30 fps, 25 fps, 24 fps @ 1280 x 720: 60 fps, 50 fps, 30 fps, 24 fps @ 640 x 480: 30 fps, 25 fps, 24 fps Continuous Shooting Time 1920 x 1080 25 min. 1280 x 720 25 min. 640 x 480 25 min. Exposure Compensation -2 EV to +2 EV Focus Auto Manual Continuous Shooting Time 1920 x 1080 25 min. 1280 x 720 25 min. 640 x 480 25 min. Audio Recording With Video, Mono Performance In-Camera Image Editing Base Parameter Adjustment, Color, Extract Color, Fisheye, High Contrast, Invert   Color, Miniature Effect, Monochrome, Pastel, Posterization, Retro, Shading,   Sketch Filter, Slim, Soft Focus, Tone Expansion, Toy Camera, Watercolor Self Timer 2 sec, 12 sec Interval Recording Yes Connectivity AV Output, USB 2.0 Software Requirements Windows: XP (SP3), Vista, 7, 8 Mac: OS X 10.5 or later Power Battery 1x D-LI109\u00a0 Rechargeable Lithium-Ion Battery Pack, 7.4VDC, 1050mAh 4x AA AC Power Adapter K-AC128 (Optional) Operating/Storage Temperature Operating 14 to 104 \u00b0F (-10 to 40 \u00b0C) Physical Dimensions (WxHxD) 5.1 x 3.8 x 2.8\"\u00a0/\u00a013.0 x 9.7 x 7.1 cm Weight 22.9 oz\u00a0/\u00a0649\u00a0 g With   li-ion battery and memory card",
    "viewfindermagnification": "Approx. 0.92x",
    "freeshipping": "Yes",
    "brand": "Pentax",
    "sensortypesize": "CMOS, 23.7 x 15.7 mm",
    "connectivity": "AV Output, USB 2.0",
    "cameraformat": "APS-C / (1.5x Crop Factor)",
    "focustype": "Auto\u00a0   & Manual",
    "included": "Pentax K-50 Digital SLR Camera (Body) Rechargeable Li-Ion Battery D-Li109 K-BC109 Battery Charger Kit for D-LI109 Battery AC Plug Cord I-USB7 USB Interface Cable Hotshoe Cover FK Eyecup FR for K7 Digital SLR Camera (replacement) SLR Body Mount Cover Camera Strap Software CD-ROM Limited Warranty",
    "videorecording": "Yes, NTSC/PAL",
    "aspectratio": "16:9",
    "displayscreen": "3.0\" Rear Screen Live Preview LCD (921,000)",
    "fileformats": "Still Images: DNG, JPEG, RAW Movies: MOV, MPEG-4 AVC/H.264",
    "condition": "New",
    "intervalrecording": "Yes",
    "otherresolutions": "12MP: 4224 x 2816 @ 3:2 8MP: 3456 x 2304 @ 3:2 5MP: 2688 x 1792 @ 3:2",
    "remotecontrol": "Remote Control F or O-RC1 (Optional)",
    "diopteradjustment": "- 2.5 to +1.5 m",
    "cameratype": "Digital SLR with Interchangeable lenses",
    "flashmodes": "Red-eye Reduction Second-curtain Sync Slow Sync TTL Auto",
    "builtinflash": "Yes",
    "framerate": "@ 1920 x 1080: 30 fps, 25 fps, 24 fps @ 1280 x 720: 60 fps, 50 fps, 30 fps, 24 fps @ 640 x 480: 30 fps, 25 fps, 24 fps",
    "dedicatedflashsystem": "P-TTL Remote Firing",
    "opticalzoom": "Interchangable Lens",
    "focusmode": "Single-servo AF (S), Continuous-servo AF (C), Manual Focus (M),   Focus Lock AF Area Mode",
    "flashcompensation": "-2 EV to +1 EV (in 0.5 EV steps)",
    "viewfindertype": "Pentaprism",
    "autofocuspoints": "11",
    "exposurecompensation": "-2 EV to +2 EV",
    "maxresolution": "16MP: 4928 x 3264 @ 3:2",
    "guideno": "39.37' (12 m) ISO100",
    "resolution": "16 Megapixels"
}