{
    "itemid": "RIDWG4B",
    "features": "No",
    "weight": "8.3 oz\u00a0/\u00a0235 g with battery and memory card",
    "includedsoftwarerequirements": "Windows: XP   (SP3), Vista, 7, 8 Mac: OS X 10.4 or later",
    "battery": "1x   D-LI92\u00a0Rechargeable Lithium-Ion   Battery Pack, 3.7VDC, 925mAh",
    "isosensitivity": "Auto, 125-6400",
    "memorycardtype": "SD SDHC SDXC",
    "acpoweradapter": "K-AC117U   (Optional)",
    "maximumeffectiveflashrange": "Wide: Up To 34'   (10.36 m) Telephoto: Up To 14' (4.27 m)",
    "shootingmodes": "1cm Macro Movie Blue Sky Candle Digital Microscope Digital Panorama Digital SR Digital Wide Fireworks Flower Food Green Group Photo HDR Handheld Night Shot High Speed Movie Interval Movie Interval Shooting Kids Landscape Night Portrait Night Scene Pet Mode Portrait Portrait x Backlight Portrait x Blue Sky Portrait x Sunset Report Sports Standard Sunset Surf & Snow Text Time-Lapse Movie Underwater Underwater Movie",
    "attr1star": "2 stars3 stars4 stars5 stars",
    "videorecording": "Yes, NTSC/PAL",
    "burstrate": "Up to 1.5 fps at   16 MP Up to 14 fps at 5 MP for up to   30 frames",
    "operatingstoragetemperature": "Operating 14 to 104\u00b0F (-10 to 40\u00b0C)",
    "pixels": "Actual: 16.79   Megapixel Effective: 16 Megapixel",
    "selftimer": "10\u00a0Sec, 2\u00a0Sec",
    "specifications": "New Page 2 Imaging Pixels Actual: 16.79   Megapixel Effective: 16 Megapixel Sensor 1/2.3\" CMOS File Formats Still Images: JPEG Movies: MP4, MPEG-4 AVC/H.264 Audio: WAV Max Resolution 16MP: 4608 x   3456 Aspect Ratio 1:1, 4:3, 16:9 Image   Stabilization Sensor-Shift Optics Lens 9 elements in 7   groups 4 Aspherical EFL: 4.5-18 mm\u00a0(35 mm   equivalent: 25-100 mm) Aperture: f/2 (W) - 4.9 (T) Zoom Optical: 4x Digital: 7.2x Intelligent Zoom: 6x Intelligent Zoom: 28.8x Focus Range Normal: 1.31'   (39.93 cm) - Infinity Macro: 0.33' (10.06 cm) - 1.64'   (49.99 cm) Super-Macro: 0.39\" (1 cm) -   0.98' (29.87 cm) Exposure Control ISO Sensitivity Auto, 125-6400 Shutter Type: Electronic   & Mechanical Speed: 1/4 - 1/4000\u00a0sec Type: Electronic & Mechanical Speed: 4 - 1/2000\u00a0sec in Shutter   Priority Mode Type: Electronic & Mechanical Speed: 4 - 1/2000\u00a0sec in Night   Scene Mode Exposure   Metering Center-weighted,   Multi, Spot Exposure Modes Modes: Auto,   Movie, Programmed Auto, Shutter   Priority, Underwater, User Compensation: -2 EV to +2 EV (in   1/3 EV steps) Shooting Modes 1cm Macro Movie Blue Sky Candle Digital Microscope Digital Panorama Digital SR Digital Wide Fireworks Flower Food Green Group Photo HDR Handheld Night Shot High Speed Movie Interval Movie Interval Shooting Kids Landscape Night Portrait Night Scene Pet Mode Portrait Portrait x Backlight Portrait x Blue Sky Portrait x Sunset Report Sports Standard Sunset Surf & Snow Text Time-Lapse Movie Underwater Underwater Movie White Balance   Modes Auto, Daylight,   Fluorescent (Day White),   Fluorescent (Daylight),   Fluorescent (White), Manual,   Shade, Tungsten Burst Rate Up to 1.5 fps at   16 MP Up to 14 fps at 5 MP for up to   30 frames Self Timer 10\u00a0Sec, 2\u00a0Sec Interval   Recording Yes Remote Control O-RC1 (Optional) Flash Flash Modes Auto Auto/Red-eye Reduction Flash On Flash On w/ Red-eye Reduction Off Built-in Flash Yes Maximum   Effective Flash Range Wide: Up To 34'   (10.36 m) Telephoto: Up To 14' (4.27 m) Memory Built-in Memory 70MB Memory Card Type SD SDHC SDXC Recording Video Recording Yes, NTSC/PAL Resolution 1920 x 1080: 30   fps 1280 x 720: 60 fps, 30 fps Video Video Clip   Length Up to 26\u00a0Min Audio Recording Built-in Mic:   With Video, Stereo Viewfinder/Display Screen 3.0\" LCD\u00a0Rear   Screen\u00a0(460,000 pixels) Connectivity/System Requirements Connectivity AV Output, HDMI   D (Micro), USB 2.0 Included   Software Requirements Windows: XP   (SP3), Vista, 7, 8 Mac: OS X 10.4 or later Environmental Operating/Storage Temperature Operating 14 to 104\u00b0F (-10 to 40\u00b0C) Waterproofing 45.9' (14.0 m) Power Battery 1x   D-LI92\u00a0Rechargeable Lithium-Ion   Battery Pack, 3.7VDC, 925mAh AC Power Adapter K-AC117U   (Optional) Physical Dimensions (WxHxD) 4.9 x 2.5 x   1.3\"\u00a0/\u00a012.4 x 6.4 x 3.3 cm Weight 8.3 oz\u00a0/\u00a0235 g with battery and memory card",
    "builtinmemory": "70MB",
    "dimensionswxhxd": "4.9 x 2.5 x   1.3\"\u00a0/\u00a012.4 x 6.4 x 3.3 cm",
    "sensor": "1/2.3\" CMOS",
    "screen": "3.0\" LCD\u00a0Rear   Screen\u00a0(460,000 pixels)",
    "whitebalancemodes": "Auto, Daylight,   Fluorescent (Day White),   Fluorescent (Daylight),   Fluorescent (White), Manual,   Shade, Tungsten",
    "category": "camera",
    "freeshipping": "Yes",
    "brand": "Ricoh",
    "imagestabilization": "Sensor-Shift",
    "lens": "9 elements in 7   groups 4 Aspherical EFL: 4.5-18 mm\u00a0(35 mm   equivalent: 25-100 mm) Aperture: f/2 (W) - 4.9 (T)",
    "connectivity": "AV Output, HDMI   D (Micro), USB 2.0",
    "focusrange": "Normal: 1.31'   (39.93 cm) - Infinity Macro: 0.33' (10.06 cm) - 1.64'   (49.99 cm) Super-Macro: 0.39\" (1 cm) -   0.98' (29.87 cm)",
    "included": "Ricoh WG-4 GPS Digital Camera 16MP, 4x Optical Zoom, Water, Dust, Crush, Shock, and Coldproof, Built-In GPS Module and Digital Compass (Black) D-LI92 Rechargeable Li-Ion Battery for Pentax X70 Digital Camera Power Adapter D-PA135J I-USB7 USB Interface Cable Carabiner Strap O-ST144 Software CD-ROM S-SW145 Limited 1-Year Warranty",
    "aspectratio": "1:1, 4:3, 16:9",
    "fileformats": "Still Images: JPEG Movies: MP4, MPEG-4 AVC/H.264 Audio: WAV",
    "condition": "New",
    "intervalrecording": "Yes",
    "remotecontrol": "O-RC1 (Optional)",
    "waterproofing": "45.9' (14.0 m)",
    "builtinflash": "Yes",
    "exposuremodes": "Modes: Auto,   Movie, Programmed Auto, Shutter   Priority, Underwater, User Compensation: -2 EV to +2 EV (in   1/3 EV steps)",
    "zoom": "Optical: 4x Digital: 7.2x Intelligent Zoom: 6x Intelligent Zoom: 28.8x",
    "audiorecording": "Built-in Mic:   With Video, Stereo",
    "shutter": "Type: Electronic   & Mechanical Speed: 1/4 - 1/4000\u00a0sec Type: Electronic & Mechanical Speed: 4 - 1/2000\u00a0sec in Shutter   Priority Mode Type: Electronic & Mechanical Speed: 4 - 1/2000\u00a0sec in Night   Scene Mode",
    "flashmodes": "Auto Auto/Red-eye Reduction Flash On Flash On w/ Red-eye Reduction Off",
    "videocliplength": "Up to 26\u00a0Min",
    "maxresolution": "16MP: 4608 x   3456",
    "exposuremetering": "Center-weighted,   Multi, Spot",
    "resolution": "1920 x 1080: 30   fps 1280 x 720: 60 fps, 30 fps"
}