{
    "externalflashconnection": "Hot Shoe",
    "exposurecontrol": "Auto Manual",
    "weight": "6.88 oz (195 g)",
    "mirrorlockup": "Yes",
    "battery": "1x EN-EL14a\u00a0 Rechargeable Lithium-Ion Battery Pack, 7.2VDC, 1230mAh",
    "exposuremodes": "Modes: Aperture Priority, Auto, Manual, Programmed Auto, Scene Modes,     Shutter Priority Metering Range: EV 0.0 - EV 20.0 Compensation: -5     EV to +5 EV (in 1/3 or 1/2 EV steps)",
    "isosensitivity": "Auto, 100-12800 (Extended Mode: 100-25600)",
    "focallength": "18 - 55mm Comparable 35mm Focal Length: 27 - 82.5 mm",
    "focus": "Auto Manual Continuous Auto",
    "memorycardtype": "SD SDHC SDXC",
    "diaphragmblades": "7, Rounded",
    "acpoweradapter": "EH-5b (Optional)",
    "aspectratio": "16:9",
    "viewfindercoverage": "95%",
    "attr1star": "2 stars3 stars4 stars5 stars",
    "shutter": "Type: Electronic & Mechanical Speed: 30 - 1/4000\u00a0sec, Bulb Mode",
    "videorecording": "Yes",
    "dimensions": "No",
    "minimumfocusdistance": "11.02\"\u00a0(28 cm)",
    "operatingstoragetemperature": "Operating 32 to 104\u00b0F (0 to 40\u00b0C)",
    "dimensionsdxl": "Approx. 2.34 x 2.60\" (59.5 x 66 mm)",
    "pixels": "Actual: 24.78 Megapixel Effective: 24.2 Megapixel",
    "selftimer": "2 sec, 5 sec, 10 sec, 20 sec Number of Shots: 1-9",
    "specifications": "Imaging Lens Mount Nikon F Camera Format DX / (1.5x Crop Factor) Pixels Actual: 24.78 Megapixel Effective: 24.2 Megapixel Max Resolution 24MP: 6000 x 4000 Aspect Ratio 3:2 Sensor Type / Size CMOS, 23.5 x 15.6 mm File Formats Still Images: JPEG, RAW Movies: MOV, MPEG-4     AVC/H.264 Audio: Linear PCM Bit Depth 14-bit Dust Reduction System Yes Memory Card Type SD SDHC SDXC Focus Control Focus Type Auto & Manual Focus Mode Single-servo AF (S), Continuous-servo AF (C), Manual Focus (M) Autofocus Points Phase Detection: 39 Viewfinder/Display Viewfinder Type Pentamirror Viewfinder Coverage 95% Viewfinder Magnification Approx. 0.82x Diopter Adjustment - 1.7 to +1 m Display Screen 3.2\"\u00a0Rear Screen\u00a0Swivel\u00a0\u00a0LCD (1,037,000) Screen Coverage 100% Diagonal Angle of View 170.0\u00b0 Exposure Control ISO Sensitivity Auto, 100-12800 (Extended Mode: 100-25600) Shutter Type: Electronic & Mechanical Speed: 30 - 1/4000\u00a0sec, Bulb Mode Remote Control MC-DC2 (Optional) Mirror Lock-Up Yes Metering Method 3D Color Matrix Metering, Center-weighted average metering, Spot     metering Exposure Modes Modes: Aperture Priority, Auto, Manual, Programmed Auto, Scene Modes,     Shutter Priority Metering Range: EV 0.0 - EV 20.0 Compensation: -5     EV to +5 EV (in 1/3 or 1/2 EV steps) White Balance Modes Auto, Cloudy, Direct Sunlight, Flash, Fluorescent, Incandescent, Preset     Manual, Shade Flash Flash Modes Auto Auto/Red-eye Reduction Fill-in Off Rear Curtain/Slow     Sync Rear Sync Red-eye Reduction Slow Sync Slow Sync/Red-eye     Reduction Built-in Flash Yes Guide No. 42.65'\u00a0(13 m)\u00a0ISO100 Max Sync Speed 1 / 200 sec Flash Compensation -3 EV to +1 EV (in 1/3 or 1/2 EV steps) Dedicated Flash System iTTL External Flash Connection Hot Shoe AV Recording Video Recording Yes File Size 1920 x 1080p\u00a0(Full HD) 1280 x 720p\u00a0(HD) 640 x 424p\u00a0(SD) Aspect Ratio 16:9 Frame Rate @ 1920 x 1080: 60 fps, 50 fps, 30 fps, 25 fps, 24 fps @ 1280 x 720:     60 fps, 50 fps @ 640 x 424: 30 fps, 25 fps Exposure Control Auto Manual Focus Auto Manual Continuous Auto Video Clip Length 1920 x 1080 @ 60 fps: 20 min. @ 30 fps: 29 min. Audio Recording Built-in Mic: With Video, Stereo Optional External Mic: With Video Performance Continuous Shooting Up to 5 fps Self Timer 2 sec, 5 sec, 10 sec, 20 sec Number of Shots: 1-9 Interval Recording Yes Connectivity 1/8\" Microphone, AV Output, HDMI C (Mini), USB 2.0 Wi-Fi Capable Yes Power Battery 1x EN-EL14a\u00a0 Rechargeable Lithium-Ion Battery Pack, 7.2VDC, 1230mAh AC Power Adapter EH-5b (Optional) Operating/Storage Temperature Operating 32 to 104\u00b0F (0 to 40\u00b0C) Physical Dimensions (WxHxD) 4.9 x 3.9 x 3.0\"\u00a0/\u00a0125.0 x 98.0 x 76.0 mm Weight 1.06 lb\u00a0/\u00a0480 g body     only Kit Lens Focal Length 18 - 55mm Comparable 35mm Focal Length: 27 - 82.5 mm Aperture Maximum: f/3.5 - 5.6 Minimum: f/22 - 36 Angle of View 76\u00b0 - 28\u00b0\u00a050' Minimum Focus Distance 11.02\"\u00a0(28 cm) Magnification 0.31x Elements/Groups 11/8 Diaphragm Blades 7, Rounded Autofocus Yes Image Stabilization Yes Filter Thread Front:52 mm Dimensions (DxL) Approx. 2.34 x 2.60\" (59.5 x 66 mm) Weight 6.88 oz (195 g)",
    "magnification": "0.31x",
    "filesize": "1920 x 1080p\u00a0(Full HD) 1280 x 720p\u00a0(HD) 640 x 424p\u00a0(SD)",
    "aperture": "Maximum: f/3.5 - 5.6 Minimum: f/22 - 36",
    "dimensionswxhxd": "4.9 x 3.9 x 3.0\"\u00a0/\u00a0125.0 x 98.0 x 76.0 mm",
    "autofocus": "Yes",
    "continuousshooting": "Up to 5 fps",
    "meteringmethod": "3D Color Matrix Metering, Center-weighted average metering, Spot     metering",
    "audiorecording": "Built-in Mic: With Video, Stereo Optional External Mic: With Video",
    "whitebalancemodes": "Auto, Cloudy, Direct Sunlight, Flash, Fluorescent, Incandescent, Preset     Manual, Shade",
    "dustreductionsystem": "Yes",
    "category": "camera",
    "screencoverage": "100%",
    "viewfindermagnification": "Approx. 0.82x",
    "freeshipping": "Yes",
    "brand": "Nikon",
    "sensortypesize": "CMOS, 23.5 x 15.6 mm",
    "filterthread": "Front:52 mm",
    "connectivity": "1/8\" Microphone, AV Output, HDMI C (Mini), USB 2.0",
    "cameraformat": "DX / (1.5x Crop Factor)",
    "diagonalangleofview": "170.0\u00b0",
    "angleofview": "76\u00b0 - 28\u00b0\u00a050'",
    "focustype": "Auto & Manual",
    "included": "Nikon D5300 DSLR Camera with 18-55mm Lens (Black) AF-S NIKKOR 18-55mm f/3.5-5.6G VR II DX Lens EN-EL14A Rechargeable Li-Ion Battery for Select Nikon Cameras MH-24 Quick Charger for EN-EL14 Battery EG-CP16 Nikon Audio/Video Cable UC-E17 USB Cable DK-25 Rubber Eyecup AN-DC3 Camera Strap (Black) DK-5 Eyepiece Shield (Replacement) BF-1B Body Cap BS-1 Hot-Shoe Cover Nikon View NX2 Software CD-ROM 1-Year CameraBox Warranty PLUS: Nikon\u00a052mm Clear NC Glass Filter",
    "bitdepth": "14-bit",
    "lensmount": "Nikon F",
    "displayscreen": "3.2\"\u00a0Rear Screen\u00a0Swivel\u00a0\u00a0LCD (1,037,000)",
    "fileformats": "Still Images: JPEG, RAW Movies: MOV, MPEG-4     AVC/H.264 Audio: Linear PCM",
    "condition": "New",
    "intervalrecording": "Yes",
    "imagestabilization": "Yes",
    "remotecontrol": "MC-DC2 (Optional)",
    "diopteradjustment": "- 1.7 to +1 m",
    "videocliplength": "1920 x 1080 @ 60 fps: 20 min. @ 30 fps: 29 min.",
    "builtinflash": "Yes",
    "framerate": "@ 1920 x 1080: 60 fps, 50 fps, 30 fps, 25 fps, 24 fps @ 1280 x 720:     60 fps, 50 fps @ 640 x 424: 30 fps, 25 fps",
    "opticalzoom": "Interchangable Lens",
    "focusmode": "Single-servo AF (S), Continuous-servo AF (C), Manual Focus (M)",
    "flashmodes": "Auto Auto/Red-eye Reduction Fill-in Off Rear Curtain/Slow     Sync Rear Sync Red-eye Reduction Slow Sync Slow Sync/Red-eye     Reduction",
    "flashcompensation": "-3 EV to +1 EV (in 1/3 or 1/2 EV steps)",
    "viewfindertype": "Pentamirror",
    "maxsyncspeed": "1 / 200 sec",
    "autofocuspoints": "Phase Detection: 39",
    "dedicatedflashsystem": "iTTL",
    "maxresolution": "24MP: 6000 x 4000",
    "guideno": "42.65'\u00a0(13 m)\u00a0ISO100",
    "resolution": "24 Megapixels",
    "wificapable": "Yes",
    "elementsgroups": "11/8"
}