{
    "itemid": "NIDD7100KE",
    "shutter": "Type: Electronic Speed: 30 - 1/8000\u00a0seconds",
    "externalflashconnection": "Hot Shoe",
    "exposurecontrol": "Auto:\u00a0Shutter Speed, Aperture, ISO Manual:\u00a0Shutter Speed, Aperture, ISO",
    "weight": "14.82 oz (420 g)",
    "mirrorlockup": "Yes",
    "battery": "1x EN-EL15\u00a0 Rechargeable Lithium-Ion Battery Pack",
    "exposuremodes": "Modes: Aperture Priority, Auto, Bulb, Flash Off, Manual,     Programmed Auto, Shutter Priority Compensation: -5 EV to +5 EV (in 1/3 or 1/2 EV steps)",
    "isosensitivity": "Auto, 100 - 6400, Expandable to 25600",
    "noisereduction": "Yes",
    "focallength": "18 - 105 mm Comparable 35mm Focal Length: 27 - 157.5 mm",
    "focus": "Auto Manual Continuous Auto",
    "memorycardtype": "SD SDHC SDXC",
    "diaphragmblades": "7",
    "acpoweradapter": "EH-5b (Optional)",
    "incameraimageediting": "Color Balance, Color Outline, D-Lighting, Edit Movie,     Filter Effects, Fisheye, Image Overlay, Miniature Effect, Monochrome,     NEF (RAW) Processing, Perspective Control, Quick Retouch, Red-eye     Correction, Resize Image, Selective Color, Straighten, Trim",
    "aspectratio": "3:2, 16:9",
    "viewfindercoverage": "100%",
    "attr1star": "2 stars3 stars4 stars5 stars",
    "datetimestamp": "Yes",
    "continuousshooting": "Up to 6 fps",
    "dimensions": "No",
    "liveview": "Yes",
    "operatingstoragetemperature": "Operating 32 to 104\u00b0F (0 to 40\u00b0C) Humidity: 0 - 85%",
    "dimensionsdxl": "Approx. 2.99 x 3.50\" (76 x 89 mm)",
    "pixels": "Actual: 24.71 Megapixel Effective: 24.1 Megapixel",
    "selftimer": "2 sec, 5 sec, 10 sec, 20 sec Number of Shots: 1-9",
    "specifications": "New Page 1 Camera Type Digital SLR with Interchangeable lenses Lens Mount Nikon F Camera Format DX / (1.5x Crop Factor) Pixels Actual: 24.71 Megapixel Effective: 24.1 Megapixel Max Resolution 24.1MP: 6000 x 4000 @ 3:2 Other Resolutions 4494 x 3000 @ 3:2 2992 x 2000 @ 3:2 13.5MP: 4800 x 3200 @ 3:2 8.6MP: 3600 x 2400 @ 3:2 3.8MP: 2400 x 1600 @ 3:2 20.2MP: 6000 x 3368 @ 16:9 11.4MP: 4496 x 2528 @ 16:9 5.0MP: 2992 x 1680 @ 16:9 12.9MP: 4800 x 2696 @ 16:9 7.3MP: 3600 x 2024 @ 16:9 3.2MP: 2400 x 1344 @ 16:9 Aspect Ratio 3:2, 16:9 Sensor Type / Size CMOS, 23.5 x 15.6 mm File Formats Still Images: JPEG, RAW Movies: MPEG-4 AVC/H.264,     MOV Audio: Linear PCM Bit Depth 14-bit Noise Reduction Yes Memory Card Type SD SDHC SDXC Image Stabilization None Focus Type Auto & Manual Focus Mode Single-servo AF (S), Continuous-servo AF (C), Manual     Focus (M) , Focus Lock AF Area Mode Autofocus Points 51 Viewfinder Type Pentaprism Viewfinder Coverage 100% Viewfinder Magnification Approx. 0.94x Diopter Adjustment - 2 to +1 m Display Screen 3.2\"\u00a0Rear Screen\u00a0\u00a0Live Preview\u00a0LCD (1,229,000) Screen Coverage 100% Angle of View 170.0\u00b0 Live View Yes ISO Sensitivity Auto, 100-6400 (Extended Mode: 12800-25600) Shutter Type: Electronic Speed: 30 - 1/8000\u00a0seconds Remote Control ML-L3 (Optional) Mirror Lock-Up Yes Metering Method 3D Color Matrix Metering, Center-weighted average     metering, Spot metering Exposure Modes Modes: Aperture Priority, Auto, Bulb, Flash Off, Manual,     Programmed Auto, Shutter Priority Compensation: -5 EV to +5 EV (in 1/3 or 1/2 EV steps) White Balance Modes Auto, Cloudy, Daylight, Flash, Fluorescent, Fluorescent     (Day White), Fluorescent (Natural White), Fluorescent (White),     Fluorescent H, Incandescent, Kelvin, Preset Manual, Shade Flash Modes 1st Curtain Sync Auto Auto/Red-eye Reduction Fill-in Off Rear Curtain/Slow Sync Red-eye Reduction Second-curtain Sync Slow Sync Slow Sync./Red-eye Reduction Built-in Flash Yes Guide No. 39'\u00a0(11.89 m)\u00a0ISO100 Max Sync Speed 1 / 250 sec Flash Compensation -3 EV to +1 EV (in 1/3 or 1/2 EV steps) Dedicated Flash System iTTL\u00a0Remote Firing External Flash Connection Hot Shoe Video Recording Yes, NTSC/PAL File Size 1920 x 1080p\u00a0(Full HD) 1920 x 1080i\u00a0(Full HD) 1280 x 720p\u00a0(HD) Frame Rate @ 1920 x 1080: 60 fps, 50 fps @ 1920 x 1080: 30 fps, 25 fps, 24 fps @ 1280 x 720: 60 fps, 50 fps Exposure Control Auto:\u00a0Shutter Speed, Aperture, ISO Manual:\u00a0Shutter Speed, Aperture, ISO ISO Sensitivity Auto, 100 - 6400, Expandable to 25600 Exposure Compensation -5 EV to +5 EV (in 1/31/2 EV steps) Focus Auto Manual Continuous Auto Continuous Shooting Time 1920 x 1080 20 min. 1280 x 720 29.59 min. Audio Recording With Video, Stereo, Via Optional External Mic Continuous Shooting Up to 6 fps Self Timer 2 sec, 5 sec, 10 sec, 20 sec Number of Shots: 1-9 Interval Recording Yes Date & Time Stamp Yes In-Camera Image Editing Color Balance, Color Outline, D-Lighting, Edit Movie,     Filter Effects, Fisheye, Image Overlay, Miniature Effect, Monochrome,     NEF (RAW) Processing, Perspective Control, Quick Retouch, Red-eye     Correction, Resize Image, Selective Color, Straighten, Trim Connectivity 1/8\" Microphone, HDMI C (Mini), USB 2.0 Wi-Fi Capable Yes Battery 1x EN-EL15\u00a0 Rechargeable Lithium-Ion Battery Pack AC Power Adapter EH-5b (Optional) Operating/Storage Temperature Operating 32 to 104\u00b0F (0 to 40\u00b0C) Humidity: 0 - 85% Dimensions (WxHxD) 5.3 x 4.2 x 3.0\"\u00a0/\u00a0135.5 x 106.5 x 76.0 mm Weight 1.49 lb\u00a0/\u00a0675\u00a0 g camera     body only Focal Length 18 - 105 mm Comparable 35mm Focal Length: 27 - 157.5 mm Aperture Maximum: f/3.5 - 5.6 Minimum: f/22 Angle of View 76\u00b0 - 15\u00b0\u00a020' Minimum Focus Distance 1.48'\u00a0(.45 m) Magnification 0.20x Maximum Reproduction Ratio 1:5 Groups/Elements 11/15 Diaphragm Blades 7 Autofocus Yes Image Stabilization Yes Filter Thread Front: 67 mm Dimensions (DxL) Approx. 2.99 x 3.50\" (76 x 89 mm) Weight 14.82 oz (420 g)",
    "magnification": "0.20x",
    "filesize": "1920 x 1080p\u00a0(Full HD) 1920 x 1080i\u00a0(Full HD) 1280 x 720p\u00a0(HD)",
    "videorecording": "Yes, NTSC/PAL",
    "aperture": "Maximum: f/3.5 - 5.6 Minimum: f/22",
    "dimensionswxhxd": "5.3 x 4.2 x 3.0\"\u00a0/\u00a0135.5 x 106.5 x 76.0 mm",
    "autofocus": "Yes",
    "otherresolutions": "4494 x 3000 @ 3:2 2992 x 2000 @ 3:2 13.5MP: 4800 x 3200 @ 3:2 8.6MP: 3600 x 2400 @ 3:2 3.8MP: 2400 x 1600 @ 3:2 20.2MP: 6000 x 3368 @ 16:9 11.4MP: 4496 x 2528 @ 16:9 5.0MP: 2992 x 1680 @ 16:9 12.9MP: 4800 x 2696 @ 16:9 7.3MP: 3600 x 2024 @ 16:9 3.2MP: 2400 x 1344 @ 16:9",
    "meteringmethod": "3D Color Matrix Metering, Center-weighted average     metering, Spot metering",
    "audiorecording": "With Video, Stereo, Via Optional External Mic",
    "whitebalancemodes": "Auto, Cloudy, Daylight, Flash, Fluorescent, Fluorescent     (Day White), Fluorescent (Natural White), Fluorescent (White),     Fluorescent H, Incandescent, Kelvin, Preset Manual, Shade",
    "category": "camera",
    "sensortypesize": "CMOS, 23.5 x 15.6 mm",
    "screencoverage": "100%",
    "viewfindermagnification": "Approx. 0.94x",
    "freeshipping": "Yes",
    "brand": "Nikon",
    "continuousshootingtime": "1920 x 1080 20 min. 1280 x 720 29.59 min.",
    "filterthread": "Front: 67 mm",
    "connectivity": "1/8\" Microphone, HDMI C (Mini), USB 2.0",
    "cameraformat": "DX / (1.5x Crop Factor)",
    "groupselements": "11/15",
    "angleofview": "76\u00b0 - 15\u00b0\u00a020'",
    "focustype": "Auto & Manual",
    "included": "Nikon D7100 DSLR Camera Nikon 18-105mm f/3.5-5.6G ED VR DX Lens EN-EL15 Lithium-Ion Battery MH-25 QuickCharger Camera Strap UC-E17 USB Cable 67mm Snap-On Lens Cap LF-1 Rear Lens Cap for F Mount Lenses HB-32 Lens Hood DK-5 Eyepiece Shield DK-23 Rubber Eyecup BF-1B Body Cap BS-1 Hot-Shoe Cover CL-1018 Lens Case ViewNX 2 CD-ROM User's Manual",
    "bitdepth": "14-bit",
    "lensmount": "Nikon F",
    "displayscreen": "3.2\"\u00a0Rear Screen\u00a0\u00a0Live Preview\u00a0LCD (1,229,000)",
    "fileformats": "Still Images: JPEG, RAW Movies: MPEG-4 AVC/H.264,     MOV Audio: Linear PCM",
    "condition": "New",
    "intervalrecording": "Yes",
    "flashmodes": "1st Curtain Sync Auto Auto/Red-eye Reduction Fill-in Off Rear Curtain/Slow Sync Red-eye Reduction Second-curtain Sync Slow Sync Slow Sync./Red-eye Reduction",
    "imagestabilization": "Yes",
    "remotecontrol": "ML-L3 (Optional)",
    "diopteradjustment": "- 2 to +1 m",
    "exposurecompensation": "-5 EV to +5 EV (in 1/31/2 EV steps)",
    "builtinflash": "Yes",
    "cameratype": "Digital SLR with Interchangeable lenses",
    "framerate": "@ 1920 x 1080: 60 fps, 50 fps @ 1920 x 1080: 30 fps, 25 fps, 24 fps @ 1280 x 720: 60 fps, 50 fps",
    "opticalzoom": "Interchangable Lens",
    "maximumreproductionratio": "1:5",
    "focusmode": "Single-servo AF (S), Continuous-servo AF (C), Manual     Focus (M) , Focus Lock AF Area Mode",
    "minimumfocusdistance": "1.48'\u00a0(.45 m)",
    "flashcompensation": "-3 EV to +1 EV (in 1/3 or 1/2 EV steps)",
    "viewfindertype": "Pentaprism",
    "maxsyncspeed": "1 / 250 sec",
    "autofocuspoints": "51",
    "dedicatedflashsystem": "iTTL\u00a0Remote Firing",
    "maxresolution": "24.1MP: 6000 x 4000 @ 3:2",
    "guideno": "39'\u00a0(11.89 m)\u00a0ISO100",
    "resolution": "24 Megapixels",
    "wificapable": "Yes"
}