{
    "itemid": "NIDD3200BE",
    "externalflashconnection": "Hot Shoe",
    "features": "No",
    "weight": "1.0 lb",
    "battery": "1x EN-EL14\u00a0 Rechargeable                Lithium-Ion Battery Pack,                7.4VDC, 1030mAh",
    "isosensitivity": "100-6400 (High Sensitivity                Mode: 100-12800)",
    "screencoverage": "100%",
    "memorycardtype": "SD SDHC SDXC",
    "acpoweradapter": "EH-5b (Optional)",
    "incameraimageediting": "Color Balance, Color                Outline, Distortion Control,                Edit Movie, Filter Effects,                Fisheye, Image Overlay,                Miniature Effect,                Monochrome, NEF (RAW)                Processing, Perspective                Control, Quick Retouch,                Red-eye Correction,                Straighten, Trim",
    "lensmount": "Nikon F",
    "viewfindercoverage": "95%",
    "attr1star": "2 stars3 stars4 stars5 stars",
    "shutter": "Type: Electronic Speed: 1/4000 - 30\u00a0sec",
    "maxsyncspeed": "1 / 200 sec",
    "operatingstoragetemperature": "Operating 32 to 104 \u00b0F (0 to 40 \u00b0C)",
    "selftimer": "2 sec, 5 sec, 10 sec, 20 sec",
    "liveview": "Yes",
    "videorecording": "Yes, NTSC/PAL",
    "dimensionswxhxd": "5.0 x 3.8 x 3.1\"",
    "meteringmethod": "Spot metering,                Center-weighted average                metering, 3D Color Matrix                Metering",
    "audiorecording": "With Video, Stereo, Via                Optional External Mic",
    "whitebalancemodes": "Auto, Cloudy, Daylight,                Flash, Fluorescent,                Incandescent, Preset Manual,                Shade",
    "category": "camera",
    "specifications": "New Page 2 Imaging Camera Type Digital SLR with                Interchangeable lenses Lens Mount Nikon F Camera Format DX / (1.5x Crop Factor) Resolution Actual Pixels: 24.2                Megapixels Max Resolution: 24.2 MP:                6016 x 4000 Aspect Ratio 3:2 Sensor Type / Size CMOS, 23.2 x 15.4 mm File Formats Still Images: JPEG,                RAW Movies: MPEG-4                AVC/H.264, MOV Audio: Linear                PCM Memory Card Type SD SDHC SDXC Focus Control Focus Type Auto & Manual Focus Mode Single-servo AF (S),                Continuous-servo AF (C),                Manual Focus (M) , Focus                Lock AF Area Mode Autofocus Points 11 Viewfinder/Display Viewfinder Type Pentamirror, LCD Display Viewfinder Coverage 95% Viewfinder Magnification Approx. 0.8x Diopter Adjustment - -1.7 to +0.5 m Display Screen 3.0\"\u00a0Rear Screen\u00a0\u00a0\u00a0LCD                (921000) Screen Coverage 100% Live View Yes Exposure Control ISO Sensitivity 100-6400 (High Sensitivity                Mode: 100-12800) Shutter Type: Electronic Speed: 1/4000 - 30\u00a0sec Remote Control ML-L3 (Optional) Metering Method Spot metering,                Center-weighted average                metering, 3D Color Matrix                Metering Exposure Modes Modes: Aperture Priority,                Auto, Manual, Programmed                Auto, Shutter Priority Compensation: -5 EV to +5 EV                (in 1/3 EV steps) White Balance Modes Auto, Cloudy, Daylight,                Flash, Fluorescent,                Incandescent, Preset Manual,                Shade Flash Built-in Flash Yes: Auto, Auto/Red-eye                Reduction, Off,                Second-curtain Sync, Slow                Sync, Slow Sync./Red-eye                Reduction Max Sync Speed 1 / 200 sec Continuous Shooting Up to 4 fps Dedicated Flash System iTTL External Flash Connection Hot Shoe AV Recording Video Recording Yes, NTSC/PAL Audio Recording With Video, Stereo, Via                Optional External Mic Performance In-Camera Image Editing Color Balance, Color                Outline, Distortion Control,                Edit Movie, Filter Effects,                Fisheye, Image Overlay,                Miniature Effect,                Monochrome, NEF (RAW)                Processing, Perspective                Control, Quick Retouch,                Red-eye Correction,                Straighten, Trim Self Timer 2 sec, 5 sec, 10 sec, 20 sec Connectivity HDMI C (Mini), USB 2.0 Wi-Fi Capable (With Optional                Transmitter) Yes Power Battery 1x EN-EL14\u00a0 Rechargeable                Lithium-Ion Battery Pack,                7.4VDC, 1030mAh AC Power Adapter EH-5b (Optional) Operating/Storage                Temperature Operating 32 to 104 \u00b0F (0 to 40 \u00b0C) Physical Dimensions (WxHxD) 5.0 x 3.8 x 3.1\" Weight 1.0 lb",
    "viewfindermagnification": "Approx. 0.8x",
    "freeshipping": "Yes",
    "brand": "Nikon",
    "sensortypesize": "CMOS, 23.2 x 15.4 mm",
    "connectivity": "HDMI C (Mini), USB 2.0",
    "cameraformat": "DX / (1.5x Crop Factor)",
    "focustype": "Auto & Manual",
    "included": "D3200 Camera body with body cap and accessory shoe cover installed  Viewfinder eyepiece cover EN-EL14 (1030mAh) Lithium Ion battery pack MH-24 battery charger Nylon adjustable shoulder strap Nikon ViewNX2 Software CD-ROM Nikon Reference Manual CD-ROM User Manual Quick Start Guide",
    "continuousshooting": "Up to 4 fps",
    "aspectratio": "3:2",
    "displayscreen": "3.0\"\u00a0Rear Screen\u00a0\u00a0\u00a0LCD                (921000)",
    "fileformats": "Still Images: JPEG,                RAW Movies: MPEG-4                AVC/H.264, MOV Audio: Linear                PCM",
    "condition": "New",
    "remotecontrol": "ML-L3 (Optional)",
    "diopteradjustment": "- -1.7 to +0.5 m",
    "cameratype": "Digital SLR with                Interchangeable lenses",
    "builtinflash": "Yes: Auto, Auto/Red-eye                Reduction, Off,                Second-curtain Sync, Slow                Sync, Slow Sync./Red-eye                Reduction",
    "exposuremodes": "Modes: Aperture Priority,                Auto, Manual, Programmed                Auto, Shutter Priority Compensation: -5 EV to +5 EV                (in 1/3 EV steps)",
    "focusmode": "Single-servo AF (S),                Continuous-servo AF (C),                Manual Focus (M) , Focus                Lock AF Area Mode",
    "wificapablewithoptionaltransmitter": "Yes",
    "viewfindertype": "Pentamirror, LCD Display",
    "autofocuspoints": "11",
    "dedicatedflashsystem": "iTTL",
    "resolution": "Actual Pixels: 24.2                Megapixels Max Resolution: 24.2 MP:                6016 x 4000"
}