{
    "itemid": "NIDD51001855E",
    "externalflashconnection": "Sync Terminal Adapter AS-15            (available separately)",
    "weight": "1 lb. 2 oz./510 g (camera            body only)",
    "sensitivity": "100-6400 ISO in steps of 1/3            EV; can also be set to approx. 0.3, 0.7, 1            or 2 EV (ISO 25600 equivalent) above ISO 6400; auto            ISO sensitivity control available",
    "metering": "Matrix: 3D color matrix            metering II (type G and D lenses); color            matrix metering II (other CPU lenses) Center-weighted: Weight of 75% given to 8-mm            circle in center of frame Spot: Meters 3.5-mm circle (about 2.5% of            frame) centered on selected focus point",
    "shutterspeeds": "30 seconds to 1/4000s",
    "memorycardtype": "SD (Secure Digital), SDHC            and SDXC memory cards",
    "diaphragmblades": "7",
    "poweradapter": "AC Adapter EH-5a/5b;            requires Power Connector EP-5A (available            separately)",
    "batterytype": "Rechargeable Li-ion Battery            EN-EL14",
    "viewfindercoverage": "Approx. 95% horizontal and            95% vertical",
    "attr1star": "2 stars3 stars4 stars5 stars",
    "maxsyncspeed": "X=1/200s; synchronizes with            shutter at 1/200s or slower",
    "dimensions": "5.0 \u00d7 3.8 \u00d7 3.1\" (12.8 \u00d7 9.7            \u00d7 7.9 cm)",
    "operatingstoragetemperature": "32 to 104\u00b0F/0 to 40\u00b0C            operating temperature",
    "compatibility": "Nikon DX FX in DX Crop Mode",
    "selftimer": "2s, 5s, 10s, 20s; 1 to 9            exposures",
    "specifications": "New Page 1 New Page 1 Camera Type Digital SLR camera Imaging Resolution 16.2MP Sensor 16.2MP CMOS sensor File Formats NEF (RAW): 14 bit,            compressed JPEG: JPEG-Baseline compliant with fine            (approx. 1:4), normal (approx. 1:8) or basic            (approx. 1:16) compression NEF (RAW) + JPEG: Single photograph recorded            in both NEF (RAW) and JPEG formats Video: H.264/MPEG-4 Advanced Video Coding Audio: Linear PCM with built-in monaural or            optional external stereo microphone;            sensitivity adjustable File Size Still photos: 4,928 \u00d7 3,264            (L), 3,696 \u00d7 2,448 (M), 2,464 \u00d7 1,632 (S) Video: 1,920 \u00d7 1,080, 30p/25p/24p, H            high/normal 1,280 \u00d7 720, 30p/25p/24p, high/normal 640 \u00d7 424, 30p/25p, high/normal A frame rate of 30p (actual frame rate 29.97            fps) is available when NTSC is selected for            video mode; 25p is available when PAL is            selected for video mode; Actual frame rate            when 24p is selected is 23.976 fps Crop Factor 1.5x Optics Lens Nikon 18-55mm f/3.5-5.6G ED            II AF-S DX Zoom-Nikkor autofocus lens Lens Mount Nikon F Aperture Maximum: f/3.5 - 5.6 Minimum: f/22 Compatibility Nikon DX FX in DX Crop Mode Angle of View DX: 76 - 28\u00b0 Minimum Focus Distance 11\" (28cm) Magnification 0.31x Groups/Elements 5/7 Diaphragm Blades 7 Autofocus Yes Filter Thread 52mm Dimensions Approx. 2.7 x 2.9\" (6.86 x            7.37cm) Weight 7.2 oz (204g) Sensitivity 100-6400 ISO in steps of 1/3            EV; can also be set to approx. 0.3, 0.7, 1            or 2 EV (ISO 25600 equivalent) above ISO 6400; auto            ISO sensitivity control available Shutter Speeds 30 seconds to 1/4000s Metering Matrix: 3D color matrix            metering II (type G and D lenses); color            matrix metering II (other CPU lenses) Center-weighted: Weight of 75% given to 8-mm            circle in center of frame Spot: Meters 3.5-mm circle (about 2.5% of            frame) centered on selected focus point Exposure Modes Auto modes (auto; auto            [flash off]); programmed auto with flexible            program (P); shutter-priority auto (S);            aperture-priority auto (A); manual (M);            scene modes (portrait; landscape; child;            sports; close up; night portrait; night            landscape; party/indoor; beach/snow; sunset;            dusk/dawn; pet portrait; candlelight;            blossom; autumn colors; food); special            effects modes (night vision; color sketch;            (miniature effect; selective color;            silhouette; high key; low key) vision; g            color sketch; ( miniature effect; 3            selective color; 1 silhouette; 2 high key; 3            low key) x candlelight; y blossom; z autumn            colors; 0 food); special effects modes (%            night vision; g color sketch; ( miniature            effect; 3 selective color; 1 silhouette; 2            high key; 3 low key) White Balance Auto, incandescent,            fluorescent (7 types), direct sunlight,            flash, cloudy, shade, preset manual, all            except preset manual with fine tuning White balance bracketing 3 frames in steps            of 1 Burst Capability Up to 4 fps (manual focus,            mode M or S, shutter speed 1/250 s or            faster, and other settings at default            values) Self Timer 2s, 5s, 10s, 20s; 1 to 9            exposures Flash Built-in Flash Yes Effective Flash Range Guide number: Approx. 39/12,            43/13 with manual flash (ft./m, ISO 100,            68\u00b0F/20\u00b0C) External Flash Connection Sync Terminal Adapter AS-15            (available separately) Dedicated Flash System TTL: i-TTL balanced            fill-flash and standard i-TTL flash for            digital SLR using 420-pixel RGB sensor are            available with built-in flash, SB-900,            SB-800, SB-700, SB-600 or SB-400 (i-TTL            balanced fill-flash is available when matrix            or center-weighted metering is selected) Auto aperture: Available with SB-900/SB-800            and CPU lens Non-TTL auto: Supported flash units include            SB-900, SB-800, SB-80DX, SB-28DX, SB-28,            SB-27 and SB-22S Distance-priority manual: Available with            SB-900, SB-800 and SB-700 Max Sync Speed X=1/200s; synchronizes with            shutter at 1/200s or slower Memory Built-in Memory None Memory Card Type SD (Secure Digital), SDHC            and SDXC memory cards A/V Recording Video Recording H.264/MPEG-4 Advanced Video            Coding Video Resolution 1,920 \u00d7 1,080, 1,280 \u00d7 720,            640 \u00d7 424 Audio Recording Built-in monaural or            external stereo microphone; sensitivity            adjustable with video Viewfinder/Display Viewfinder Type Eye-level pentamirror            single-lens reflex viewfinder Viewfinder Coverage Approx. 95% horizontal and            95% vertical Display 3.0\" (7.5 cm) approx.            921k-dot (VGA), vari-angle low-temperature            polysilicon TFT LCD with 170\u00b0 viewing angle,            approx. 100% frame coverage, and brightness            adjustment Connectivity/System            Requirements Connectivity Hi-Speed USB, NTSC, PAL            video output, Type C mini-pin HDMI            connector, Audio input--stereo mini-pin jack            (3.5-mm diameter) Environmental Operating/Storage            Temperature 32 to 104\u00b0F/0 to 40\u00b0C            operating temperature Power Battery Type Rechargeable Li-ion Battery            EN-EL14 Power Adapter AC Adapter EH-5a/5b;            requires Power Connector EP-5A (available            separately) Physical Dimensions 5.0 \u00d7 3.8 \u00d7 3.1\" (12.8 \u00d7 9.7            \u00d7 7.9 cm) Weight 1 lb. 2 oz./510 g (camera            body only)",
    "magnification": "0.31x",
    "builtinmemory": "None",
    "aperture": "Maximum: f/3.5 - 5.6 Minimum: f/22",
    "autofocus": "Yes",
    "sensor": "16.2MP CMOS sensor",
    "audiorecording": "Built-in monaural or            external stereo microphone; sensitivity            adjustable with video",
    "filesize": "Still photos: 4,928 \u00d7 3,264            (L), 3,696 \u00d7 2,448 (M), 2,464 \u00d7 1,632 (S) Video: 1,920 \u00d7 1,080, 30p/25p/24p, H            high/normal 1,280 \u00d7 720, 30p/25p/24p, high/normal 640 \u00d7 424, 30p/25p, high/normal A frame rate of 30p (actual frame rate 29.97            fps) is available when NTSC is selected for            video mode; 25p is available when PAL is            selected for video mode; Actual frame rate            when 24p is selected is 23.976 fps",
    "category": "camera",
    "freeshipping": "Yes",
    "cropfactor": "1.5x",
    "brand": "Nikon",
    "filterthread": "52mm",
    "lens": "Nikon 18-55mm f/3.5-5.6G ED            II AF-S DX Zoom-Nikkor autofocus lens",
    "connectivity": "Hi-Speed USB, NTSC, PAL            video output, Type C mini-pin HDMI            connector, Audio input--stereo mini-pin jack            (3.5-mm diameter)",
    "groupselements": "5/7",
    "angleofview": "DX: 76 - 28\u00b0",
    "included": "Nikon D5100 Digital SLR Camera With 18-55mm VR Lens (Imported Model) EN-EL14 Lithium-Ion Battery (1030mAh) MH-24 Quick Charger for EN-EL14 Battery DK-5 Eyepiece Shield (Replacement) DK-20 Rubber Eyecup UC-E6 USB Cable EG-CP14 A/V Cable AN-DC3 Camera Strap BF-1B Body Cap BS-1 Hot-Shoe Cover ViewNX 2 CD-ROM 1-Year Limited Warranty",
    "videorecording": "H.264/MPEG-4 Advanced Video            Coding",
    "lensmount": "Nikon F",
    "burstcapability": "Up to 4 fps (manual focus,            mode M or S, shutter speed 1/250 s or            faster, and other settings at default            values)",
    "fileformats": "NEF (RAW): 14 bit,            compressed JPEG: JPEG-Baseline compliant with fine            (approx. 1:4), normal (approx. 1:8) or basic            (approx. 1:16) compression NEF (RAW) + JPEG: Single photograph recorded            in both NEF (RAW) and JPEG formats Video: H.264/MPEG-4 Advanced Video Coding Audio: Linear PCM with built-in monaural or            optional external stereo microphone;            sensitivity adjustable",
    "condition": "New",
    "builtinflash": "Yes",
    "resolution": "16.2MP",
    "exposuremodes": "Auto modes (auto; auto            [flash off]); programmed auto with flexible            program (P); shutter-priority auto (S);            aperture-priority auto (A); manual (M);            scene modes (portrait; landscape; child;            sports; close up; night portrait; night            landscape; party/indoor; beach/snow; sunset;            dusk/dawn; pet portrait; candlelight;            blossom; autumn colors; food); special            effects modes (night vision; color sketch;            (miniature effect; selective color;            silhouette; high key; low key) vision; g            color sketch; ( miniature effect; 3            selective color; 1 silhouette; 2 high key; 3            low key) x candlelight; y blossom; z autumn            colors; 0 food); special effects modes (%            night vision; g color sketch; ( miniature            effect; 3 selective color; 1 silhouette; 2            high key; 3 low key)",
    "opticalzoom": "Interchangable Lens",
    "whitebalance": "Auto, incandescent,            fluorescent (7 types), direct sunlight,            flash, cloudy, shade, preset manual, all            except preset manual with fine tuning White balance bracketing 3 frames in steps            of 1",
    "minimumfocusdistance": "11\" (28cm)",
    "viewfindertype": "Eye-level pentamirror            single-lens reflex viewfinder",
    "effectiveflashrange": "Guide number: Approx. 39/12,            43/13 with manual flash (ft./m, ISO 100,            68\u00b0F/20\u00b0C)",
    "dedicatedflashsystem": "TTL: i-TTL balanced            fill-flash and standard i-TTL flash for            digital SLR using 420-pixel RGB sensor are            available with built-in flash, SB-900,            SB-800, SB-700, SB-600 or SB-400 (i-TTL            balanced fill-flash is available when matrix            or center-weighted metering is selected) Auto aperture: Available with SB-900/SB-800            and CPU lens Non-TTL auto: Supported flash units include            SB-900, SB-800, SB-80DX, SB-28DX, SB-28,            SB-27 and SB-22S Distance-priority manual: Available with            SB-900, SB-800 and SB-700",
    "videoresolution": "1,920 \u00d7 1,080, 1,280 \u00d7 720,            640 \u00d7 424",
    "display": "3.0\" (7.5 cm) approx.            921k-dot (VGA), vari-angle low-temperature            polysilicon TFT LCD with 170\u00b0 viewing angle,            approx. 100% frame coverage, and brightness            adjustment"
}