{
    "itemid": "CADT31855",
    "externalflashconnection": "Hot Shoe",
    "imagestabilization": "Yes",
    "weight": "7.1 oz (201 g)",
    "battery": "1x LP-E10\u00a0 Rechargeable Lithium-Ion            Battery Pack",
    "isosensitivity": "Auto, 100 - 6400",
    "focallength": "18 - 55 mm Comparable APS-C Focal Length: 28 - 90 mm",
    "focus": "Auto",
    "memorycardtype": "SD SDHC SDXC",
    "diaphragmblades": "6",
    "acpoweradapter": "ACK-E10 (Optional)",
    "aspectratio": "3:2, 16:9",
    "viewfindercoverage": "95%",
    "attr1star": "2 stars3 stars4 stars5 stars",
    "shutter": "Type: Mechanical Speed: 30 - 1/4000\u00a0sec",
    "maxsyncspeed": "1 / 200 sec",
    "dimensions": "No",
    "minimumfocusdistance": "9.8\"\u00a0(24.89 cm)",
    "operatingstoragetemperature": "Operating 32 to 104 \u00b0F (0 to 40 \u00b0C)",
    "pixels": "12.2 Megapixel",
    "selftimer": "2 sec, 10 sec",
    "specifications": "New Page 2 Imaging Camera Type Digital SLR with Interchangeable lenses Lens Mount Canon EF Camera Format Canon APS-C (1.6x Crop Factor) Pixels 12.2 Megapixel Max Resolution 12.2MP: 4272 x 2848 @ 3:2 Aspect Ratio 3:2, 16:9 Sensor Type / Size CMOS, 22.0 x 14.7 mm File Formats Still Images: JPEG,            RAW Movies: MOV Audio: Linear            PCM Memory Card Type SD SDHC SDXC Focus Control Focus Type Auto & Manual Focus Mode Single-servo AF (S), Continuous-servo AF            (C), Manual Focus (M) Autofocus Points 9 Viewfinder/Display Viewfinder Type Pentamirror Viewfinder Coverage 95% Viewfinder Magnification Approx. 0.8x Diopter Adjustment - 2.5 to +0.5 m Display Screen 2.7\"\u00a0Rear Screen\u00a0\u00a0\u00a0LCD (230000) Screen Coverage 99% Exposure Control ISO Sensitivity 100-6400 Shutter Type: Mechanical Speed: 30 - 1/4000\u00a0sec Remote Control RS-60E3 (Optional) Metering Method Center-weighted average metering Exposure Modes Modes: Aperture Priority, Manual,            Program Shift, Shutter Priority White Balance Modes Auto Flash Built-in Flash Yes: Auto Max Sync Speed 1 / 200 sec Continuous Shooting Up to 3.0 fps External Flash Connection Hot Shoe AV Recording Video Recording Yes, NTSC/PAL ISO Sensitivity Auto, 100 - 6400 Focus Auto Audio Recording With Video, Mono Performance Self Timer 2 sec, 10 sec Power Battery 1x LP-E10\u00a0 Rechargeable Lithium-Ion            Battery Pack AC Power Adapter ACK-E10 (Optional) Operating/Storage Temperature Operating 32 to 104 \u00b0F (0 to 40 \u00b0C) Physical Dimensions (WxHxD) 5.1 x 3.9 x 3.1\"\u00a0/\u00a012.95 x 9.91 x 7.87            cm Weight 17.4 oz\u00a0/\u00a0493\u00a0 g           only Kit Lens Focal Length 18 - 55 mm Comparable APS-C Focal Length: 28 - 90 mm Aperture Maximum: f/3.5 - 5.6 Minimum: f/22 - 38 Angle of View 74.2\u00b0 - 27.5\u00b0 Minimum Focus Distance 9.8\"\u00a0(24.89 cm) Magnification 0.34x Maximum Reproduction Ratio 1:2.9 Groups/Elements 9/11 Diaphragm Blades 6 Autofocus Yes Image Stabilization Yes Filter Thread Front: 58 mm Dimensions (DxL) Approx. 2.7 x 2.8\" (6.86 x 7.11 cm) Weight 7.1 oz (201 g)",
    "magnification": "0.34x",
    "videorecording": "Yes, NTSC/PAL",
    "aperture": "Maximum: f/3.5 - 5.6 Minimum: f/22 - 38",
    "dimensionswxhxd": "5.1 x 3.9 x 3.1\"\u00a0/\u00a012.95 x 9.91 x 7.87            cm",
    "autofocus": "Yes",
    "meteringmethod": "Center-weighted average metering",
    "audiorecording": "With Video, Mono",
    "whitebalancemodes": "Auto",
    "category": "camera",
    "screencoverage": "99%",
    "viewfindermagnification": "Approx. 0.8x",
    "freeshipping": "Yes",
    "brand": "Canon",
    "sensortypesize": "CMOS, 22.0 x 14.7 mm",
    "filterthread": "Front: 58 mm",
    "cameraformat": "Canon APS-C (1.6x Crop Factor)",
    "groupselements": "9/11",
    "angleofview": "74.2\u00b0 - 27.5\u00b0",
    "focustype": "Auto & Manual",
    "included": "Canon EOS Rebel T3 Digital Camera and 18-55mm f/3.5-5.6 IS II Autofocus Lens Eyecup Wide Strap Interface Cable LP-E10 Lithium-Ion Battery Pack LC-E10 Battery Charger for EOS Rebel T3 EOS Digital Solution Disk and Instruction Manuals Great Photography is Easy\" Booklet \"Do More with Macro\" Booklet Canon 1-Year Warranty",
    "continuousshooting": "Up to 3.0 fps",
    "lensmount": "Canon EF",
    "displayscreen": "2.7\"\u00a0Rear Screen\u00a0\u00a0\u00a0LCD (230000)",
    "fileformats": "Still Images: JPEG,            RAW Movies: MOV Audio: Linear            PCM",
    "condition": "New",
    "remotecontrol": "RS-60E3 (Optional)",
    "diopteradjustment": "- 2.5 to +0.5 m",
    "cameratype": "Digital SLR with Interchangeable lenses",
    "builtinflash": "Yes: Auto",
    "exposuremodes": "Modes: Aperture Priority, Manual,            Program Shift, Shutter Priority",
    "opticalzoom": "Interchangable Lens",
    "maximumreproductionratio": "1:2.9",
    "focusmode": "Single-servo AF (S), Continuous-servo AF            (C), Manual Focus (M)",
    "dimensionsdxl": "Approx. 2.7 x 2.8\" (6.86 x 7.11 cm)",
    "viewfindertype": "Pentamirror",
    "autofocuspoints": "9",
    "maxresolution": "12.2MP: 4272 x 2848 @ 3:2",
    "resolution": "12 Megapixels"
}