{
    "itemid": "PKDX5SL",
    "externalflashconnection": "None",
    "acpoweradapter": "K-AC106 (Optional)",
    "weight": "17.9 oz",
    "battery": "4x AA Batteries",
    "memorycardtype": "SD, SDHC, SDXC",
    "stillimagespergb": "JPEG: 182 @ Highest           Resolution - 7544 @ Lowest Resolution",
    "viewfindercoverage": "Not Specified By Manufacturer",
    "attr1star": "2 stars3 stars4 stars5 stars",
    "videorecording": "Yes, NTSC/PAL",
    "dimensions": "4.7 x 3.4 x 4.2\"",
    "operatingstoragetemperature": "Operating 32 to 104 \u00b0F (0 to 40 \u00b0C)",
    "fileformats": "Still Images:\u00a0JPEG Audio:\u00a0WAV",
    "specifications": "New Page 3 New Page 2 New Page 1 New Page 1 New Page 1 Imaging Pixels Actual: 16.37 Megapixel Sensor 1/2.33\" File Formats Still Images:\u00a0JPEG Audio:\u00a0WAV Max Resolution 16MP: 4608 x 3456 @ 4:3 Other            Resolutions 12MP: 3456 x 3456 @ 1:1 12MP: 4608 x 2592 @ 16:9 7MP: 3072 x 2304 @ 4:3 Aspect Ratio 1:1, 4:3, 16:9 Lens 12 elements in 9 groups 3 Aspheric EFL: 4-104 mm\u00a0(35 mm equivalent: 22.3-580 mm) Filter Thread None Zoom Optical: 26x Intelligent Zoom: 39x Speed: 4 - 1/1500\u00a0sec in Manual Mode Exposure            Metering Center-weighted, Multi, Spot, TTL 256-zones Exposure Modes Modes: Manual, Programmed Auto Compensation: -2 EV to +2 EV (in 1/3 EV steps) White Balance            Modes Auto, Daylight, Fluorescent (Day White),           Fluorescent (Natural White), Fluorescent           (White), Manual, Shade, Tungsten Burst Rate Up to 10 fps at 5 MP for up to 30 frames Flash Modes Auto Flash On w/ Red-eye Reduction Auto/Red-eye Reduction Off Slow Sync Effective Flash            Range Wide: 0.66 - 38' (0.20 - 11.58 m) Telephoto: 4.9 - 20' (1.49 - 6.10 m) External Flash            Connection None Memory Built-in Memory 75.3MB Memory Card Type SD, SDHC, SDXC Still Images per            GB JPEG: 182 @ Highest           Resolution - 7544 @ Lowest Resolution Video Recording Yes, NTSC/PAL Video Video Clip            Length Up to 25\u00a0Minutes Audio Recording With Video, Stereo Viewfinder/Display Viewfinder Type Electronic Diopter            Adjustment Not Specified By Manufacturer Viewfinder            Coverage Not Specified By Manufacturer Screen 3\" LCD Screen Connectivity/System Requirements Connectivity AV Output, DC Input, HDMI D (Micro), USB 2.0 Software            Requirements Windows: XP (SP1), Vista Mac: OS X 10.3.9 or later Environmental Operating/Storage Temperature Operating 32 to 104 \u00b0F (0 to 40 \u00b0C) Power Battery 4x AA Batteries AC Power Adapter K-AC106 (Optional) Physical Dimensions (WxHxD) 4.7 x 3.4 x 4.2\"\u00a0/\u00a011.94 x 8.64 x 10.67 cm Weight 17.9 oz New Page 2 New Page 4 New Page 3 New Page 3 New Page 2 New Page 3 New Page 1 New Page 1 New Page 1 New Page 1 New Page 1 New Page 1 New Page 1 New Page 4 New Page 1 New Page 1 New Page 1 New Page 2",
    "builtinmemory": "75.3MB",
    "dimensionswxhxd": "4.7 x 3.4 x 4.2\"\u00a0/\u00a011.94 x 8.64 x 10.67 cm",
    "otherresolutions": "12MP: 3456 x 3456 @ 1:1 12MP: 4608 x 2592 @ 16:9 7MP: 3072 x 2304 @ 4:3",
    "sensor": "1/2.33\"",
    "screen": "3\" LCD Screen",
    "whitebalancemodes": "Auto, Daylight, Fluorescent (Day White),           Fluorescent (Natural White), Fluorescent           (White), Manual, Shade, Tungsten",
    "category": "camera",
    "freeshipping": "Yes",
    "brand": "Pentax",
    "softwarerequirements": "Windows: XP (SP1), Vista Mac: OS X 10.3.9 or later",
    "filterthread": "None",
    "lens": "12 elements in 9 groups 3 Aspheric EFL: 4-104 mm\u00a0(35 mm equivalent: 22.3-580 mm)",
    "connectivity": "AV Output, DC Input, HDMI D (Micro), USB 2.0",
    "diopteradjustment": "Not Specified By Manufacturer",
    "included": "Pentax X-5 Digital Camera (Silver) O-ST92 Strap O-LC129 Lens Cap I-USB7 USB Cable S-SW129 Software (CD-ROM) 4 x AA Batteries One Year Limited Warranty",
    "aspectratio": "1:1, 4:3, 16:9",
    "pixels": "Actual: 16.37 Megapixel",
    "condition": "New",
    "burstrate": "Up to 10 fps at 5 MP for up to 30 frames",
    "flashmodes": "Auto Flash On w/ Red-eye Reduction Auto/Red-eye Reduction Off Slow Sync",
    "effectiveflashrange": "Wide: 0.66 - 38' (0.20 - 11.58 m) Telephoto: 4.9 - 20' (1.49 - 6.10 m)",
    "exposuremodes": "Modes: Manual, Programmed Auto Compensation: -2 EV to +2 EV (in 1/3 EV steps)",
    "zoom": "Optical: 26x Intelligent Zoom: 39x Speed: 4 - 1/1500\u00a0sec in Manual Mode",
    "opticalzoom": "26x Zoom",
    "audiorecording": "With Video, Stereo",
    "viewfindertype": "Electronic",
    "videocliplength": "Up to 25\u00a0Minutes",
    "maxresolution": "16MP: 4608 x 3456 @ 4:3",
    "exposuremetering": "Center-weighted, Multi, Spot, TTL 256-zones",
    "resolution": "16 Megapixels"
}