{
    "itemid": "NIDCPS4300BK-k1",
    "acpoweradapter": "EF-69P (Included)",
    "weight": "4.90 oz / 139 g Including Battery and Memory Card",
    "battery": "EN-EL19 Rechargeable Lithium-Ion Battery Pack",
    "isosensitivity": "80-3200",
    "memorycardtype": "SD SDHC SDXC",
    "imagestabilization": "Optical",
    "attr1star": "2 stars3 stars4 stars5 stars",
    "videorecording": "Yes, NTSC/PAL",
    "dimensions": "No",
    "operatingstoragetemperature": "Operating 32 to 104 \u00b0F (0 to 40 \u00b0C)",
    "fileformats": "Still Images: JPEG Movies: AVI, MJPEG Audio: WAV",
    "selftimer": "10 Sec, 2 Second",
    "freeshipping": "Yes",
    "builtinmemory": "74MB",
    "dimensionswxhxd": "3.8 x 2.4 x 0.9\" / 9.65 x 6.10 x 2.29 cm",
    "sensor": "1/2.3\" CCD",
    "screen": "3\" LCD Touchscreen (460000 pixels)",
    "whitebalancemodes": "Auto, Cloudy, Daylight, Flash, Fluorescent,     Incandescent, Manual",
    "category": "camera",
    "specifications": "New Page 1 New Page 1 New Page 1 New Page 1 New Page 1 New Page 1 New Page 1 Imaging Pixels 16 Megapixel Sensor 1/2.3\" CCD File Formats Still Images: JPEG Movies: AVI, MJPEG Audio: WAV Max Resolution 16MP: 4608 x 3456 @ 4:3 Aspect Ratio 4:3 Image Stabilization Optical Optics Lens NIKKOR, 5 elements in 5 groups EFL: 4.6-27.6 mm (35 mm equivalent: 26-156 mm) Zoom Optical: 6x Digital: 4x Focus Range Wide: 1.64' (50 cm) - Infinity Telephoto: 3.28' (1.0 m) - Infinity Wide Macro: 1.97\" (5.0 cm) - Infinity Exposure            Control ISO Sensitivity 80-3200 Shutter Type: Electronic & Mechanical Speed: 4 - 1/2000 sec Exposure Metering Center-weighted, Matrix Exposure Modes Modes: Programmed Auto Compensation: -2 EV to +2 EV (in 0.33 EV steps) White Balance Modes Auto, Cloudy, Daylight, Flash, Fluorescent,     Incandescent, Manual Burst Rate Up to 1.3 fps at 16 MP for up to 6 frames Self Timer 10 Sec, 2 Second Flash Flash Modes Auto Built-in Flash Yes Effective Flash Range Wide: 1.64 - 14.76' (0.5 - 4.5 m) Telephoto: 1.64' (0.5 - 2.4 m) Memory Built-in Memory 74MB Memory Card Type SD SDHC SDXC Recording Video Recording Yes, NTSC/PAL Video Video Clip Length Limited by Memory Card Capacity Audio Recording With Video Viewfinder/Display Viewfinder Type LCD Display Screen 3\" LCD Touchscreen (460000 pixels) Connectivity/System Requirements Connectivity AV Output, USB 1.1 Environmental Operating/Storage Temperature Operating 32 to 104 \u00b0F (0 to 40 \u00b0C) Power Battery EN-EL19 Rechargeable Lithium-Ion Battery Pack AC Power Adapter EF-69P (Included) Physical Dimensions (WxHxD) 3.8 x 2.4 x 0.9\" / 9.65 x 6.10 x 2.29 cm Weight 4.90 oz / 139 g Including Battery and Memory Card",
    "brand": "Nikon",
    "lens": "NIKKOR, 5 elements in 5 groups EFL: 4.6-27.6 mm (35 mm equivalent: 26-156 mm)",
    "connectivity": "AV Output, USB 1.1",
    "focusrange": "Wide: 1.64' (50 cm) - Infinity Telephoto: 3.28' (1.0 m) - Infinity Wide Macro: 1.97\" (5.0 cm) - Infinity",
    "included": "Nikon Coolpix S4300 Digital Camera (Black) AN-CP19 Strap UC-E6 USB Cable EG-CP14 A/V Cable EN-EL19 Lithium-Ion Battery (700mAh) Replacement EH-69P AC Adapter Charger TP-1 Touch Stylus Pen (Replacement) NikonView NX 2 Limited 1 Year Warranty Plus: Transcend 16GB SDHC Memory Card 10 UHS-I",
    "aspectratio": "4:3",
    "pixels": "16 Megapixel",
    "condition": "New",
    "burstrate": "Up to 1.3 fps at 16 MP for up to 6 frames",
    "flashmodes": "Auto",
    "builtinflash": "Yes",
    "exposuremodes": "Modes: Programmed Auto Compensation: -2 EV to +2 EV (in 0.33 EV steps)",
    "zoom": "Optical: 6x Digital: 4x",
    "opticalzoom": "6x Zoom",
    "audiorecording": "With Video",
    "shutter": "Type: Electronic & Mechanical Speed: 4 - 1/2000 sec",
    "viewfindertype": "LCD Display",
    "effectiveflashrange": "Wide: 1.64 - 14.76' (0.5 - 4.5 m) Telephoto: 1.64' (0.5 - 2.4 m)",
    "videocliplength": "Limited by Memory Card Capacity",
    "maxresolution": "16MP: 4608 x 3456 @ 4:3",
    "exposuremetering": "Center-weighted, Matrix",
    "resolution": "16 Megapixels"
}