{
    "itemid": "LIA367R",
    "features": "No",
    "weight": "8.64 oz\u00a0/\u00a0245 lithium batteries & MicroSD Card",
    "battery": "Rechargeable Lithium-Ion Battery Pack, 1200mAh",
    "displaytype": "LCD",
    "builtinspeaker": "No",
    "poweradapter": "None",
    "stillimageresolution": "JPEG: 12 Megapixel, 4000 x 3000",
    "videoformat": "High Definition MPEG AVC/H.264 1920 x 1080p, 1280 x 720p\u00a0(30/60 fps)",
    "attr1star": "2 stars3 stars4 stars5 stars",
    "system": "NTSC",
    "specifications": "New Page 1 New Page 5 New Page 1 New Page 1 New Page 1 Optics Sensor 5 Megapixel 1/3.2\" CMOS Lens Fixed Focus 3.02 mm f/3.2 Recording System NTSC Recording Media microSD/SDHC\u00a0Up To 32GB\u00a0Video/Image Internal Flash Memory\u00a032MB\u00a0Video/Image Recording Time MicroSD/SDHC 16GB Card: 300 min of H.264 Video Video Format High Definition MPEG AVC/H.264 1920 x 1080p, 1280 x 720p\u00a0(30/60 fps) Still Image            Resolution JPEG: 12 Megapixel, 4000 x 3000 Display Display Type LCD Features Built-in Mic Yes Built-in Speaker No Built-in            Light/Flash Light - No Flash - No Input/Output            Connectors Outputs 1x\u00a0USB 2.0 Microphone Input No Headphone Jack No General System            Requirements Windows XP, Vista, 7 Mac OS X 10.4 or higher Battery Rechargeable Lithium-Ion Battery Pack, 1200mAh Power Adapter None Dimensions (WxHxD) 8.46 x 4.53 x 3.74\"\u00a0/\u00a021.5 x 11.5 x 9.5 cm Weight 8.64 oz\u00a0/\u00a0245 lithium batteries & MicroSD Card",
    "dimensionswxhxd": "8.46 x 4.53 x 3.74\"\u00a0/\u00a021.5 x 11.5 x 9.5 cm",
    "sensor": "5 Megapixel 1/3.2\" CMOS",
    "category": "camera",
    "freeshipping": "Yes",
    "outputs": "1x\u00a0USB 2.0",
    "brand": "Liquid Image",
    "headphonejack": "No",
    "lens": "Fixed Focus 3.02 mm f/3.2",
    "builtinmic": "Yes",
    "included": "Liquid Image Impact Series Off-Road Goggle with Full HD Camera (Red) 2 x Anti-Fog Treatment Lexan Goggle Lenses 4GB MicroSDHC Card USB 2.0 Cable Rechargeable Lithium Battery Micro Bag 1-Year Limited Warranty",
    "condition": "New",
    "microphoneinput": "No",
    "recordingmedia": "microSD/SDHC\u00a0Up To 32GB\u00a0Video/Image Internal Flash Memory\u00a032MB\u00a0Video/Image",
    "systemrequirements": "Windows XP, Vista, 7 Mac OS X 10.4 or higher",
    "recordingtime": "MicroSD/SDHC 16GB Card: 300 min of H.264 Video"
}