{
    "itemid": "NIDD5100",
    "externalflashconnection": "Hot Shoe",
    "weight": "1.12 lb\u00a0/\u00a0510 g Body            only",
    "battery": "1x EN-EL14\u00a0 Rechargeable Lithium-Ion            Battery Pack",
    "isosensitivity": "100-",
    "memorycardtype": "SD, SDHC, SDXC",
    "acpoweradapter": "AC Adapter EH-5a/5b; requires Power            Connector EP-5A (available separately)            (Optional)",
    "lensmount": "Nikon F",
    "viewfindercoverage": "95%",
    "attr1star": "2 stars3 stars4 stars5 stars",
    "maxsyncspeed": "1 / 200 sec",
    "dimensions": "No",
    "operatingstoragetemperature": "32 to 104 \u00b0F (0 to 40 \u00b0C)",
    "selftimer": "2 sec, 5 sec, 10 sec, 20 sec",
    "specifications": "New Page 1 New Page 2 Imaging Camera Type Digital SLR with Interchangeable lenses Lens Mount Nikon F Camera Format APS-C / (1.5x Crop Factor) Resolution Effective Pixels: 16.2 Megapixels Max Resolution: File Formats Still Images: JPEG,            RAW Movies: MPEG-4            AVC/H.264 Audio: Linear            PCM Memory Card Type SD, SDHC, SDXC AV Recording Video Recording Yes, NTSC/PAL Aspect Ratio 4:3, 16:9 Video Clip Length Up to 20\u00a0Min Audio Recording With Video, Mono Viewfinder/Display Viewfinder Type Pentamirror Viewfinder Coverage 95% Display Screen 3\"\u00a0Rear Screen\u00a0\u00a0\u00a0LCD (921000) Screen Coverage 100% Exposure Control ISO Sensitivity 100- Shutter 30 - 1/4000\u00a0sec Metering Method Spot metering, Center-weighted average            metering, 3D Color Matrix Metering Exposure Modes Modes: Aperture Priority, Auto, Manual,            Program, Shutter Priority White Balance Modes Auto, Cloudy, Flash, Fluorescent,            Fluorescent (Day White), Fluorescent            (Natural White), Fluorescent (White),            Fluorescent H, Incandescent, Manual, Shade Flash Built-in Flash Yes: Auto Max Sync Speed 1 / 200 sec Continuous Shooting Up to 4 fps External Flash Connection Hot Shoe Performance Self Timer 2 sec, 5 sec, 10 sec, 20 sec Connectivity AV Output, HDMI C (Mini), USB 2.0 Power Battery 1x EN-EL14\u00a0 Rechargeable Lithium-Ion            Battery Pack AC Power Adapter AC Adapter EH-5a/5b; requires Power            Connector EP-5A (available separately)            (Optional) Operating/Storage Temperature 32 to 104 \u00b0F (0 to 40 \u00b0C) Physical Dimensions (WxHxD) 5.0 x 3.8 x 3.1\"\u00a0/\u00a012.70 x 9.65 x 7.87            cm Weight 1.12 lb\u00a0/\u00a0510 g Body            only",
    "videorecording": "Yes, NTSC/PAL",
    "dimensionswxhxd": "5.0 x 3.8 x 3.1\"\u00a0/\u00a012.70 x 9.65 x 7.87            cm",
    "meteringmethod": "Spot metering, Center-weighted average            metering, 3D Color Matrix Metering",
    "audiorecording": "With Video, Mono",
    "whitebalancemodes": "Auto, Cloudy, Flash, Fluorescent,            Fluorescent (Day White), Fluorescent            (Natural White), Fluorescent (White),            Fluorescent H, Incandescent, Manual, Shade",
    "category": "camera",
    "screencoverage": "100%",
    "freeshipping": "Yes",
    "brand": "Nikon",
    "connectivity": "AV Output, HDMI C (Mini), USB 2.0",
    "cameraformat": "APS-C / (1.5x Crop Factor)",
    "included": "Nikon D5100 Digital SLR Camera (Body Only) Imported EN-EL14 Lithium-Ion Battery (1030mAh) MH-24 Quick Charger for EN-EL14 Battery DK-5 Eyepiece Shield (Replacement) DK-20 Rubber Eyecup UC-E6 USB Cable EG-CP14 A/V Cable AN-DC3 Camera Strap BF-1B Body Cap BS-1 Hot-Shoe Cover ViewNX 2 CD-ROM",
    "continuousshooting": "Up to 4 fps",
    "aspectratio": "4:3, 16:9",
    "displayscreen": "3\"\u00a0Rear Screen\u00a0\u00a0\u00a0LCD (921000)",
    "fileformats": "Still Images: JPEG,            RAW Movies: MPEG-4            AVC/H.264 Audio: Linear            PCM",
    "condition": "New",
    "cameratype": "Digital SLR with Interchangeable lenses",
    "builtinflash": "Yes: Auto",
    "exposuremodes": "Modes: Aperture Priority, Auto, Manual,            Program, Shutter Priority",
    "opticalzoom": "Interchangable Lens",
    "shutter": "30 - 1/4000\u00a0sec",
    "viewfindertype": "Pentamirror",
    "videocliplength": "Up to 20\u00a0Min",
    "resolution": "Effective Pixels: 16.2 Megapixels Max Resolution:"
}