{
    "itemid": "NIDD800U",
    "externalflashconnection": "PC Terminal",
    "weight": "2.20 lb\u00a0/\u00a01000 g",
    "mirrorlockup": "Yes",
    "battery": "1x EN-EL15\u00a0 Rechargeable Lithium-Ion            Battery Pack",
    "isosensitivity": "Auto, 100-6400 (High Sensitivity Mode:            50-25600)",
    "noisereduction": "Yes",
    "memorycardtype": "SD SDHC SDXC CompactFlash",
    "acpoweradapter": "EH-5b (Optional)",
    "screencoverage": "100%",
    "viewfindercoverage": "100%",
    "attr1star": "2 stars3 stars4 stars5 stars",
    "shutter": "Type: Electronic Speed: 1/8000 - 30\u00a0seconds",
    "videorecording": "Yes",
    "dimensions": "No",
    "operatingstoragetemperature": "32 to 104 \u00b0F (0 to 40 \u00b0C) Humidity: 0 - 85%",
    "pixels": "Actual: 36.8 Megapixel Effective: 36.3 Megapixel",
    "selftimer": "2 sec, 5 sec, 10 sec, 20 sec",
    "liveview": "Yes",
    "dimensionswxhxd": "5.7 x 4.8 x 3.2\"\u00a0/\u00a0144.78 x 121.92 x            81.28 mm",
    "continuousshooting": "Up to 6 fps",
    "meteringmethod": "Spot metering, Center-weighted average            metering, 3D Color Matrix Metering",
    "whitebalancemodes": "Auto, Cloudy, Daylight, Flash,            Fluorescent, Incandescent, Kelvin, Preset            Manual, Shade",
    "category": "camera",
    "specifications": "New Page 3 Imaging Camera Type Digital SLR with Interchangeable lenses Lens Mount Not Specified By Manufacturer Camera Format Full-Frame Pixels Actual: 36.8 Megapixel Effective: 36.3 Megapixel Sensor Type / Size CMOS, 35.9 x 24.0 mm File Formats Still Images: JPEG,            RAW, TIFF Movies: MPEG-4            AVC/H.264, MOV Audio: Linear            PCM Bit Depth 14-bit Noise Reduction Yes Memory Card Type SD SDHC SDXC CompactFlash Focus Control Focus Type Auto & Manual Focus Mode Single-servo AF (S), Continuous-servo AF            (C), Manual Focus (M) , Focus Lock AF Area            Mode Autofocus Points 51 Viewfinder/Display Viewfinder Type Pentaprism Viewfinder Coverage 100% Viewfinder Magnification Approx. 0.7x Diopter Adjustment - 3 to +1 m Display Screen 3.2\"\u00a0Rear Screen\u00a0\u00a0\u00a0LCD (921000) Screen Coverage 100% Live View Yes Exposure Control ISO Sensitivity Auto, 100-6400 (High Sensitivity Mode:            50-25600) Shutter Type: Electronic Speed: 1/8000 - 30\u00a0seconds Remote Control ML-3 (Optional) Mirror Lock-Up Yes Metering Method Spot metering, Center-weighted average            metering, 3D Color Matrix Metering Exposure Modes Modes: Aperture Priority, Manual,            Program, Shutter Priority Compensation: -5 EV to +5 EV (in 1/3 EV            steps) White Balance Modes Auto, Cloudy, Daylight, Flash,            Fluorescent, Incandescent, Kelvin, Preset            Manual, Shade Flash Built-in Flash Yes: 1st Curtain Sync, Auto, Red-eye            Reduction, Second-curtain Sync, Slow Sync,            Slow Sync./Red-eye Reduction Max Sync Speed 1 / 250 sec Continuous Shooting Up to 6 fps Dedicated Flash System iTTL\u00a0Remote Firing External Flash Connection PC Terminal AV Recording Video Recording Yes Performance Self Timer 2 sec, 5 sec, 10 sec, 20 sec Interval Recording Yes Connectivity 10-pin Terminal, Audio Out, HDMI C            (Mini), USB 3.0 Wi-Fi Capable (With Optional            Transmitter) Yes Power Battery 1x EN-EL15\u00a0 Rechargeable Lithium-Ion            Battery Pack AC Power Adapter EH-5b (Optional) Operating/Storage Temperature 32 to 104 \u00b0F (0 to 40 \u00b0C) Humidity: 0 - 85% Physical Dimensions (WxHxD) 5.7 x 4.8 x 3.2\"\u00a0/\u00a0144.78 x 121.92 x            81.28 mm Weight 2.20 lb\u00a0/\u00a01000 g",
    "viewfindermagnification": "Approx. 0.7x",
    "freeshipping": "Yes",
    "brand": "Nikon",
    "sensortypesize": "CMOS, 35.9 x 24.0 mm",
    "connectivity": "10-pin Terminal, Audio Out, HDMI C            (Mini), USB 3.0",
    "cameraformat": "Full-Frame",
    "focustype": "Auto & Manual",
    "included": "Nikon D800 SLR Digital Camera (Body Only) Nikon ENEL15 Battery (1900mAH) MH-25 Charger DK-17 Finder Eyepiece UC-E14 USB CAblev USB Cable Clip Camera Strap LCD Monitor Cover Body Capv Hot Shoe Cover ViewNX 2 CD-ROM 1 Year Nikon Limited Warranty Card",
    "bitdepth": "14-bit",
    "lensmount": "Not Specified By Manufacturer",
    "displayscreen": "3.2\"\u00a0Rear Screen\u00a0\u00a0\u00a0LCD (921000)",
    "fileformats": "Still Images: JPEG,            RAW, TIFF Movies: MPEG-4            AVC/H.264, MOV Audio: Linear            PCM",
    "condition": "New",
    "intervalrecording": "Yes",
    "remotecontrol": "ML-3 (Optional)",
    "diopteradjustment": "- 3 to +1 m",
    "cameratype": "Digital SLR with Interchangeable lenses",
    "builtinflash": "Yes: 1st Curtain Sync, Auto, Red-eye            Reduction, Second-curtain Sync, Slow Sync,            Slow Sync./Red-eye Reduction",
    "exposuremodes": "Modes: Aperture Priority, Manual,            Program, Shutter Priority Compensation: -5 EV to +5 EV (in 1/3 EV            steps)",
    "opticalzoom": "Interchangable Lens",
    "focusmode": "Single-servo AF (S), Continuous-servo AF            (C), Manual Focus (M) , Focus Lock AF Area            Mode",
    "wificapablewithoptionaltransmitter": "Yes",
    "viewfindertype": "Pentaprism",
    "maxsyncspeed": "1 / 250 sec",
    "autofocuspoints": "51",
    "dedicatedflashsystem": "iTTL\u00a0Remote Firing",
    "resolution": "36 Megapixels"
}