{
    "itemid": "SMDNX2000KWT",
    "externalflashconnection": "Hot Shoe",
    "weight": "4.20 oz (119 g)",
    "battery": "1x ED-BP1130\u00a0 Rechargeable Lithium-Ion Battery Pack, 7.6VDC, 1130mAh",
    "isosensitivity": "Auto, 100-25600",
    "memorycardtype": "microSD microSDHC microSDXC",
    "diaphragmblades": "7",
    "imagestabilization": "No",
    "lensmount": "Samsung NX",
    "attr1star": "2 stars3 stars4 stars5 stars",
    "shutter": "Type: Electronic & Mechanical Speed: 30 - 1/4000\u00a0sec in Auto Mode Type: Electronic & Mechanical Speed: 30 - 1/4000\u00a0sec in Manual Mode Type: Electronic & Mechanical Speed: 240 - 1/4000\u00a0sec in Bulb Mode",
    "maxsyncspeed": "1 / 180 sec",
    "dimensions": "No",
    "minimumfocusdistance": "11.02\"\u00a0(28 cm)",
    "operatingstoragetemperature": "Operating 32 to 104\u00b0F (0 to 40\u00b0C) Humidity: 5 - 85%",
    "dimensionsdxl": "Approx. 2.52 x 1.57\" (64 x 39.8 mm)",
    "pixels": "Actual: 21.6 Megapixel Effective: 20.3 Megapixel",
    "selftimer": "2 sec, 30 sec Custom: 2-30 sec at 1.0 sec intervals",
    "focallength": "20 - 50 mm Comparable 35mm Focal Length: 30.8 - 77 mm",
    "magnification": "0.22x",
    "videorecording": "Yes, NTSC/PAL",
    "aperture": "Maximum: f/3.5 - 5.6 Minimum: f/22",
    "dimensionswxhxd": "4.7 x 2.5 x 1.4\"\u00a0/\u00a0119.0 x 64.5 x 35.7 mm excluding   protrusions",
    "autofocus": "Yes",
    "meteringmethod": "Center-weighted average metering, Multi-zone metering, Spot metering",
    "audiorecording": "With Video, Stereo",
    "softwaresystemrequirements": "Windows: XP (SP2), Vista, 7, 8 Mac: OS X 10.5 or later",
    "dustreductionsystem": "Yes",
    "category": "camera",
    "specifications": "New Page 2 Imaging Lens Mount Samsung NX Camera Format APS-C (1.5x Crop Factor) Pixels Actual: 21.6 Megapixel Effective: 20.3 Megapixel Max Resolution 20MP: 5472 x 3648 Sensor Type / Size CMOS, 23.5 x 15.7 mm File Formats Still Images: JPEG, MPO, RAW Movies: MPEG-4 AVC/H.264 Audio: AAC Dust Reduction System Yes Memory Card Type microSD microSDHC microSDXC Image Stabilization Optical AV Recording Video Recording Yes, NTSC/PAL Resolution 1920 x 1080: 30 fps 1920 x 810: 30 fps, 24 fps 1280 x 720: 30 fps 640 x 480: 30 fps 320 x 240: 30 fps Aspect Ratio 4:3, 16:9 Video Clip Length Up to 29\u00a0Min\u00a059\u00a0Sec Audio Recording With Video, Stereo Focus Control Focus Type Auto & Manual Focus Mode Single-servo AF (S), Continuous-servo AF (C), Manual Focus (M) Autofocus Points Contrast Detection: 1 Contrast Detection: 21 Contrast Detection: 35 Contrast Detection: 10 Viewfinder/Display Display Screen 3.7\"\u00a0Rear Touchscreen\u00a0\u00a0\u00a0LCD (1,152,000) Screen Coverage 100% Exposure Control ISO Sensitivity Auto, 100-25600 Shutter Type: Electronic & Mechanical Speed: 30 - 1/4000\u00a0sec in Auto Mode Type: Electronic & Mechanical Speed: 30 - 1/4000\u00a0sec in Manual Mode Type: Electronic & Mechanical Speed: 240 - 1/4000\u00a0sec in Bulb Mode Remote Control SR2NX02 (Optional) Metering Method Center-weighted average metering, Multi-zone metering, Spot metering Exposure Modes Modes: Aperture Priority, Auto, Custom, Manual, Program, Shutter Priority,   Smart, Wi-Fi Metering Range: EV 0.0 - EV 18.0 Compensation: -3 EV to +3 EV (in 1/3 EV steps) White Balance Modes Auto, Cloudy, Custom, Daylight, Flash, Fluorescent (Day White), Fluorescent   (Natural White), Fluorescent (White), Manual, Tungsten Burst Rate Up to 8 fps at 20 MP Flash Flash Modes 1st Curtain Sync Auto Auto/Red-eye Reduction Fill-in Fill-in/Red-eye Reduction Off Second-curtain Sync Smart Built-in Flash No Max Sync Speed 1 / 180 sec Flash Compensation -2 EV to +2 EV (in 1/2 EV steps) External Flash Connection Hot Shoe Performance Continuous Shooting Up to 8 fps Self Timer 2 sec, 30 sec Custom: 2-30 sec at 1.0 sec intervals Connectivity HDMI D (Micro) Micro-USB USB 2.0 Wi-Fi Capable Yes Software System Requirements Windows: XP (SP2), Vista, 7, 8 Mac: OS X 10.5 or later Power Battery 1x ED-BP1130\u00a0 Rechargeable Lithium-Ion Battery Pack, 7.6VDC, 1130mAh Operating/Storage Temperature Operating 32 to 104\u00b0F (0 to 40\u00b0C) Humidity: 5 - 85% Physical Dimensions (WxHxD) 4.7 x 2.5 x 1.4\"\u00a0/\u00a0119.0 x 64.5 x 35.7 mm excluding   protrusions Weight 8.04 oz\u00a0/\u00a0228 g without   battery Kit Lens Focal Length 20 - 50 mm Comparable 35mm Focal Length: 30.8 - 77 mm Aperture Maximum: f/3.5 - 5.6 Minimum: f/22 Angle of View 70.2\u00b0 - 31.4\u00b0 Minimum Focus Distance 11.02\"\u00a0(28 cm) Magnification 0.22x Elements/Groups 9/8 Diaphragm Blades 7 Autofocus Yes Image Stabilization No Filter Thread Front:40.5 mm Dimensions (DxL) Approx. 2.52 x 1.57\" (64 x 39.8 mm) Weight 4.20 oz (119 g)",
    "flashcompensation": "-2 EV to +2 EV (in 1/2 EV steps)",
    "freeshipping": "Yes",
    "brand": "Samsung",
    "sensortypesize": "CMOS, 23.5 x 15.7 mm",
    "filterthread": "Front:40.5 mm",
    "connectivity": "HDMI D (Micro) Micro-USB USB 2.0",
    "cameraformat": "APS-C (1.5x Crop Factor)",
    "elementsgroups": "9/8",
    "angleofview": "70.2\u00b0 - 31.4\u00b0",
    "focustype": "Auto & Manual",
    "included": "Samsung NX2000 Mirrorless Digital Camera with 20-50mm f/3.5-5.6 Lens (White) 20-50mm f/3.5-5.6 ED II Lens - White ED-BP1130 Rechargeable Lithium-Ion Battery Pack (7.6VDC, 1130mAh) SEF-8A Hot Shoe Mount Flash Unit AC Adapter/USB Cable Strap Software CD-ROM Adobe Photoshop Lightroom 4 DVD-ROM Limited 1-Year Warranty",
    "continuousshooting": "Up to 8 fps",
    "aspectratio": "4:3, 16:9",
    "displayscreen": "3.7\"\u00a0Rear Touchscreen\u00a0\u00a0\u00a0LCD (1,152,000)",
    "fileformats": "Still Images: JPEG, MPO, RAW Movies: MPEG-4 AVC/H.264 Audio: AAC",
    "condition": "New",
    "burstrate": "Up to 8 fps at 20 MP",
    "remotecontrol": "SR2NX02 (Optional)",
    "screencoverage": "100%",
    "builtinflash": "No",
    "exposuremodes": "Modes: Aperture Priority, Auto, Custom, Manual, Program, Shutter Priority,   Smart, Wi-Fi Metering Range: EV 0.0 - EV 18.0 Compensation: -3 EV to +3 EV (in 1/3 EV steps)",
    "opticalzoom": "Interchangable Lens",
    "focusmode": "Single-servo AF (S), Continuous-servo AF (C), Manual Focus (M)",
    "flashmodes": "1st Curtain Sync Auto Auto/Red-eye Reduction Fill-in Fill-in/Red-eye Reduction Off Second-curtain Sync Smart",
    "whitebalancemodes": "Auto, Cloudy, Custom, Daylight, Flash, Fluorescent (Day White), Fluorescent   (Natural White), Fluorescent (White), Manual, Tungsten",
    "autofocuspoints": "Contrast Detection: 1 Contrast Detection: 21 Contrast Detection: 35 Contrast Detection: 10",
    "videocliplength": "Up to 29\u00a0Min\u00a059\u00a0Sec",
    "maxresolution": "20MP: 5472 x 3648",
    "resolution": "1920 x 1080: 30 fps 1920 x 810: 30 fps, 24 fps 1280 x 720: 30 fps 640 x 480: 30 fps 320 x 240: 30 fps",
    "wificapable": "Yes"
}