{
    "acpoweradapter": "EH-5b   (Optional)",
    "weight": "4.1 oz (116   g)",
    "battery": "1x EN-EL20   Rechargeable Lithium-Ion   Battery Pack",
    "isosensitivity": "100-6400",
    "memorycardtype": "SD SDHC SDXC",
    "diaphragmblades": "7",
    "imagestabilization": "Yes",
    "lensmount": "Nikon 1   Mount",
    "attr1star": "2 stars3 stars4 stars5 stars",
    "shutter": "Type:   Electronic Speed: 1/3 - 1/16000 sec",
    "videorecording": "Yes",
    "dimensions": "Approx. 2.3 x 7.1\" (5.84 x 18.03 cm)",
    "minimumfocusdistance": "7.87\" (19.99   cm)",
    "operatingstoragetemperature": "32 to 104 \u00b0F   (0 to 40 \u00b0C) Humidity: 0 - 85%",
    "selftimer": "2 sec, 5   sec, 10 sec",
    "focallength": "10 - 30 mm Comparable Nikon CX Format   Focal Length: 27 - 81 mm",
    "aperture": "Maximum:   f/3.5 Minimum: f/16",
    "dimensionswxhxd": "4.2 x 2.4 x   1.2\" / 10.67 x 6.10 x 3.05   cm",
    "autofocus": "Yes",
    "meteringmethod": "Center-weighted average   metering, Multi-zone   metering",
    "audiorecording": "With Video,   Stereo",
    "whitebalancemodes": "Auto,   Cloudy, Flash, Fluorescent,   Incandescent, Preset Manual,   Shade",
    "category": "camera",
    "specifications": "Imaging Lens Mount Nikon 1   Mount Camera   Format Nikon CX   (2.7x Crop Factor) Resolution Effective   Pixels: 10.1 Megapixels Max Resolution: 10 MP: 3872   x 2592 Sensor Type   / Size CMOS, 13.2 x   8.8 mm File Formats Still   Images: JPEG, RAW Movies: MPEG-4 AVC/H.264,   MOV Audio: AAC Memory Card   Type SD SDHC SDXC AV Recording Video   Recording Yes Aspect Ratio 16:9 Audio   Recording With Video,   Stereo Focus Control Focus Type Auto &   Manual Focus Mode Single-servo   AF (S), Continuous-servo AF   (C), Manual Focus (M) Autofocus   Points 41 Viewfinder Display Display   Screen 3\" Rear   Screen LCD (460000) Screen   Coverage 100% Exposure Control ISO   Sensitivity 100-6400 Shutter Type:   Electronic Speed: 1/3 - 1/16000 sec Metering   Method Center-weighted average   metering, Multi-zone   metering Exposure   Modes Modes:   Aperture Priority, Auto,   Manual, Shutter Priority Compensation: -3 EV to +3 EV   (in 0.33 EV steps) White   Balance Modes Auto,   Cloudy, Flash, Fluorescent,   Incandescent, Preset Manual,   Shade Flash Built-in   Flash Yes:   Fill-in, Red-eye Reduction,   Second-curtain Sync, Slow   Sync, Slow Sync./Red-eye   Reduction Continuous   Shooting Up to 60 fps Performance Self Timer 2 sec, 5   sec, 10 sec Connectivity HDMI C   (Mini), USB 2.0 Power Battery 1x EN-EL20   Rechargeable Lithium-Ion   Battery Pack AC Power   Adapter EH-5b   (Optional) Operating/Storage   Temperature 32 to 104 \u00b0F   (0 to 40 \u00b0C) Humidity: 0 - 85% Physical Dimensions (WxHxD) 4.2 x 2.4 x   1.2\" / 10.67 x 6.10 x 3.05   cm Weight 8.3 oz / 235   g Body only Kit Lens Focal Length 10 - 30 mm Comparable Nikon CX Format   Focal Length: 27 - 81 mm Aperture Maximum:   f/3.5 Minimum: f/16 Angle of   View 77\u00b0 - 29.4\u00b0 Minimum   Focus Distance 7.87\" (19.99   cm) Groups/Elements 9/12 Diaphragm   Blades 7 Autofocus Yes Image   Stabilization Yes Filter   Thread Front: 40.5   mm Dimensions (DxL) Approx. 2.3   x 7.1\" (5.84 x 18.03 cm) Weight 4.1 oz (116   g)",
    "freeshipping": "Yes",
    "brand": "Nikon",
    "sensortypesize": "CMOS, 13.2 x   8.8 mm",
    "filterthread": "Front: 40.5   mm",
    "connectivity": "HDMI C   (Mini), USB 2.0",
    "cameraformat": "Nikon CX   (2.7x Crop Factor)",
    "groupselements": "9/12",
    "angleofview": "77\u00b0 - 29.4\u00b0",
    "focustype": "Auto &   Manual",
    "included": "Nikon 1 J1 Mirrorless Digital Camera with 10-30mm VR Zoom Lens (Black) 1 Nikkor VR 10-30 mm f/3.5-5.6 Lens for CX Format (Black) EN-EL20 Rechargeable Li-ion Battery BF-N1000 Body Cap AN-N1000 Strap MH-27 Battery Charger UC-E6 USB Cable ViewNX 2 Short Movie Creator CD User Manual Reference Manual CD 1-Year Limited Warranty",
    "continuousshooting": "Up to 60 fps",
    "aspectratio": "16:9",
    "displayscreen": "3\" Rear   Screen LCD (460000)",
    "fileformats": "Still   Images: JPEG, RAW Movies: MPEG-4 AVC/H.264,   MOV Audio: AAC",
    "condition": "New",
    "screencoverage": "100%",
    "builtinflash": "Yes:   Fill-in, Red-eye Reduction,   Second-curtain Sync, Slow   Sync, Slow Sync./Red-eye   Reduction",
    "exposuremodes": "Modes:   Aperture Priority, Auto,   Manual, Shutter Priority Compensation: -3 EV to +3 EV   (in 0.33 EV steps)",
    "opticalzoom": "Interchangable Lens",
    "focusmode": "Single-servo   AF (S), Continuous-servo AF   (C), Manual Focus (M)",
    "dimensionsdxl": "Approx. 2.3   x 7.1\" (5.84 x 18.03 cm)",
    "autofocuspoints": "41",
    "resolution": "Effective   Pixels: 10.1 Megapixels Max Resolution: 10 MP: 3872   x 2592"
}