{
    "itemid": "NIDCPS01R-k2",
    "acpoweradapter": "EH-69P   (Included)",
    "weight": "3.4 oz\u00a0/\u00a096   g",
    "battery": "NIENEL11\u00a0Rechargeable   Lithium-Ion Battery Pack,   3.7VDC, 680mAh",
    "isosensitivity": "Auto,   80-1600",
    "memorycardtype": "None",
    "imagestabilization": "Optical",
    "shootingmodes": "Portrait",
    "attr1star": "2 stars3 stars4 stars5 stars",
    "videorecording": "Yes,   NTSC/PAL",
    "dimensions": "3.1 x 2.1 x 0.7",
    "brand": "Nikon",
    "fileformats": "Still   Images: JPEG Movies: MPEG-4 AVC/H.264,   MOV Audio: AAC, WAV",
    "specifications": "Imaging Pixels Actual:   10.34 Megapixel Effective: 10.1 Megapixel Sensor 1/2.9\" CCD File Formats Still   Images: JPEG Movies: MPEG-4 AVC/H.264,   MOV Audio: AAC, WAV Max   Resolution 10MP: 3648 x   2736 @ 4:3 Aspect Ratio 4:3 Image   Stabilization Optical Optics Lens NIKKOR, 6   elements in 5 groups EFL: 4.1-12.3 mm\u00a0(35 mm   equivalent: 29-87 mm) Aperture: f/3.3 (W) - 5.9   (T) Filter   Thread None Zoom Optical: 3x Digital: 4x Focus Range Auto: 1.64'   (0.50 m) - Infinity Wide: 20\" (50.80 cm) -   Infinity Macro: 2\" (5.08 cm) -   Infinity Exposure   Control ISO   Sensitivity Auto,   80-1600 Shutter Type:   Electronic & Mechanical Speed: 1.0 - 1/2000\u00a0sec Exposure   Modes Modes:   Programmed Auto Compensation: -2 EV to +2 EV   (in .33 EV steps) Shooting   Modes Portrait White   Balance Modes Auto Flash Flash Modes Auto Built-in   Flash Yes Effective   Flash Range Wide: 0.02 -   0.05' (0.5 - 1.4 cm) Telephoto: 3.94 - 1.64' (1.2   - 0.5 m) Memory Built-in   Memory 7.3GB Memory Card   Type None Recording Video   Recording Yes,   NTSC/PAL Resolution 1280 x 720:   30 fps 640 x 480: 30 fps Video Audio   Recording With Video,   Stereo Viewfinder/Display Viewfinder   Type None Screen 2.5\"   LCD\u00a0Rear Touch   Screen\u00a0(230,000 pixels) Connectivity/System   Requirements Connectivity 1x AV Output, USB 2.0\u00a0(out) Environmental Waterproofing None Power Battery NIENEL11\u00a0Rechargeable   Lithium-Ion Battery Pack,   3.7VDC, 680mAh AC Power   Adapter EH-69P   (Included) Physical Dimensions (WxHxD) 3.1 x 2.1 x   0.7\"\u00a0/\u00a07.9 x 5.3 x 1.8 cm Weight 3.4 oz\u00a0/\u00a096   g",
    "builtinmemory": "7.3GB",
    "dimensionswxhxd": "3.1 x 2.1 x   0.7\"\u00a0/\u00a07.9 x 5.3 x 1.8 cm",
    "sensor": "1/2.9\" CCD",
    "audiorecording": "With Video,   Stereo",
    "whitebalancemodes": "Auto",
    "category": "camera",
    "freeshipping": "Yes",
    "screen": "2.5\"   LCD\u00a0Rear Touch   Screen\u00a0(230,000 pixels)",
    "filterthread": "None",
    "lens": "NIKKOR, 6   elements in 5 groups EFL: 4.1-12.3 mm\u00a0(35 mm   equivalent: 29-87 mm) Aperture: f/3.3 (W) - 5.9   (T)",
    "connectivity": "1x AV Output, USB 2.0\u00a0(out)",
    "focusrange": "Auto: 1.64'   (0.50 m) - Infinity Wide: 20\" (50.80 cm) -   Infinity Macro: 2\" (5.08 cm) -   Infinity",
    "included": "Nikon COOLPIX S01 Digital Camera (Red) Nikon CS-CP4-1 Case (Red) AN-CP19 Strap UC-E16 Replacement USB Cable for CoolPix S30 and L26 Replacement EH-69P AC Adapter Charger",
    "aspectratio": "4:3",
    "pixels": "Actual:   10.34 Megapixel Effective: 10.1 Megapixel",
    "condition": "New",
    "waterproofing": "None",
    "effectiveflashrange": "Wide: 0.02 -   0.05' (0.5 - 1.4 cm) Telephoto: 3.94 - 1.64' (1.2   - 0.5 m)",
    "exposuremodes": "Modes:   Programmed Auto Compensation: -2 EV to +2 EV   (in .33 EV steps)",
    "zoom": "Optical: 3x Digital: 4x",
    "opticalzoom": "3x Zoom",
    "shutter": "Type:   Electronic & Mechanical Speed: 1.0 - 1/2000\u00a0sec",
    "flashmodes": "Auto",
    "viewfindertype": "None",
    "builtinflash": "Yes",
    "maxresolution": "10MP: 3648 x   2736 @ 4:3",
    "resolution": "1280 x 720:   30 fps 640 x 480: 30 fps"
}