{
    "category": "camera",
    "internationalbuyerspleasenoteimportdutiesandbrokeragefeesarenotincludedintheitempriceorshippingchargesthesechargesarethebuyersresponsibilityallusbuyersmustincludetheirphoneintheirshippingdetailspleasecheckwithyourlocalcustomsofficetodeterminewhattheseadditionalcostswillbepriortobiddingbuyingwearenotabletoestimatequotethesechargesthesechargesarenormallycollectedbythedeliveringfreightshippingcompanyorwhenyoupicktheitemupwedonotmarkmerchandisevaluesbelowvalueormarkitemsasgiftsuscanadianandinternationalgovernmentregulationsprohibitsuchbehaviourthankyounoticepleasebeawaretaxeswillbechargedonallcanadianpurchasestaxesandratesarenonnegotiablerateswillbereflectiveofyourprovinceofresidenceandareoutlinedhereatsurplusbydesignitemssoldasisorworkingasisarenoteligibleforreturnsrefundsandorexchangesasisorworkingasisitemsarefinalsaleupondiscoveryofissueswithasisandworkingasisitemswestoptestingandissuesmaynotbelimitedtothoseoutlinedinourlistingwecannotguaranteethefullfunctionalityofallpartsonasisandworkingasisitemspleasebidcarefully": "SPECIFICATIONS: Type: Digital Camera Brand: Fujifilm Model: Finepix XP60 Megapixels: 16.4 Video Resolution: 1080p Optical Zoom: 5x Colour: Blue Additional Features: Waterproof to 20 ft.,  Shockproof to 5 ft.,  Freeze proof to 14\u00c2\u00b0F and Dust/Sand proof. Full HD movie recording (1920 x 1080p) with a dedicated Movie Recording Button and Burst Mode Button Country/Region of Manufacture: China Screen Size: 2.7\" INCLUDES: Battery Battery Charger Manual OEM Box Software Disc Strap (Neck or Wrist) EXCLUDES: USB Cable(s) ITEM DETAILS: This product has been used, we have tested all components and all of them work as they are supposed to. PHYSICAL CONDITION: Very good There are only one or two minor scuffs on the screen. FUNCTIONAL CONDITION: Used We have stress-tested all product components  and they work as they are supposed to. Product has been reset to near factory condition. 28075",
    "videoresolution": "1080p",
    "colour": "Blue",
    "megapixels": "16.4",
    "opticalzoom": "5x",
    "additionalfeatures": "Waterproof to 20 ft.,  Shockproof to 5 ft.,  Freeze proof to 14\u00c2\u00b0F and Dust/Sand proof. Full HD movie recording (1920 x 1080p) with a dedicated Movie Recording Button and Burst Mode Button",
    "screensize": "2.7\"",
    "model": "Finepix XP60",
    "type": "Digital Camera",
    "brand": "Fujifilm",
    "countryregionofmanufacture": "China"
}