{
    "category": "camera",
    "internationalbuyerspleasenoteimportdutiesandbrokeragefeesarenotincludedintheitempriceorshippingchargesthesechargesarethebuyersresponsibilityallusbuyersmustincludetheirphoneintheirshippingdetailspleasecheckwithyourlocalcustomsofficetodeterminewhattheseadditionalcostswillbepriortobiddingbuyingwearenotabletoestimatequotethesechargesthesechargesarenormallycollectedbythedeliveringfreightshippingcompanyorwhenyoupicktheitemupwedonotmarkmerchandisevaluesbelowvalueormarkitemsasgiftsuscanadianandinternationalgovernmentregulationsprohibitsuchbehaviourthankyounoticepleasebeawaretaxeswillbechargedonallcanadianpurchasestaxesandratesarenonnegotiablerateswillbereflectiveofyourprovinceofresidenceandareoutlinedhereatsurplusbydesignitemssoldasisorworkingasisarenoteligibleforreturnsrefundsandorexchangesasisorworkingasisitemsarefinalsaleupondiscoveryofissueswithasisandworkingasisitemswestoptestingandissuesmaynotbelimitedtothoseoutlinedinourlistingwecannotguaranteethefullfunctionalityofallpartsonasisandworkingasisitemspleasebidcarefully": "SPECIFICATIONS: Type: Point & Shoot Brand: Nikon Model: Coolpix s9600 Megapixels: 16 Video Resolution: HD Optical Zoom: 22x Colour: Black Country/Region of Manufacture: China Screen Size: 3\" INCLUDES: AC Adapter Battery OEM Box Strap (Neck or Wrist) USB Cable(s) EXCLUDES: ITEM DETAILS: Although this unit has been previously used, it is in complete working order. Physically the unit is in great condition without any marks on it. PHYSICAL CONDITION: Great Physically the unit is in great condition without any marks on it. FUNCTIONAL CONDITION: Used Although this unit has been previously used, it is in complete working order. 27140",
    "videoresolution": "HD",
    "colour": "Black",
    "megapixels": "16",
    "opticalzoom": "22x",
    "screensize": "3\"",
    "model": "Coolpix s9600",
    "type": "Point & Shoot",
    "brand": "Nikon",
    "countryregionofmanufacture": "China"
}