{
    "category": "camera",
    "internationalbuyerspleasenoteimportdutiesandbrokeragefeesarenotincludedintheitempriceorshippingchargesthesechargesarethebuyersresponsibilityallusbuyersmustincludetheirphoneintheirshippingdetailspleasecheckwithyourlocalcustomsofficetodeterminewhattheseadditionalcostswillbepriortobiddingbuyingwearenotabletoestimatequotethesechargesthesechargesarenormallycollectedbythedeliveringfreightshippingcompanyorwhenyoupicktheitemupwedonotmarkmerchandisevaluesbelowvalueormarkitemsasgiftsuscanadianandinternationalgovernmentregulationsprohibitsuchbehaviourthankyounoticepleasebeawaretaxeswillbechargedonallcanadianpurchasestaxesandratesarenonnegotiablerateswillbereflectiveofyourprovinceofresidenceandareoutlinedhereatsurplusbydesignitemssoldasisorworkingasisarenoteligibleforreturnsrefundsandorexchangesasisorworkingasisitemsarefinalsaleupondiscoveryofissueswithasisandworkingasisitemswestoptestingandissuesmaynotbelimitedtothoseoutlinedinourlistingwecannotguaranteethefullfunctionalityofallpartsonasisandworkingasisitemspleasebidcarefully": "SPECIFICATIONS: Type: Mini Digital Camera Brand: Fujifilm Model: FinePix S8200 Megapixels: 16.2MP Lens: Fujinon 40x optical zoom lens Video Resolution: 1920 x 1080 Optical Zoom: 40x Digital Zoom: approx. 2.0x Colour: Black Country/Region of Manufacture: China Screen Size: 3.0\" INCLUDES: Lens Cap OEM Box Strap (Neck or Wrist) USB Cable(s) EXCLUDES: ITEM DETAILS: Although this unit has been previously used, it is in complete working order. Physically the unit is in great condition without any marks on it. PHYSICAL CONDITION: Great Physically the unit is in great condition without any marks on it. FUNCTIONAL CONDITION: Used Although this unit has been previously used, it is in complete working order. 27337",
    "videoresolution": "1920 x 1080",
    "colour": "Black",
    "megapixels": "16.2MP",
    "opticalzoom": "40x",
    "lens": "Fujinon 40x optical zoom lens",
    "digitalzoom": "approx. 2.0x",
    "screensize": "3.0\"",
    "model": "FinePix S8200",
    "type": "Mini Digital Camera",
    "brand": "Fujifilm",
    "countryregionofmanufacture": "China"
}